Workbook

Sheet Guide
B1: Silva Annual Plan – Template Guide (v2)
B2: Built to the structure agreed in "Silva Plan – Revised Template Structure (v2)". Prepared by SPX for review.
B4: TABS
B5: Summary | C5: Category metrics, man-days and budget for the five categories, plus scenario budgets for comparison. Nothing is typed here.
B6: Settings | C6: Farm name, plan year, the +25% / +50% bands, working days, and staff settings.
B7: Nursery | C7: One tab per category (Nursery, Young Coffee, Matured Coffee, Infilling, Harvesting). See "How a category tab works" below.
B8: Monthly | C8: Monthly cost and man-days from the Chaka Buna plan rows of all five category tabs.
B9: Staff & Overheads | C9: Parked – not yet in the Summary or Monthly tabs.
B10: Benchmark Data | C10: Rates from all six B-Agro farm plans (2019 EFY). Source of every industry-average value.
B12: HOW A CATEGORY TAB WORKS
B13: 1. Plan basis (top of the tab): choose Industry average, +25%, +50% or Expert input. It sets the Chaka Buna plan row of every activity on the tab.
B14: 2. General information: enter the category metrics (areas, tree counts, beds…). Activity quantities link to these, and the Summary shows them.
B15: 3. Each activity has five rows: Industry average · +25% · +50% · Expert input · Chaka Buna plan. Only the Chaka Buna plan row counts in totals.
B16: 4. Cost per unit = man-days per unit × wage per man-day on every row. The bands raise the wage by 25% / 50%; man-days stay the same.
B17: 5. Enter the activity quantity per round once, on the Industry average row (green = already linked to a metric; yellow blank = type it).
B18: 6. The agronomist overwrites man-days, wage or frequency on the Expert input row (pre-filled with the industry average).
B19: 7. Activities with no industry-average rate always use the Expert input row, whatever the plan basis says.
B20: 8. Phasing % is entered on the Chaka Buna plan row (pre-filled from B-Agro's seasonal timing). It turns red if it does not add up to 100%.
B21: 9. Use the outline buttons (1 / 2) at the top-left of the sheet to collapse each activity to its Chaka Buna plan row.
B23: COLOUR CODE
B24: Blue text, yellow cell | C24: Input – type here.
B25: Green text, yellow cell | C25: Pre-filled suggestion (link to a benchmark or metric) – overwrite if needed.
B26: Green text | C26: Link from another tab – do not edit.
B27: Green row | C27: Chaka Buna plan row – the one that counts.
B28: Black text | C28: Calculation – do not edit.
B30: ABOUT THE BENCHMARKS
B31: • Industry average = Telli, Gawi and Chetu, the three B-Agro farms closest to Silva, counting only the farms that plan the activity.
B32: • Industry wage per man-day = average cost ÷ average man-days, so the Industry average row reproduces the three farms' average cost.
B33: • 124 activities: 102 have a rate at one or more of the three farms; 9 only at the other B-Agro farms (six-farm average pre-fills the Expert input row); 13 have no B-Agro rate (10 SPX additions and 3 B-Agro lines with no rate) – enter them on the Expert input row.
B34: • Benchmarks are B-Agro budgets, not actual costs.
C36: REVIEW LOG
B37: # | C37: Tab / code / cell | D37: Comment | E37: Raised by | F37: Date | G37: SPX response | H37: Status
B38: 1
B39: 2
B40: 3
B41: 4
B42: 5
B43: 6
B44: 7
B45: 8
B46: 9
B47: 10
B48: 11
B49: 12
... B62: 25

Sheet Summary
B1: Silva Annual Plan – Summary
B2: ="Farm: "&Settings!$C$6&" | Plan year: "&Settings!$C$7 -> Farm: Chaka Buna Estate (Silva Forest Coffee) | Plan year: 2019 EFY (2026/27) – confirm
B3: Everything on this tab comes from the category tabs: metrics from each "General information" block, man-days and budget from the Chaka Buna plan rows.
B5: CATEGORY METRICS | G5: CHAKA BUNA PLAN | J5: BUDGET BY SCENARIO (for comparison)
B6: Category | C6: Metric (Amharic) | D6: Metric (English) | E6: Unit | F6: Quantity | G6: Plan basis | H6: Total man-days | I6: Budget (birr) | J6: Industry average | K6: +25% | L6: +50% | M6: Expert input
B7: Nursery | C7: =Nursery!D8 -> የሚተከል የቦታ ስፋት (ሄ/ር) | D7: =Nursery!C8 -> Plantation area | E7: =Nursery!E8 -> ha | F7: =Nursery!F8 -> 0 | G7: =Nursery!D4 -> Industry average | H7: =Nursery!N12 -> 0 | I7: =Nursery!O12 -> 0 | J7: =Nursery!O8 -> 0 | K7: =Nursery!O9 -> 0 | L7: =Nursery!O10 -> 0 | M7: =Nursery!O11 -> 0
C8: =Nursery!D9 -> የሚዘጋጅ ችግኝ ብዛት (ቁጥር) | D8: =Nursery!C9 -> Total seedlings | E8: =Nursery!E9 -> no. | F8: =Nursery!F9 -> 0
C9: =Nursery!D10 -> የችግኝ ጣቢያ ስፋት | D9: =Nursery!C10 -> Nursery site area | E9: =Nursery!E10 -> ha | F9: =Nursery!F10 -> 0
C10: =Nursery!D11 -> የዘር መደብ | D10: =Nursery!C11 -> Germination seedbeds | E10: =Nursery!E11 -> bed | F10: =Nursery!F11 -> 0
C11: =Nursery!D12 -> የፖሊቲዩብ መደብ | D11: =Nursery!C12 -> Polytube beds | E11: =Nursery!E12 -> bed | F11: =Nursery!F12 -> 0
B12: Young Coffee | C12: ='Young Coffee'!C7 -> የቡና እግር ብዛት (ቁጥር) | D12: ='Young Coffee'!B7 -> Total trees (net area) | E12: ='Young Coffee'!D7 -> no. | F12: ='Young Coffee'!E7 -> 0 | G12: ='Young Coffee'!C3 -> Industry average | H12: ='Young Coffee'!M11 -> 0 | I12: ='Young Coffee'!N11 -> 0 | J12: ='Young Coffee'!N7 -> 0 | K12: ='Young Coffee'!N8 -> 0 | L12: ='Young Coffee'!N9 -> 0 | M12: ='Young Coffee'!N10 -> 0
C13: ='Young Coffee'!C8 -> ጠቅላላ የማሳ ስፋት (ሄ/ር) | D13: ='Young Coffee'!B8 -> Gross area | E13: ='Young Coffee'!D8 -> ha | F13: ='Young Coffee'!E8 -> 0
C14: ='Young Coffee'!C9 -> የቡና እግር አማካይ (ሄ/ር) | D14: ='Young Coffee'!B9 -> Average trees per ha | E14: ='Young Coffee'!D9 -> trees/ha | F14: ='Young Coffee'!E9 -> 0
B15: Matured Coffee | C15: ='Matured Coffee'!C7 -> ጠቅላላ የመሬት (ሄ/ር) | D15: ='Matured Coffee'!B7 -> Total coffee area | E15: ='Matured Coffee'!D7 -> ha | F15: ='Matured Coffee'!E7 -> 0 | G15: ='Matured Coffee'!C3 -> Industry average | H15: ='Matured Coffee'!M11 -> 0 | I15: ='Matured Coffee'!N11 -> 0 | J15: ='Matured Coffee'!N7 -> 0 | K15: ='Matured Coffee'!N8 -> 0 | L15: ='Matured Coffee'!N9 -> 0 | M15: ='Matured Coffee'!N10 -> 0
C16: ='Matured Coffee'!C8 -> እናት ቡና እግር ብዛት (ቁጥር) | D16: ='Matured Coffee'!B8 -> Total mature trees (net area) | E16: ='Matured Coffee'!D8 -> no. | F16: ='Matured Coffee'!E8 -> 0
C17: ='Matured Coffee'!C9 -> የቡና እግር አማካይ (ሄ/ር) | D17: ='Matured Coffee'!B9 -> Average trees per ha | E17: ='Matured Coffee'!D9 -> trees/ha | F17: ='Matured Coffee'!E9 -> 0
C18: ='Matured Coffee'!C10 -> የሚጎነደል ቡና | D18: ='Matured Coffee'!B10 -> Trees to stump | E18: ='Matured Coffee'!D10 -> no. | F18: ='Matured Coffee'!E10 -> 0
B19: Infilling | C19: =Infilling!C7 -> ጠቅላላ የመሬት (ሄ/ር) | D19: =Infilling!B7 -> Total coffee area | E19: =Infilling!D7 -> ha | F19: =Infilling!E7 -> 0 | G19: =Infilling!C3 -> Industry average | H19: =Infilling!M11 -> 0 | I19: =Infilling!N11 -> 0 | J19: =Infilling!N7 -> 0 | K19: =Infilling!N8 -> 0 | L19: =Infilling!N9 -> 0 | M19: =Infilling!N10 -> 0
C20: =Infilling!C8 -> ሞተ ከዳ ቁጥር | D20: =Infilling!B8 -> Trees to infill | E20: =Infilling!D8 -> no. | F20: =Infilling!E8 -> 0
C21: =Infilling!C9 -> የቡና እግር አማካይ (ሄ/ር) | D21: =Infilling!B9 -> Average trees per ha (trees to infill ÷ area) | E21: =Infilling!D9 -> trees/ha | F21: =Infilling!E9 -> 0
B22: Harvesting & Related | C22: =Harvesting!C7 -> ምርታማ የቡና እግር ቁጥር | D22: =Harvesting!B7 -> Productive trees | E22: =Harvesting!D7 -> no. | F22: =Harvesting!E7 -> 0 | G22: =Harvesting!C3 -> Industry average | H22: =Harvesting!M11 -> 0 | I22: =Harvesting!N11 -> 0 | J22: =Harvesting!N7 -> 0 | K22: =Harvesting!N8 -> 0 | L22: =Harvesting!N9 -> 0 | M22: =Harvesting!N10 -> 0
C23: =Harvesting!C8 -> ጠቅላላ የቦታ ስፋት (ሄ/ር) | D23: =Harvesting!B8 -> Gross plantation area | E23: =Harvesting!D8 -> ha | F23: =Harvesting!E8 -> 0
C24: =Harvesting!C9 -> ምርታማነት አማካይ (ኩ/ል/ሄ/ር) | D24: =Harvesting!B9 -> Average productivity | E24: =Harvesting!D9 -> qt clean coffee/ha | F24: =Harvesting!E9 -> 0
C25: =Harvesting!C10 -> አጠቃላይ የሚመረት ንፁህ ቡና (ኩ/ል) | D25: =Harvesting!B10 -> Total clean coffee production | E25: =Harvesting!D10 -> qt | F25: =Harvesting!E10 -> 0
C26: =Harvesting!C11 -> ቀይ ቡና | D26: =Harvesting!B11 -> Red cherry to pick | E26: =Harvesting!D11 -> kg | F26: =Harvesting!E11 -> 0
C27: =Harvesting!C12 -> የቡና ማስጫ አልጋ | D27: =Harvesting!B12 -> Drying beds | E27: =Harvesting!D12 -> bed | F27: =Harvesting!E12 -> 0
C28: =Harvesting!C13 -> ደረቅ ቡና ኬሻ | D28: =Harvesting!B13 -> Dry cherry bags | E28: =Harvesting!D13 -> bag | F28: =Harvesting!E13 -> 0
B29: TOTAL – ALL FIELD WORK | H29: =H7+H12+H15+H19+H22 -> 0 | I29: =I7+I12+I15+I19+I22 -> 0 | J29: =J7+J12+J15+J19+J22 -> 0 | K29: =K7+K12+K15+K19+K22 -> 0 | L29: =L7+L12+L15+L19+L22 -> 0 | M29: =M7+M12+M15+M19+M22 -> 0
B30: =IF(ABS(I29-Monthly!B11)>0.5,"Check: Summary total differs from Monthly total","")

Sheet Settings
B2: Settings
B3: Values used across the workbook. Quantities now sit in each category tab ("General information" block).
B5: Setting | C5: Value | D5: Unit | E5: Source / note
B6: Farm | C6: Chaka Buna Estate (Silva Forest Coffee) | D6: text | E6: Appears in the tab headers.
B7: Plan year | C7: 2019 EFY (2026/27) – confirm | D7: text | E7: Months run Tikimt–Meskerem (Oct–Sep), as in the B-Agro plans. Confirm against Chaka Buna's financial year.
B8: Band 1 above industry average | C8: 0.25 | D8: % | E8: Applied to wage per man-day on the "+25%" rows. The row labels stay "+25%" if you change this value.
B9: Band 2 above industry average | C9: 0.5 | D9: % | E9: Applied to wage per man-day on the "+50%" rows. The row labels stay "+50%" if you change this value.
B10: Working days per month | C10: 26 | D10: days | E10: Converts monthly man-days into workers needed (Monthly tab).
B11: Employer pension contribution | C11: 0.11 | D11: % of salary | E11: Staff & Overheads tab only. Rate used in all B-Agro salary sheets.
B12: Salary increment for plan year | C12: 0.1 | D12: % of salary | E12: Staff & Overheads tab only. B-Agro applied 10% in its 2018 EFY Chetu plan. Assumption – confirm.
B13: Bonus | C13: 1 | D13: months of salary | E13: Staff & Overheads tab only. B-Agro plans budget one month. Assumption – confirm.

Sheet Nursery
B1: Nursery – activity plan and budget
B2: ="Farm: "&Settings!$C$6&" | Plan year: "&Settings!$C$7 -> Farm: Chaka Buna Estate (Silva Forest Coffee) | Plan year: 2019 EFY (2026/27) – confirm
C4: Plan basis (drop-down) ► | D4: Industry average | E4: Sets the Chaka Buna plan row of every activity on this tab. Activities with no industry-average rate always use the Expert input row.
C6: GENERAL INFORMATION | G6: CATEGORY TOTALS
C7: Metric (English) | D7: Metric (Amharic) | E7: Unit | F7: Quantity | G7: Rate scenario | N7: Total man-days | O7: Total cost (birr) | P7: Plan phasing (% of cost) | AB7: Plan monthly totals
C8: Plantation area | D8: የሚተከል የቦታ ስፋት (ሄ/ር) | E8: ha | G8: Industry average | N8: =SUMIF($G$18:$G$182,"Industry average",N$18:N$182) -> 0 | O8: =SUMIF($G$18:$G$182,"Industry average",O$18:O$182) -> 0
C9: Total seedlings | D9: የሚዘጋጅ ችግኝ ብዛት (ቁጥር) | E9: no. | G9: +25% | N9: =SUMIF($G$18:$G$182,"+25%",N$18:N$182) -> 0 | O9: =SUMIF($G$18:$G$182,"+25%",O$18:O$182) -> 0
C10: Nursery site area | D10: የችግኝ ጣቢያ ስፋት | E10: ha | G10: +50% | N10: =SUMIF($G$18:$G$182,"+50%",N$18:N$182) -> 0 | O10: =SUMIF($G$18:$G$182,"+50%",O$18:O$182) -> 0
C11: Germination seedbeds | D11: የዘር መደብ | E11: bed | G11: Expert input | N11: =SUMIF($G$18:$G$182,"Expert input",N$18:N$182) -> 0 | O11: =SUMIF($G$18:$G$182,"Expert input",O$18:O$182) -> 0
C12: Polytube beds | D12: የፖሊቲዩብ መደብ | E12: bed | G12: Chaka Buna plan – counts in Summary | N12: =SUMIF($G$18:$G$182,"Chaka Buna plan",N$18:N$182) -> 0 | O12: =SUMIF($G$18:$G$182,"Chaka Buna plan",O$18:O$182) -> 0 | P12: =IFERROR(AC12/$O$12,0) -> 0 | Q12: =IFERROR(AE12/$O$12,0) -> 0 | R12: =IFERROR(AG12/$O$12,0) -> 0 | S12: =IFERROR(AI12/$O$12,0) -> 0 | T12: =IFERROR(AK12/$O$12,0) -> 0 | U12: =IFERROR(AM12/$O$12,0) -> 0 | V12: =IFERROR(AO12/$O$12,0) -> 0 | W12: =IFERROR(AQ12/$O$12,0) -> 0 | X12: =IFERROR(AS12/$O$12,0) -> 0 | Y12: =IFERROR(AU12/$O$12,0) -> 0 | Z12: =IFERROR(AW12/$O$12,0) -> 0 | AA12: =IFERROR(AY12/$O$12,0) -> 0 | AB12: =SUM(AB18:AB182) -> 0 | AC12: =SUM(AC18:AC182) -> 0 | AD12: =SUM(AD18:AD182) -> 0 | AE12: =SUM(AE18:AE182) -> 0 | AF12: =SUM(AF18:AF182) -> 0 | AG12: =SUM(AG18:AG182) -> 0 | AH12: =SUM(AH18:AH182) -> 0 | AI12: =SUM(AI18:AI182) -> 0 | ... AY12: =SUM(AY18:AY182) -> 0
B16: ACTIVITY | G16: RATE (cost per unit = man-days × wage) | K16: QUANTITY | M16: TOTALS (calculated) | P16: PHASING – % of annual (input on the Chaka Buna plan row) | AB16: MONTHLY MAN-DAYS AND COST (Chaka Buna plan row)
B17: Code | C17: Activity | D17: Activity (Amharic) | E17: Sub-group | F17: Unit | G17: Rate scenario | H17: Man-days per unit | I17: Wage per man-day (birr) | J17: Cost per unit (birr) | K17: Activity quantity per round | L17: Frequency (times / year) | M17: Total activity quantity | N17: Total man-days per activity | O17: Total cost per activity (birr) | P17: Tikimt (Oct) | Q17: Hidar (Nov) | R17: Tahsas (Dec) | S17: Tir (Jan) | T17: Yekatit (Feb) | U17: Megabit (Mar) | V17: Miyazya (Apr) | W17: Ginbot (May) | X17: Sene (Jun) | Y17: Hamle (Jul) | Z17: Nehase (Aug) | AA17: Meskerem (Sep) | AB17: Tikimt (Oct) – man-days | AC17: Tikimt (Oct) – cost | AD17: Hidar (Nov) – man-days | AE17: Hidar (Nov) – cost | AF17: Tahsas (Dec) – man-days | AG17: Tahsas (Dec) – cost | AH17: Tir (Jan) – man-days | AI17: Tir (Jan) – cost | AJ17: Yekatit (Feb) – man-days | AK17: Yekatit (Feb) – cost | AL17: Megabit (Mar) – man-days | AM17: Megabit (Mar) – cost | AN17: Miyazya (Apr) – man-days | AO17: Miyazya (Apr) – cost | AP17: Ginbot (May) – man-days | AQ17: Ginbot (May) – cost | AR17: Sene (Jun) – man-days | AS17: Sene (Jun) – cost | AT17: Hamle (Jul) – man-days | AU17: Hamle (Jul) – cost | AV17: Nehase (Aug) – man-days | AW17: Nehase (Aug) – cost | AX17: Meskerem (Sep) – man-days | AY17: Meskerem (Sep) – cost
B18: NU-01 | C18: Land clearing | D18: ምንጣሮ | E18: Site preparation | F18: ha | G18: Industry average | H18: =IFERROR(INDEX('Benchmark Data'!$AC$7:$AC$130,MATCH($B18,'Benchmark Data'!$A$7:$A$130,0)),0) -> 20 | I18: =IFERROR(INDEX('Benchmark Data'!$AD$7:$AD$130,MATCH($B18,'Benchmark Data'!$A$7:$A$130,0)),0) -> 183.33333 | J18: =H18*I18 -> 3666.6667 | K18: =$F$10 -> 0 | L18: =IFERROR(INDEX('Benchmark Data'!$AE$7:$AE$130,MATCH($B18,'Benchmark Data'!$A$7:$A$130,0)),0) -> 1 | M18: =K18*L18 -> 0 | N18: =M18*H18 -> 0 | O18: =M18*J18 -> 0
B19: NU-01 | C19: Land clearing | D19: ምንጣሮ | E19: Site preparation | F19: ha | G19: +25% | H19: =H18 -> 20 | I19: =I18*(1+Settings!$C$8) -> 229.16667 | J19: =H19*I19 -> 4583.3333 | K19: =K18 -> 0 | L19: =L18 -> 1 | M19: =K19*L19 -> 0 | N19: =M19*H19 -> 0 | O19: =M19*J19 -> 0
B20: NU-01 | C20: Land clearing | D20: ምንጣሮ | E20: Site preparation | F20: ha | G20: +50% | H20: =H18 -> 20 | I20: =I18*(1+Settings!$C$9) -> 275 | J20: =H20*I20 -> 5500 | K20: =K18 -> 0 | L20: =L18 -> 1 | M20: =K20*L20 -> 0 | N20: =M20*H20 -> 0 | O20: =M20*J20 -> 0
B21: NU-01 | C21: Land clearing | D21: ምንጣሮ | E21: Site preparation | F21: ha | G21: Expert input | H21: =H18 -> 20 | I21: =I18 -> 183.33333 | J21: =H21*I21 -> 3666.6667 | K21: =K18 -> 0 | L21: =L18 -> 1 | M21: =K21*L21 -> 0 | N21: =M21*H21 -> 0 | O21: =M21*J21 -> 0
B22: NU-01 | C22: Land clearing | D22: ምንጣሮ | E22: Site preparation | F22: ha | G22: Chaka Buna plan | H22: =CHOOSE(IF(OR($D$4="Expert input",$J$18=0),4,IF($D$4="+25%",2,IF($D$4="+50%",3,1))),H18,H19,H20,H21) -> 20 | I22: =CHOOSE(IF(OR($D$4="Expert input",$J$18=0),4,IF($D$4="+25%",2,IF($D$4="+50%",3,1))),I18,I19,I20,I21) -> 183.33333 | J22: =H22*I22 -> 3666.6667 | K22: =K18 -> 0 | L22: =CHOOSE(IF(OR($D$4="Expert input",$J$18=0),4,IF($D$4="+25%",2,IF($D$4="+50%",3,1))),L18,L19,L20,L21) -> 1 | M22: =K22*L22 -> 0 | N22: =M22*H22 -> 0 | O22: =M22*J22 -> 0 | Q22: 1 | AB22: =P22*$N22 -> 0 | AC22: =P22*$O22 -> 0 | AD22: =Q22*$N22 -> 0 | AE22: =Q22*$O22 -> 0 | AF22: =R22*$N22 -> 0 | AG22: =R22*$O22 -> 0 | AH22: =S22*$N22 -> 0 | AI22: =S22*$O22 -> 0 | AJ22: =T22*$N22 -> 0 | AK22: =T22*$O22 -> 0 | AL22: =U22*$N22 -> 0 | AM22: =U22*$O22 -> 0 | AN22: =V22*$N22 -> 0 | AO22: =V22*$O22 -> 0 | AP22: =W22*$N22 -> 0 | AQ22: =W22*$O22 -> 0 | AR22: =X22*$N22 -> 0 | AS22: =X22*$O22 -> 0 | AT22: =Y22*$N22 -> 0 | AU22: =Y22*$O22 -> 0 | AV22: =Z22*$N22 -> 0 | AW22: =Z22*$O22 -> 0 | AX22: =AA22*$N22 -> 0 | AY22: =AA22*$O22 -> 0
B23: NU-02 | C23: Tree felling / stump removal | D23: ዛፍ መጣል / ጉቶ መንቀል | E23: Site preparation | F23: ha | G23: Industry average | H23: =IFERROR(INDEX('Benchmark Data'!$AC$7:$AC$130,MATCH($B23,'Benchmark Data'!$A$7:$A$130,0)),0) -> 24 | I23: =IFERROR(INDEX('Benchmark Data'!$AD$7:$AD$130,MATCH($B23,'Benchmark Data'!$A$7:$A$130,0)),0) -> 125 | J23: =H23*I23 -> 3000 | K23: =$F$10 -> 0 | L23: =IFERROR(INDEX('Benchmark Data'!$AE$7:$AE$130,MATCH($B23,'Benchmark Data'!$A$7:$A$130,0)),0) -> 1 | M23: =K23*L23 -> 0 | N23: =M23*H23 -> 0 | O23: =M23*J23 -> 0
B24: NU-02 | C24: Tree felling / stump removal | D24: ዛፍ መጣል / ጉቶ መንቀል | E24: Site preparation | F24: ha | G24: +25% | H24: =H23 -> 24 | I24: =I23*(1+Settings!$C$8) -> 156.25 | J24: =H24*I24 -> 3750 | K24: =K23 -> 0 | L24: =L23 -> 1 | M24: =K24*L24 -> 0 | N24: =M24*H24 -> 0 | O24: =M24*J24 -> 0
B25: NU-02 | C25: Tree felling / stump removal | D25: ዛፍ መጣል / ጉቶ መንቀል | E25: Site preparation | F25: ha | G25: +50% | H25: =H23 -> 24 | I25: =I23*(1+Settings!$C$9) -> 187.5 | J25: =H25*I25 -> 4500 | K25: =K23 -> 0 | L25: =L23 -> 1 | M25: =K25*L25 -> 0 | N25: =M25*H25 -> 0 | O25: =M25*J25 -> 0
B26: NU-02 | C26: Tree felling / stump removal | D26: ዛፍ መጣል / ጉቶ መንቀል | E26: Site preparation | F26: ha | G26: Expert input | H26: =H23 -> 24 | I26: =I23 -> 125 | J26: =H26*I26 -> 3000 | K26: =K23 -> 0 | L26: =L23 -> 1 | M26: =K26*L26 -> 0 | N26: =M26*H26 -> 0 | O26: =M26*J26 -> 0
B27: NU-02 | C27: Tree felling / stump removal | D27: ዛፍ መጣል / ጉቶ መንቀል | E27: Site preparation | F27: ha | G27: Chaka Buna plan | H27: =CHOOSE(IF(OR($D$4="Expert input",$J$23=0),4,IF($D$4="+25%",2,IF($D$4="+50%",3,1))),H23,H24,H25,H26) -> 24 | I27: =CHOOSE(IF(OR($D$4="Expert input",$J$23=0),4,IF($D$4="+25%",2,IF($D$4="+50%",3,1))),I23,I24,I25,I26) -> 125 | J27: =H27*I27 -> 3000 | K27: =K23 -> 0 | L27: =CHOOSE(IF(OR($D$4="Expert input",$J$23=0),4,IF($D$4="+25%",2,IF($D$4="+50%",3,1))),L23,L24,L25,L26) -> 1 | M27: =K27*L27 -> 0 | N27: =M27*H27 -> 0 | O27: =M27*J27 -> 0 | Q27: 1 | AB27: =P27*$N27 -> 0 | AC27: =P27*$O27 -> 0 | AD27: =Q27*$N27 -> 0 | AE27: =Q27*$O27 -> 0 | AF27: =R27*$N27 -> 0 | AG27: =R27*$O27 -> 0 | AH27: =S27*$N27 -> 0 | AI27: =S27*$O27 -> 0 | AJ27: =T27*$N27 -> 0 | AK27: =T27*$O27 -> 0 | AL27: =U27*$N27 -> 0 | AM27: =U27*$O27 -> 0 | AN27: =V27*$N27 -> 0 | AO27: =V27*$O27 -> 0 | AP27: =W27*$N27 -> 0 | AQ27: =W27*$O27 -> 0 | AR27: =X27*$N27 -> 0 | AS27: =X27*$O27 -> 0 | AT27: =Y27*$N27 -> 0 | AU27: =Y27*$O27 -> 0 | AV27: =Z27*$N27 -> 0 | AW27: =Z27*$O27 -> 0 | AX27: =AA27*$N27 -> 0 | AY27: =AA27*$O27 -> 0
B28: NU-03 | C28: Digging | D28: መቆፈር | E28: Site preparation | F28: ha | G28: Industry average | H28: =IFERROR(INDEX('Benchmark Data'!$AC$7:$AC$130,MATCH($B28,'Benchmark Data'!$A$7:$A$130,0)),0) -> 33.111111 | I28: =IFERROR(INDEX('Benchmark Data'!$AD$7:$AD$130,MATCH($B28,'Benchmark Data'!$A$7:$A$130,0)),0) -> 158.05369 | J28: =H28*I28 -> 5233.3333 | K28: =$F$10 -> 0 | L28: =IFERROR(INDEX('Benchmark Data'!$AE$7:$AE$130,MATCH($B28,'Benchmark Data'!$A$7:$A$130,0)),0) -> 1 | M28: =K28*L28 -> 0 | N28: =M28*H28 -> 0 | O28: =M28*J28 -> 0
B29: NU-03 | C29: Digging | D29: መቆፈር | E29: Site preparation | F29: ha | G29: +25% | H29: =H28 -> 33.111111 | I29: =I28*(1+Settings!$C$8) -> 197.56711 | J29: =H29*I29 -> 6541.6667 | K29: =K28 -> 0 | L29: =L28 -> 1 | M29: =K29*L29 -> 0 | N29: =M29*H29 -> 0 | O29: =M29*J29 -> 0
B30: NU-03 | C30: Digging | D30: መቆፈር | E30: Site preparation | F30: ha | G30: +50% | H30: =H28 -> 33.111111 | I30: =I28*(1+Settings!$C$9) -> 237.08054 | J30: =H30*I30 -> 7850 | K30: =K28 -> 0 | L30: =L28 -> 1 | M30: =K30*L30 -> 0 | N30: =M30*H30 -> 0 | O30: =M30*J30 -> 0
B31: NU-03 | C31: Digging | D31: መቆፈር | E31: Site preparation | F31: ha | G31: Expert input | H31: =H28 -> 33.111111 | I31: =I28 -> 158.05369 | J31: =H31*I31 -> 5233.3333 | K31: =K28 -> 0 | L31: =L28 -> 1 | M31: =K31*L31 -> 0 | N31: =M31*H31 -> 0 | O31: =M31*J31 -> 0
B32: NU-03 | C32: Digging | D32: መቆፈር | E32: Site preparation | F32: ha | G32: Chaka Buna plan | H32: =CHOOSE(IF(OR($D$4="Expert input",$J$28=0),4,IF($D$4="+25%",2,IF($D$4="+50%",3,1))),H28,H29,H30,H31) -> 33.111111 | I32: =CHOOSE(IF(OR($D$4="Expert input",$J$28=0),4,IF($D$4="+25%",2,IF($D$4="+50%",3,1))),I28,I29,I30,I31) -> 158.05369 | J32: =H32*I32 -> 5233.3333 | K32: =K28 -> 0 | L32: =CHOOSE(IF(OR($D$4="Expert input",$J$28=0),4,IF($D$4="+25%",2,IF($D$4="+50%",3,1))),L28,L29,L30,L31) -> 1 | M32: =K32*L32 -> 0 | N32: =M32*H32 -> 0 | O32: =M32*J32 -> 0 | Q32: 1 | AB32: =P32*$N32 -> 0 | AC32: =P32*$O32 -> 0 | AD32: =Q32*$N32 -> 0 | AE32: =Q32*$O32 -> 0 | AF32: =R32*$N32 -> 0 | AG32: =R32*$O32 -> 0 | AH32: =S32*$N32 -> 0 | AI32: =S32*$O32 -> 0 | AJ32: =T32*$N32 -> 0 | AK32: =T32*$O32 -> 0 | AL32: =U32*$N32 -> 0 | AM32: =U32*$O32 -> 0 | AN32: =V32*$N32 -> 0 | AO32: =V32*$O32 -> 0 | AP32: =W32*$N32 -> 0 | AQ32: =W32*$O32 -> 0 | AR32: =X32*$N32 -> 0 | AS32: =X32*$O32 -> 0 | AT32: =Y32*$N32 -> 0 | AU32: =Y32*$O32 -> 0 | AV32: =Z32*$N32 -> 0 | AW32: =Z32*$O32 -> 0 | AX32: =AA32*$N32 -> 0 | AY32: =AA32*$O32 -> 0
B33: NU-04 | C33: Trash removal | D33: ጥራጎ ማስወገድ | E33: Site preparation | F33: ha | G33: Industry average | H33: =IFERROR(INDEX('Benchmark Data'!$AC$7:$AC$130,MATCH($B33,'Benchmark Data'!$A$7:$A$130,0)),0) -> 15 | I33: =IFERROR(INDEX('Benchmark Data'!$AD$7:$AD$130,MATCH($B33,'Benchmark Data'!$A$7:$A$130,0)),0) -> 160 | J33: =H33*I33 -> 2400 | K33: =$F$10 -> 0 | L33: =IFERROR(INDEX('Benchmark Data'!$AE$7:$AE$130,MATCH($B33,'Benchmark Data'!$A$7:$A$130,0)),0) -> 1 | M33: =K33*L33 -> 0 | N33: =M33*H33 -> 0 | O33: =M33*J33 -> 0
B34: NU-04 | C34: Trash removal | D34: ጥራጎ ማስወገድ | E34: Site preparation | F34: ha | G34: +25% | H34: =H33 -> 15 | I34: =I33*(1+Settings!$C$8) -> 200 | J34: =H34*I34 -> 3000 | K34: =K33 -> 0 | L34: =L33 -> 1 | M34: =K34*L34 -> 0 | N34: =M34*H34 -> 0 | O34: =M34*J34 -> 0
B35: NU-04 | C35: Trash removal | D35: ጥራጎ ማስወገድ | E35: Site preparation | F35: ha | G35: +50% | H35: =H33 -> 15 | I35: =I33*(1+Settings!$C$9) -> 240 | J35: =H35*I35 -> 3600 | K35: =K33 -> 0 | L35: =L33 -> 1 | M35: =K35*L35 -> 0 | N35: =M35*H35 -> 0 | O35: =M35*J35 -> 0
B36: NU-04 | C36: Trash removal | D36: ጥራጎ ማስወገድ | E36: Site preparation | F36: ha | G36: Expert input | H36: =H33 -> 15 | I36: =I33 -> 160 | J36: =H36*I36 -> 2400 | K36: =K33 -> 0 | L36: =L33 -> 1 | M36: =K36*L36 -> 0 | N36: =M36*H36 -> 0 | O36: =M36*J36 -> 0
B37: NU-04 | C37: Trash removal | D37: ጥራጎ ማስወገድ | E37: Site preparation | F37: ha | G37: Chaka Buna plan | H37: =CHOOSE(IF(OR($D$4="Expert input",$J$33=0),4,IF($D$4="+25%",2,IF($D$4="+50%",3,1))),H33,H34,H35,H36) -> 15 | I37: =CHOOSE(IF(OR($D$4="Expert input",$J$33=0),4,IF($D$4="+25%",2,IF($D$4="+50%",3,1))),I33,I34,I35,I36) -> 160 | J37: =H37*I37 -> 2400 | K37: =K33 -> 0 | L37: =CHOOSE(IF(OR($D$4="Expert input",$J$33=0),4,IF($D$4="+25%",2,IF($D$4="+50%",3,1))),L33,L34,L35,L36) -> 1 | M37: =K37*L37 -> 0 | N37: =M37*H37 -> 0 | O37: =M37*J37 -> 0 | Q37: 1 | AB37: =P37*$N37 -> 0 | AC37: =P37*$O37 -> 0 | AD37: =Q37*$N37 -> 0 | AE37: =Q37*$O37 -> 0 | AF37: =R37*$N37 -> 0 | AG37: =R37*$O37 -> 0 | AH37: =S37*$N37 -> 0 | AI37: =S37*$O37 -> 0 | AJ37: =T37*$N37 -> 0 | AK37: =T37*$O37 -> 0 | AL37: =U37*$N37 -> 0 | AM37: =U37*$O37 -> 0 | AN37: =V37*$N37 -> 0 | AO37: =V37*$O37 -> 0 | AP37: =W37*$N37 -> 0 | AQ37: =W37*$O37 -> 0 | AR37: =X37*$N37 -> 0 | AS37: =X37*$O37 -> 0 | AT37: =Y37*$N37 -> 0 | AU37: =Y37*$O37 -> 0 | AV37: =Z37*$N37 -> 0 | AW37: =Z37*$O37 -> 0 | AX37: =AA37*$N37 -> 0 | AY37: =AA37*$O37 -> 0
B38: NU-05 | C38: Topsoil heaping | D38: ለም አፈር መቆለል | E38: Soil & polytube | F38: m³ | G38: Industry average | H38: =IFERROR(INDEX('Benchmark Data'!$AC$7:$AC$130,MATCH($B38,'Benchmark Data'!$A$7:$A$130,0)),0) -> 0.56666667 | I38: =IFERROR(INDEX('Benchmark Data'!$AD$7:$AD$130,MATCH($B38,'Benchmark Data'!$A$7:$A$130,0)),0) -> 100 | J38: =H38*I38 -> 56.666667 | L38: =IFERROR(INDEX('Benchmark Data'!$AE$7:$AE$130,MATCH($B38,'Benchmark Data'!$A$7:$A$130,0)),0) -> 1 | M38: =K38*L38 -> 0 | N38: =M38*H38 -> 0 | O38: =M38*J38 -> 0
B39: NU-05 | C39: Topsoil heaping | D39: ለም አፈር መቆለል | E39: Soil & polytube | F39: m³ | G39: +25% | H39: =H38 -> 0.56666667 | I39: =I38*(1+Settings!$C$8) -> 125 | J39: =H39*I39 -> 70.833333 | K39: =K38 -> 0 | L39: =L38 -> 1 | M39: =K39*L39 -> 0 | N39: =M39*H39 -> 0 | O39: =M39*J39 -> 0
B40: NU-05 | C40: Topsoil heaping | D40: ለም አፈር መቆለል | E40: Soil & polytube | F40: m³ | G40: +50% | H40: =H38 -> 0.56666667 | I40: =I38*(1+Settings!$C$9) -> 150 | J40: =H40*I40 -> 85 | K40: =K38 -> 0 | L40: =L38 -> 1 | M40: =K40*L40 -> 0 | N40: =M40*H40 -> 0 | O40: =M40*J40 -> 0
B41: NU-05 | C41: Topsoil heaping | D41: ለም አፈር መቆለል | E41: Soil & polytube | F41: m³ | G41: Expert input | H41: =H38 -> 0.56666667 | I41: =I38 -> 100 | J41: =H41*I41 -> 56.666667 | K41: =K38 -> 0 | L41: =L38 -> 1 | M41: =K41*L41 -> 0 | N41: =M41*H41 -> 0 | O41: =M41*J41 -> 0
B42: NU-05 | C42: Topsoil heaping | D42: ለም አፈር መቆለል | E42: Soil & polytube | F42: m³ | G42: Chaka Buna plan | H42: =CHOOSE(IF(OR($D$4="Expert input",$J$38=0),4,IF($D$4="+25%",2,IF($D$4="+50%",3,1))),H38,H39,H40,H41) -> 0.56666667 | I42: =CHOOSE(IF(OR($D$4="Expert input",$J$38=0),4,IF($D$4="+25%",2,IF($D$4="+50%",3,1))),I38,I39,I40,I41) -> 100 | J42: =H42*I42 -> 56.666667 | K42: =K38 -> 0 | L42: =CHOOSE(IF(OR($D$4="Expert input",$J$38=0),4,IF($D$4="+25%",2,IF($D$4="+50%",3,1))),L38,L39,L40,L41) -> 1 | M42: =K42*L42 -> 0 | N42: =M42*H42 -> 0 | O42: =M42*J42 -> 0 | Q42: 0.67 | R42: 0.33 | AB42: =P42*$N42 -> 0 | AC42: =P42*$O42 -> 0 | AD42: =Q42*$N42 -> 0 | AE42: =Q42*$O42 -> 0 | AF42: =R42*$N42 -> 0 | AG42: =R42*$O42 -> 0 | AH42: =S42*$N42 -> 0 | AI42: =S42*$O42 -> 0 | AJ42: =T42*$N42 -> 0 | AK42: =T42*$O42 -> 0 | AL42: =U42*$N42 -> 0 | AM42: =U42*$O42 -> 0 | AN42: =V42*$N42 -> 0 | AO42: =V42*$O42 -> 0 | AP42: =W42*$N42 -> 0 | AQ42: =W42*$O42 -> 0 | AR42: =X42*$N42 -> 0 | AS42: =X42*$O42 -> 0 | AT42: =Y42*$N42 -> 0 | AU42: =Y42*$O42 -> 0 | AV42: =Z42*$N42 -> 0 | AW42: =Z42*$O42 -> 0 | AX42: =AA42*$N42 -> 0 | AY42: =AA42*$O42 -> 0
B43: NU-06 | C43: Topsoil sieving | D43: ለም አፈር ማበጠር | E43: Soil & polytube | F43: m³ | G43: Industry average | H43: =IFERROR(INDEX('Benchmark Data'!$AC$7:$AC$130,MATCH($B43,'Benchmark Data'!$A$7:$A$130,0)),0) -> 0.5 | I43: =IFERROR(INDEX('Benchmark Data'!$AD$7:$AD$130,MATCH($B43,'Benchmark Data'!$A$7:$A$130,0)),0) -> 100 | J43: =H43*I43 -> 50 | L43: =IFERROR(INDEX('Benchmark Data'!$AE$7:$AE$130,MATCH($B43,'Benchmark Data'!$A$7:$A$130,0)),0) -> 1 | M43: =K43*L43 -> 0 | N43: =M43*H43 -> 0 | O43: =M43*J43 -> 0
B44: NU-06 | C44: Topsoil sieving | D44: ለም አፈር ማበጠር | E44: Soil & polytube | F44: m³ | G44: +25% | H44: =H43 -> 0.5 | I44: =I43*(1+Settings!$C$8) -> 125 | J44: =H44*I44 -> 62.5 | K44: =K43 -> 0 | L44: =L43 -> 1 | M44: =K44*L44 -> 0 | N44: =M44*H44 -> 0 | O44: =M44*J44 -> 0
B45: NU-06 | C45: Topsoil sieving | D45: ለም አፈር ማበጠር | E45: Soil & polytube | F45: m³ | G45: +50% | H45: =H43 -> 0.5 | I45: =I43*(1+Settings!$C$9) -> 150 | J45: =H45*I45 -> 75 | K45: =K43 -> 0 | L45: =L43 -> 1 | M45: =K45*L45 -> 0 | N45: =M45*H45 -> 0 | O45: =M45*J45 -> 0
B46: NU-06 | C46: Topsoil sieving | D46: ለም አፈር ማበጠር | E46: Soil & polytube | F46: m³ | G46: Expert input | H46: =H43 -> 0.5 | I46: =I43 -> 100 | J46: =H46*I46 -> 50 | K46: =K43 -> 0 | L46: =L43 -> 1 | M46: =K46*L46 -> 0 | N46: =M46*H46 -> 0 | O46: =M46*J46 -> 0
B47: NU-06 | C47: Topsoil sieving | D47: ለም አፈር ማበጠር | E47: Soil & polytube | F47: m³ | G47: Chaka Buna plan | H47: =CHOOSE(IF(OR($D$4="Expert input",$J$43=0),4,IF($D$4="+25%",2,IF($D$4="+50%",3,1))),H43,H44,H45,H46) -> 0.5 | I47: =CHOOSE(IF(OR($D$4="Expert input",$J$43=0),4,IF($D$4="+25%",2,IF($D$4="+50%",3,1))),I43,I44,I45,I46) -> 100 | J47: =H47*I47 -> 50 | K47: =K43 -> 0 | L47: =CHOOSE(IF(OR($D$4="Expert input",$J$43=0),4,IF($D$4="+25%",2,IF($D$4="+50%",3,1))),L43,L44,L45,L46) -> 1 | M47: =K47*L47 -> 0 | N47: =M47*H47 -> 0 | O47: =M47*J47 -> 0 | Q47: 1 | AB47: =P47*$N47 -> 0 | AC47: =P47*$O47 -> 0 | AD47: =Q47*$N47 -> 0 | AE47: =Q47*$O47 -> 0 | AF47: =R47*$N47 -> 0 | AG47: =R47*$O47 -> 0 | AH47: =S47*$N47 -> 0 | AI47: =S47*$O47 -> 0 | AJ47: =T47*$N47 -> 0 | AK47: =T47*$O47 -> 0 | AL47: =U47*$N47 -> 0 | AM47: =U47*$O47 -> 0 | AN47: =V47*$N47 -> 0 | AO47: =V47*$O47 -> 0 | AP47: =W47*$N47 -> 0 | AQ47: =W47*$O47 -> 0 | AR47: =X47*$N47 -> 0 | AS47: =X47*$O47 -> 0 | AT47: =Y47*$N47 -> 0 | AU47: =Y47*$O47 -> 0 | AV47: =Z47*$N47 -> 0 | AW47: =Z47*$O47 -> 0 | AX47: =AA47*$N47 -> 0 | AY47: =AA47*$O47 -> 0
B48: NU-07 | C48: Polytube cutting | D48: ፖሊ ቲዩብ ቆረጣ | E48: Soil & polytube | F48: kg | G48: Industry average | H48: =IFERROR(INDEX('Benchmark Data'!$AC$7:$AC$130,MATCH($B48,'Benchmark Data'!$A$7:$A$130,0)),0) -> 0.10833333 | I48: =IFERROR(INDEX('Benchmark Data'!$AD$7:$AD$130,MATCH($B48,'Benchmark Data'!$A$7:$A$130,0)),0) -> 138.46154 | J48: =H48*I48 -> 15 | L48: =IFERROR(INDEX('Benchmark Data'!$AE$7:$AE$130,MATCH($B48,'Benchmark Data'!$A$7:$A$130,0)),0) -> 1 | M48: =K48*L48 -> 0 | N48: =M48*H48 -> 0 | O48: =M48*J48 -> 0
B49: NU-07 | C49: Polytube cutting | D49: ፖሊ ቲዩብ ቆረጣ | E49: Soil & polytube | F49: kg | G49: +25% | H49: =H48 -> 0.10833333 | I49: =I48*(1+Settings!$C$8) -> 173.07692 | J49: =H49*I49 -> 18.75 | K49: =K48 -> 0 | L49: =L48 -> 1 | M49: =K49*L49 -> 0 | N49: =M49*H49 -> 0 | O49: =M49*J49 -> 0
B50: NU-07 | C50: Polytube cutting | D50: ፖሊ ቲዩብ ቆረጣ | E50: Soil & polytube | F50: kg | G50: +50% | H50: =H48 -> 0.10833333 | I50: =I48*(1+Settings!$C$9) -> 207.69231 | J50: =H50*I50 -> 22.5 | K50: =K48 -> 0 | L50: =L48 -> 1 | M50: =K50*L50 -> 0 | N50: =M50*H50 -> 0 | O50: =M50*J50 -> 0
B51: NU-07 | C51: Polytube cutting | D51: ፖሊ ቲዩብ ቆረጣ | E51: Soil & polytube | F51: kg | G51: Expert input | H51: =H48 -> 0.10833333 | I51: =I48 -> 138.46154 | J51: =H51*I51 -> 15 | K51: =K48 -> 0 | L51: =L48 -> 1 | M51: =K51*L51 -> 0 | N51: =M51*H51 -> 0 | O51: =M51*J51 -> 0
B52: NU-07 | C52: Polytube cutting | D52: ፖሊ ቲዩብ ቆረጣ | E52: Soil & polytube | F52: kg | G52: Chaka Buna plan | H52: =CHOOSE(IF(OR($D$4="Expert input",$J$48=0),4,IF($D$4="+25%",2,IF($D$4="+50%",3,1))),H48,H49,H50,H51) -> 0.10833333 | I52: =CHOOSE(IF(OR($D$4="Expert input",$J$48=0),4,IF($D$4="+25%",2,IF($D$4="+50%",3,1))),I48,I49,I50,I51) -> 138.46154 | J52: =H52*I52 -> 15 | K52: =K48 -> 0 | L52: =CHOOSE(IF(OR($D$4="Expert input",$J$48=0),4,IF($D$4="+25%",2,IF($D$4="+50%",3,1))),L48,L49,L50,L51) -> 1 | M52: =K52*L52 -> 0 | N52: =M52*H52 -> 0 | O52: =M52*J52 -> 0 | R52: 0.67 | S52: 0.33 | AB52: =P52*$N52 -> 0 | AC52: =P52*$O52 -> 0 | AD52: =Q52*$N52 -> 0 | AE52: =Q52*$O52 -> 0 | AF52: =R52*$N52 -> 0 | AG52: =R52*$O52 -> 0 | AH52: =S52*$N52 -> 0 | AI52: =S52*$O52 -> 0 | AJ52: =T52*$N52 -> 0 | AK52: =T52*$O52 -> 0 | AL52: =U52*$N52 -> 0 | AM52: =U52*$O52 -> 0 | AN52: =V52*$N52 -> 0 | AO52: =V52*$O52 -> 0 | AP52: =W52*$N52 -> 0 | AQ52: =W52*$O52 -> 0 | AR52: =X52*$N52 -> 0 | AS52: =X52*$O52 -> 0 | AT52: =Y52*$N52 -> 0 | AU52: =Y52*$O52 -> 0 | AV52: =Z52*$N52 -> 0 | AW52: =Z52*$O52 -> 0 | AX52: =AA52*$N52 -> 0 | AY52: =AA52*$O52 -> 0
B53: NU-08 | C53: Polytube filling | D53: ፖሊቲዩብ ጥቅጣቆ | E53: Soil & polytube | F53: polytube | G53: Industry average | H53: =IFERROR(INDEX('Benchmark Data'!$AC$7:$AC$130,MATCH($B53,'Benchmark Data'!$A$7:$A$130,0)),0) -> 0.005 | I53: =IFERROR(INDEX('Benchmark Data'!$AD$7:$AD$130,MATCH($B53,'Benchmark Data'!$A$7:$A$130,0)),0) -> 186.66667 | J53: =H53*I53 -> 0.93333333 | K53: =$F$9 -> 0 | L53: =IFERROR(INDEX('Benchmark Data'!$AE$7:$AE$130,MATCH($B53,'Benchmark Data'!$A$7:$A$130,0)),0) -> 1 | M53: =K53*L53 -> 0 | N53: =M53*H53 -> 0 | O53: =M53*J53 -> 0
B54: NU-08 | C54: Polytube filling | D54: ፖሊቲዩብ ጥቅጣቆ | E54: Soil & polytube | F54: polytube | G54: +25% | H54: =H53 -> 0.005 | I54: =I53*(1+Settings!$C$8) -> 233.33333 | J54: =H54*I54 -> 1.1666667 | K54: =K53 -> 0 | L54: =L53 -> 1 | M54: =K54*L54 -> 0 | N54: =M54*H54 -> 0 | O54: =M54*J54 -> 0
B55: NU-08 | C55: Polytube filling | D55: ፖሊቲዩብ ጥቅጣቆ | E55: Soil & polytube | F55: polytube | G55: +50% | H55: =H53 -> 0.005 | I55: =I53*(1+Settings!$C$9) -> 280 | J55: =H55*I55 -> 1.4 | K55: =K53 -> 0 | L55: =L53 -> 1 | M55: =K55*L55 -> 0 | N55: =M55*H55 -> 0 | O55: =M55*J55 -> 0
B56: NU-08 | C56: Polytube filling | D56: ፖሊቲዩብ ጥቅጣቆ | E56: Soil & polytube | F56: polytube | G56: Expert input | H56: =H53 -> 0.005 | I56: =I53 -> 186.66667 | J56: =H56*I56 -> 0.93333333 | K56: =K53 -> 0 | L56: =L53 -> 1 | M56: =K56*L56 -> 0 | N56: =M56*H56 -> 0 | O56: =M56*J56 -> 0
B57: NU-08 | C57: Polytube filling | D57: ፖሊቲዩብ ጥቅጣቆ | E57: Soil & polytube | F57: polytube | G57: Chaka Buna plan | H57: =CHOOSE(IF(OR($D$4="Expert input",$J$53=0),4,IF($D$4="+25%",2,IF($D$4="+50%",3,1))),H53,H54,H55,H56) -> 0.005 | I57: =CHOOSE(IF(OR($D$4="Expert input",$J$53=0),4,IF($D$4="+25%",2,IF($D$4="+50%",3,1))),I53,I54,I55,I56) -> 186.66667 | J57: =H57*I57 -> 0.93333333 | K57: =K53 -> 0 | L57: =CHOOSE(IF(OR($D$4="Expert input",$J$53=0),4,IF($D$4="+25%",2,IF($D$4="+50%",3,1))),L53,L54,L55,L56) -> 1 | M57: =K57*L57 -> 0 | N57: =M57*H57 -> 0 | O57: =M57*J57 -> 0 | R57: 0.66 | S57: 0.17 | T57: 0.17 | AB57: =P57*$N57 -> 0 | AC57: =P57*$O57 -> 0 | AD57: =Q57*$N57 -> 0 | AE57: =Q57*$O57 -> 0 | AF57: =R57*$N57 -> 0 | AG57: =R57*$O57 -> 0 | AH57: =S57*$N57 -> 0 | AI57: =S57*$O57 -> 0 | AJ57: =T57*$N57 -> 0 | AK57: =T57*$O57 -> 0 | AL57: =U57*$N57 -> 0 | AM57: =U57*$O57 -> 0 | AN57: =V57*$N57 -> 0 | AO57: =V57*$O57 -> 0 | AP57: =W57*$N57 -> 0 | AQ57: =W57*$O57 -> 0 | AR57: =X57*$N57 -> 0 | AS57: =X57*$O57 -> 0 | AT57: =Y57*$N57 -> 0 | AU57: =Y57*$O57 -> 0 | AV57: =Z57*$N57 -> 0 | AW57: =Z57*$O57 -> 0 | AX57: =AA57*$N57 -> 0 | AY57: =AA57*$O57 -> 0
B58: NU-09 | C58: Polytube transport | D58: ፖሊ ማጓጓዝ | E58: Soil & polytube | F58: polytube | G58: Industry average | H58: =IFERROR(INDEX('Benchmark Data'!$AC$7:$AC$130,MATCH($B58,'Benchmark Data'!$A$7:$A$130,0)),0) -> 0.0055555556 | I58: =IFERROR(INDEX('Benchmark Data'!$AD$7:$AD$130,MATCH($B58,'Benchmark Data'!$A$7:$A$130,0)),0) -> 180 | J58: =H58*I58 -> 1 | K58: =$F$9 -> 0 | L58: =IFERROR(INDEX('Benchmark Data'!$AE$7:$AE$130,MATCH($B58,'Benchmark Data'!$A$7:$A$130,0)),0) -> 1 | M58: =K58*L58 -> 0 | N58: =M58*H58 -> 0 | O58: =M58*J58 -> 0
B59: NU-09 | C59: Polytube transport | D59: ፖሊ ማጓጓዝ | E59: Soil & polytube | F59: polytube | G59: +25% | H59: =H58 -> 0.0055555556 | I59: =I58*(1+Settings!$C$8) -> 225 | J59: =H59*I59 -> 1.25 | K59: =K58 -> 0 | L59: =L58 -> 1 | M59: =K59*L59 -> 0 | N59: =M59*H59 -> 0 | O59: =M59*J59 -> 0
B60: NU-09 | C60: Polytube transport | D60: ፖሊ ማጓጓዝ | E60: Soil & polytube | F60: polytube | G60: +50% | H60: =H58 -> 0.0055555556 | I60: =I58*(1+Settings!$C$9) -> 270 | J60: =H60*I60 -> 1.5 | K60: =K58 -> 0 | L60: =L58 -> 1 | M60: =K60*L60 -> 0 | N60: =M60*H60 -> 0 | O60: =M60*J60 -> 0
B61: NU-09 | C61: Polytube transport | D61: ፖሊ ማጓጓዝ | E61: Soil & polytube | F61: polytube | G61: Expert input | H61: =H58 -> 0.0055555556 | I61: =I58 -> 180 | J61: =H61*I61 -> 1 | K61: =K58 -> 0 | L61: =L58 -> 1 | M61: =K61*L61 -> 0 | N61: =M61*H61 -> 0 | O61: =M61*J61 -> 0
B62: NU-09 | C62: Polytube transport | D62: ፖሊ ማጓጓዝ | E62: Soil & polytube | F62: polytube | G62: Chaka Buna plan | H62: =CHOOSE(IF(OR($D$4="Expert input",$J$58=0),4,IF($D$4="+25%",2,IF($D$4="+50%",3,1))),H58,H59,H60,H61) -> 0.0055555556 | I62: =CHOOSE(IF(OR($D$4="Expert input",$J$58=0),4,IF($D$4="+25%",2,IF($D$4="+50%",3,1))),I58,I59,I60,I61) -> 180 | J62: =H62*I62 -> 1 | K62: =K58 -> 0 | L62: =CHOOSE(IF(OR($D$4="Expert input",$J$58=0),4,IF($D$4="+25%",2,IF($D$4="+50%",3,1))),L58,L59,L60,L61) -> 1 | M62: =K62*L62 -> 0 | N62: =M62*H62 -> 0 | O62: =M62*J62 -> 0 | R62: 0.33 | S62: 0.5 | T62: 0.17 | AB62: =P62*$N62 -> 0 | AC62: =P62*$O62 -> 0 | AD62: =Q62*$N62 -> 0 | AE62: =Q62*$O62 -> 0 | AF62: =R62*$N62 -> 0 | AG62: =R62*$O62 -> 0 | AH62: =S62*$N62 -> 0 | AI62: =S62*$O62 -> 0 | AJ62: =T62*$N62 -> 0 | AK62: =T62*$O62 -> 0 | AL62: =U62*$N62 -> 0 | AM62: =U62*$O62 -> 0 | AN62: =V62*$N62 -> 0 | AO62: =V62*$O62 -> 0 | AP62: =W62*$N62 -> 0 | AQ62: =W62*$O62 -> 0 | AR62: =X62*$N62 -> 0 | AS62: =X62*$O62 -> 0 | AT62: =Y62*$N62 -> 0 | AU62: =Y62*$O62 -> 0 | AV62: =Z62*$N62 -> 0 | AW62: =Z62*$O62 -> 0 | AX62: =AA62*$N62 -> 0 | AY62: =AA62*$O62 -> 0
B63: NU-10 | C63: Polytube arranging | D63: ፖሊ ድርዳሮ | E63: Soil & polytube | F63: bed | G63: Industry average | H63: =IFERROR(INDEX('Benchmark Data'!$AC$7:$AC$130,MATCH($B63,'Benchmark Data'!$A$7:$A$130,0)),0) -> 1 | I63: =IFERROR(INDEX('Benchmark Data'!$AD$7:$AD$130,MATCH($B63,'Benchmark Data'!$A$7:$A$130,0)),0) -> 200 | J63: =H63*I63 -> 200 | K63: =$F$12 -> 0 | L63: =IFERROR(INDEX('Benchmark Data'!$AE$7:$AE$130,MATCH($B63,'Benchmark Data'!$A$7:$A$130,0)),0) -> 1 | M63: =K63*L63 -> 0 | N63: =M63*H63 -> 0 | O63: =M63*J63 -> 0
B64: NU-10 | C64: Polytube arranging | D64: ፖሊ ድርዳሮ | E64: Soil & polytube | F64: bed | G64: +25% | H64: =H63 -> 1 | I64: =I63*(1+Settings!$C$8) -> 250 | J64: =H64*I64 -> 250 | K64: =K63 -> 0 | L64: =L63 -> 1 | M64: =K64*L64 -> 0 | N64: =M64*H64 -> 0 | O64: =M64*J64 -> 0
B65: NU-10 | C65: Polytube arranging | D65: ፖሊ ድርዳሮ | E65: Soil & polytube | F65: bed | G65: +50% | H65: =H63 -> 1 | I65: =I63*(1+Settings!$C$9) -> 300 | J65: =H65*I65 -> 300 | K65: =K63 -> 0 | L65: =L63 -> 1 | M65: =K65*L65 -> 0 | N65: =M65*H65 -> 0 | O65: =M65*J65 -> 0
B66: NU-10 | C66: Polytube arranging | D66: ፖሊ ድርዳሮ | E66: Soil & polytube | F66: bed | G66: Expert input | H66: =H63 -> 1 | I66: =I63 -> 200 | J66: =H66*I66 -> 200 | K66: =K63 -> 0 | L66: =L63 -> 1 | M66: =K66*L66 -> 0 | N66: =M66*H66 -> 0 | O66: =M66*J66 -> 0
B67: NU-10 | C67: Polytube arranging | D67: ፖሊ ድርዳሮ | E67: Soil & polytube | F67: bed | G67: Chaka Buna plan | H67: =CHOOSE(IF(OR($D$4="Expert input",$J$63=0),4,IF($D$4="+25%",2,IF($D$4="+50%",3,1))),H63,H64,H65,H66) -> 1 | I67: =CHOOSE(IF(OR($D$4="Expert input",$J$63=0),4,IF($D$4="+25%",2,IF($D$4="+50%",3,1))),I63,I64,I65,I66) -> 200 | J67: =H67*I67 -> 200 | K67: =K63 -> 0 | L67: =CHOOSE(IF(OR($D$4="Expert input",$J$63=0),4,IF($D$4="+25%",2,IF($D$4="+50%",3,1))),L63,L64,L65,L66) -> 1 | M67: =K67*L67 -> 0 | N67: =M67*H67 -> 0 | O67: =M67*J67 -> 0 | S67: 0.67 | T67: 0.33 | AB67: =P67*$N67 -> 0 | AC67: =P67*$O67 -> 0 | AD67: =Q67*$N67 -> 0 | AE67: =Q67*$O67 -> 0 | AF67: =R67*$N67 -> 0 | AG67: =R67*$O67 -> 0 | AH67: =S67*$N67 -> 0 | AI67: =S67*$O67 -> 0 | AJ67: =T67*$N67 -> 0 | AK67: =T67*$O67 -> 0 | AL67: =U67*$N67 -> 0 | AM67: =U67*$O67 -> 0 | AN67: =V67*$N67 -> 0 | AO67: =V67*$O67 -> 0 | AP67: =W67*$N67 -> 0 | AQ67: =W67*$O67 -> 0 | AR67: =X67*$N67 -> 0 | AS67: =X67*$O67 -> 0 | AT67: =Y67*$N67 -> 0 | AU67: =Y67*$O67 -> 0 | AV67: =Z67*$N67 -> 0 | AW67: =Z67*$O67 -> 0 | AX67: =AA67*$N67 -> 0 | AY67: =AA67*$O67 -> 0
B68: NU-11 | C68: Seedbed preparation | D68: መደብ ዝግጅት | E68: Seedbed & sowing | F68: bed | G68: Industry average | H68: =IFERROR(INDEX('Benchmark Data'!$AC$7:$AC$130,MATCH($B68,'Benchmark Data'!$A$7:$A$130,0)),0) -> 1.1666667 | I68: =IFERROR(INDEX('Benchmark Data'!$AD$7:$AD$130,MATCH($B68,'Benchmark Data'!$A$7:$A$130,0)),0) -> 200 | J68: =H68*I68 -> 233.33333 | K68: =$F$11 -> 0 | L68: =IFERROR(INDEX('Benchmark Data'!$AE$7:$AE$130,MATCH($B68,'Benchmark Data'!$A$7:$A$130,0)),0) -> 1 | M68: =K68*L68 -> 0 | N68: =M68*H68 -> 0 | O68: =M68*J68 -> 0
B69: NU-11 | C69: Seedbed preparation | D69: መደብ ዝግጅት | E69: Seedbed & sowing | F69: bed | G69: +25% | H69: =H68 -> 1.1666667 | I69: =I68*(1+Settings!$C$8) -> 250 | J69: =H69*I69 -> 291.66667 | K69: =K68 -> 0 | L69: =L68 -> 1 | M69: =K69*L69 -> 0 | N69: =M69*H69 -> 0 | O69: =M69*J69 -> 0
B70: NU-11 | C70: Seedbed preparation | D70: መደብ ዝግጅት | E70: Seedbed & sowing | F70: bed | G70: +50% | H70: =H68 -> 1.1666667 | I70: =I68*(1+Settings!$C$9) -> 300 | J70: =H70*I70 -> 350 | K70: =K68 -> 0 | L70: =L68 -> 1 | M70: =K70*L70 -> 0 | N70: =M70*H70 -> 0 | O70: =M70*J70 -> 0
B71: NU-11 | C71: Seedbed preparation | D71: መደብ ዝግጅት | E71: Seedbed & sowing | F71: bed | G71: Expert input | H71: =H68 -> 1.1666667 | I71: =I68 -> 200 | J71: =H71*I71 -> 233.33333 | K71: =K68 -> 0 | L71: =L68 -> 1 | M71: =K71*L71 -> 0 | N71: =M71*H71 -> 0 | O71: =M71*J71 -> 0
B72: NU-11 | C72: Seedbed preparation | D72: መደብ ዝግጅት | E72: Seedbed & sowing | F72: bed | G72: Chaka Buna plan | H72: =CHOOSE(IF(OR($D$4="Expert input",$J$68=0),4,IF($D$4="+25%",2,IF($D$4="+50%",3,1))),H68,H69,H70,H71) -> 1.1666667 | I72: =CHOOSE(IF(OR($D$4="Expert input",$J$68=0),4,IF($D$4="+25%",2,IF($D$4="+50%",3,1))),I68,I69,I70,I71) -> 200 | J72: =H72*I72 -> 233.33333 | K72: =K68 -> 0 | L72: =CHOOSE(IF(OR($D$4="Expert input",$J$68=0),4,IF($D$4="+25%",2,IF($D$4="+50%",3,1))),L68,L69,L70,L71) -> 1 | M72: =K72*L72 -> 0 | N72: =M72*H72 -> 0 | O72: =M72*J72 -> 0 | Q72: 0.33 | R72: 0.67 | AB72: =P72*$N72 -> 0 | AC72: =P72*$O72 -> 0 | AD72: =Q72*$N72 -> 0 | AE72: =Q72*$O72 -> 0 | AF72: =R72*$N72 -> 0 | AG72: =R72*$O72 -> 0 | AH72: =S72*$N72 -> 0 | AI72: =S72*$O72 -> 0 | AJ72: =T72*$N72 -> 0 | AK72: =T72*$O72 -> 0 | AL72: =U72*$N72 -> 0 | AM72: =U72*$O72 -> 0 | AN72: =V72*$N72 -> 0 | AO72: =V72*$O72 -> 0 | AP72: =W72*$N72 -> 0 | AQ72: =W72*$O72 -> 0 | AR72: =X72*$N72 -> 0 | AS72: =X72*$O72 -> 0 | AT72: =Y72*$N72 -> 0 | AU72: =Y72*$O72 -> 0 | AV72: =Z72*$N72 -> 0 | AW72: =Z72*$O72 -> 0 | AX72: =AA72*$N72 -> 0 | AY72: =AA72*$O72 -> 0
B73: NU-12 | C73: Pre-watering seedbed | D73: ቅድመ ዘር ዉኃ ማጠጣት | E73: Seedbed & sowing | F73: bed | G73: Industry average | H73: =IFERROR(INDEX('Benchmark Data'!$AC$7:$AC$130,MATCH($B73,'Benchmark Data'!$A$7:$A$130,0)),0) -> 0.91666667 | I73: =IFERROR(INDEX('Benchmark Data'!$AD$7:$AD$130,MATCH($B73,'Benchmark Data'!$A$7:$A$130,0)),0) -> 47.272727 | J73: =H73*I73 -> 43.333333 | K73: =$F$11 -> 0 | L73: =IFERROR(INDEX('Benchmark Data'!$AE$7:$AE$130,MATCH($B73,'Benchmark Data'!$A$7:$A$130,0)),0) -> 2 | M73: =K73*L73 -> 0 | N73: =M73*H73 -> 0 | O73: =M73*J73 -> 0
B74: NU-12 | C74: Pre-watering seedbed | D74: ቅድመ ዘር ዉኃ ማጠጣት | E74: Seedbed & sowing | F74: bed | G74: +25% | H74: =H73 -> 0.91666667 | I74: =I73*(1+Settings!$C$8) -> 59.090909 | J74: =H74*I74 -> 54.166667 | K74: =K73 -> 0 | L74: =L73 -> 2 | M74: =K74*L74 -> 0 | N74: =M74*H74 -> 0 | O74: =M74*J74 -> 0
B75: NU-12 | C75: Pre-watering seedbed | D75: ቅድመ ዘር ዉኃ ማጠጣት | E75: Seedbed & sowing | F75: bed | G75: +50% | H75: =H73 -> 0.91666667 | I75: =I73*(1+Settings!$C$9) -> 70.909091 | J75: =H75*I75 -> 65 | K75: =K73 -> 0 | L75: =L73 -> 2 | M75: =K75*L75 -> 0 | N75: =M75*H75 -> 0 | O75: =M75*J75 -> 0
B76: NU-12 | C76: Pre-watering seedbed | D76: ቅድመ ዘር ዉኃ ማጠጣት | E76: Seedbed & sowing | F76: bed | G76: Expert input | H76: =H73 -> 0.91666667 | I76: =I73 -> 47.272727 | J76: =H76*I76 -> 43.333333 | K76: =K73 -> 0 | L76: =L73 -> 2 | M76: =K76*L76 -> 0 | N76: =M76*H76 -> 0 | O76: =M76*J76 -> 0
B77: NU-12 | C77: Pre-watering seedbed | D77: ቅድመ ዘር ዉኃ ማጠጣት | E77: Seedbed & sowing | F77: bed | G77: Chaka Buna plan | H77: =CHOOSE(IF(OR($D$4="Expert input",$J$73=0),4,IF($D$4="+25%",2,IF($D$4="+50%",3,1))),H73,H74,H75,H76) -> 0.91666667 | I77: =CHOOSE(IF(OR($D$4="Expert input",$J$73=0),4,IF($D$4="+25%",2,IF($D$4="+50%",3,1))),I73,I74,I75,I76) -> 47.272727 | J77: =H77*I77 -> 43.333333 | K77: =K73 -> 0 | L77: =CHOOSE(IF(OR($D$4="Expert input",$J$73=0),4,IF($D$4="+25%",2,IF($D$4="+50%",3,1))),L73,L74,L75,L76) -> 2 | M77: =K77*L77 -> 0 | N77: =M77*H77 -> 0 | O77: =M77*J77 -> 0 | Q77: 0.17 | R77: 0.83 | AB77: =P77*$N77 -> 0 | AC77: =P77*$O77 -> 0 | AD77: =Q77*$N77 -> 0 | AE77: =Q77*$O77 -> 0 | AF77: =R77*$N77 -> 0 | AG77: =R77*$O77 -> 0 | AH77: =S77*$N77 -> 0 | AI77: =S77*$O77 -> 0 | AJ77: =T77*$N77 -> 0 | AK77: =T77*$O77 -> 0 | AL77: =U77*$N77 -> 0 | AM77: =U77*$O77 -> 0 | AN77: =V77*$N77 -> 0 | AO77: =V77*$O77 -> 0 | AP77: =W77*$N77 -> 0 | AQ77: =W77*$O77 -> 0 | AR77: =X77*$N77 -> 0 | AS77: =X77*$O77 -> 0 | AT77: =Y77*$N77 -> 0 | AU77: =Y77*$O77 -> 0 | AV77: =Z77*$N77 -> 0 | AW77: =Z77*$O77 -> 0 | AX77: =AA77*$N77 -> 0 | AY77: =AA77*$O77 -> 0
B78: NU-13 | C78: Sowing seed | D78: ዘር ማፍሰስ | E78: Seedbed & sowing | F78: bed | G78: Industry average | H78: =IFERROR(INDEX('Benchmark Data'!$AC$7:$AC$130,MATCH($B78,'Benchmark Data'!$A$7:$A$130,0)),0) -> 2.3333333 | I78: =IFERROR(INDEX('Benchmark Data'!$AD$7:$AD$130,MATCH($B78,'Benchmark Data'!$A$7:$A$130,0)),0) -> 100 | J78: =H78*I78 -> 233.33333 | K78: =$F$11 -> 0 | L78: =IFERROR(INDEX('Benchmark Data'!$AE$7:$AE$130,MATCH($B78,'Benchmark Data'!$A$7:$A$130,0)),0) -> 1 | M78: =K78*L78 -> 0 | N78: =M78*H78 -> 0 | O78: =M78*J78 -> 0
B79: NU-13 | C79: Sowing seed | D79: ዘር ማፍሰስ | E79: Seedbed & sowing | F79: bed | G79: +25% | H79: =H78 -> 2.3333333 | I79: =I78*(1+Settings!$C$8) -> 125 | J79: =H79*I79 -> 291.66667 | K79: =K78 -> 0 | L79: =L78 -> 1 | M79: =K79*L79 -> 0 | N79: =M79*H79 -> 0 | O79: =M79*J79 -> 0
B80: NU-13 | C80: Sowing seed | D80: ዘር ማፍሰስ | E80: Seedbed & sowing | F80: bed | G80: +50% | H80: =H78 -> 2.3333333 | I80: =I78*(1+Settings!$C$9) -> 150 | J80: =H80*I80 -> 350 | K80: =K78 -> 0 | L80: =L78 -> 1 | M80: =K80*L80 -> 0 | N80: =M80*H80 -> 0 | O80: =M80*J80 -> 0
B81: NU-13 | C81: Sowing seed | D81: ዘር ማፍሰስ | E81: Seedbed & sowing | F81: bed | G81: Expert input | H81: =H78 -> 2.3333333 | I81: =I78 -> 100 | J81: =H81*I81 -> 233.33333 | K81: =K78 -> 0 | L81: =L78 -> 1 | M81: =K81*L81 -> 0 | N81: =M81*H81 -> 0 | O81: =M81*J81 -> 0
B82: NU-13 | C82: Sowing seed | D82: ዘር ማፍሰስ | E82: Seedbed & sowing | F82: bed | G82: Chaka Buna plan | H82: =CHOOSE(IF(OR($D$4="Expert input",$J$78=0),4,IF($D$4="+25%",2,IF($D$4="+50%",3,1))),H78,H79,H80,H81) -> 2.3333333 | I82: =CHOOSE(IF(OR($D$4="Expert input",$J$78=0),4,IF($D$4="+25%",2,IF($D$4="+50%",3,1))),I78,I79,I80,I81) -> 100 | J82: =H82*I82 -> 233.33333 | K82: =K78 -> 0 | L82: =CHOOSE(IF(OR($D$4="Expert input",$J$78=0),4,IF($D$4="+25%",2,IF($D$4="+50%",3,1))),L78,L79,L80,L81) -> 1 | M82: =K82*L82 -> 0 | N82: =M82*H82 -> 0 | O82: =M82*J82 -> 0 | R82: 1 | AB82: =P82*$N82 -> 0 | AC82: =P82*$O82 -> 0 | AD82: =Q82*$N82 -> 0 | AE82: =Q82*$O82 -> 0 | AF82: =R82*$N82 -> 0 | AG82: =R82*$O82 -> 0 | AH82: =S82*$N82 -> 0 | AI82: =S82*$O82 -> 0 | AJ82: =T82*$N82 -> 0 | AK82: =T82*$O82 -> 0 | AL82: =U82*$N82 -> 0 | AM82: =U82*$O82 -> 0 | AN82: =V82*$N82 -> 0 | AO82: =V82*$O82 -> 0 | AP82: =W82*$N82 -> 0 | AQ82: =W82*$O82 -> 0 | AR82: =X82*$N82 -> 0 | AS82: =X82*$O82 -> 0 | AT82: =Y82*$N82 -> 0 | AU82: =Y82*$O82 -> 0 | AV82: =Z82*$N82 -> 0 | AW82: =Z82*$O82 -> 0 | AX82: =AA82*$N82 -> 0 | AY82: =AA82*$O82 -> 0
B83: NU-14 | C83: Mulch material preparation & transport | D83: ጉዝጓዝ ዝግጅት እና ማጓጓዝ | E83: Seedbed & sowing | F83: load | G83: Industry average | H83: =IFERROR(INDEX('Benchmark Data'!$AC$7:$AC$130,MATCH($B83,'Benchmark Data'!$A$7:$A$130,0)),0) -> 0.8 | I83: =IFERROR(INDEX('Benchmark Data'!$AD$7:$AD$130,MATCH($B83,'Benchmark Data'!$A$7:$A$130,0)),0) -> 100 | J83: =H83*I83 -> 80 | L83: =IFERROR(INDEX('Benchmark Data'!$AE$7:$AE$130,MATCH($B83,'Benchmark Data'!$A$7:$A$130,0)),0) -> 2 | M83: =K83*L83 -> 0 | N83: =M83*H83 -> 0 | O83: =M83*J83 -> 0
B84: NU-14 | C84: Mulch material preparation & transport | D84: ጉዝጓዝ ዝግጅት እና ማጓጓዝ | E84: Seedbed & sowing | F84: load | G84: +25% | H84: =H83 -> 0.8 | I84: =I83*(1+Settings!$C$8) -> 125 | J84: =H84*I84 -> 100 | K84: =K83 -> 0 | L84: =L83 -> 2 | M84: =K84*L84 -> 0 | N84: =M84*H84 -> 0 | O84: =M84*J84 -> 0
B85: NU-14 | C85: Mulch material preparation & transport | D85: ጉዝጓዝ ዝግጅት እና ማጓጓዝ | E85: Seedbed & sowing | F85: load | G85: +50% | H85: =H83 -> 0.8 | I85: =I83*(1+Settings!$C$9) -> 150 | J85: =H85*I85 -> 120 | K85: =K83 -> 0 | L85: =L83 -> 2 | M85: =K85*L85 -> 0 | N85: =M85*H85 -> 0 | O85: =M85*J85 -> 0
B86: NU-14 | C86: Mulch material preparation & transport | D86: ጉዝጓዝ ዝግጅት እና ማጓጓዝ | E86: Seedbed & sowing | F86: load | G86: Expert input | H86: =H83 -> 0.8 | I86: =I83 -> 100 | J86: =H86*I86 -> 80 | K86: =K83 -> 0 | L86: =L83 -> 2 | M86: =K86*L86 -> 0 | N86: =M86*H86 -> 0 | O86: =M86*J86 -> 0
B87: NU-14 | C87: Mulch material preparation & transport | D87: ጉዝጓዝ ዝግጅት እና ማጓጓዝ | E87: Seedbed & sowing | F87: load | G87: Chaka Buna plan | H87: =CHOOSE(IF(OR($D$4="Expert input",$J$83=0),4,IF($D$4="+25%",2,IF($D$4="+50%",3,1))),H83,H84,H85,H86) -> 0.8 | I87: =CHOOSE(IF(OR($D$4="Expert input",$J$83=0),4,IF($D$4="+25%",2,IF($D$4="+50%",3,1))),I83,I84,I85,I86) -> 100 | J87: =H87*I87 -> 80 | K87: =K83 -> 0 | L87: =CHOOSE(IF(OR($D$4="Expert input",$J$83=0),4,IF($D$4="+25%",2,IF($D$4="+50%",3,1))),L83,L84,L85,L86) -> 2 | M87: =K87*L87 -> 0 | N87: =M87*H87 -> 0 | O87: =M87*J87 -> 0 | Q87: 0.33 | R87: 0.67 | AB87: =P87*$N87 -> 0 | AC87: =P87*$O87 -> 0 | AD87: =Q87*$N87 -> 0 | AE87: =Q87*$O87 -> 0 | AF87: =R87*$N87 -> 0 | AG87: =R87*$O87 -> 0 | AH87: =S87*$N87 -> 0 | AI87: =S87*$O87 -> 0 | AJ87: =T87*$N87 -> 0 | AK87: =T87*$O87 -> 0 | AL87: =U87*$N87 -> 0 | AM87: =U87*$O87 -> 0 | AN87: =V87*$N87 -> 0 | AO87: =V87*$O87 -> 0 | AP87: =W87*$N87 -> 0 | AQ87: =W87*$O87 -> 0 | AR87: =X87*$N87 -> 0 | AS87: =X87*$O87 -> 0 | AT87: =Y87*$N87 -> 0 | AU87: =Y87*$O87 -> 0 | AV87: =Z87*$N87 -> 0 | AW87: =Z87*$O87 -> 0 | AX87: =AA87*$N87 -> 0 | AY87: =AA87*$O87 -> 0
B88: NU-15 | C88: Mulch application | D88: ጉዝጓዝ ማድረግ | E88: Seedbed & sowing | F88: bed | G88: Industry average | H88: =IFERROR(INDEX('Benchmark Data'!$AC$7:$AC$130,MATCH($B88,'Benchmark Data'!$A$7:$A$130,0)),0) -> 0.56666667 | I88: =IFERROR(INDEX('Benchmark Data'!$AD$7:$AD$130,MATCH($B88,'Benchmark Data'!$A$7:$A$130,0)),0) -> 52.941176 | J88: =H88*I88 -> 30 | K88: =$F$11 -> 0 | L88: =IFERROR(INDEX('Benchmark Data'!$AE$7:$AE$130,MATCH($B88,'Benchmark Data'!$A$7:$A$130,0)),0) -> 1 | M88: =K88*L88 -> 0 | N88: =M88*H88 -> 0 | O88: =M88*J88 -> 0
B89: NU-15 | C89: Mulch application | D89: ጉዝጓዝ ማድረግ | E89: Seedbed & sowing | F89: bed | G89: +25% | H89: =H88 -> 0.56666667 | I89: =I88*(1+Settings!$C$8) -> 66.176471 | J89: =H89*I89 -> 37.5 | K89: =K88 -> 0 | L89: =L88 -> 1 | M89: =K89*L89 -> 0 | N89: =M89*H89 -> 0 | O89: =M89*J89 -> 0
B90: NU-15 | C90: Mulch application | D90: ጉዝጓዝ ማድረግ | E90: Seedbed & sowing | F90: bed | G90: +50% | H90: =H88 -> 0.56666667 | I90: =I88*(1+Settings!$C$9) -> 79.411765 | J90: =H90*I90 -> 45 | K90: =K88 -> 0 | L90: =L88 -> 1 | M90: =K90*L90 -> 0 | N90: =M90*H90 -> 0 | O90: =M90*J90 -> 0
B91: NU-15 | C91: Mulch application | D91: ጉዝጓዝ ማድረግ | E91: Seedbed & sowing | F91: bed | G91: Expert input | H91: =H88 -> 0.56666667 | I91: =I88 -> 52.941176 | J91: =H91*I91 -> 30 | K91: =K88 -> 0 | L91: =L88 -> 1 | M91: =K91*L91 -> 0 | N91: =M91*H91 -> 0 | O91: =M91*J91 -> 0
B92: NU-15 | C92: Mulch application | D92: ጉዝጓዝ ማድረግ | E92: Seedbed & sowing | F92: bed | G92: Chaka Buna plan | H92: =CHOOSE(IF(OR($D$4="Expert input",$J$88=0),4,IF($D$4="+25%",2,IF($D$4="+50%",3,1))),H88,H89,H90,H91) -> 0.56666667 | I92: =CHOOSE(IF(OR($D$4="Expert input",$J$88=0),4,IF($D$4="+25%",2,IF($D$4="+50%",3,1))),I88,I89,I90,I91) -> 52.941176 | J92: =H92*I92 -> 30 | K92: =K88 -> 0 | L92: =CHOOSE(IF(OR($D$4="Expert input",$J$88=0),4,IF($D$4="+25%",2,IF($D$4="+50%",3,1))),L88,L89,L90,L91) -> 1 | M92: =K92*L92 -> 0 | N92: =M92*H92 -> 0 | O92: =M92*J92 -> 0 | R92: 1 | AB92: =P92*$N92 -> 0 | AC92: =P92*$O92 -> 0 | AD92: =Q92*$N92 -> 0 | AE92: =Q92*$O92 -> 0 | AF92: =R92*$N92 -> 0 | AG92: =R92*$O92 -> 0 | AH92: =S92*$N92 -> 0 | AI92: =S92*$O92 -> 0 | AJ92: =T92*$N92 -> 0 | AK92: =T92*$O92 -> 0 | AL92: =U92*$N92 -> 0 | AM92: =U92*$O92 -> 0 | AN92: =V92*$N92 -> 0 | AO92: =V92*$O92 -> 0 | AP92: =W92*$N92 -> 0 | AQ92: =W92*$O92 -> 0 | AR92: =X92*$N92 -> 0 | AS92: =X92*$O92 -> 0 | AT92: =Y92*$N92 -> 0 | AU92: =Y92*$O92 -> 0 | AV92: =Z92*$N92 -> 0 | AW92: =Z92*$O92 -> 0 | AX92: =AA92*$N92 -> 0 | AY92: =AA92*$O92 -> 0
B93: NU-16 | C93: Mulch removal | D93: ጉዝጓዝ ማንሳት | E93: Seedbed & sowing | F93: bed | G93: Industry average | H93: =IFERROR(INDEX('Benchmark Data'!$AC$7:$AC$130,MATCH($B93,'Benchmark Data'!$A$7:$A$130,0)),0) -> 0.56666667 | I93: =IFERROR(INDEX('Benchmark Data'!$AD$7:$AD$130,MATCH($B93,'Benchmark Data'!$A$7:$A$130,0)),0) -> 52.941176 | J93: =H93*I93 -> 30 | K93: =$F$11 -> 0 | L93: =IFERROR(INDEX('Benchmark Data'!$AE$7:$AE$130,MATCH($B93,'Benchmark Data'!$A$7:$A$130,0)),0) -> 1 | M93: =K93*L93 -> 0 | N93: =M93*H93 -> 0 | O93: =M93*J93 -> 0
B94: NU-16 | C94: Mulch removal | D94: ጉዝጓዝ ማንሳት | E94: Seedbed & sowing | F94: bed | G94: +25% | H94: =H93 -> 0.56666667 | I94: =I93*(1+Settings!$C$8) -> 66.176471 | J94: =H94*I94 -> 37.5 | K94: =K93 -> 0 | L94: =L93 -> 1 | M94: =K94*L94 -> 0 | N94: =M94*H94 -> 0 | O94: =M94*J94 -> 0
B95: NU-16 | C95: Mulch removal | D95: ጉዝጓዝ ማንሳት | E95: Seedbed & sowing | F95: bed | G95: +50% | H95: =H93 -> 0.56666667 | I95: =I93*(1+Settings!$C$9) -> 79.411765 | J95: =H95*I95 -> 45 | K95: =K93 -> 0 | L95: =L93 -> 1 | M95: =K95*L95 -> 0 | N95: =M95*H95 -> 0 | O95: =M95*J95 -> 0
B96: NU-16 | C96: Mulch removal | D96: ጉዝጓዝ ማንሳት | E96: Seedbed & sowing | F96: bed | G96: Expert input | H96: =H93 -> 0.56666667 | I96: =I93 -> 52.941176 | J96: =H96*I96 -> 30 | K96: =K93 -> 0 | L96: =L93 -> 1 | M96: =K96*L96 -> 0 | N96: =M96*H96 -> 0 | O96: =M96*J96 -> 0
B97: NU-16 | C97: Mulch removal | D97: ጉዝጓዝ ማንሳት | E97: Seedbed & sowing | F97: bed | G97: Chaka Buna plan | H97: =CHOOSE(IF(OR($D$4="Expert input",$J$93=0),4,IF($D$4="+25%",2,IF($D$4="+50%",3,1))),H93,H94,H95,H96) -> 0.56666667 | I97: =CHOOSE(IF(OR($D$4="Expert input",$J$93=0),4,IF($D$4="+25%",2,IF($D$4="+50%",3,1))),I93,I94,I95,I96) -> 52.941176 | J97: =H97*I97 -> 30 | K97: =K93 -> 0 | L97: =CHOOSE(IF(OR($D$4="Expert input",$J$93=0),4,IF($D$4="+25%",2,IF($D$4="+50%",3,1))),L93,L94,L95,L96) -> 1 | M97: =K97*L97 -> 0 | N97: =M97*H97 -> 0 | O97: =M97*J97 -> 0 | R97: 0.34 | S97: 0.33 | U97: 0.33 | AB97: =P97*$N97 -> 0 | AC97: =P97*$O97 -> 0 | AD97: =Q97*$N97 -> 0 | AE97: =Q97*$O97 -> 0 | AF97: =R97*$N97 -> 0 | AG97: =R97*$O97 -> 0 | AH97: =S97*$N97 -> 0 | AI97: =S97*$O97 -> 0 | AJ97: =T97*$N97 -> 0 | AK97: =T97*$O97 -> 0 | AL97: =U97*$N97 -> 0 | AM97: =U97*$O97 -> 0 | AN97: =V97*$N97 -> 0 | AO97: =V97*$O97 -> 0 | AP97: =W97*$N97 -> 0 | AQ97: =W97*$O97 -> 0 | AR97: =X97*$N97 -> 0 | AS97: =X97*$O97 -> 0 | AT97: =Y97*$N97 -> 0 | AU97: =Y97*$O97 -> 0 | AV97: =Z97*$N97 -> 0 | AW97: =Z97*$O97 -> 0 | AX97: =AA97*$N97 -> 0 | AY97: =AA97*$O97 -> 0
B98: NU-17 | C98: Transplanting seedlings to polytube | D98: ችግኝ ማዘዋወር | E98: Seedbed & sowing | F98: seedling | G98: Industry average | H98: =IFERROR(INDEX('Benchmark Data'!$AC$7:$AC$130,MATCH($B98,'Benchmark Data'!$A$7:$A$130,0)),0) -> 0.0025 | I98: =IFERROR(INDEX('Benchmark Data'!$AD$7:$AD$130,MATCH($B98,'Benchmark Data'!$A$7:$A$130,0)),0) -> 133.33333 | J98: =H98*I98 -> 0.33333333 | K98: =$F$9 -> 0 | L98: =IFERROR(INDEX('Benchmark Data'!$AE$7:$AE$130,MATCH($B98,'Benchmark Data'!$A$7:$A$130,0)),0) -> 1 | M98: =K98*L98 -> 0 | N98: =M98*H98 -> 0 | O98: =M98*J98 -> 0
B99: NU-17 | C99: Transplanting seedlings to polytube | D99: ችግኝ ማዘዋወር | E99: Seedbed & sowing | F99: seedling | G99: +25% | H99: =H98 -> 0.0025 | I99: =I98*(1+Settings!$C$8) -> 166.66667 | J99: =H99*I99 -> 0.41666667 | K99: =K98 -> 0 | L99: =L98 -> 1 | M99: =K99*L99 -> 0 | N99: =M99*H99 -> 0 | O99: =M99*J99 -> 0
B100: NU-17 | C100: Transplanting seedlings to polytube | D100: ችግኝ ማዘዋወር | E100: Seedbed & sowing | F100: seedling | G100: +50% | H100: =H98 -> 0.0025 | I100: =I98*(1+Settings!$C$9) -> 200 | J100: =H100*I100 -> 0.5 | K100: =K98 -> 0 | L100: =L98 -> 1 | M100: =K100*L100 -> 0 | N100: =M100*H100 -> 0 | O100: =M100*J100 -> 0
B101: NU-17 | C101: Transplanting seedlings to polytube | D101: ችግኝ ማዘዋወር | E101: Seedbed & sowing | F101: seedling | G101: Expert input | H101: =H98 -> 0.0025 | I101: =I98 -> 133.33333 | J101: =H101*I101 -> 0.33333333 | K101: =K98 -> 0 | L101: =L98 -> 1 | M101: =K101*L101 -> 0 | N101: =M101*H101 -> 0 | O101: =M101*J101 -> 0
B102: NU-17 | C102: Transplanting seedlings to polytube | D102: ችግኝ ማዘዋወር | E102: Seedbed & sowing | F102: seedling | G102: Chaka Buna plan | H102: =CHOOSE(IF(OR($D$4="Expert input",$J$98=0),4,IF($D$4="+25%",2,IF($D$4="+50%",3,1))),H98,H99,H100,H101) -> 0.0025 | I102: =CHOOSE(IF(OR($D$4="Expert input",$J$98=0),4,IF($D$4="+25%",2,IF($D$4="+50%",3,1))),I98,I99,I100,I101) -> 133.33333 | J102: =H102*I102 -> 0.33333333 | K102: =K98 -> 0 | L102: =CHOOSE(IF(OR($D$4="Expert input",$J$98=0),4,IF($D$4="+25%",2,IF($D$4="+50%",3,1))),L98,L99,L100,L101) -> 1 | M102: =K102*L102 -> 0 | N102: =M102*H102 -> 0 | O102: =M102*J102 -> 0 | S102: 0.5 | T102: 0.17 | U102: 0.33 | AB102: =P102*$N102 -> 0 | AC102: =P102*$O102 -> 0 | AD102: =Q102*$N102 -> 0 | AE102: =Q102*$O102 -> 0 | AF102: =R102*$N102 -> 0 | AG102: =R102*$O102 -> 0 | AH102: =S102*$N102 -> 0 | AI102: =S102*$O102 -> 0 | AJ102: =T102*$N102 -> 0 | AK102: =T102*$O102 -> 0 | AL102: =U102*$N102 -> 0 | AM102: =U102*$O102 -> 0 | AN102: =V102*$N102 -> 0 | AO102: =V102*$O102 -> 0 | AP102: =W102*$N102 -> 0 | AQ102: =W102*$O102 -> 0 | AR102: =X102*$N102 -> 0 | AS102: =X102*$O102 -> 0 | AT102: =Y102*$N102 -> 0 | AU102: =Y102*$O102 -> 0 | AV102: =Z102*$N102 -> 0 | AW102: =Z102*$O102 -> 0 | AX102: =AA102*$N102 -> 0 | AY102: =AA102*$O102 -> 0
B103: NU-18 | C103: Shade poles preparation & transport | D103: ለዳስ ፍልጥ/ባላ ዝግጅት እና ማጓጓዝ | E103: Nursery shade | F103: bed | G103: Industry average | H103: =IFERROR(INDEX('Benchmark Data'!$AC$7:$AC$130,MATCH($B103,'Benchmark Data'!$A$7:$A$130,0)),0) -> 0.48148148 | I103: =IFERROR(INDEX('Benchmark Data'!$AD$7:$AD$130,MATCH($B103,'Benchmark Data'!$A$7:$A$130,0)),0) -> 380.76923 | J103: =H103*I103 -> 183.33333 | K103: =$F$12 -> 0 | L103: =IFERROR(INDEX('Benchmark Data'!$AE$7:$AE$130,MATCH($B103,'Benchmark Data'!$A$7:$A$130,0)),0) -> 2 | M103: =K103*L103 -> 0 | N103: =M103*H103 -> 0 | O103: =M103*J103 -> 0
B104: NU-18 | C104: Shade poles preparation & transport | D104: ለዳስ ፍልጥ/ባላ ዝግጅት እና ማጓጓዝ | E104: Nursery shade | F104: bed | G104: +25% | H104: =H103 -> 0.48148148 | I104: =I103*(1+Settings!$C$8) -> 475.96154 | J104: =H104*I104 -> 229.16667 | K104: =K103 -> 0 | L104: =L103 -> 2 | M104: =K104*L104 -> 0 | N104: =M104*H104 -> 0 | O104: =M104*J104 -> 0
B105: NU-18 | C105: Shade poles preparation & transport | D105: ለዳስ ፍልጥ/ባላ ዝግጅት እና ማጓጓዝ | E105: Nursery shade | F105: bed | G105: +50% | H105: =H103 -> 0.48148148 | I105: =I103*(1+Settings!$C$9) -> 571.15385 | J105: =H105*I105 -> 275 | K105: =K103 -> 0 | L105: =L103 -> 2 | M105: =K105*L105 -> 0 | N105: =M105*H105 -> 0 | O105: =M105*J105 -> 0
...

Sheet Young Coffee
A1: Young Coffee – activity plan and budget
A2: ="Farm: "&Settings!$C$6&" | Plan year: "&Settings!$C$7 -> Farm: Chaka Buna Estate (Silva Forest Coffee) | Plan year: 2019 EFY (2026/27) – confirm
B3: Plan basis (drop-down) ► | C3: Industry average | D3: Sets the Chaka Buna plan row of every activity on this tab. Activities with no industry-average rate always use the Expert input row.
B5: GENERAL INFORMATION | F5: CATEGORY TOTALS
B6: Metric (English) | C6: Metric (Amharic) | D6: Unit | E6: Quantity | F6: Rate scenario | M6: Total man-days | N6: Total cost (birr) | O6: Plan phasing (% of cost) | AA6: Plan monthly totals
B7: Total trees (net area) | C7: የቡና እግር ብዛት (ቁጥር) | D7: no. | F7: Industry average | M7: =SUMIF($F$17:$F$91,"Industry average",M$17:M$91) -> 0 | N7: =SUMIF($F$17:$F$91,"Industry average",N$17:N$91) -> 0
B8: Gross area | C8: ጠቅላላ የማሳ ስፋት (ሄ/ር) | D8: ha | F8: +25% | M8: =SUMIF($F$17:$F$91,"+25%",M$17:M$91) -> 0 | N8: =SUMIF($F$17:$F$91,"+25%",N$17:N$91) -> 0
B9: Average trees per ha | C9: የቡና እግር አማካይ (ሄ/ር) | D9: trees/ha | E9: =IFERROR($E$7/$E$8,0) -> 0 | F9: +50% | M9: =SUMIF($F$17:$F$91,"+50%",M$17:M$91) -> 0 | N9: =SUMIF($F$17:$F$91,"+50%",N$17:N$91) -> 0
F10: Expert input | M10: =SUMIF($F$17:$F$91,"Expert input",M$17:M$91) -> 0 | N10: =SUMIF($F$17:$F$91,"Expert input",N$17:N$91) -> 0
F11: Chaka Buna plan – counts in Summary | M11: =SUMIF($F$17:$F$91,"Chaka Buna plan",M$17:M$91) -> 0 | N11: =SUMIF($F$17:$F$91,"Chaka Buna plan",N$17:N$91) -> 0 | O11: =IFERROR(AB11/$N$11,0) -> 0 | P11: =IFERROR(AD11/$N$11,0) -> 0 | Q11: =IFERROR(AF11/$N$11,0) -> 0 | R11: =IFERROR(AH11/$N$11,0) -> 0 | S11: =IFERROR(AJ11/$N$11,0) -> 0 | T11: =IFERROR(AL11/$N$11,0) -> 0 | U11: =IFERROR(AN11/$N$11,0) -> 0 | V11: =IFERROR(AP11/$N$11,0) -> 0 | W11: =IFERROR(AR11/$N$11,0) -> 0 | X11: =IFERROR(AT11/$N$11,0) -> 0 | Y11: =IFERROR(AV11/$N$11,0) -> 0 | Z11: =IFERROR(AX11/$N$11,0) -> 0 | AA11: =SUM(AA17:AA91) -> 0 | AB11: =SUM(AB17:AB91) -> 0 | AC11: =SUM(AC17:AC91) -> 0 | AD11: =SUM(AD17:AD91) -> 0 | AE11: =SUM(AE17:AE91) -> 0 | AF11: =SUM(AF17:AF91) -> 0 | AG11: =SUM(AG17:AG91) -> 0 | AH11: =SUM(AH17:AH91) -> 0 | ... AX11: =SUM(AX17:AX91) -> 0
A15: ACTIVITY | F15: RATE (cost per unit = man-days × wage) | J15: QUANTITY | L15: TOTALS (calculated) | O15: PHASING – % of annual (input on the Chaka Buna plan row) | AA15: MONTHLY MAN-DAYS AND COST (Chaka Buna plan row)
A16: Code | B16: Activity | C16: Activity (Amharic) | D16: Sub-group | E16: Unit | F16: Rate scenario | G16: Man-days per unit | H16: Wage per man-day (birr) | I16: Cost per unit (birr) | J16: Activity quantity per round | K16: Frequency (times / year) | L16: Total activity quantity | M16: Total man-days per activity | N16: Total cost per activity (birr) | O16: Tikimt (Oct) | P16: Hidar (Nov) | Q16: Tahsas (Dec) | R16: Tir (Jan) | S16: Yekatit (Feb) | T16: Megabit (Mar) | U16: Miyazya (Apr) | V16: Ginbot (May) | W16: Sene (Jun) | X16: Hamle (Jul) | Y16: Nehase (Aug) | Z16: Meskerem (Sep) | AA16: Tikimt (Oct) – man-days | AB16: Tikimt (Oct) – cost | AC16: Hidar (Nov) – man-days | AD16: Hidar (Nov) – cost | AE16: Tahsas (Dec) – man-days | AF16: Tahsas (Dec) – cost | AG16: Tir (Jan) – man-days | AH16: Tir (Jan) – cost | AI16: Yekatit (Feb) – man-days | AJ16: Yekatit (Feb) – cost | AK16: Megabit (Mar) – man-days | AL16: Megabit (Mar) – cost | AM16: Miyazya (Apr) – man-days | AN16: Miyazya (Apr) – cost | AO16: Ginbot (May) – man-days | AP16: Ginbot (May) – cost | AQ16: Sene (Jun) – man-days | AR16: Sene (Jun) – cost | AS16: Hamle (Jul) – man-days | AT16: Hamle (Jul) – cost | AU16: Nehase (Aug) – man-days | AV16: Nehase (Aug) – cost | AW16: Meskerem (Sep) – man-days | AX16: Meskerem (Sep) – cost
A17: YC-01 | B17: Manual weeding (slashing) | C17: አረም ቁጥጥር በገጀራ | D17: Weed & soil care | E17: ha | F17: Industry average | G17: =IFERROR(INDEX('Benchmark Data'!$AC$7:$AC$130,MATCH($A17,'Benchmark Data'!$A$7:$A$130,0)),0) -> 20 | H17: =IFERROR(INDEX('Benchmark Data'!$AD$7:$AD$130,MATCH($A17,'Benchmark Data'!$A$7:$A$130,0)),0) -> 200 | I17: =G17*H17 -> 4000 | J17: =$E$8 -> 0 | K17: =IFERROR(INDEX('Benchmark Data'!$AE$7:$AE$130,MATCH($A17,'Benchmark Data'!$A$7:$A$130,0)),0) -> 4 | L17: =J17*K17 -> 0 | M17: =L17*G17 -> 0 | N17: =L17*I17 -> 0
A18: YC-01 | B18: Manual weeding (slashing) | C18: አረም ቁጥጥር በገጀራ | D18: Weed & soil care | E18: ha | F18: +25% | G18: =G17 -> 20 | H18: =H17*(1+Settings!$C$8) -> 250 | I18: =G18*H18 -> 5000 | J18: =J17 -> 0 | K18: =K17 -> 4 | L18: =J18*K18 -> 0 | M18: =L18*G18 -> 0 | N18: =L18*I18 -> 0
A19: YC-01 | B19: Manual weeding (slashing) | C19: አረም ቁጥጥር በገጀራ | D19: Weed & soil care | E19: ha | F19: +50% | G19: =G17 -> 20 | H19: =H17*(1+Settings!$C$9) -> 300 | I19: =G19*H19 -> 6000 | J19: =J17 -> 0 | K19: =K17 -> 4 | L19: =J19*K19 -> 0 | M19: =L19*G19 -> 0 | N19: =L19*I19 -> 0
A20: YC-01 | B20: Manual weeding (slashing) | C20: አረም ቁጥጥር በገጀራ | D20: Weed & soil care | E20: ha | F20: Expert input | G20: =G17 -> 20 | H20: =H17 -> 200 | I20: =G20*H20 -> 4000 | J20: =J17 -> 0 | K20: =K17 -> 4 | L20: =J20*K20 -> 0 | M20: =L20*G20 -> 0 | N20: =L20*I20 -> 0
A21: YC-01 | B21: Manual weeding (slashing) | C21: አረም ቁጥጥር በገጀራ | D21: Weed & soil care | E21: ha | F21: Chaka Buna plan | G21: =CHOOSE(IF(OR($C$3="Expert input",$I$17=0),4,IF($C$3="+25%",2,IF($C$3="+50%",3,1))),G17,G18,G19,G20) -> 20 | H21: =CHOOSE(IF(OR($C$3="Expert input",$I$17=0),4,IF($C$3="+25%",2,IF($C$3="+50%",3,1))),H17,H18,H19,H20) -> 200 | I21: =G21*H21 -> 4000 | J21: =J17 -> 0 | K21: =CHOOSE(IF(OR($C$3="Expert input",$I$17=0),4,IF($C$3="+25%",2,IF($C$3="+50%",3,1))),K17,K18,K19,K20) -> 4 | L21: =J21*K21 -> 0 | M21: =L21*G21 -> 0 | N21: =L21*I21 -> 0 | O21: 0.25 | R21: 0.25 | V21: 0.25 | Y21: 0.25 | AA21: =O21*$M21 -> 0 | AB21: =O21*$N21 -> 0 | AC21: =P21*$M21 -> 0 | AD21: =P21*$N21 -> 0 | AE21: =Q21*$M21 -> 0 | AF21: =Q21*$N21 -> 0 | AG21: =R21*$M21 -> 0 | AH21: =R21*$N21 -> 0 | AI21: =S21*$M21 -> 0 | AJ21: =S21*$N21 -> 0 | AK21: =T21*$M21 -> 0 | AL21: =T21*$N21 -> 0 | AM21: =U21*$M21 -> 0 | AN21: =U21*$N21 -> 0 | AO21: =V21*$M21 -> 0 | AP21: =V21*$N21 -> 0 | AQ21: =W21*$M21 -> 0 | AR21: =W21*$N21 -> 0 | AS21: =X21*$M21 -> 0 | AT21: =X21*$N21 -> 0 | AU21: =Y21*$M21 -> 0 | AV21: =Y21*$N21 -> 0 | AW21: =Z21*$M21 -> 0 | AX21: =Z21*$N21 -> 0
A22: YC-02 | B22: Hoeing | C22: ኩትኳቶ | D22: Weed & soil care | E22: tree | F22: Industry average | G22: =IFERROR(INDEX('Benchmark Data'!$AC$7:$AC$130,MATCH($A22,'Benchmark Data'!$A$7:$A$130,0)),0) -> 0.0096666667 | H22: =IFERROR(INDEX('Benchmark Data'!$AD$7:$AD$130,MATCH($A22,'Benchmark Data'!$A$7:$A$130,0)),0) -> 168.96552 | I22: =G22*H22 -> 1.6333333 | J22: =$E$7 -> 0 | K22: =IFERROR(INDEX('Benchmark Data'!$AE$7:$AE$130,MATCH($A22,'Benchmark Data'!$A$7:$A$130,0)),0) -> 1 | L22: =J22*K22 -> 0 | M22: =L22*G22 -> 0 | N22: =L22*I22 -> 0
A23: YC-02 | B23: Hoeing | C23: ኩትኳቶ | D23: Weed & soil care | E23: tree | F23: +25% | G23: =G22 -> 0.0096666667 | H23: =H22*(1+Settings!$C$8) -> 211.2069 | I23: =G23*H23 -> 2.0416667 | J23: =J22 -> 0 | K23: =K22 -> 1 | L23: =J23*K23 -> 0 | M23: =L23*G23 -> 0 | N23: =L23*I23 -> 0
A24: YC-02 | B24: Hoeing | C24: ኩትኳቶ | D24: Weed & soil care | E24: tree | F24: +50% | G24: =G22 -> 0.0096666667 | H24: =H22*(1+Settings!$C$9) -> 253.44828 | I24: =G24*H24 -> 2.45 | J24: =J22 -> 0 | K24: =K22 -> 1 | L24: =J24*K24 -> 0 | M24: =L24*G24 -> 0 | N24: =L24*I24 -> 0
A25: YC-02 | B25: Hoeing | C25: ኩትኳቶ | D25: Weed & soil care | E25: tree | F25: Expert input | G25: =G22 -> 0.0096666667 | H25: =H22 -> 168.96552 | I25: =G25*H25 -> 1.6333333 | J25: =J22 -> 0 | K25: =K22 -> 1 | L25: =J25*K25 -> 0 | M25: =L25*G25 -> 0 | N25: =L25*I25 -> 0
A26: YC-02 | B26: Hoeing | C26: ኩትኳቶ | D26: Weed & soil care | E26: tree | F26: Chaka Buna plan | G26: =CHOOSE(IF(OR($C$3="Expert input",$I$22=0),4,IF($C$3="+25%",2,IF($C$3="+50%",3,1))),G22,G23,G24,G25) -> 0.0096666667 | H26: =CHOOSE(IF(OR($C$3="Expert input",$I$22=0),4,IF($C$3="+25%",2,IF($C$3="+50%",3,1))),H22,H23,H24,H25) -> 168.96552 | I26: =G26*H26 -> 1.6333333 | J26: =J22 -> 0 | K26: =CHOOSE(IF(OR($C$3="Expert input",$I$22=0),4,IF($C$3="+25%",2,IF($C$3="+50%",3,1))),K22,K23,K24,K25) -> 1 | L26: =J26*K26 -> 0 | M26: =L26*G26 -> 0 | N26: =L26*I26 -> 0 | P26: 0.17 | Q26: 0.17 | V26: 0.33 | X26: 0.33 | AA26: =O26*$M26 -> 0 | AB26: =O26*$N26 -> 0 | AC26: =P26*$M26 -> 0 | AD26: =P26*$N26 -> 0 | AE26: =Q26*$M26 -> 0 | AF26: =Q26*$N26 -> 0 | AG26: =R26*$M26 -> 0 | AH26: =R26*$N26 -> 0 | AI26: =S26*$M26 -> 0 | AJ26: =S26*$N26 -> 0 | AK26: =T26*$M26 -> 0 | AL26: =T26*$N26 -> 0 | AM26: =U26*$M26 -> 0 | AN26: =U26*$N26 -> 0 | AO26: =V26*$M26 -> 0 | AP26: =V26*$N26 -> 0 | AQ26: =W26*$M26 -> 0 | AR26: =W26*$N26 -> 0 | AS26: =X26*$M26 -> 0 | AT26: =X26*$N26 -> 0 | AU26: =Y26*$M26 -> 0 | AV26: =Y26*$N26 -> 0 | AW26: =Z26*$M26 -> 0 | AX26: =Z26*$N26 -> 0
A27: YC-03 | B27: Ring weeding | C27: ችግኝ ቡና ዙሪያ አረም | D27: Weed & soil care | E27: tree | F27: Industry average | G27: =IFERROR(INDEX('Benchmark Data'!$AC$7:$AC$130,MATCH($A27,'Benchmark Data'!$A$7:$A$130,0)),0) -> 0.0096666667 | H27: =IFERROR(INDEX('Benchmark Data'!$AD$7:$AD$130,MATCH($A27,'Benchmark Data'!$A$7:$A$130,0)),0) -> 134.48276 | I27: =G27*H27 -> 1.3 | J27: =$E$7 -> 0 | K27: =IFERROR(INDEX('Benchmark Data'!$AE$7:$AE$130,MATCH($A27,'Benchmark Data'!$A$7:$A$130,0)),0) -> 2 | L27: =J27*K27 -> 0 | M27: =L27*G27 -> 0 | N27: =L27*I27 -> 0
A28: YC-03 | B28: Ring weeding | C28: ችግኝ ቡና ዙሪያ አረም | D28: Weed & soil care | E28: tree | F28: +25% | G28: =G27 -> 0.0096666667 | H28: =H27*(1+Settings!$C$8) -> 168.10345 | I28: =G28*H28 -> 1.625 | J28: =J27 -> 0 | K28: =K27 -> 2 | L28: =J28*K28 -> 0 | M28: =L28*G28 -> 0 | N28: =L28*I28 -> 0
A29: YC-03 | B29: Ring weeding | C29: ችግኝ ቡና ዙሪያ አረም | D29: Weed & soil care | E29: tree | F29: +50% | G29: =G27 -> 0.0096666667 | H29: =H27*(1+Settings!$C$9) -> 201.72414 | I29: =G29*H29 -> 1.95 | J29: =J27 -> 0 | K29: =K27 -> 2 | L29: =J29*K29 -> 0 | M29: =L29*G29 -> 0 | N29: =L29*I29 -> 0
A30: YC-03 | B30: Ring weeding | C30: ችግኝ ቡና ዙሪያ አረም | D30: Weed & soil care | E30: tree | F30: Expert input | G30: =G27 -> 0.0096666667 | H30: =H27 -> 134.48276 | I30: =G30*H30 -> 1.3 | J30: =J27 -> 0 | K30: =K27 -> 2 | L30: =J30*K30 -> 0 | M30: =L30*G30 -> 0 | N30: =L30*I30 -> 0
A31: YC-03 | B31: Ring weeding | C31: ችግኝ ቡና ዙሪያ አረም | D31: Weed & soil care | E31: tree | F31: Chaka Buna plan | G31: =CHOOSE(IF(OR($C$3="Expert input",$I$27=0),4,IF($C$3="+25%",2,IF($C$3="+50%",3,1))),G27,G28,G29,G30) -> 0.0096666667 | H31: =CHOOSE(IF(OR($C$3="Expert input",$I$27=0),4,IF($C$3="+25%",2,IF($C$3="+50%",3,1))),H27,H28,H29,H30) -> 134.48276 | I31: =G31*H31 -> 1.3 | J31: =J27 -> 0 | K31: =CHOOSE(IF(OR($C$3="Expert input",$I$27=0),4,IF($C$3="+25%",2,IF($C$3="+50%",3,1))),K27,K28,K29,K30) -> 2 | L31: =J31*K31 -> 0 | M31: =L31*G31 -> 0 | N31: =L31*I31 -> 0 | O31: 0.17 | Q31: 0.17 | T31: 0.17 | X31: 0.17 | Z31: 0.32 | AA31: =O31*$M31 -> 0 | AB31: =O31*$N31 -> 0 | AC31: =P31*$M31 -> 0 | AD31: =P31*$N31 -> 0 | AE31: =Q31*$M31 -> 0 | AF31: =Q31*$N31 -> 0 | AG31: =R31*$M31 -> 0 | AH31: =R31*$N31 -> 0 | AI31: =S31*$M31 -> 0 | AJ31: =S31*$N31 -> 0 | AK31: =T31*$M31 -> 0 | AL31: =T31*$N31 -> 0 | AM31: =U31*$M31 -> 0 | AN31: =U31*$N31 -> 0 | AO31: =V31*$M31 -> 0 | AP31: =V31*$N31 -> 0 | AQ31: =W31*$M31 -> 0 | AR31: =W31*$N31 -> 0 | AS31: =X31*$M31 -> 0 | AT31: =X31*$N31 -> 0 | AU31: =Y31*$M31 -> 0 | AV31: =Y31*$N31 -> 0 | AW31: =Z31*$M31 -> 0 | AX31: =Z31*$N31 -> 0
A32: YC-04 | B32: Mulch application | C32: ችግኝ ቡና ጉዝጓዝ ማድረግ | D32: Weed & soil care | E32: tree | F32: Industry average | G32: =IFERROR(INDEX('Benchmark Data'!$AC$7:$AC$130,MATCH($A32,'Benchmark Data'!$A$7:$A$130,0)),0) -> 0.01 | H32: =IFERROR(INDEX('Benchmark Data'!$AD$7:$AD$130,MATCH($A32,'Benchmark Data'!$A$7:$A$130,0)),0) -> 120 | I32: =G32*H32 -> 1.2 | J32: =$E$7 -> 0 | K32: =IFERROR(INDEX('Benchmark Data'!$AE$7:$AE$130,MATCH($A32,'Benchmark Data'!$A$7:$A$130,0)),0) -> 1 | L32: =J32*K32 -> 0 | M32: =L32*G32 -> 0 | N32: =L32*I32 -> 0
A33: YC-04 | B33: Mulch application | C33: ችግኝ ቡና ጉዝጓዝ ማድረግ | D33: Weed & soil care | E33: tree | F33: +25% | G33: =G32 -> 0.01 | H33: =H32*(1+Settings!$C$8) -> 150 | I33: =G33*H33 -> 1.5 | J33: =J32 -> 0 | K33: =K32 -> 1 | L33: =J33*K33 -> 0 | M33: =L33*G33 -> 0 | N33: =L33*I33 -> 0
A34: YC-04 | B34: Mulch application | C34: ችግኝ ቡና ጉዝጓዝ ማድረግ | D34: Weed & soil care | E34: tree | F34: +50% | G34: =G32 -> 0.01 | H34: =H32*(1+Settings!$C$9) -> 180 | I34: =G34*H34 -> 1.8 | J34: =J32 -> 0 | K34: =K32 -> 1 | L34: =J34*K34 -> 0 | M34: =L34*G34 -> 0 | N34: =L34*I34 -> 0
A35: YC-04 | B35: Mulch application | C35: ችግኝ ቡና ጉዝጓዝ ማድረግ | D35: Weed & soil care | E35: tree | F35: Expert input | G35: =G32 -> 0.01 | H35: =H32 -> 120 | I35: =G35*H35 -> 1.2 | J35: =J32 -> 0 | K35: =K32 -> 1 | L35: =J35*K35 -> 0 | M35: =L35*G35 -> 0 | N35: =L35*I35 -> 0
A36: YC-04 | B36: Mulch application | C36: ችግኝ ቡና ጉዝጓዝ ማድረግ | D36: Weed & soil care | E36: tree | F36: Chaka Buna plan | G36: =CHOOSE(IF(OR($C$3="Expert input",$I$32=0),4,IF($C$3="+25%",2,IF($C$3="+50%",3,1))),G32,G33,G34,G35) -> 0.01 | H36: =CHOOSE(IF(OR($C$3="Expert input",$I$32=0),4,IF($C$3="+25%",2,IF($C$3="+50%",3,1))),H32,H33,H34,H35) -> 120 | I36: =G36*H36 -> 1.2 | J36: =J32 -> 0 | K36: =CHOOSE(IF(OR($C$3="Expert input",$I$32=0),4,IF($C$3="+25%",2,IF($C$3="+50%",3,1))),K32,K33,K34,K35) -> 1 | L36: =J36*K36 -> 0 | M36: =L36*G36 -> 0 | N36: =L36*I36 -> 0 | R36: 1 | AA36: =O36*$M36 -> 0 | AB36: =O36*$N36 -> 0 | AC36: =P36*$M36 -> 0 | AD36: =P36*$N36 -> 0 | AE36: =Q36*$M36 -> 0 | AF36: =Q36*$N36 -> 0 | AG36: =R36*$M36 -> 0 | AH36: =R36*$N36 -> 0 | AI36: =S36*$M36 -> 0 | AJ36: =S36*$N36 -> 0 | AK36: =T36*$M36 -> 0 | AL36: =T36*$N36 -> 0 | AM36: =U36*$M36 -> 0 | AN36: =U36*$N36 -> 0 | AO36: =V36*$M36 -> 0 | AP36: =V36*$N36 -> 0 | AQ36: =W36*$M36 -> 0 | AR36: =W36*$N36 -> 0 | AS36: =X36*$M36 -> 0 | AT36: =X36*$N36 -> 0 | AU36: =Y36*$M36 -> 0 | AV36: =Y36*$N36 -> 0 | AW36: =Z36*$M36 -> 0 | AX36: =Z36*$N36 -> 0
A37: YC-05 | B37: Full block digging | C37: ሙሉ ብሎክ ማስቆፈር | D37: Weed & soil care | E37: ha | F37: Industry average | G37: =IFERROR(INDEX('Benchmark Data'!$AC$7:$AC$130,MATCH($A37,'Benchmark Data'!$A$7:$A$130,0)),0) -> 0 | H37: =IFERROR(INDEX('Benchmark Data'!$AD$7:$AD$130,MATCH($A37,'Benchmark Data'!$A$7:$A$130,0)),0) -> 0 | I37: =G37*H37 -> 0 | K37: =IFERROR(INDEX('Benchmark Data'!$AE$7:$AE$130,MATCH($A37,'Benchmark Data'!$A$7:$A$130,0)),0) -> 1 | L37: =J37*K37 -> 0 | M37: =L37*G37 -> 0 | N37: =L37*I37 -> 0
A38: YC-05 | B38: Full block digging | C38: ሙሉ ብሎክ ማስቆፈር | D38: Weed & soil care | E38: ha | F38: +25% | G38: =G37 -> 0 | H38: =H37*(1+Settings!$C$8) -> 0 | I38: =G38*H38 -> 0 | J38: =J37 -> 0 | K38: =K37 -> 1 | L38: =J38*K38 -> 0 | M38: =L38*G38 -> 0 | N38: =L38*I38 -> 0
A39: YC-05 | B39: Full block digging | C39: ሙሉ ብሎክ ማስቆፈር | D39: Weed & soil care | E39: ha | F39: +50% | G39: =G37 -> 0 | H39: =H37*(1+Settings!$C$9) -> 0 | I39: =G39*H39 -> 0 | J39: =J37 -> 0 | K39: =K37 -> 1 | L39: =J39*K39 -> 0 | M39: =L39*G39 -> 0 | N39: =L39*I39 -> 0
A40: YC-05 | B40: Full block digging | C40: ሙሉ ብሎክ ማስቆፈር | D40: Weed & soil care | E40: ha | F40: Expert input | G40: =IFERROR(INDEX('Benchmark Data'!$AH$7:$AH$130,MATCH($A40,'Benchmark Data'!$A$7:$A$130,0)),0) -> 10 | H40: =IFERROR(INDEX('Benchmark Data'!$AI$7:$AI$130,MATCH($A40,'Benchmark Data'!$A$7:$A$130,0)),0) -> 800 | I40: =G40*H40 -> 8000 | J40: =J37 -> 0 | K40: =IFERROR(INDEX('Benchmark Data'!$AJ$7:$AJ$130,MATCH($A40,'Benchmark Data'!$A$7:$A$130,0)),0) -> 1 | L40: =J40*K40 -> 0 | M40: =L40*G40 -> 0 | N40: =L40*I40 -> 0
A41: YC-05 | B41: Full block digging | C41: ሙሉ ብሎክ ማስቆፈር | D41: Weed & soil care | E41: ha | F41: Chaka Buna plan | G41: =CHOOSE(IF(OR($C$3="Expert input",$I$37=0),4,IF($C$3="+25%",2,IF($C$3="+50%",3,1))),G37,G38,G39,G40) -> 10 | H41: =CHOOSE(IF(OR($C$3="Expert input",$I$37=0),4,IF($C$3="+25%",2,IF($C$3="+50%",3,1))),H37,H38,H39,H40) -> 800 | I41: =G41*H41 -> 8000 | J41: =J37 -> 0 | K41: =CHOOSE(IF(OR($C$3="Expert input",$I$37=0),4,IF($C$3="+25%",2,IF($C$3="+50%",3,1))),K37,K38,K39,K40) -> 1 | L41: =J41*K41 -> 0 | M41: =L41*G41 -> 0 | N41: =L41*I41 -> 0 | R41: 0.34 | S41: 0.33 | T41: 0.33 | AA41: =O41*$M41 -> 0 | AB41: =O41*$N41 -> 0 | AC41: =P41*$M41 -> 0 | AD41: =P41*$N41 -> 0 | AE41: =Q41*$M41 -> 0 | AF41: =Q41*$N41 -> 0 | AG41: =R41*$M41 -> 0 | AH41: =R41*$N41 -> 0 | AI41: =S41*$M41 -> 0 | AJ41: =S41*$N41 -> 0 | AK41: =T41*$M41 -> 0 | AL41: =T41*$N41 -> 0 | AM41: =U41*$M41 -> 0 | AN41: =U41*$N41 -> 0 | AO41: =V41*$M41 -> 0 | AP41: =V41*$N41 -> 0 | AQ41: =W41*$M41 -> 0 | AR41: =W41*$N41 -> 0 | AS41: =X41*$M41 -> 0 | AT41: =X41*$N41 -> 0 | AU41: =Y41*$M41 -> 0 | AV41: =Y41*$N41 -> 0 | AW41: =Z41*$M41 -> 0 | AX41: =Z41*$N41 -> 0
A42: YC-06 | B42: Fertiliser application | C42: ማዳበሪያ ማድረግ | D42: Nutrition | E42: tree | F42: Industry average | G42: =IFERROR(INDEX('Benchmark Data'!$AC$7:$AC$130,MATCH($A42,'Benchmark Data'!$A$7:$A$130,0)),0) -> 0.0095 | H42: =IFERROR(INDEX('Benchmark Data'!$AD$7:$AD$130,MATCH($A42,'Benchmark Data'!$A$7:$A$130,0)),0) -> 100 | I42: =G42*H42 -> 0.95 | J42: =$E$7 -> 0 | K42: =IFERROR(INDEX('Benchmark Data'!$AE$7:$AE$130,MATCH($A42,'Benchmark Data'!$A$7:$A$130,0)),0) -> 1 | L42: =J42*K42 -> 0 | M42: =L42*G42 -> 0 | N42: =L42*I42 -> 0
A43: YC-06 | B43: Fertiliser application | C43: ማዳበሪያ ማድረግ | D43: Nutrition | E43: tree | F43: +25% | G43: =G42 -> 0.0095 | H43: =H42*(1+Settings!$C$8) -> 125 | I43: =G43*H43 -> 1.1875 | J43: =J42 -> 0 | K43: =K42 -> 1 | L43: =J43*K43 -> 0 | M43: =L43*G43 -> 0 | N43: =L43*I43 -> 0
A44: YC-06 | B44: Fertiliser application | C44: ማዳበሪያ ማድረግ | D44: Nutrition | E44: tree | F44: +50% | G44: =G42 -> 0.0095 | H44: =H42*(1+Settings!$C$9) -> 150 | I44: =G44*H44 -> 1.425 | J44: =J42 -> 0 | K44: =K42 -> 1 | L44: =J44*K44 -> 0 | M44: =L44*G44 -> 0 | N44: =L44*I44 -> 0
A45: YC-06 | B45: Fertiliser application | C45: ማዳበሪያ ማድረግ | D45: Nutrition | E45: tree | F45: Expert input | G45: =G42 -> 0.0095 | H45: =H42 -> 100 | I45: =G45*H45 -> 0.95 | J45: =J42 -> 0 | K45: =K42 -> 1 | L45: =J45*K45 -> 0 | M45: =L45*G45 -> 0 | N45: =L45*I45 -> 0
A46: YC-06 | B46: Fertiliser application | C46: ማዳበሪያ ማድረግ | D46: Nutrition | E46: tree | F46: Chaka Buna plan | G46: =CHOOSE(IF(OR($C$3="Expert input",$I$42=0),4,IF($C$3="+25%",2,IF($C$3="+50%",3,1))),G42,G43,G44,G45) -> 0.0095 | H46: =CHOOSE(IF(OR($C$3="Expert input",$I$42=0),4,IF($C$3="+25%",2,IF($C$3="+50%",3,1))),H42,H43,H44,H45) -> 100 | I46: =G46*H46 -> 0.95 | J46: =J42 -> 0 | K46: =CHOOSE(IF(OR($C$3="Expert input",$I$42=0),4,IF($C$3="+25%",2,IF($C$3="+50%",3,1))),K42,K43,K44,K45) -> 1 | L46: =J46*K46 -> 0 | M46: =L46*G46 -> 0 | N46: =L46*I46 -> 0 | W46: 0.5 | Y46: 0.5 | AA46: =O46*$M46 -> 0 | AB46: =O46*$N46 -> 0 | AC46: =P46*$M46 -> 0 | AD46: =P46*$N46 -> 0 | AE46: =Q46*$M46 -> 0 | AF46: =Q46*$N46 -> 0 | AG46: =R46*$M46 -> 0 | AH46: =R46*$N46 -> 0 | AI46: =S46*$M46 -> 0 | AJ46: =S46*$N46 -> 0 | AK46: =T46*$M46 -> 0 | AL46: =T46*$N46 -> 0 | AM46: =U46*$M46 -> 0 | AN46: =U46*$N46 -> 0 | AO46: =V46*$M46 -> 0 | AP46: =V46*$N46 -> 0 | AQ46: =W46*$M46 -> 0 | AR46: =W46*$N46 -> 0 | AS46: =X46*$M46 -> 0 | AT46: =X46*$N46 -> 0 | AU46: =Y46*$M46 -> 0 | AV46: =Y46*$N46 -> 0 | AW46: =Z46*$M46 -> 0 | AX46: =Z46*$N46 -> 0
A47: YC-07 | B47: Compost preparation | C47: የተፈጥሮ ማዳበሪያ ዝግጅት | D47: Nutrition | E47: m³ | F47: Industry average | G47: =IFERROR(INDEX('Benchmark Data'!$AC$7:$AC$130,MATCH($A47,'Benchmark Data'!$A$7:$A$130,0)),0) -> 0.41111111 | H47: =IFERROR(INDEX('Benchmark Data'!$AD$7:$AD$130,MATCH($A47,'Benchmark Data'!$A$7:$A$130,0)),0) -> 437.83784 | I47: =G47*H47 -> 180 | K47: =IFERROR(INDEX('Benchmark Data'!$AE$7:$AE$130,MATCH($A47,'Benchmark Data'!$A$7:$A$130,0)),0) -> 1 | L47: =J47*K47 -> 0 | M47: =L47*G47 -> 0 | N47: =L47*I47 -> 0
A48: YC-07 | B48: Compost preparation | C48: የተፈጥሮ ማዳበሪያ ዝግጅት | D48: Nutrition | E48: m³ | F48: +25% | G48: =G47 -> 0.41111111 | H48: =H47*(1+Settings!$C$8) -> 547.2973 | I48: =G48*H48 -> 225 | J48: =J47 -> 0 | K48: =K47 -> 1 | L48: =J48*K48 -> 0 | M48: =L48*G48 -> 0 | N48: =L48*I48 -> 0
A49: YC-07 | B49: Compost preparation | C49: የተፈጥሮ ማዳበሪያ ዝግጅት | D49: Nutrition | E49: m³ | F49: +50% | G49: =G47 -> 0.41111111 | H49: =H47*(1+Settings!$C$9) -> 656.75676 | I49: =G49*H49 -> 270 | J49: =J47 -> 0 | K49: =K47 -> 1 | L49: =J49*K49 -> 0 | M49: =L49*G49 -> 0 | N49: =L49*I49 -> 0
A50: YC-07 | B50: Compost preparation | C50: የተፈጥሮ ማዳበሪያ ዝግጅት | D50: Nutrition | E50: m³ | F50: Expert input | G50: =G47 -> 0.41111111 | H50: =H47 -> 437.83784 | I50: =G50*H50 -> 180 | J50: =J47 -> 0 | K50: =K47 -> 1 | L50: =J50*K50 -> 0 | M50: =L50*G50 -> 0 | N50: =L50*I50 -> 0
A51: YC-07 | B51: Compost preparation | C51: የተፈጥሮ ማዳበሪያ ዝግጅት | D51: Nutrition | E51: m³ | F51: Chaka Buna plan | G51: =CHOOSE(IF(OR($C$3="Expert input",$I$47=0),4,IF($C$3="+25%",2,IF($C$3="+50%",3,1))),G47,G48,G49,G50) -> 0.41111111 | H51: =CHOOSE(IF(OR($C$3="Expert input",$I$47=0),4,IF($C$3="+25%",2,IF($C$3="+50%",3,1))),H47,H48,H49,H50) -> 437.83784 | I51: =G51*H51 -> 180 | J51: =J47 -> 0 | K51: =CHOOSE(IF(OR($C$3="Expert input",$I$47=0),4,IF($C$3="+25%",2,IF($C$3="+50%",3,1))),K47,K48,K49,K50) -> 1 | L51: =J51*K51 -> 0 | M51: =L51*G51 -> 0 | N51: =L51*I51 -> 0 | S51: 0.34 | U51: 0.33 | W51: 0.33 | AA51: =O51*$M51 -> 0 | AB51: =O51*$N51 -> 0 | AC51: =P51*$M51 -> 0 | AD51: =P51*$N51 -> 0 | AE51: =Q51*$M51 -> 0 | AF51: =Q51*$N51 -> 0 | AG51: =R51*$M51 -> 0 | AH51: =R51*$N51 -> 0 | AI51: =S51*$M51 -> 0 | AJ51: =S51*$N51 -> 0 | AK51: =T51*$M51 -> 0 | AL51: =T51*$N51 -> 0 | AM51: =U51*$M51 -> 0 | AN51: =U51*$N51 -> 0 | AO51: =V51*$M51 -> 0 | AP51: =V51*$N51 -> 0 | AQ51: =W51*$M51 -> 0 | AR51: =W51*$N51 -> 0 | AS51: =X51*$M51 -> 0 | AT51: =X51*$N51 -> 0 | AU51: =Y51*$M51 -> 0 | AV51: =Y51*$N51 -> 0 | AW51: =Z51*$M51 -> 0 | AX51: =Z51*$N51 -> 0
A52: YC-08 | B52: Compost application | C52: የተፈጥሮ ማዳበሪያ ማድረግ | D52: Nutrition | E52: tree | F52: Industry average | G52: =IFERROR(INDEX('Benchmark Data'!$AC$7:$AC$130,MATCH($A52,'Benchmark Data'!$A$7:$A$130,0)),0) -> 0.01 | H52: =IFERROR(INDEX('Benchmark Data'!$AD$7:$AD$130,MATCH($A52,'Benchmark Data'!$A$7:$A$130,0)),0) -> 200 | I52: =G52*H52 -> 2 | K52: =IFERROR(INDEX('Benchmark Data'!$AE$7:$AE$130,MATCH($A52,'Benchmark Data'!$A$7:$A$130,0)),0) -> 1 | L52: =J52*K52 -> 0 | M52: =L52*G52 -> 0 | N52: =L52*I52 -> 0
A53: YC-08 | B53: Compost application | C53: የተፈጥሮ ማዳበሪያ ማድረግ | D53: Nutrition | E53: tree | F53: +25% | G53: =G52 -> 0.01 | H53: =H52*(1+Settings!$C$8) -> 250 | I53: =G53*H53 -> 2.5 | J53: =J52 -> 0 | K53: =K52 -> 1 | L53: =J53*K53 -> 0 | M53: =L53*G53 -> 0 | N53: =L53*I53 -> 0
A54: YC-08 | B54: Compost application | C54: የተፈጥሮ ማዳበሪያ ማድረግ | D54: Nutrition | E54: tree | F54: +50% | G54: =G52 -> 0.01 | H54: =H52*(1+Settings!$C$9) -> 300 | I54: =G54*H54 -> 3 | J54: =J52 -> 0 | K54: =K52 -> 1 | L54: =J54*K54 -> 0 | M54: =L54*G54 -> 0 | N54: =L54*I54 -> 0
A55: YC-08 | B55: Compost application | C55: የተፈጥሮ ማዳበሪያ ማድረግ | D55: Nutrition | E55: tree | F55: Expert input | G55: =G52 -> 0.01 | H55: =H52 -> 200 | I55: =G55*H55 -> 2 | J55: =J52 -> 0 | K55: =K52 -> 1 | L55: =J55*K55 -> 0 | M55: =L55*G55 -> 0 | N55: =L55*I55 -> 0
A56: YC-08 | B56: Compost application | C56: የተፈጥሮ ማዳበሪያ ማድረግ | D56: Nutrition | E56: tree | F56: Chaka Buna plan | G56: =CHOOSE(IF(OR($C$3="Expert input",$I$52=0),4,IF($C$3="+25%",2,IF($C$3="+50%",3,1))),G52,G53,G54,G55) -> 0.01 | H56: =CHOOSE(IF(OR($C$3="Expert input",$I$52=0),4,IF($C$3="+25%",2,IF($C$3="+50%",3,1))),H52,H53,H54,H55) -> 200 | I56: =G56*H56 -> 2 | J56: =J52 -> 0 | K56: =CHOOSE(IF(OR($C$3="Expert input",$I$52=0),4,IF($C$3="+25%",2,IF($C$3="+50%",3,1))),K52,K53,K54,K55) -> 1 | L56: =J56*K56 -> 0 | M56: =L56*G56 -> 0 | N56: =L56*I56 -> 0 | U56: 1 | AA56: =O56*$M56 -> 0 | AB56: =O56*$N56 -> 0 | AC56: =P56*$M56 -> 0 | AD56: =P56*$N56 -> 0 | AE56: =Q56*$M56 -> 0 | AF56: =Q56*$N56 -> 0 | AG56: =R56*$M56 -> 0 | AH56: =R56*$N56 -> 0 | AI56: =S56*$M56 -> 0 | AJ56: =S56*$N56 -> 0 | AK56: =T56*$M56 -> 0 | AL56: =T56*$N56 -> 0 | AM56: =U56*$M56 -> 0 | AN56: =U56*$N56 -> 0 | AO56: =V56*$M56 -> 0 | AP56: =V56*$N56 -> 0 | AQ56: =W56*$M56 -> 0 | AR56: =W56*$N56 -> 0 | AS56: =X56*$M56 -> 0 | AT56: =X56*$N56 -> 0 | AU56: =Y56*$M56 -> 0 | AV56: =Y56*$N56 -> 0 | AW56: =Z56*$M56 -> 0 | AX56: =Z56*$N56 -> 0
A57: YC-09 | B57: Topping | C57: ቁመት መግታት | D57: Canopy & shade | E57: tree | F57: Industry average | G57: =IFERROR(INDEX('Benchmark Data'!$AC$7:$AC$130,MATCH($A57,'Benchmark Data'!$A$7:$A$130,0)),0) -> 0.01 | H57: =IFERROR(INDEX('Benchmark Data'!$AD$7:$AD$130,MATCH($A57,'Benchmark Data'!$A$7:$A$130,0)),0) -> 100 | I57: =G57*H57 -> 1 | K57: =IFERROR(INDEX('Benchmark Data'!$AE$7:$AE$130,MATCH($A57,'Benchmark Data'!$A$7:$A$130,0)),0) -> 1 | L57: =J57*K57 -> 0 | M57: =L57*G57 -> 0 | N57: =L57*I57 -> 0
A58: YC-09 | B58: Topping | C58: ቁመት መግታት | D58: Canopy & shade | E58: tree | F58: +25% | G58: =G57 -> 0.01 | H58: =H57*(1+Settings!$C$8) -> 125 | I58: =G58*H58 -> 1.25 | J58: =J57 -> 0 | K58: =K57 -> 1 | L58: =J58*K58 -> 0 | M58: =L58*G58 -> 0 | N58: =L58*I58 -> 0
A59: YC-09 | B59: Topping | C59: ቁመት መግታት | D59: Canopy & shade | E59: tree | F59: +50% | G59: =G57 -> 0.01 | H59: =H57*(1+Settings!$C$9) -> 150 | I59: =G59*H59 -> 1.5 | J59: =J57 -> 0 | K59: =K57 -> 1 | L59: =J59*K59 -> 0 | M59: =L59*G59 -> 0 | N59: =L59*I59 -> 0
A60: YC-09 | B60: Topping | C60: ቁመት መግታት | D60: Canopy & shade | E60: tree | F60: Expert input | G60: =G57 -> 0.01 | H60: =H57 -> 100 | I60: =G60*H60 -> 1 | J60: =J57 -> 0 | K60: =K57 -> 1 | L60: =J60*K60 -> 0 | M60: =L60*G60 -> 0 | N60: =L60*I60 -> 0
A61: YC-09 | B61: Topping | C61: ቁመት መግታት | D61: Canopy & shade | E61: tree | F61: Chaka Buna plan | G61: =CHOOSE(IF(OR($C$3="Expert input",$I$57=0),4,IF($C$3="+25%",2,IF($C$3="+50%",3,1))),G57,G58,G59,G60) -> 0.01 | H61: =CHOOSE(IF(OR($C$3="Expert input",$I$57=0),4,IF($C$3="+25%",2,IF($C$3="+50%",3,1))),H57,H58,H59,H60) -> 100 | I61: =G61*H61 -> 1 | J61: =J57 -> 0 | K61: =CHOOSE(IF(OR($C$3="Expert input",$I$57=0),4,IF($C$3="+25%",2,IF($C$3="+50%",3,1))),K57,K58,K59,K60) -> 1 | L61: =J61*K61 -> 0 | M61: =L61*G61 -> 0 | N61: =L61*I61 -> 0 | R61: 0.5 | S61: 0.5 | AA61: =O61*$M61 -> 0 | AB61: =O61*$N61 -> 0 | AC61: =P61*$M61 -> 0 | AD61: =P61*$N61 -> 0 | AE61: =Q61*$M61 -> 0 | AF61: =Q61*$N61 -> 0 | AG61: =R61*$M61 -> 0 | AH61: =R61*$N61 -> 0 | AI61: =S61*$M61 -> 0 | AJ61: =S61*$N61 -> 0 | AK61: =T61*$M61 -> 0 | AL61: =T61*$N61 -> 0 | AM61: =U61*$M61 -> 0 | AN61: =U61*$N61 -> 0 | AO61: =V61*$M61 -> 0 | AP61: =V61*$N61 -> 0 | AQ61: =W61*$M61 -> 0 | AR61: =W61*$N61 -> 0 | AS61: =X61*$M61 -> 0 | AT61: =X61*$N61 -> 0 | AU61: =Y61*$M61 -> 0 | AV61: =Y61*$N61 -> 0 | AW61: =Z61*$M61 -> 0 | AX61: =Z61*$N61 -> 0
A62: YC-10 | B62: Shade tree regulation | C62: ጥላ ዛፍ ቅነሳ | D62: Canopy & shade | E62: ha | F62: Industry average | G62: =IFERROR(INDEX('Benchmark Data'!$AC$7:$AC$130,MATCH($A62,'Benchmark Data'!$A$7:$A$130,0)),0) -> 11 | H62: =IFERROR(INDEX('Benchmark Data'!$AD$7:$AD$130,MATCH($A62,'Benchmark Data'!$A$7:$A$130,0)),0) -> 227.27273 | I62: =G62*H62 -> 2500 | J62: =$E$8 -> 0 | K62: =IFERROR(INDEX('Benchmark Data'!$AE$7:$AE$130,MATCH($A62,'Benchmark Data'!$A$7:$A$130,0)),0) -> 1 | L62: =J62*K62 -> 0 | M62: =L62*G62 -> 0 | N62: =L62*I62 -> 0
A63: YC-10 | B63: Shade tree regulation | C63: ጥላ ዛፍ ቅነሳ | D63: Canopy & shade | E63: ha | F63: +25% | G63: =G62 -> 11 | H63: =H62*(1+Settings!$C$8) -> 284.09091 | I63: =G63*H63 -> 3125 | J63: =J62 -> 0 | K63: =K62 -> 1 | L63: =J63*K63 -> 0 | M63: =L63*G63 -> 0 | N63: =L63*I63 -> 0
A64: YC-10 | B64: Shade tree regulation | C64: ጥላ ዛፍ ቅነሳ | D64: Canopy & shade | E64: ha | F64: +50% | G64: =G62 -> 11 | H64: =H62*(1+Settings!$C$9) -> 340.90909 | I64: =G64*H64 -> 3750 | J64: =J62 -> 0 | K64: =K62 -> 1 | L64: =J64*K64 -> 0 | M64: =L64*G64 -> 0 | N64: =L64*I64 -> 0
A65: YC-10 | B65: Shade tree regulation | C65: ጥላ ዛፍ ቅነሳ | D65: Canopy & shade | E65: ha | F65: Expert input | G65: =G62 -> 11 | H65: =H62 -> 227.27273 | I65: =G65*H65 -> 2500 | J65: =J62 -> 0 | K65: =K62 -> 1 | L65: =J65*K65 -> 0 | M65: =L65*G65 -> 0 | N65: =L65*I65 -> 0
A66: YC-10 | B66: Shade tree regulation | C66: ጥላ ዛፍ ቅነሳ | D66: Canopy & shade | E66: ha | F66: Chaka Buna plan | G66: =CHOOSE(IF(OR($C$3="Expert input",$I$62=0),4,IF($C$3="+25%",2,IF($C$3="+50%",3,1))),G62,G63,G64,G65) -> 11 | H66: =CHOOSE(IF(OR($C$3="Expert input",$I$62=0),4,IF($C$3="+25%",2,IF($C$3="+50%",3,1))),H62,H63,H64,H65) -> 227.27273 | I66: =G66*H66 -> 2500 | J66: =J62 -> 0 | K66: =CHOOSE(IF(OR($C$3="Expert input",$I$62=0),4,IF($C$3="+25%",2,IF($C$3="+50%",3,1))),K62,K63,K64,K65) -> 1 | L66: =J66*K66 -> 0 | M66: =L66*G66 -> 0 | N66: =L66*I66 -> 0 | R66: 0.75 | S66: 0.25 | AA66: =O66*$M66 -> 0 | AB66: =O66*$N66 -> 0 | AC66: =P66*$M66 -> 0 | AD66: =P66*$N66 -> 0 | AE66: =Q66*$M66 -> 0 | AF66: =Q66*$N66 -> 0 | AG66: =R66*$M66 -> 0 | AH66: =R66*$N66 -> 0 | AI66: =S66*$M66 -> 0 | AJ66: =S66*$N66 -> 0 | AK66: =T66*$M66 -> 0 | AL66: =T66*$N66 -> 0 | AM66: =U66*$M66 -> 0 | AN66: =U66*$N66 -> 0 | AO66: =V66*$M66 -> 0 | AP66: =V66*$N66 -> 0 | AQ66: =W66*$M66 -> 0 | AR66: =W66*$N66 -> 0 | AS66: =X66*$M66 -> 0 | AT66: =X66*$N66 -> 0 | AU66: =Y66*$M66 -> 0 | AV66: =Y66*$N66 -> 0 | AW66: =Z66*$M66 -> 0 | AX66: =Z66*$N66 -> 0
A67: YC-11 | B67: Terrace construction | C67: እርከን ስራ | D67: Soil conservation | E67: m | F67: Industry average | G67: =IFERROR(INDEX('Benchmark Data'!$AC$7:$AC$130,MATCH($A67,'Benchmark Data'!$A$7:$A$130,0)),0) -> 0.14777778 | H67: =IFERROR(INDEX('Benchmark Data'!$AD$7:$AD$130,MATCH($A67,'Benchmark Data'!$A$7:$A$130,0)),0) -> 124.06015 | I67: =G67*H67 -> 18.333333 | K67: =IFERROR(INDEX('Benchmark Data'!$AE$7:$AE$130,MATCH($A67,'Benchmark Data'!$A$7:$A$130,0)),0) -> 1 | L67: =J67*K67 -> 0 | M67: =L67*G67 -> 0 | N67: =L67*I67 -> 0
A68: YC-11 | B68: Terrace construction | C68: እርከን ስራ | D68: Soil conservation | E68: m | F68: +25% | G68: =G67 -> 0.14777778 | H68: =H67*(1+Settings!$C$8) -> 155.07519 | I68: =G68*H68 -> 22.916667 | J68: =J67 -> 0 | K68: =K67 -> 1 | L68: =J68*K68 -> 0 | M68: =L68*G68 -> 0 | N68: =L68*I68 -> 0
A69: YC-11 | B69: Terrace construction | C69: እርከን ስራ | D69: Soil conservation | E69: m | F69: +50% | G69: =G67 -> 0.14777778 | H69: =H67*(1+Settings!$C$9) -> 186.09023 | I69: =G69*H69 -> 27.5 | J69: =J67 -> 0 | K69: =K67 -> 1 | L69: =J69*K69 -> 0 | M69: =L69*G69 -> 0 | N69: =L69*I69 -> 0
A70: YC-11 | B70: Terrace construction | C70: እርከን ስራ | D70: Soil conservation | E70: m | F70: Expert input | G70: =G67 -> 0.14777778 | H70: =H67 -> 124.06015 | I70: =G70*H70 -> 18.333333 | J70: =J67 -> 0 | K70: =K67 -> 1 | L70: =J70*K70 -> 0 | M70: =L70*G70 -> 0 | N70: =L70*I70 -> 0
A71: YC-11 | B71: Terrace construction | C71: እርከን ስራ | D71: Soil conservation | E71: m | F71: Chaka Buna plan | G71: =CHOOSE(IF(OR($C$3="Expert input",$I$67=0),4,IF($C$3="+25%",2,IF($C$3="+50%",3,1))),G67,G68,G69,G70) -> 0.14777778 | H71: =CHOOSE(IF(OR($C$3="Expert input",$I$67=0),4,IF($C$3="+25%",2,IF($C$3="+50%",3,1))),H67,H68,H69,H70) -> 124.06015 | I71: =G71*H71 -> 18.333333 | J71: =J67 -> 0 | K71: =CHOOSE(IF(OR($C$3="Expert input",$I$67=0),4,IF($C$3="+25%",2,IF($C$3="+50%",3,1))),K67,K68,K69,K70) -> 1 | L71: =J71*K71 -> 0 | M71: =L71*G71 -> 0 | N71: =L71*I71 -> 0 | R71: 0.5 | S71: 0.34 | T71: 0.16 | AA71: =O71*$M71 -> 0 | AB71: =O71*$N71 -> 0 | AC71: =P71*$M71 -> 0 | AD71: =P71*$N71 -> 0 | AE71: =Q71*$M71 -> 0 | AF71: =Q71*$N71 -> 0 | AG71: =R71*$M71 -> 0 | AH71: =R71*$N71 -> 0 | AI71: =S71*$M71 -> 0 | AJ71: =S71*$N71 -> 0 | AK71: =T71*$M71 -> 0 | AL71: =T71*$N71 -> 0 | AM71: =U71*$M71 -> 0 | AN71: =U71*$N71 -> 0 | AO71: =V71*$M71 -> 0 | AP71: =V71*$N71 -> 0 | AQ71: =W71*$M71 -> 0 | AR71: =W71*$N71 -> 0 | AS71: =X71*$M71 -> 0 | AT71: =X71*$N71 -> 0 | AU71: =Y71*$M71 -> 0 | AV71: =Y71*$N71 -> 0 | AW71: =Z71*$M71 -> 0 | AX71: =Z71*$N71 -> 0
A72: YC-12 | B72: Terrace maintenance | C72: እርከን እደሳ | D72: Soil conservation | E72: m | F72: Industry average | G72: =IFERROR(INDEX('Benchmark Data'!$AC$7:$AC$130,MATCH($A72,'Benchmark Data'!$A$7:$A$130,0)),0) -> 0.061666667 | H72: =IFERROR(INDEX('Benchmark Data'!$AD$7:$AD$130,MATCH($A72,'Benchmark Data'!$A$7:$A$130,0)),0) -> 121.62162 | I72: =G72*H72 -> 7.5 | K72: =IFERROR(INDEX('Benchmark Data'!$AE$7:$AE$130,MATCH($A72,'Benchmark Data'!$A$7:$A$130,0)),0) -> 1 | L72: =J72*K72 -> 0 | M72: =L72*G72 -> 0 | N72: =L72*I72 -> 0
A73: YC-12 | B73: Terrace maintenance | C73: እርከን እደሳ | D73: Soil conservation | E73: m | F73: +25% | G73: =G72 -> 0.061666667 | H73: =H72*(1+Settings!$C$8) -> 152.02703 | I73: =G73*H73 -> 9.375 | J73: =J72 -> 0 | K73: =K72 -> 1 | L73: =J73*K73 -> 0 | M73: =L73*G73 -> 0 | N73: =L73*I73 -> 0
A74: YC-12 | B74: Terrace maintenance | C74: እርከን እደሳ | D74: Soil conservation | E74: m | F74: +50% | G74: =G72 -> 0.061666667 | H74: =H72*(1+Settings!$C$9) -> 182.43243 | I74: =G74*H74 -> 11.25 | J74: =J72 -> 0 | K74: =K72 -> 1 | L74: =J74*K74 -> 0 | M74: =L74*G74 -> 0 | N74: =L74*I74 -> 0
A75: YC-12 | B75: Terrace maintenance | C75: እርከን እደሳ | D75: Soil conservation | E75: m | F75: Expert input | G75: =G72 -> 0.061666667 | H75: =H72 -> 121.62162 | I75: =G75*H75 -> 7.5 | J75: =J72 -> 0 | K75: =K72 -> 1 | L75: =J75*K75 -> 0 | M75: =L75*G75 -> 0 | N75: =L75*I75 -> 0
A76: YC-12 | B76: Terrace maintenance | C76: እርከን እደሳ | D76: Soil conservation | E76: m | F76: Chaka Buna plan | G76: =CHOOSE(IF(OR($C$3="Expert input",$I$72=0),4,IF($C$3="+25%",2,IF($C$3="+50%",3,1))),G72,G73,G74,G75) -> 0.061666667 | H76: =CHOOSE(IF(OR($C$3="Expert input",$I$72=0),4,IF($C$3="+25%",2,IF($C$3="+50%",3,1))),H72,H73,H74,H75) -> 121.62162 | I76: =G76*H76 -> 7.5 | J76: =J72 -> 0 | K76: =CHOOSE(IF(OR($C$3="Expert input",$I$72=0),4,IF($C$3="+25%",2,IF($C$3="+50%",3,1))),K72,K73,K74,K75) -> 1 | L76: =J76*K76 -> 0 | M76: =L76*G76 -> 0 | N76: =L76*I76 -> 0 | U76: 0.67 | V76: 0.33 | AA76: =O76*$M76 -> 0 | AB76: =O76*$N76 -> 0 | AC76: =P76*$M76 -> 0 | AD76: =P76*$N76 -> 0 | AE76: =Q76*$M76 -> 0 | AF76: =Q76*$N76 -> 0 | AG76: =R76*$M76 -> 0 | AH76: =R76*$N76 -> 0 | AI76: =S76*$M76 -> 0 | AJ76: =S76*$N76 -> 0 | AK76: =T76*$M76 -> 0 | AL76: =T76*$N76 -> 0 | AM76: =U76*$M76 -> 0 | AN76: =U76*$N76 -> 0 | AO76: =V76*$M76 -> 0 | AP76: =V76*$N76 -> 0 | AQ76: =W76*$M76 -> 0 | AR76: =W76*$N76 -> 0 | AS76: =X76*$M76 -> 0 | AT76: =X76*$N76 -> 0 | AU76: =Y76*$M76 -> 0 | AV76: =Y76*$N76 -> 0 | AW76: =Z76*$M76 -> 0 | AX76: =Z76*$N76 -> 0
A77: YC-13 | B77: Vetiver planting | C77: ቪቲቫር ተከላ | D77: Soil conservation | E77: m | F77: Industry average | G77: =IFERROR(INDEX('Benchmark Data'!$AC$7:$AC$130,MATCH($A77,'Benchmark Data'!$A$7:$A$130,0)),0) -> 0 | H77: =IFERROR(INDEX('Benchmark Data'!$AD$7:$AD$130,MATCH($A77,'Benchmark Data'!$A$7:$A$130,0)),0) -> 0 | I77: =G77*H77 -> 0 | K77: =IFERROR(INDEX('Benchmark Data'!$AE$7:$AE$130,MATCH($A77,'Benchmark Data'!$A$7:$A$130,0)),0) -> 1 | L77: =J77*K77 -> 0 | M77: =L77*G77 -> 0 | N77: =L77*I77 -> 0
A78: YC-13 | B78: Vetiver planting | C78: ቪቲቫር ተከላ | D78: Soil conservation | E78: m | F78: +25% | G78: =G77 -> 0 | H78: =H77*(1+Settings!$C$8) -> 0 | I78: =G78*H78 -> 0 | J78: =J77 -> 0 | K78: =K77 -> 1 | L78: =J78*K78 -> 0 | M78: =L78*G78 -> 0 | N78: =L78*I78 -> 0
A79: YC-13 | B79: Vetiver planting | C79: ቪቲቫር ተከላ | D79: Soil conservation | E79: m | F79: +50% | G79: =G77 -> 0 | H79: =H77*(1+Settings!$C$9) -> 0 | I79: =G79*H79 -> 0 | J79: =J77 -> 0 | K79: =K77 -> 1 | L79: =J79*K79 -> 0 | M79: =L79*G79 -> 0 | N79: =L79*I79 -> 0
A80: YC-13 | B80: Vetiver planting | C80: ቪቲቫር ተከላ | D80: Soil conservation | E80: m | F80: Expert input | G80: =IFERROR(INDEX('Benchmark Data'!$AH$7:$AH$130,MATCH($A80,'Benchmark Data'!$A$7:$A$130,0)),0) -> 0.05 | H80: =IFERROR(INDEX('Benchmark Data'!$AI$7:$AI$130,MATCH($A80,'Benchmark Data'!$A$7:$A$130,0)),0) -> 100 | I80: =G80*H80 -> 5 | J80: =J77 -> 0 | K80: =IFERROR(INDEX('Benchmark Data'!$AJ$7:$AJ$130,MATCH($A80,'Benchmark Data'!$A$7:$A$130,0)),0) -> 1 | L80: =J80*K80 -> 0 | M80: =L80*G80 -> 0 | N80: =L80*I80 -> 0
A81: YC-13 | B81: Vetiver planting | C81: ቪቲቫር ተከላ | D81: Soil conservation | E81: m | F81: Chaka Buna plan | G81: =CHOOSE(IF(OR($C$3="Expert input",$I$77=0),4,IF($C$3="+25%",2,IF($C$3="+50%",3,1))),G77,G78,G79,G80) -> 0.05 | H81: =CHOOSE(IF(OR($C$3="Expert input",$I$77=0),4,IF($C$3="+25%",2,IF($C$3="+50%",3,1))),H77,H78,H79,H80) -> 100 | I81: =G81*H81 -> 5 | J81: =J77 -> 0 | K81: =CHOOSE(IF(OR($C$3="Expert input",$I$77=0),4,IF($C$3="+25%",2,IF($C$3="+50%",3,1))),K77,K78,K79,K80) -> 1 | L81: =J81*K81 -> 0 | M81: =L81*G81 -> 0 | N81: =L81*I81 -> 0 | V81: 1 | AA81: =O81*$M81 -> 0 | AB81: =O81*$N81 -> 0 | AC81: =P81*$M81 -> 0 | AD81: =P81*$N81 -> 0 | AE81: =Q81*$M81 -> 0 | AF81: =Q81*$N81 -> 0 | AG81: =R81*$M81 -> 0 | AH81: =R81*$N81 -> 0 | AI81: =S81*$M81 -> 0 | AJ81: =S81*$N81 -> 0 | AK81: =T81*$M81 -> 0 | AL81: =T81*$N81 -> 0 | AM81: =U81*$M81 -> 0 | AN81: =U81*$N81 -> 0 | AO81: =V81*$M81 -> 0 | AP81: =V81*$N81 -> 0 | AQ81: =W81*$M81 -> 0 | AR81: =W81*$N81 -> 0 | AS81: =X81*$M81 -> 0 | AT81: =X81*$N81 -> 0 | AU81: =Y81*$M81 -> 0 | AV81: =Y81*$N81 -> 0 | AW81: =Z81*$M81 -> 0 | AX81: =Z81*$N81 -> 0
A82: YC-14 | B82: Vetiver maintenance | C82: ቪቲቫር እንክብካቤ | D82: Soil conservation | E82: m | F82: Industry average | G82: =IFERROR(INDEX('Benchmark Data'!$AC$7:$AC$130,MATCH($A82,'Benchmark Data'!$A$7:$A$130,0)),0) -> 0 | H82: =IFERROR(INDEX('Benchmark Data'!$AD$7:$AD$130,MATCH($A82,'Benchmark Data'!$A$7:$A$130,0)),0) -> 0 | I82: =G82*H82 -> 0 | K82: =IFERROR(INDEX('Benchmark Data'!$AE$7:$AE$130,MATCH($A82,'Benchmark Data'!$A$7:$A$130,0)),0) -> 1 | L82: =J82*K82 -> 0 | M82: =L82*G82 -> 0 | N82: =L82*I82 -> 0
A83: YC-14 | B83: Vetiver maintenance | C83: ቪቲቫር እንክብካቤ | D83: Soil conservation | E83: m | F83: +25% | G83: =G82 -> 0 | H83: =H82*(1+Settings!$C$8) -> 0 | I83: =G83*H83 -> 0 | J83: =J82 -> 0 | K83: =K82 -> 1 | L83: =J83*K83 -> 0 | M83: =L83*G83 -> 0 | N83: =L83*I83 -> 0
A84: YC-14 | B84: Vetiver maintenance | C84: ቪቲቫር እንክብካቤ | D84: Soil conservation | E84: m | F84: +50% | G84: =G82 -> 0 | H84: =H82*(1+Settings!$C$9) -> 0 | I84: =G84*H84 -> 0 | J84: =J82 -> 0 | K84: =K82 -> 1 | L84: =J84*K84 -> 0 | M84: =L84*G84 -> 0 | N84: =L84*I84 -> 0
A85: YC-14 | B85: Vetiver maintenance | C85: ቪቲቫር እንክብካቤ | D85: Soil conservation | E85: m | F85: Expert input | I85: =G85*H85 -> 0 | J85: =J82 -> 0 | K85: 1 | L85: =J85*K85 -> 0 | M85: =L85*G85 -> 0 | N85: =L85*I85 -> 0
A86: YC-14 | B86: Vetiver maintenance | C86: ቪቲቫር እንክብካቤ | D86: Soil conservation | E86: m | F86: Chaka Buna plan | G86: =CHOOSE(IF(OR($C$3="Expert input",$I$82=0),4,IF($C$3="+25%",2,IF($C$3="+50%",3,1))),G82,G83,G84,G85) -> 0 | H86: =CHOOSE(IF(OR($C$3="Expert input",$I$82=0),4,IF($C$3="+25%",2,IF($C$3="+50%",3,1))),H82,H83,H84,H85) -> 0 | I86: =G86*H86 -> 0 | J86: =J82 -> 0 | K86: =CHOOSE(IF(OR($C$3="Expert input",$I$82=0),4,IF($C$3="+25%",2,IF($C$3="+50%",3,1))),K82,K83,K84,K85) -> 1 | L86: =J86*K86 -> 0 | M86: =L86*G86 -> 0 | N86: =L86*I86 -> 0 | AA86: =O86*$M86 -> 0 | AB86: =O86*$N86 -> 0 | AC86: =P86*$M86 -> 0 | AD86: =P86*$N86 -> 0 | AE86: =Q86*$M86 -> 0 | AF86: =Q86*$N86 -> 0 | AG86: =R86*$M86 -> 0 | AH86: =R86*$N86 -> 0 | AI86: =S86*$M86 -> 0 | AJ86: =S86*$N86 -> 0 | AK86: =T86*$M86 -> 0 | AL86: =T86*$N86 -> 0 | AM86: =U86*$M86 -> 0 | AN86: =U86*$N86 -> 0 | AO86: =V86*$M86 -> 0 | AP86: =V86*$N86 -> 0 | AQ86: =W86*$M86 -> 0 | AR86: =W86*$N86 -> 0 | AS86: =X86*$M86 -> 0 | AT86: =X86*$N86 -> 0 | AU86: =Y86*$M86 -> 0 | AV86: =Y86*$N86 -> 0 | AW86: =Z86*$M86 -> 0 | AX86: =Z86*$N86 -> 0
A87: YC-15 | B87: Survival count & gap recording | D87: SPX addition – no B-Agro benchmark | E87: tree | F87: Industry average | G87: =IFERROR(INDEX('Benchmark Data'!$AC$7:$AC$130,MATCH($A87,'Benchmark Data'!$A$7:$A$130,0)),0) -> 0 | H87: =IFERROR(INDEX('Benchmark Data'!$AD$7:$AD$130,MATCH($A87,'Benchmark Data'!$A$7:$A$130,0)),0) -> 0 | I87: =G87*H87 -> 0 | J87: =$E$7 -> 0 | K87: =IFERROR(INDEX('Benchmark Data'!$AE$7:$AE$130,MATCH($A87,'Benchmark Data'!$A$7:$A$130,0)),0) -> 1 | L87: =J87*K87 -> 0 | M87: =L87*G87 -> 0 | N87: =L87*I87 -> 0
A88: YC-15 | B88: Survival count & gap recording | D88: SPX addition – no B-Agro benchmark | E88: tree | F88: +25% | G88: =G87 -> 0 | H88: =H87*(1+Settings!$C$8) -> 0 | I88: =G88*H88 -> 0 | J88: =J87 -> 0 | K88: =K87 -> 1 | L88: =J88*K88 -> 0 | M88: =L88*G88 -> 0 | N88: =L88*I88 -> 0
A89: YC-15 | B89: Survival count & gap recording | D89: SPX addition – no B-Agro benchmark | E89: tree | F89: +50% | G89: =G87 -> 0 | H89: =H87*(1+Settings!$C$9) -> 0 | I89: =G89*H89 -> 0 | J89: =J87 -> 0 | K89: =K87 -> 1 | L89: =J89*K89 -> 0 | M89: =L89*G89 -> 0 | N89: =L89*I89 -> 0
A90: YC-15 | B90: Survival count & gap recording | D90: SPX addition – no B-Agro benchmark | E90: tree | F90: Expert input | I90: =G90*H90 -> 0 | J90: =J87 -> 0 | K90: 1 | L90: =J90*K90 -> 0 | M90: =L90*G90 -> 0 | N90: =L90*I90 -> 0
A91: YC-15 | B91: Survival count & gap recording | D91: SPX addition – no B-Agro benchmark | E91: tree | F91: Chaka Buna plan | G91: =CHOOSE(IF(OR($C$3="Expert input",$I$87=0),4,IF($C$3="+25%",2,IF($C$3="+50%",3,1))),G87,G88,G89,G90) -> 0 | H91: =CHOOSE(IF(OR($C$3="Expert input",$I$87=0),4,IF($C$3="+25%",2,IF($C$3="+50%",3,1))),H87,H88,H89,H90) -> 0 | I91: =G91*H91 -> 0 | J91: =J87 -> 0 | K91: =CHOOSE(IF(OR($C$3="Expert input",$I$87=0),4,IF($C$3="+25%",2,IF($C$3="+50%",3,1))),K87,K88,K89,K90) -> 1 | L91: =J91*K91 -> 0 | M91: =L91*G91 -> 0 | N91: =L91*I91 -> 0 | AA91: =O91*$M91 -> 0 | AB91: =O91*$N91 -> 0 | AC91: =P91*$M91 -> 0 | AD91: =P91*$N91 -> 0 | AE91: =Q91*$M91 -> 0 | AF91: =Q91*$N91 -> 0 | AG91: =R91*$M91 -> 0 | AH91: =R91*$N91 -> 0 | AI91: =S91*$M91 -> 0 | AJ91: =S91*$N91 -> 0 | AK91: =T91*$M91 -> 0 | AL91: =T91*$N91 -> 0 | AM91: =U91*$M91 -> 0 | AN91: =U91*$N91 -> 0 | AO91: =V91*$M91 -> 0 | AP91: =V91*$N91 -> 0 | AQ91: =W91*$M91 -> 0 | AR91: =W91*$N91 -> 0 | AS91: =X91*$M91 -> 0 | AT91: =X91*$N91 -> 0 | AU91: =Y91*$M91 -> 0 | AV91: =Y91*$N91 -> 0 | AW91: =Z91*$M91 -> 0 | AX91: =Z91*$N91 -> 0

Sheet Matured Coffee
A1: Matured Coffee – activity plan and budget
A2: ="Farm: "&Settings!$C$6&" | Plan year: "&Settings!$C$7 -> Farm: Chaka Buna Estate (Silva Forest Coffee) | Plan year: 2019 EFY (2026/27) – confirm
B3: Plan basis (drop-down) ► | C3: Industry average | D3: Sets the Chaka Buna plan row of every activity on this tab. Activities with no industry-average rate always use the Expert input row.
B5: GENERAL INFORMATION | F5: CATEGORY TOTALS
B6: Metric (English) | C6: Metric (Amharic) | D6: Unit | E6: Quantity | F6: Rate scenario | M6: Total man-days | N6: Total cost (birr) | O6: Plan phasing (% of cost) | AA6: Plan monthly totals
B7: Total coffee area | C7: ጠቅላላ የመሬት (ሄ/ር) | D7: ha | F7: Industry average | M7: =SUMIF($F$17:$F$191,"Industry average",M$17:M$191) -> 0 | N7: =SUMIF($F$17:$F$191,"Industry average",N$17:N$191) -> 0
B8: Total mature trees (net area) | C8: እናት ቡና እግር ብዛት (ቁጥር) | D8: no. | F8: +25% | M8: =SUMIF($F$17:$F$191,"+25%",M$17:M$191) -> 0 | N8: =SUMIF($F$17:$F$191,"+25%",N$17:N$191) -> 0
B9: Average trees per ha | C9: የቡና እግር አማካይ (ሄ/ር) | D9: trees/ha | E9: =IFERROR($E$8/$E$7,0) -> 0 | F9: +50% | M9: =SUMIF($F$17:$F$191,"+50%",M$17:M$191) -> 0 | N9: =SUMIF($F$17:$F$191,"+50%",N$17:N$191) -> 0
B10: Trees to stump | C10: የሚጎነደል ቡና | D10: no. | F10: Expert input | M10: =SUMIF($F$17:$F$191,"Expert input",M$17:M$191) -> 0 | N10: =SUMIF($F$17:$F$191,"Expert input",N$17:N$191) -> 0
F11: Chaka Buna plan – counts in Summary | M11: =SUMIF($F$17:$F$191,"Chaka Buna plan",M$17:M$191) -> 0 | N11: =SUMIF($F$17:$F$191,"Chaka Buna plan",N$17:N$191) -> 0 | O11: =IFERROR(AB11/$N$11,0) -> 0 | P11: =IFERROR(AD11/$N$11,0) -> 0 | Q11: =IFERROR(AF11/$N$11,0) -> 0 | R11: =IFERROR(AH11/$N$11,0) -> 0 | S11: =IFERROR(AJ11/$N$11,0) -> 0 | T11: =IFERROR(AL11/$N$11,0) -> 0 | U11: =IFERROR(AN11/$N$11,0) -> 0 | V11: =IFERROR(AP11/$N$11,0) -> 0 | W11: =IFERROR(AR11/$N$11,0) -> 0 | X11: =IFERROR(AT11/$N$11,0) -> 0 | Y11: =IFERROR(AV11/$N$11,0) -> 0 | Z11: =IFERROR(AX11/$N$11,0) -> 0 | AA11: =SUM(AA17:AA191) -> 0 | AB11: =SUM(AB17:AB191) -> 0 | AC11: =SUM(AC17:AC191) -> 0 | AD11: =SUM(AD17:AD191) -> 0 | AE11: =SUM(AE17:AE191) -> 0 | AF11: =SUM(AF17:AF191) -> 0 | AG11: =SUM(AG17:AG191) -> 0 | AH11: =SUM(AH17:AH191) -> 0 | ... AX11: =SUM(AX17:AX191) -> 0
A15: ACTIVITY | F15: RATE (cost per unit = man-days × wage) | J15: QUANTITY | L15: TOTALS (calculated) | O15: PHASING – % of annual (input on the Chaka Buna plan row) | AA15: MONTHLY MAN-DAYS AND COST (Chaka Buna plan row)
A16: Code | B16: Activity | C16: Activity (Amharic) | D16: Sub-group | E16: Unit | F16: Rate scenario | G16: Man-days per unit | H16: Wage per man-day (birr) | I16: Cost per unit (birr) | J16: Activity quantity per round | K16: Frequency (times / year) | L16: Total activity quantity | M16: Total man-days per activity | N16: Total cost per activity (birr) | O16: Tikimt (Oct) | P16: Hidar (Nov) | Q16: Tahsas (Dec) | R16: Tir (Jan) | S16: Yekatit (Feb) | T16: Megabit (Mar) | U16: Miyazya (Apr) | V16: Ginbot (May) | W16: Sene (Jun) | X16: Hamle (Jul) | Y16: Nehase (Aug) | Z16: Meskerem (Sep) | AA16: Tikimt (Oct) – man-days | AB16: Tikimt (Oct) – cost | AC16: Hidar (Nov) – man-days | AD16: Hidar (Nov) – cost | AE16: Tahsas (Dec) – man-days | AF16: Tahsas (Dec) – cost | AG16: Tir (Jan) – man-days | AH16: Tir (Jan) – cost | AI16: Yekatit (Feb) – man-days | AJ16: Yekatit (Feb) – cost | AK16: Megabit (Mar) – man-days | AL16: Megabit (Mar) – cost | AM16: Miyazya (Apr) – man-days | AN16: Miyazya (Apr) – cost | AO16: Ginbot (May) – man-days | AP16: Ginbot (May) – cost | AQ16: Sene (Jun) – man-days | AR16: Sene (Jun) – cost | AS16: Hamle (Jul) – man-days | AT16: Hamle (Jul) – cost | AU16: Nehase (Aug) – man-days | AV16: Nehase (Aug) – cost | AW16: Meskerem (Sep) – man-days | AX16: Meskerem (Sep) – cost
A17: MC-01 | B17: Manual weeding (slashing) | C17: አረም ቁጥጥር በገጀራ | D17: Weed control | E17: ha | F17: Industry average | G17: =IFERROR(INDEX('Benchmark Data'!$AC$7:$AC$130,MATCH($A17,'Benchmark Data'!$A$7:$A$130,0)),0) -> 20 | H17: =IFERROR(INDEX('Benchmark Data'!$AD$7:$AD$130,MATCH($A17,'Benchmark Data'!$A$7:$A$130,0)),0) -> 200 | I17: =G17*H17 -> 4000 | J17: =$E$7 -> 0 | K17: =IFERROR(INDEX('Benchmark Data'!$AE$7:$AE$130,MATCH($A17,'Benchmark Data'!$A$7:$A$130,0)),0) -> 3 | L17: =J17*K17 -> 0 | M17: =L17*G17 -> 0 | N17: =L17*I17 -> 0
A18: MC-01 | B18: Manual weeding (slashing) | C18: አረም ቁጥጥር በገጀራ | D18: Weed control | E18: ha | F18: +25% | G18: =G17 -> 20 | H18: =H17*(1+Settings!$C$8) -> 250 | I18: =G18*H18 -> 5000 | J18: =J17 -> 0 | K18: =K17 -> 3 | L18: =J18*K18 -> 0 | M18: =L18*G18 -> 0 | N18: =L18*I18 -> 0
A19: MC-01 | B19: Manual weeding (slashing) | C19: አረም ቁጥጥር በገጀራ | D19: Weed control | E19: ha | F19: +50% | G19: =G17 -> 20 | H19: =H17*(1+Settings!$C$9) -> 300 | I19: =G19*H19 -> 6000 | J19: =J17 -> 0 | K19: =K17 -> 3 | L19: =J19*K19 -> 0 | M19: =L19*G19 -> 0 | N19: =L19*I19 -> 0
A20: MC-01 | B20: Manual weeding (slashing) | C20: አረም ቁጥጥር በገጀራ | D20: Weed control | E20: ha | F20: Expert input | G20: =G17 -> 20 | H20: =H17 -> 200 | I20: =G20*H20 -> 4000 | J20: =J17 -> 0 | K20: =K17 -> 3 | L20: =J20*K20 -> 0 | M20: =L20*G20 -> 0 | N20: =L20*I20 -> 0
A21: MC-01 | B21: Manual weeding (slashing) | C21: አረም ቁጥጥር በገጀራ | D21: Weed control | E21: ha | F21: Chaka Buna plan | G21: =CHOOSE(IF(OR($C$3="Expert input",$I$17=0),4,IF($C$3="+25%",2,IF($C$3="+50%",3,1))),G17,G18,G19,G20) -> 20 | H21: =CHOOSE(IF(OR($C$3="Expert input",$I$17=0),4,IF($C$3="+25%",2,IF($C$3="+50%",3,1))),H17,H18,H19,H20) -> 200 | I21: =G21*H21 -> 4000 | J21: =J17 -> 0 | K21: =CHOOSE(IF(OR($C$3="Expert input",$I$17=0),4,IF($C$3="+25%",2,IF($C$3="+50%",3,1))),K17,K18,K19,K20) -> 3 | L21: =J21*K21 -> 0 | M21: =L21*G21 -> 0 | N21: =L21*I21 -> 0 | Q21: 0.14 | R21: 0.02 | S21: 0.15 | T21: 0.13 | U21: 0.05 | V21: 0.15 | W21: 0.04 | X21: 0.15 | Y21: 0.04 | Z21: 0.13 | AA21: =O21*$M21 -> 0 | AB21: =O21*$N21 -> 0 | AC21: =P21*$M21 -> 0 | AD21: =P21*$N21 -> 0 | AE21: =Q21*$M21 -> 0 | AF21: =Q21*$N21 -> 0 | AG21: =R21*$M21 -> 0 | AH21: =R21*$N21 -> 0 | AI21: =S21*$M21 -> 0 | AJ21: =S21*$N21 -> 0 | AK21: =T21*$M21 -> 0 | AL21: =T21*$N21 -> 0 | AM21: =U21*$M21 -> 0 | AN21: =U21*$N21 -> 0 | AO21: =V21*$M21 -> 0 | AP21: =V21*$N21 -> 0 | AQ21: =W21*$M21 -> 0 | AR21: =W21*$N21 -> 0 | AS21: =X21*$M21 -> 0 | AT21: =X21*$N21 -> 0 | AU21: =Y21*$M21 -> 0 | AV21: =Y21*$N21 -> 0 | AW21: =Z21*$M21 -> 0 | AX21: =Z21*$N21 -> 0
A22: MC-02 | B22: Chemical weeding | C22: ፀረ-አረም መድሃኒት ርጭት | D22: Weed control | E22: ha | F22: Industry average | G22: =IFERROR(INDEX('Benchmark Data'!$AC$7:$AC$130,MATCH($A22,'Benchmark Data'!$A$7:$A$130,0)),0) -> 3.4444444 | H22: =IFERROR(INDEX('Benchmark Data'!$AD$7:$AD$130,MATCH($A22,'Benchmark Data'!$A$7:$A$130,0)),0) -> 240 | I22: =G22*H22 -> 826.66667 | K22: =IFERROR(INDEX('Benchmark Data'!$AE$7:$AE$130,MATCH($A22,'Benchmark Data'!$A$7:$A$130,0)),0) -> 2 | L22: =J22*K22 -> 0 | M22: =L22*G22 -> 0 | N22: =L22*I22 -> 0
A23: MC-02 | B23: Chemical weeding | C23: ፀረ-አረም መድሃኒት ርጭት | D23: Weed control | E23: ha | F23: +25% | G23: =G22 -> 3.4444444 | H23: =H22*(1+Settings!$C$8) -> 300 | I23: =G23*H23 -> 1033.3333 | J23: =J22 -> 0 | K23: =K22 -> 2 | L23: =J23*K23 -> 0 | M23: =L23*G23 -> 0 | N23: =L23*I23 -> 0
A24: MC-02 | B24: Chemical weeding | C24: ፀረ-አረም መድሃኒት ርጭት | D24: Weed control | E24: ha | F24: +50% | G24: =G22 -> 3.4444444 | H24: =H22*(1+Settings!$C$9) -> 360 | I24: =G24*H24 -> 1240 | J24: =J22 -> 0 | K24: =K22 -> 2 | L24: =J24*K24 -> 0 | M24: =L24*G24 -> 0 | N24: =L24*I24 -> 0
A25: MC-02 | B25: Chemical weeding | C25: ፀረ-አረም መድሃኒት ርጭት | D25: Weed control | E25: ha | F25: Expert input | G25: =G22 -> 3.4444444 | H25: =H22 -> 240 | I25: =G25*H25 -> 826.66667 | J25: =J22 -> 0 | K25: =K22 -> 2 | L25: =J25*K25 -> 0 | M25: =L25*G25 -> 0 | N25: =L25*I25 -> 0
A26: MC-02 | B26: Chemical weeding | C26: ፀረ-አረም መድሃኒት ርጭት | D26: Weed control | E26: ha | F26: Chaka Buna plan | G26: =CHOOSE(IF(OR($C$3="Expert input",$I$22=0),4,IF($C$3="+25%",2,IF($C$3="+50%",3,1))),G22,G23,G24,G25) -> 3.4444444 | H26: =CHOOSE(IF(OR($C$3="Expert input",$I$22=0),4,IF($C$3="+25%",2,IF($C$3="+50%",3,1))),H22,H23,H24,H25) -> 240 | I26: =G26*H26 -> 826.66667 | J26: =J22 -> 0 | K26: =CHOOSE(IF(OR($C$3="Expert input",$I$22=0),4,IF($C$3="+25%",2,IF($C$3="+50%",3,1))),K22,K23,K24,K25) -> 2 | L26: =J26*K26 -> 0 | M26: =L26*G26 -> 0 | N26: =L26*I26 -> 0 | O26: 0.22 | T26: 0.09 | U26: 0.05 | V26: 0.17 | W26: 0.07 | Y26: 0.23 | Z26: 0.17 | AA26: =O26*$M26 -> 0 | AB26: =O26*$N26 -> 0 | AC26: =P26*$M26 -> 0 | AD26: =P26*$N26 -> 0 | AE26: =Q26*$M26 -> 0 | AF26: =Q26*$N26 -> 0 | AG26: =R26*$M26 -> 0 | AH26: =R26*$N26 -> 0 | AI26: =S26*$M26 -> 0 | AJ26: =S26*$N26 -> 0 | AK26: =T26*$M26 -> 0 | AL26: =T26*$N26 -> 0 | AM26: =U26*$M26 -> 0 | AN26: =U26*$N26 -> 0 | AO26: =V26*$M26 -> 0 | AP26: =V26*$N26 -> 0 | AQ26: =W26*$M26 -> 0 | AR26: =W26*$N26 -> 0 | AS26: =X26*$M26 -> 0 | AT26: =X26*$N26 -> 0 | AU26: =Y26*$M26 -> 0 | AV26: =Y26*$N26 -> 0 | AW26: =Z26*$M26 -> 0 | AX26: =Z26*$N26 -> 0
A27: MC-03 | B27: Water fetching for spraying | C27: ለፀረ-አረም መድሃኒት ውሃ መቅዳት | D27: Weed control | E27: knapsack | F27: Industry average | G27: =IFERROR(INDEX('Benchmark Data'!$AC$7:$AC$130,MATCH($A27,'Benchmark Data'!$A$7:$A$130,0)),0) -> 0.22222222 | H27: =IFERROR(INDEX('Benchmark Data'!$AD$7:$AD$130,MATCH($A27,'Benchmark Data'!$A$7:$A$130,0)),0) -> 120 | I27: =G27*H27 -> 26.666667 | K27: =IFERROR(INDEX('Benchmark Data'!$AE$7:$AE$130,MATCH($A27,'Benchmark Data'!$A$7:$A$130,0)),0) -> 2 | L27: =J27*K27 -> 0 | M27: =L27*G27 -> 0 | N27: =L27*I27 -> 0
A28: MC-03 | B28: Water fetching for spraying | C28: ለፀረ-አረም መድሃኒት ውሃ መቅዳት | D28: Weed control | E28: knapsack | F28: +25% | G28: =G27 -> 0.22222222 | H28: =H27*(1+Settings!$C$8) -> 150 | I28: =G28*H28 -> 33.333333 | J28: =J27 -> 0 | K28: =K27 -> 2 | L28: =J28*K28 -> 0 | M28: =L28*G28 -> 0 | N28: =L28*I28 -> 0
A29: MC-03 | B29: Water fetching for spraying | C29: ለፀረ-አረም መድሃኒት ውሃ መቅዳት | D29: Weed control | E29: knapsack | F29: +50% | G29: =G27 -> 0.22222222 | H29: =H27*(1+Settings!$C$9) -> 180 | I29: =G29*H29 -> 40 | J29: =J27 -> 0 | K29: =K27 -> 2 | L29: =J29*K29 -> 0 | M29: =L29*G29 -> 0 | N29: =L29*I29 -> 0
A30: MC-03 | B30: Water fetching for spraying | C30: ለፀረ-አረም መድሃኒት ውሃ መቅዳት | D30: Weed control | E30: knapsack | F30: Expert input | G30: =G27 -> 0.22222222 | H30: =H27 -> 120 | I30: =G30*H30 -> 26.666667 | J30: =J27 -> 0 | K30: =K27 -> 2 | L30: =J30*K30 -> 0 | M30: =L30*G30 -> 0 | N30: =L30*I30 -> 0
A31: MC-03 | B31: Water fetching for spraying | C31: ለፀረ-አረም መድሃኒት ውሃ መቅዳት | D31: Weed control | E31: knapsack | F31: Chaka Buna plan | G31: =CHOOSE(IF(OR($C$3="Expert input",$I$27=0),4,IF($C$3="+25%",2,IF($C$3="+50%",3,1))),G27,G28,G29,G30) -> 0.22222222 | H31: =CHOOSE(IF(OR($C$3="Expert input",$I$27=0),4,IF($C$3="+25%",2,IF($C$3="+50%",3,1))),H27,H28,H29,H30) -> 120 | I31: =G31*H31 -> 26.666667 | J31: =J27 -> 0 | K31: =CHOOSE(IF(OR($C$3="Expert input",$I$27=0),4,IF($C$3="+25%",2,IF($C$3="+50%",3,1))),K27,K28,K29,K30) -> 2 | L31: =J31*K31 -> 0 | M31: =L31*G31 -> 0 | N31: =L31*I31 -> 0 | O31: 0.22 | T31: 0.09 | U31: 0.05 | V31: 0.17 | W31: 0.07 | Y31: 0.23 | Z31: 0.17 | AA31: =O31*$M31 -> 0 | AB31: =O31*$N31 -> 0 | AC31: =P31*$M31 -> 0 | AD31: =P31*$N31 -> 0 | AE31: =Q31*$M31 -> 0 | AF31: =Q31*$N31 -> 0 | AG31: =R31*$M31 -> 0 | AH31: =R31*$N31 -> 0 | AI31: =S31*$M31 -> 0 | AJ31: =S31*$N31 -> 0 | AK31: =T31*$M31 -> 0 | AL31: =T31*$N31 -> 0 | AM31: =U31*$M31 -> 0 | AN31: =U31*$N31 -> 0 | AO31: =V31*$M31 -> 0 | AP31: =V31*$N31 -> 0 | AQ31: =W31*$M31 -> 0 | AR31: =W31*$N31 -> 0 | AS31: =X31*$M31 -> 0 | AT31: =X31*$N31 -> 0 | AU31: =Y31*$M31 -> 0 | AV31: =Y31*$N31 -> 0 | AW31: =Z31*$M31 -> 0 | AX31: =Z31*$N31 -> 0
A32: MC-04 | B32: Ring weeding for fertiliser | C32: ለማዳበሪያ ዙሪያ ማውጣት | D32: Nutrition | E32: tree | F32: Industry average | G32: =IFERROR(INDEX('Benchmark Data'!$AC$7:$AC$130,MATCH($A32,'Benchmark Data'!$A$7:$A$130,0)),0) -> 0.01 | H32: =IFERROR(INDEX('Benchmark Data'!$AD$7:$AD$130,MATCH($A32,'Benchmark Data'!$A$7:$A$130,0)),0) -> 100 | I32: =G32*H32 -> 1 | J32: =$E$8 -> 0 | K32: =IFERROR(INDEX('Benchmark Data'!$AE$7:$AE$130,MATCH($A32,'Benchmark Data'!$A$7:$A$130,0)),0) -> 1 | L32: =J32*K32 -> 0 | M32: =L32*G32 -> 0 | N32: =L32*I32 -> 0
A33: MC-04 | B33: Ring weeding for fertiliser | C33: ለማዳበሪያ ዙሪያ ማውጣት | D33: Nutrition | E33: tree | F33: +25% | G33: =G32 -> 0.01 | H33: =H32*(1+Settings!$C$8) -> 125 | I33: =G33*H33 -> 1.25 | J33: =J32 -> 0 | K33: =K32 -> 1 | L33: =J33*K33 -> 0 | M33: =L33*G33 -> 0 | N33: =L33*I33 -> 0
A34: MC-04 | B34: Ring weeding for fertiliser | C34: ለማዳበሪያ ዙሪያ ማውጣት | D34: Nutrition | E34: tree | F34: +50% | G34: =G32 -> 0.01 | H34: =H32*(1+Settings!$C$9) -> 150 | I34: =G34*H34 -> 1.5 | J34: =J32 -> 0 | K34: =K32 -> 1 | L34: =J34*K34 -> 0 | M34: =L34*G34 -> 0 | N34: =L34*I34 -> 0
A35: MC-04 | B35: Ring weeding for fertiliser | C35: ለማዳበሪያ ዙሪያ ማውጣት | D35: Nutrition | E35: tree | F35: Expert input | G35: =G32 -> 0.01 | H35: =H32 -> 100 | I35: =G35*H35 -> 1 | J35: =J32 -> 0 | K35: =K32 -> 1 | L35: =J35*K35 -> 0 | M35: =L35*G35 -> 0 | N35: =L35*I35 -> 0
A36: MC-04 | B36: Ring weeding for fertiliser | C36: ለማዳበሪያ ዙሪያ ማውጣት | D36: Nutrition | E36: tree | F36: Chaka Buna plan | G36: =CHOOSE(IF(OR($C$3="Expert input",$I$32=0),4,IF($C$3="+25%",2,IF($C$3="+50%",3,1))),G32,G33,G34,G35) -> 0.01 | H36: =CHOOSE(IF(OR($C$3="Expert input",$I$32=0),4,IF($C$3="+25%",2,IF($C$3="+50%",3,1))),H32,H33,H34,H35) -> 100 | I36: =G36*H36 -> 1 | J36: =J32 -> 0 | K36: =CHOOSE(IF(OR($C$3="Expert input",$I$32=0),4,IF($C$3="+25%",2,IF($C$3="+50%",3,1))),K32,K33,K34,K35) -> 1 | L36: =J36*K36 -> 0 | M36: =L36*G36 -> 0 | N36: =L36*I36 -> 0 | U36: 0.17 | V36: 0.39 | W36: 0.11 | X36: 0.22 | Y36: 0.11 | AA36: =O36*$M36 -> 0 | AB36: =O36*$N36 -> 0 | AC36: =P36*$M36 -> 0 | AD36: =P36*$N36 -> 0 | AE36: =Q36*$M36 -> 0 | AF36: =Q36*$N36 -> 0 | AG36: =R36*$M36 -> 0 | AH36: =R36*$N36 -> 0 | AI36: =S36*$M36 -> 0 | AJ36: =S36*$N36 -> 0 | AK36: =T36*$M36 -> 0 | AL36: =T36*$N36 -> 0 | AM36: =U36*$M36 -> 0 | AN36: =U36*$N36 -> 0 | AO36: =V36*$M36 -> 0 | AP36: =V36*$N36 -> 0 | AQ36: =W36*$M36 -> 0 | AR36: =W36*$N36 -> 0 | AS36: =X36*$M36 -> 0 | AT36: =X36*$N36 -> 0 | AU36: =Y36*$M36 -> 0 | AV36: =Y36*$N36 -> 0 | AW36: =Z36*$M36 -> 0 | AX36: =Z36*$N36 -> 0
A37: MC-05 | B37: Fertiliser application | C37: ማዳበሪያ ማድረግ | D37: Nutrition | E37: tree | F37: Industry average | G37: =IFERROR(INDEX('Benchmark Data'!$AC$7:$AC$130,MATCH($A37,'Benchmark Data'!$A$7:$A$130,0)),0) -> 0.01 | H37: =IFERROR(INDEX('Benchmark Data'!$AD$7:$AD$130,MATCH($A37,'Benchmark Data'!$A$7:$A$130,0)),0) -> 96.666667 | I37: =G37*H37 -> 0.96666667 | J37: =$E$8 -> 0 | K37: =IFERROR(INDEX('Benchmark Data'!$AE$7:$AE$130,MATCH($A37,'Benchmark Data'!$A$7:$A$130,0)),0) -> 1 | L37: =J37*K37 -> 0 | M37: =L37*G37 -> 0 | N37: =L37*I37 -> 0
A38: MC-05 | B38: Fertiliser application | C38: ማዳበሪያ ማድረግ | D38: Nutrition | E38: tree | F38: +25% | G38: =G37 -> 0.01 | H38: =H37*(1+Settings!$C$8) -> 120.83333 | I38: =G38*H38 -> 1.2083333 | J38: =J37 -> 0 | K38: =K37 -> 1 | L38: =J38*K38 -> 0 | M38: =L38*G38 -> 0 | N38: =L38*I38 -> 0
A39: MC-05 | B39: Fertiliser application | C39: ማዳበሪያ ማድረግ | D39: Nutrition | E39: tree | F39: +50% | G39: =G37 -> 0.01 | H39: =H37*(1+Settings!$C$9) -> 145 | I39: =G39*H39 -> 1.45 | J39: =J37 -> 0 | K39: =K37 -> 1 | L39: =J39*K39 -> 0 | M39: =L39*G39 -> 0 | N39: =L39*I39 -> 0
A40: MC-05 | B40: Fertiliser application | C40: ማዳበሪያ ማድረግ | D40: Nutrition | E40: tree | F40: Expert input | G40: =G37 -> 0.01 | H40: =H37 -> 96.666667 | I40: =G40*H40 -> 0.96666667 | J40: =J37 -> 0 | K40: =K37 -> 1 | L40: =J40*K40 -> 0 | M40: =L40*G40 -> 0 | N40: =L40*I40 -> 0
A41: MC-05 | B41: Fertiliser application | C41: ማዳበሪያ ማድረግ | D41: Nutrition | E41: tree | F41: Chaka Buna plan | G41: =CHOOSE(IF(OR($C$3="Expert input",$I$37=0),4,IF($C$3="+25%",2,IF($C$3="+50%",3,1))),G37,G38,G39,G40) -> 0.01 | H41: =CHOOSE(IF(OR($C$3="Expert input",$I$37=0),4,IF($C$3="+25%",2,IF($C$3="+50%",3,1))),H37,H38,H39,H40) -> 96.666667 | I41: =G41*H41 -> 0.96666667 | J41: =J37 -> 0 | K41: =CHOOSE(IF(OR($C$3="Expert input",$I$37=0),4,IF($C$3="+25%",2,IF($C$3="+50%",3,1))),K37,K38,K39,K40) -> 1 | L41: =J41*K41 -> 0 | M41: =L41*G41 -> 0 | N41: =L41*I41 -> 0 | U41: 0.17 | V41: 0.39 | W41: 0.11 | X41: 0.22 | Y41: 0.11 | AA41: =O41*$M41 -> 0 | AB41: =O41*$N41 -> 0 | AC41: =P41*$M41 -> 0 | AD41: =P41*$N41 -> 0 | AE41: =Q41*$M41 -> 0 | AF41: =Q41*$N41 -> 0 | AG41: =R41*$M41 -> 0 | AH41: =R41*$N41 -> 0 | AI41: =S41*$M41 -> 0 | AJ41: =S41*$N41 -> 0 | AK41: =T41*$M41 -> 0 | AL41: =T41*$N41 -> 0 | AM41: =U41*$M41 -> 0 | AN41: =U41*$N41 -> 0 | AO41: =V41*$M41 -> 0 | AP41: =V41*$N41 -> 0 | AQ41: =W41*$M41 -> 0 | AR41: =W41*$N41 -> 0 | AS41: =X41*$M41 -> 0 | AT41: =X41*$N41 -> 0 | AU41: =Y41*$M41 -> 0 | AV41: =Y41*$N41 -> 0 | AW41: =Z41*$M41 -> 0 | AX41: =Z41*$N41 -> 0
A42: MC-06 | B42: Foliar urea spraying | C42: ዩሪያ በቅጠል መርጨት | D42: Nutrition | E42: knapsack | F42: Industry average | G42: =IFERROR(INDEX('Benchmark Data'!$AC$7:$AC$130,MATCH($A42,'Benchmark Data'!$A$7:$A$130,0)),0) -> 0.175 | H42: =IFERROR(INDEX('Benchmark Data'!$AD$7:$AD$130,MATCH($A42,'Benchmark Data'!$A$7:$A$130,0)),0) -> 157.14286 | I42: =G42*H42 -> 27.5 | K42: =IFERROR(INDEX('Benchmark Data'!$AE$7:$AE$130,MATCH($A42,'Benchmark Data'!$A$7:$A$130,0)),0) -> 1 | L42: =J42*K42 -> 0 | M42: =L42*G42 -> 0 | N42: =L42*I42 -> 0
A43: MC-06 | B43: Foliar urea spraying | C43: ዩሪያ በቅጠል መርጨት | D43: Nutrition | E43: knapsack | F43: +25% | G43: =G42 -> 0.175 | H43: =H42*(1+Settings!$C$8) -> 196.42857 | I43: =G43*H43 -> 34.375 | J43: =J42 -> 0 | K43: =K42 -> 1 | L43: =J43*K43 -> 0 | M43: =L43*G43 -> 0 | N43: =L43*I43 -> 0
A44: MC-06 | B44: Foliar urea spraying | C44: ዩሪያ በቅጠል መርጨት | D44: Nutrition | E44: knapsack | F44: +50% | G44: =G42 -> 0.175 | H44: =H42*(1+Settings!$C$9) -> 235.71429 | I44: =G44*H44 -> 41.25 | J44: =J42 -> 0 | K44: =K42 -> 1 | L44: =J44*K44 -> 0 | M44: =L44*G44 -> 0 | N44: =L44*I44 -> 0
A45: MC-06 | B45: Foliar urea spraying | C45: ዩሪያ በቅጠል መርጨት | D45: Nutrition | E45: knapsack | F45: Expert input | G45: =G42 -> 0.175 | H45: =H42 -> 157.14286 | I45: =G45*H45 -> 27.5 | J45: =J42 -> 0 | K45: =K42 -> 1 | L45: =J45*K45 -> 0 | M45: =L45*G45 -> 0 | N45: =L45*I45 -> 0
A46: MC-06 | B46: Foliar urea spraying | C46: ዩሪያ በቅጠል መርጨት | D46: Nutrition | E46: knapsack | F46: Chaka Buna plan | G46: =CHOOSE(IF(OR($C$3="Expert input",$I$42=0),4,IF($C$3="+25%",2,IF($C$3="+50%",3,1))),G42,G43,G44,G45) -> 0.175 | H46: =CHOOSE(IF(OR($C$3="Expert input",$I$42=0),4,IF($C$3="+25%",2,IF($C$3="+50%",3,1))),H42,H43,H44,H45) -> 157.14286 | I46: =G46*H46 -> 27.5 | J46: =J42 -> 0 | K46: =CHOOSE(IF(OR($C$3="Expert input",$I$42=0),4,IF($C$3="+25%",2,IF($C$3="+50%",3,1))),K42,K43,K44,K45) -> 1 | L46: =J46*K46 -> 0 | M46: =L46*G46 -> 0 | N46: =L46*I46 -> 0 | U46: 0.5 | X46: 0.25 | Y46: 0.25 | AA46: =O46*$M46 -> 0 | AB46: =O46*$N46 -> 0 | AC46: =P46*$M46 -> 0 | AD46: =P46*$N46 -> 0 | AE46: =Q46*$M46 -> 0 | AF46: =Q46*$N46 -> 0 | AG46: =R46*$M46 -> 0 | AH46: =R46*$N46 -> 0 | AI46: =S46*$M46 -> 0 | AJ46: =S46*$N46 -> 0 | AK46: =T46*$M46 -> 0 | AL46: =T46*$N46 -> 0 | AM46: =U46*$M46 -> 0 | AN46: =U46*$N46 -> 0 | AO46: =V46*$M46 -> 0 | AP46: =V46*$N46 -> 0 | AQ46: =W46*$M46 -> 0 | AR46: =W46*$N46 -> 0 | AS46: =X46*$M46 -> 0 | AT46: =X46*$N46 -> 0 | AU46: =Y46*$M46 -> 0 | AV46: =Y46*$N46 -> 0 | AW46: =Z46*$M46 -> 0 | AX46: =Z46*$N46 -> 0
A47: MC-07 | B47: Lime application | C47: ኖራ መጨመር | D47: Nutrition | E47: ha | F47: Industry average | G47: =IFERROR(INDEX('Benchmark Data'!$AC$7:$AC$130,MATCH($A47,'Benchmark Data'!$A$7:$A$130,0)),0) -> 0 | H47: =IFERROR(INDEX('Benchmark Data'!$AD$7:$AD$130,MATCH($A47,'Benchmark Data'!$A$7:$A$130,0)),0) -> 0 | I47: =G47*H47 -> 0 | K47: =IFERROR(INDEX('Benchmark Data'!$AE$7:$AE$130,MATCH($A47,'Benchmark Data'!$A$7:$A$130,0)),0) -> 1 | L47: =J47*K47 -> 0 | M47: =L47*G47 -> 0 | N47: =L47*I47 -> 0
A48: MC-07 | B48: Lime application | C48: ኖራ መጨመር | D48: Nutrition | E48: ha | F48: +25% | G48: =G47 -> 0 | H48: =H47*(1+Settings!$C$8) -> 0 | I48: =G48*H48 -> 0 | J48: =J47 -> 0 | K48: =K47 -> 1 | L48: =J48*K48 -> 0 | M48: =L48*G48 -> 0 | N48: =L48*I48 -> 0
A49: MC-07 | B49: Lime application | C49: ኖራ መጨመር | D49: Nutrition | E49: ha | F49: +50% | G49: =G47 -> 0 | H49: =H47*(1+Settings!$C$9) -> 0 | I49: =G49*H49 -> 0 | J49: =J47 -> 0 | K49: =K47 -> 1 | L49: =J49*K49 -> 0 | M49: =L49*G49 -> 0 | N49: =L49*I49 -> 0
A50: MC-07 | B50: Lime application | C50: ኖራ መጨመር | D50: Nutrition | E50: ha | F50: Expert input | G50: =IFERROR(INDEX('Benchmark Data'!$AH$7:$AH$130,MATCH($A50,'Benchmark Data'!$A$7:$A$130,0)),0) -> 10 | H50: =IFERROR(INDEX('Benchmark Data'!$AI$7:$AI$130,MATCH($A50,'Benchmark Data'!$A$7:$A$130,0)),0) -> 100 | I50: =G50*H50 -> 1000 | J50: =J47 -> 0 | K50: =IFERROR(INDEX('Benchmark Data'!$AJ$7:$AJ$130,MATCH($A50,'Benchmark Data'!$A$7:$A$130,0)),0) -> 1 | L50: =J50*K50 -> 0 | M50: =L50*G50 -> 0 | N50: =L50*I50 -> 0
A51: MC-07 | B51: Lime application | C51: ኖራ መጨመር | D51: Nutrition | E51: ha | F51: Chaka Buna plan | G51: =CHOOSE(IF(OR($C$3="Expert input",$I$47=0),4,IF($C$3="+25%",2,IF($C$3="+50%",3,1))),G47,G48,G49,G50) -> 10 | H51: =CHOOSE(IF(OR($C$3="Expert input",$I$47=0),4,IF($C$3="+25%",2,IF($C$3="+50%",3,1))),H47,H48,H49,H50) -> 100 | I51: =G51*H51 -> 1000 | J51: =J47 -> 0 | K51: =CHOOSE(IF(OR($C$3="Expert input",$I$47=0),4,IF($C$3="+25%",2,IF($C$3="+50%",3,1))),K47,K48,K49,K50) -> 1 | L51: =J51*K51 -> 0 | M51: =L51*G51 -> 0 | N51: =L51*I51 -> 0 | T51: 0.53 | U51: 0.47 | AA51: =O51*$M51 -> 0 | AB51: =O51*$N51 -> 0 | AC51: =P51*$M51 -> 0 | AD51: =P51*$N51 -> 0 | AE51: =Q51*$M51 -> 0 | AF51: =Q51*$N51 -> 0 | AG51: =R51*$M51 -> 0 | AH51: =R51*$N51 -> 0 | AI51: =S51*$M51 -> 0 | AJ51: =S51*$N51 -> 0 | AK51: =T51*$M51 -> 0 | AL51: =T51*$N51 -> 0 | AM51: =U51*$M51 -> 0 | AN51: =U51*$N51 -> 0 | AO51: =V51*$M51 -> 0 | AP51: =V51*$N51 -> 0 | AQ51: =W51*$M51 -> 0 | AR51: =W51*$N51 -> 0 | AS51: =X51*$M51 -> 0 | AT51: =X51*$N51 -> 0 | AU51: =Y51*$M51 -> 0 | AV51: =Y51*$N51 -> 0 | AW51: =Z51*$M51 -> 0 | AX51: =Z51*$N51 -> 0
A52: MC-08 | B52: Pruning | C52: ቡና ምቀሳ | D52: Canopy management | E52: tree | F52: Industry average | G52: =IFERROR(INDEX('Benchmark Data'!$AC$7:$AC$130,MATCH($A52,'Benchmark Data'!$A$7:$A$130,0)),0) -> 0.01 | H52: =IFERROR(INDEX('Benchmark Data'!$AD$7:$AD$130,MATCH($A52,'Benchmark Data'!$A$7:$A$130,0)),0) -> 166.66667 | I52: =G52*H52 -> 1.6666667 | J52: =$E$8 -> 0 | K52: =IFERROR(INDEX('Benchmark Data'!$AE$7:$AE$130,MATCH($A52,'Benchmark Data'!$A$7:$A$130,0)),0) -> 1 | L52: =J52*K52 -> 0 | M52: =L52*G52 -> 0 | N52: =L52*I52 -> 0
A53: MC-08 | B53: Pruning | C53: ቡና ምቀሳ | D53: Canopy management | E53: tree | F53: +25% | G53: =G52 -> 0.01 | H53: =H52*(1+Settings!$C$8) -> 208.33333 | I53: =G53*H53 -> 2.0833333 | J53: =J52 -> 0 | K53: =K52 -> 1 | L53: =J53*K53 -> 0 | M53: =L53*G53 -> 0 | N53: =L53*I53 -> 0
A54: MC-08 | B54: Pruning | C54: ቡና ምቀሳ | D54: Canopy management | E54: tree | F54: +50% | G54: =G52 -> 0.01 | H54: =H52*(1+Settings!$C$9) -> 250 | I54: =G54*H54 -> 2.5 | J54: =J52 -> 0 | K54: =K52 -> 1 | L54: =J54*K54 -> 0 | M54: =L54*G54 -> 0 | N54: =L54*I54 -> 0
A55: MC-08 | B55: Pruning | C55: ቡና ምቀሳ | D55: Canopy management | E55: tree | F55: Expert input | G55: =G52 -> 0.01 | H55: =H52 -> 166.66667 | I55: =G55*H55 -> 1.6666667 | J55: =J52 -> 0 | K55: =K52 -> 1 | L55: =J55*K55 -> 0 | M55: =L55*G55 -> 0 | N55: =L55*I55 -> 0
A56: MC-08 | B56: Pruning | C56: ቡና ምቀሳ | D56: Canopy management | E56: tree | F56: Chaka Buna plan | G56: =CHOOSE(IF(OR($C$3="Expert input",$I$52=0),4,IF($C$3="+25%",2,IF($C$3="+50%",3,1))),G52,G53,G54,G55) -> 0.01 | H56: =CHOOSE(IF(OR($C$3="Expert input",$I$52=0),4,IF($C$3="+25%",2,IF($C$3="+50%",3,1))),H52,H53,H54,H55) -> 166.66667 | I56: =G56*H56 -> 1.6666667 | J56: =J52 -> 0 | K56: =CHOOSE(IF(OR($C$3="Expert input",$I$52=0),4,IF($C$3="+25%",2,IF($C$3="+50%",3,1))),K52,K53,K54,K55) -> 1 | L56: =J56*K56 -> 0 | M56: =L56*G56 -> 0 | N56: =L56*I56 -> 0 | Q56: 0.11 | R56: 0.34 | S56: 0.33 | T56: 0.22 | AA56: =O56*$M56 -> 0 | AB56: =O56*$N56 -> 0 | AC56: =P56*$M56 -> 0 | AD56: =P56*$N56 -> 0 | AE56: =Q56*$M56 -> 0 | AF56: =Q56*$N56 -> 0 | AG56: =R56*$M56 -> 0 | AH56: =R56*$N56 -> 0 | AI56: =S56*$M56 -> 0 | AJ56: =S56*$N56 -> 0 | AK56: =T56*$M56 -> 0 | AL56: =T56*$N56 -> 0 | AM56: =U56*$M56 -> 0 | AN56: =U56*$N56 -> 0 | AO56: =V56*$M56 -> 0 | AP56: =V56*$N56 -> 0 | AQ56: =W56*$M56 -> 0 | AR56: =W56*$N56 -> 0 | AS56: =X56*$M56 -> 0 | AT56: =X56*$N56 -> 0 | AU56: =Y56*$M56 -> 0 | AV56: =Y56*$N56 -> 0 | AW56: =Z56*$M56 -> 0 | AX56: =Z56*$N56 -> 0
A57: MC-09 | B57: Topping | C57: ቁመት መግታት | D57: Canopy management | E57: tree | F57: Industry average | G57: =IFERROR(INDEX('Benchmark Data'!$AC$7:$AC$130,MATCH($A57,'Benchmark Data'!$A$7:$A$130,0)),0) -> 0.01 | H57: =IFERROR(INDEX('Benchmark Data'!$AD$7:$AD$130,MATCH($A57,'Benchmark Data'!$A$7:$A$130,0)),0) -> 90 | I57: =G57*H57 -> 0.9 | K57: =IFERROR(INDEX('Benchmark Data'!$AE$7:$AE$130,MATCH($A57,'Benchmark Data'!$A$7:$A$130,0)),0) -> 1 | L57: =J57*K57 -> 0 | M57: =L57*G57 -> 0 | N57: =L57*I57 -> 0
A58: MC-09 | B58: Topping | C58: ቁመት መግታት | D58: Canopy management | E58: tree | F58: +25% | G58: =G57 -> 0.01 | H58: =H57*(1+Settings!$C$8) -> 112.5 | I58: =G58*H58 -> 1.125 | J58: =J57 -> 0 | K58: =K57 -> 1 | L58: =J58*K58 -> 0 | M58: =L58*G58 -> 0 | N58: =L58*I58 -> 0
A59: MC-09 | B59: Topping | C59: ቁመት መግታት | D59: Canopy management | E59: tree | F59: +50% | G59: =G57 -> 0.01 | H59: =H57*(1+Settings!$C$9) -> 135 | I59: =G59*H59 -> 1.35 | J59: =J57 -> 0 | K59: =K57 -> 1 | L59: =J59*K59 -> 0 | M59: =L59*G59 -> 0 | N59: =L59*I59 -> 0
A60: MC-09 | B60: Topping | C60: ቁመት መግታት | D60: Canopy management | E60: tree | F60: Expert input | G60: =G57 -> 0.01 | H60: =H57 -> 90 | I60: =G60*H60 -> 0.9 | J60: =J57 -> 0 | K60: =K57 -> 1 | L60: =J60*K60 -> 0 | M60: =L60*G60 -> 0 | N60: =L60*I60 -> 0
A61: MC-09 | B61: Topping | C61: ቁመት መግታት | D61: Canopy management | E61: tree | F61: Chaka Buna plan | G61: =CHOOSE(IF(OR($C$3="Expert input",$I$57=0),4,IF($C$3="+25%",2,IF($C$3="+50%",3,1))),G57,G58,G59,G60) -> 0.01 | H61: =CHOOSE(IF(OR($C$3="Expert input",$I$57=0),4,IF($C$3="+25%",2,IF($C$3="+50%",3,1))),H57,H58,H59,H60) -> 90 | I61: =G61*H61 -> 0.9 | J61: =J57 -> 0 | K61: =CHOOSE(IF(OR($C$3="Expert input",$I$57=0),4,IF($C$3="+25%",2,IF($C$3="+50%",3,1))),K57,K58,K59,K60) -> 1 | L61: =J61*K61 -> 0 | M61: =L61*G61 -> 0 | N61: =L61*I61 -> 0 | S61: 0.25 | T61: 0.25 | U61: 0.28 | V61: 0.22 | AA61: =O61*$M61 -> 0 | AB61: =O61*$N61 -> 0 | AC61: =P61*$M61 -> 0 | AD61: =P61*$N61 -> 0 | AE61: =Q61*$M61 -> 0 | AF61: =Q61*$N61 -> 0 | AG61: =R61*$M61 -> 0 | AH61: =R61*$N61 -> 0 | AI61: =S61*$M61 -> 0 | AJ61: =S61*$N61 -> 0 | AK61: =T61*$M61 -> 0 | AL61: =T61*$N61 -> 0 | AM61: =U61*$M61 -> 0 | AN61: =U61*$N61 -> 0 | AO61: =V61*$M61 -> 0 | AP61: =V61*$N61 -> 0 | AQ61: =W61*$M61 -> 0 | AR61: =W61*$N61 -> 0 | AS61: =X61*$M61 -> 0 | AT61: =X61*$N61 -> 0 | AU61: =Y61*$M61 -> 0 | AV61: =Y61*$N61 -> 0 | AW61: =Z61*$M61 -> 0 | AX61: =Z61*$N61 -> 0
A62: MC-10 | B62: Handling & desuckering | C62: ምልመላና ቅጥያ ማሳሳት | D62: Canopy management | E62: tree | F62: Industry average | G62: =IFERROR(INDEX('Benchmark Data'!$AC$7:$AC$130,MATCH($A62,'Benchmark Data'!$A$7:$A$130,0)),0) -> 0.0083333333 | H62: =IFERROR(INDEX('Benchmark Data'!$AD$7:$AD$130,MATCH($A62,'Benchmark Data'!$A$7:$A$130,0)),0) -> 200 | I62: =G62*H62 -> 1.6666667 | J62: =$E$8 -> 0 | K62: =IFERROR(INDEX('Benchmark Data'!$AE$7:$AE$130,MATCH($A62,'Benchmark Data'!$A$7:$A$130,0)),0) -> 1 | L62: =J62*K62 -> 0 | M62: =L62*G62 -> 0 | N62: =L62*I62 -> 0
A63: MC-10 | B63: Handling & desuckering | C63: ምልመላና ቅጥያ ማሳሳት | D63: Canopy management | E63: tree | F63: +25% | G63: =G62 -> 0.0083333333 | H63: =H62*(1+Settings!$C$8) -> 250 | I63: =G63*H63 -> 2.0833333 | J63: =J62 -> 0 | K63: =K62 -> 1 | L63: =J63*K63 -> 0 | M63: =L63*G63 -> 0 | N63: =L63*I63 -> 0
A64: MC-10 | B64: Handling & desuckering | C64: ምልመላና ቅጥያ ማሳሳት | D64: Canopy management | E64: tree | F64: +50% | G64: =G62 -> 0.0083333333 | H64: =H62*(1+Settings!$C$9) -> 300 | I64: =G64*H64 -> 2.5 | J64: =J62 -> 0 | K64: =K62 -> 1 | L64: =J64*K64 -> 0 | M64: =L64*G64 -> 0 | N64: =L64*I64 -> 0
A65: MC-10 | B65: Handling & desuckering | C65: ምልመላና ቅጥያ ማሳሳት | D65: Canopy management | E65: tree | F65: Expert input | G65: =G62 -> 0.0083333333 | H65: =H62 -> 200 | I65: =G65*H65 -> 1.6666667 | J65: =J62 -> 0 | K65: =K62 -> 1 | L65: =J65*K65 -> 0 | M65: =L65*G65 -> 0 | N65: =L65*I65 -> 0
A66: MC-10 | B66: Handling & desuckering | C66: ምልመላና ቅጥያ ማሳሳት | D66: Canopy management | E66: tree | F66: Chaka Buna plan | G66: =CHOOSE(IF(OR($C$3="Expert input",$I$62=0),4,IF($C$3="+25%",2,IF($C$3="+50%",3,1))),G62,G63,G64,G65) -> 0.0083333333 | H66: =CHOOSE(IF(OR($C$3="Expert input",$I$62=0),4,IF($C$3="+25%",2,IF($C$3="+50%",3,1))),H62,H63,H64,H65) -> 200 | I66: =G66*H66 -> 1.6666667 | J66: =J62 -> 0 | K66: =CHOOSE(IF(OR($C$3="Expert input",$I$62=0),4,IF($C$3="+25%",2,IF($C$3="+50%",3,1))),K62,K63,K64,K65) -> 1 | L66: =J66*K66 -> 0 | M66: =L66*G66 -> 0 | N66: =L66*I66 -> 0 | T66: 0.11 | U66: 0.34 | V66: 0.33 | W66: 0.22 | AA66: =O66*$M66 -> 0 | AB66: =O66*$N66 -> 0 | AC66: =P66*$M66 -> 0 | AD66: =P66*$N66 -> 0 | AE66: =Q66*$M66 -> 0 | AF66: =Q66*$N66 -> 0 | AG66: =R66*$M66 -> 0 | AH66: =R66*$N66 -> 0 | AI66: =S66*$M66 -> 0 | AJ66: =S66*$N66 -> 0 | AK66: =T66*$M66 -> 0 | AL66: =T66*$N66 -> 0 | AM66: =U66*$M66 -> 0 | AN66: =U66*$N66 -> 0 | AO66: =V66*$M66 -> 0 | AP66: =V66*$N66 -> 0 | AQ66: =W66*$M66 -> 0 | AR66: =W66*$N66 -> 0 | AS66: =X66*$M66 -> 0 | AT66: =X66*$N66 -> 0 | AU66: =Y66*$M66 -> 0 | AV66: =Y66*$N66 -> 0 | AW66: =Z66*$M66 -> 0 | AX66: =Z66*$N66 -> 0
A67: MC-11 | B67: Supporting fallen coffee trees | C67: የወደቀ ቡና ማስደገፍ | D67: Canopy management | E67: tree | F67: Industry average | G67: =IFERROR(INDEX('Benchmark Data'!$AC$7:$AC$130,MATCH($A67,'Benchmark Data'!$A$7:$A$130,0)),0) -> 0.02 | H67: =IFERROR(INDEX('Benchmark Data'!$AD$7:$AD$130,MATCH($A67,'Benchmark Data'!$A$7:$A$130,0)),0) -> 70 | I67: =G67*H67 -> 1.4 | K67: =IFERROR(INDEX('Benchmark Data'!$AE$7:$AE$130,MATCH($A67,'Benchmark Data'!$A$7:$A$130,0)),0) -> 1 | L67: =J67*K67 -> 0 | M67: =L67*G67 -> 0 | N67: =L67*I67 -> 0
A68: MC-11 | B68: Supporting fallen coffee trees | C68: የወደቀ ቡና ማስደገፍ | D68: Canopy management | E68: tree | F68: +25% | G68: =G67 -> 0.02 | H68: =H67*(1+Settings!$C$8) -> 87.5 | I68: =G68*H68 -> 1.75 | J68: =J67 -> 0 | K68: =K67 -> 1 | L68: =J68*K68 -> 0 | M68: =L68*G68 -> 0 | N68: =L68*I68 -> 0
A69: MC-11 | B69: Supporting fallen coffee trees | C69: የወደቀ ቡና ማስደገፍ | D69: Canopy management | E69: tree | F69: +50% | G69: =G67 -> 0.02 | H69: =H67*(1+Settings!$C$9) -> 105 | I69: =G69*H69 -> 2.1 | J69: =J67 -> 0 | K69: =K67 -> 1 | L69: =J69*K69 -> 0 | M69: =L69*G69 -> 0 | N69: =L69*I69 -> 0
A70: MC-11 | B70: Supporting fallen coffee trees | C70: የወደቀ ቡና ማስደገፍ | D70: Canopy management | E70: tree | F70: Expert input | G70: =G67 -> 0.02 | H70: =H67 -> 70 | I70: =G70*H70 -> 1.4 | J70: =J67 -> 0 | K70: =K67 -> 1 | L70: =J70*K70 -> 0 | M70: =L70*G70 -> 0 | N70: =L70*I70 -> 0
A71: MC-11 | B71: Supporting fallen coffee trees | C71: የወደቀ ቡና ማስደገፍ | D71: Canopy management | E71: tree | F71: Chaka Buna plan | G71: =CHOOSE(IF(OR($C$3="Expert input",$I$67=0),4,IF($C$3="+25%",2,IF($C$3="+50%",3,1))),G67,G68,G69,G70) -> 0.02 | H71: =CHOOSE(IF(OR($C$3="Expert input",$I$67=0),4,IF($C$3="+25%",2,IF($C$3="+50%",3,1))),H67,H68,H69,H70) -> 70 | I71: =G71*H71 -> 1.4 | J71: =J67 -> 0 | K71: =CHOOSE(IF(OR($C$3="Expert input",$I$67=0),4,IF($C$3="+25%",2,IF($C$3="+50%",3,1))),K67,K68,K69,K70) -> 1 | L71: =J71*K71 -> 0 | M71: =L71*G71 -> 0 | N71: =L71*I71 -> 0 | X71: 0.5 | Y71: 0.5 | AA71: =O71*$M71 -> 0 | AB71: =O71*$N71 -> 0 | AC71: =P71*$M71 -> 0 | AD71: =P71*$N71 -> 0 | AE71: =Q71*$M71 -> 0 | AF71: =Q71*$N71 -> 0 | AG71: =R71*$M71 -> 0 | AH71: =R71*$N71 -> 0 | AI71: =S71*$M71 -> 0 | AJ71: =S71*$N71 -> 0 | AK71: =T71*$M71 -> 0 | AL71: =T71*$N71 -> 0 | AM71: =U71*$M71 -> 0 | AN71: =U71*$N71 -> 0 | AO71: =V71*$M71 -> 0 | AP71: =V71*$N71 -> 0 | AQ71: =W71*$M71 -> 0 | AR71: =W71*$N71 -> 0 | AS71: =X71*$M71 -> 0 | AT71: =X71*$N71 -> 0 | AU71: =Y71*$M71 -> 0 | AV71: =Y71*$N71 -> 0 | AW71: =Z71*$M71 -> 0 | AX71: =Z71*$N71 -> 0
A72: MC-12 | B72: Removing climbers from coffee | C72: ከቡና ላይ ሃረግ ማውረድ | D72: Canopy management | E72: tree | F72: Industry average | G72: =IFERROR(INDEX('Benchmark Data'!$AC$7:$AC$130,MATCH($A72,'Benchmark Data'!$A$7:$A$130,0)),0) -> 0.005 | H72: =IFERROR(INDEX('Benchmark Data'!$AD$7:$AD$130,MATCH($A72,'Benchmark Data'!$A$7:$A$130,0)),0) -> 200 | I72: =G72*H72 -> 1 | K72: =IFERROR(INDEX('Benchmark Data'!$AE$7:$AE$130,MATCH($A72,'Benchmark Data'!$A$7:$A$130,0)),0) -> 1 | L72: =J72*K72 -> 0 | M72: =L72*G72 -> 0 | N72: =L72*I72 -> 0
A73: MC-12 | B73: Removing climbers from coffee | C73: ከቡና ላይ ሃረግ ማውረድ | D73: Canopy management | E73: tree | F73: +25% | G73: =G72 -> 0.005 | H73: =H72*(1+Settings!$C$8) -> 250 | I73: =G73*H73 -> 1.25 | J73: =J72 -> 0 | K73: =K72 -> 1 | L73: =J73*K73 -> 0 | M73: =L73*G73 -> 0 | N73: =L73*I73 -> 0
A74: MC-12 | B74: Removing climbers from coffee | C74: ከቡና ላይ ሃረግ ማውረድ | D74: Canopy management | E74: tree | F74: +50% | G74: =G72 -> 0.005 | H74: =H72*(1+Settings!$C$9) -> 300 | I74: =G74*H74 -> 1.5 | J74: =J72 -> 0 | K74: =K72 -> 1 | L74: =J74*K74 -> 0 | M74: =L74*G74 -> 0 | N74: =L74*I74 -> 0
A75: MC-12 | B75: Removing climbers from coffee | C75: ከቡና ላይ ሃረግ ማውረድ | D75: Canopy management | E75: tree | F75: Expert input | G75: =G72 -> 0.005 | H75: =H72 -> 200 | I75: =G75*H75 -> 1 | J75: =J72 -> 0 | K75: =K72 -> 1 | L75: =J75*K75 -> 0 | M75: =L75*G75 -> 0 | N75: =L75*I75 -> 0
A76: MC-12 | B76: Removing climbers from coffee | C76: ከቡና ላይ ሃረግ ማውረድ | D76: Canopy management | E76: tree | F76: Chaka Buna plan | G76: =CHOOSE(IF(OR($C$3="Expert input",$I$72=0),4,IF($C$3="+25%",2,IF($C$3="+50%",3,1))),G72,G73,G74,G75) -> 0.005 | H76: =CHOOSE(IF(OR($C$3="Expert input",$I$72=0),4,IF($C$3="+25%",2,IF($C$3="+50%",3,1))),H72,H73,H74,H75) -> 200 | I76: =G76*H76 -> 1 | J76: =J72 -> 0 | K76: =CHOOSE(IF(OR($C$3="Expert input",$I$72=0),4,IF($C$3="+25%",2,IF($C$3="+50%",3,1))),K72,K73,K74,K75) -> 1 | L76: =J76*K76 -> 0 | M76: =L76*G76 -> 0 | N76: =L76*I76 -> 0 | R76: 0.12 | T76: 0.12 | V76: 0.39 | W76: 0.25 | X76: 0.12 | AA76: =O76*$M76 -> 0 | AB76: =O76*$N76 -> 0 | AC76: =P76*$M76 -> 0 | AD76: =P76*$N76 -> 0 | AE76: =Q76*$M76 -> 0 | AF76: =Q76*$N76 -> 0 | AG76: =R76*$M76 -> 0 | AH76: =R76*$N76 -> 0 | AI76: =S76*$M76 -> 0 | AJ76: =S76*$N76 -> 0 | AK76: =T76*$M76 -> 0 | AL76: =T76*$N76 -> 0 | AM76: =U76*$M76 -> 0 | AN76: =U76*$N76 -> 0 | AO76: =V76*$M76 -> 0 | AP76: =V76*$N76 -> 0 | AQ76: =W76*$M76 -> 0 | AR76: =W76*$N76 -> 0 | AS76: =X76*$M76 -> 0 | AT76: =X76*$N76 -> 0 | AU76: =Y76*$M76 -> 0 | AV76: =Y76*$N76 -> 0 | AW76: =Z76*$M76 -> 0 | AX76: =Z76*$N76 -> 0
A77: MC-13 | B77: Lichen removal | C77: ሽበት ማስወገድ | D77: Canopy management | E77: tree | F77: Industry average | G77: =IFERROR(INDEX('Benchmark Data'!$AC$7:$AC$130,MATCH($A77,'Benchmark Data'!$A$7:$A$130,0)),0) -> 0.0066666667 | H77: =IFERROR(INDEX('Benchmark Data'!$AD$7:$AD$130,MATCH($A77,'Benchmark Data'!$A$7:$A$130,0)),0) -> 300 | I77: =G77*H77 -> 2 | K77: =IFERROR(INDEX('Benchmark Data'!$AE$7:$AE$130,MATCH($A77,'Benchmark Data'!$A$7:$A$130,0)),0) -> 1 | L77: =J77*K77 -> 0 | M77: =L77*G77 -> 0 | N77: =L77*I77 -> 0
A78: MC-13 | B78: Lichen removal | C78: ሽበት ማስወገድ | D78: Canopy management | E78: tree | F78: +25% | G78: =G77 -> 0.0066666667 | H78: =H77*(1+Settings!$C$8) -> 375 | I78: =G78*H78 -> 2.5 | J78: =J77 -> 0 | K78: =K77 -> 1 | L78: =J78*K78 -> 0 | M78: =L78*G78 -> 0 | N78: =L78*I78 -> 0
A79: MC-13 | B79: Lichen removal | C79: ሽበት ማስወገድ | D79: Canopy management | E79: tree | F79: +50% | G79: =G77 -> 0.0066666667 | H79: =H77*(1+Settings!$C$9) -> 450 | I79: =G79*H79 -> 3 | J79: =J77 -> 0 | K79: =K77 -> 1 | L79: =J79*K79 -> 0 | M79: =L79*G79 -> 0 | N79: =L79*I79 -> 0
A80: MC-13 | B80: Lichen removal | C80: ሽበት ማስወገድ | D80: Canopy management | E80: tree | F80: Expert input | G80: =G77 -> 0.0066666667 | H80: =H77 -> 300 | I80: =G80*H80 -> 2 | J80: =J77 -> 0 | K80: =K77 -> 1 | L80: =J80*K80 -> 0 | M80: =L80*G80 -> 0 | N80: =L80*I80 -> 0
A81: MC-13 | B81: Lichen removal | C81: ሽበት ማስወገድ | D81: Canopy management | E81: tree | F81: Chaka Buna plan | G81: =CHOOSE(IF(OR($C$3="Expert input",$I$77=0),4,IF($C$3="+25%",2,IF($C$3="+50%",3,1))),G77,G78,G79,G80) -> 0.0066666667 | H81: =CHOOSE(IF(OR($C$3="Expert input",$I$77=0),4,IF($C$3="+25%",2,IF($C$3="+50%",3,1))),H77,H78,H79,H80) -> 300 | I81: =G81*H81 -> 2 | J81: =J77 -> 0 | K81: =CHOOSE(IF(OR($C$3="Expert input",$I$77=0),4,IF($C$3="+25%",2,IF($C$3="+50%",3,1))),K77,K78,K79,K80) -> 1 | L81: =J81*K81 -> 0 | M81: =L81*G81 -> 0 | N81: =L81*I81 -> 0 | X81: 0.5 | Y81: 0.5 | AA81: =O81*$M81 -> 0 | AB81: =O81*$N81 -> 0 | AC81: =P81*$M81 -> 0 | AD81: =P81*$N81 -> 0 | AE81: =Q81*$M81 -> 0 | AF81: =Q81*$N81 -> 0 | AG81: =R81*$M81 -> 0 | AH81: =R81*$N81 -> 0 | AI81: =S81*$M81 -> 0 | AJ81: =S81*$N81 -> 0 | AK81: =T81*$M81 -> 0 | AL81: =T81*$N81 -> 0 | AM81: =U81*$M81 -> 0 | AN81: =U81*$N81 -> 0 | AO81: =V81*$M81 -> 0 | AP81: =V81*$N81 -> 0 | AQ81: =W81*$M81 -> 0 | AR81: =W81*$N81 -> 0 | AS81: =X81*$M81 -> 0 | AT81: =X81*$N81 -> 0 | AU81: =Y81*$M81 -> 0 | AV81: =Y81*$N81 -> 0 | AW81: =Z81*$M81 -> 0 | AX81: =Z81*$N81 -> 0
A82: MC-14 | B82: Stumping | C82: ጉንደላ | D82: Rejuvenation | E82: tree | F82: Industry average | G82: =IFERROR(INDEX('Benchmark Data'!$AC$7:$AC$130,MATCH($A82,'Benchmark Data'!$A$7:$A$130,0)),0) -> 0.01 | H82: =IFERROR(INDEX('Benchmark Data'!$AD$7:$AD$130,MATCH($A82,'Benchmark Data'!$A$7:$A$130,0)),0) -> 166.66667 | I82: =G82*H82 -> 1.6666667 | J82: =$E$10 -> 0 | K82: =IFERROR(INDEX('Benchmark Data'!$AE$7:$AE$130,MATCH($A82,'Benchmark Data'!$A$7:$A$130,0)),0) -> 1 | L82: =J82*K82 -> 0 | M82: =L82*G82 -> 0 | N82: =L82*I82 -> 0
A83: MC-14 | B83: Stumping | C83: ጉንደላ | D83: Rejuvenation | E83: tree | F83: +25% | G83: =G82 -> 0.01 | H83: =H82*(1+Settings!$C$8) -> 208.33333 | I83: =G83*H83 -> 2.0833333 | J83: =J82 -> 0 | K83: =K82 -> 1 | L83: =J83*K83 -> 0 | M83: =L83*G83 -> 0 | N83: =L83*I83 -> 0
A84: MC-14 | B84: Stumping | C84: ጉንደላ | D84: Rejuvenation | E84: tree | F84: +50% | G84: =G82 -> 0.01 | H84: =H82*(1+Settings!$C$9) -> 250 | I84: =G84*H84 -> 2.5 | J84: =J82 -> 0 | K84: =K82 -> 1 | L84: =J84*K84 -> 0 | M84: =L84*G84 -> 0 | N84: =L84*I84 -> 0
A85: MC-14 | B85: Stumping | C85: ጉንደላ | D85: Rejuvenation | E85: tree | F85: Expert input | G85: =G82 -> 0.01 | H85: =H82 -> 166.66667 | I85: =G85*H85 -> 1.6666667 | J85: =J82 -> 0 | K85: =K82 -> 1 | L85: =J85*K85 -> 0 | M85: =L85*G85 -> 0 | N85: =L85*I85 -> 0
A86: MC-14 | B86: Stumping | C86: ጉንደላ | D86: Rejuvenation | E86: tree | F86: Chaka Buna plan | G86: =CHOOSE(IF(OR($C$3="Expert input",$I$82=0),4,IF($C$3="+25%",2,IF($C$3="+50%",3,1))),G82,G83,G84,G85) -> 0.01 | H86: =CHOOSE(IF(OR($C$3="Expert input",$I$82=0),4,IF($C$3="+25%",2,IF($C$3="+50%",3,1))),H82,H83,H84,H85) -> 166.66667 | I86: =G86*H86 -> 1.6666667 | J86: =J82 -> 0 | K86: =CHOOSE(IF(OR($C$3="Expert input",$I$82=0),4,IF($C$3="+25%",2,IF($C$3="+50%",3,1))),K82,K83,K84,K85) -> 1 | L86: =J86*K86 -> 0 | M86: =L86*G86 -> 0 | N86: =L86*I86 -> 0 | R86: 0.33 | S86: 0.67 | AA86: =O86*$M86 -> 0 | AB86: =O86*$N86 -> 0 | AC86: =P86*$M86 -> 0 | AD86: =P86*$N86 -> 0 | AE86: =Q86*$M86 -> 0 | AF86: =Q86*$N86 -> 0 | AG86: =R86*$M86 -> 0 | AH86: =R86*$N86 -> 0 | AI86: =S86*$M86 -> 0 | AJ86: =S86*$N86 -> 0 | AK86: =T86*$M86 -> 0 | AL86: =T86*$N86 -> 0 | AM86: =U86*$M86 -> 0 | AN86: =U86*$N86 -> 0 | AO86: =V86*$M86 -> 0 | AP86: =V86*$N86 -> 0 | AQ86: =W86*$M86 -> 0 | AR86: =W86*$N86 -> 0 | AS86: =X86*$M86 -> 0 | AT86: =X86*$N86 -> 0 | AU86: =Y86*$M86 -> 0 | AV86: =Y86*$N86 -> 0 | AW86: =Z86*$M86 -> 0 | AX86: =Z86*$N86 -> 0
A87: MC-15 | B87: Thinning sprouts on stumped coffee | C87: ጉንድል ቡና ምልማሎ | D87: Rejuvenation | E87: tree | F87: Industry average | G87: =IFERROR(INDEX('Benchmark Data'!$AC$7:$AC$130,MATCH($A87,'Benchmark Data'!$A$7:$A$130,0)),0) -> 0.01 | H87: =IFERROR(INDEX('Benchmark Data'!$AD$7:$AD$130,MATCH($A87,'Benchmark Data'!$A$7:$A$130,0)),0) -> 200 | I87: =G87*H87 -> 2 | K87: =IFERROR(INDEX('Benchmark Data'!$AE$7:$AE$130,MATCH($A87,'Benchmark Data'!$A$7:$A$130,0)),0) -> 1 | L87: =J87*K87 -> 0 | M87: =L87*G87 -> 0 | N87: =L87*I87 -> 0
A88: MC-15 | B88: Thinning sprouts on stumped coffee | C88: ጉንድል ቡና ምልማሎ | D88: Rejuvenation | E88: tree | F88: +25% | G88: =G87 -> 0.01 | H88: =H87*(1+Settings!$C$8) -> 250 | I88: =G88*H88 -> 2.5 | J88: =J87 -> 0 | K88: =K87 -> 1 | L88: =J88*K88 -> 0 | M88: =L88*G88 -> 0 | N88: =L88*I88 -> 0
A89: MC-15 | B89: Thinning sprouts on stumped coffee | C89: ጉንድል ቡና ምልማሎ | D89: Rejuvenation | E89: tree | F89: +50% | G89: =G87 -> 0.01 | H89: =H87*(1+Settings!$C$9) -> 300 | I89: =G89*H89 -> 3 | J89: =J87 -> 0 | K89: =K87 -> 1 | L89: =J89*K89 -> 0 | M89: =L89*G89 -> 0 | N89: =L89*I89 -> 0
A90: MC-15 | B90: Thinning sprouts on stumped coffee | C90: ጉንድል ቡና ምልማሎ | D90: Rejuvenation | E90: tree | F90: Expert input | G90: =G87 -> 0.01 | H90: =H87 -> 200 | I90: =G90*H90 -> 2 | J90: =J87 -> 0 | K90: =K87 -> 1 | L90: =J90*K90 -> 0 | M90: =L90*G90 -> 0 | N90: =L90*I90 -> 0
A91: MC-15 | B91: Thinning sprouts on stumped coffee | C91: ጉንድል ቡና ምልማሎ | D91: Rejuvenation | E91: tree | F91: Chaka Buna plan | G91: =CHOOSE(IF(OR($C$3="Expert input",$I$87=0),4,IF($C$3="+25%",2,IF($C$3="+50%",3,1))),G87,G88,G89,G90) -> 0.01 | H91: =CHOOSE(IF(OR($C$3="Expert input",$I$87=0),4,IF($C$3="+25%",2,IF($C$3="+50%",3,1))),H87,H88,H89,H90) -> 200 | I91: =G91*H91 -> 2 | J91: =J87 -> 0 | K91: =CHOOSE(IF(OR($C$3="Expert input",$I$87=0),4,IF($C$3="+25%",2,IF($C$3="+50%",3,1))),K87,K88,K89,K90) -> 1 | L91: =J91*K91 -> 0 | M91: =L91*G91 -> 0 | N91: =L91*I91 -> 0 | U91: 0.5 | V91: 0.5 | AA91: =O91*$M91 -> 0 | AB91: =O91*$N91 -> 0 | AC91: =P91*$M91 -> 0 | AD91: =P91*$N91 -> 0 | AE91: =Q91*$M91 -> 0 | AF91: =Q91*$N91 -> 0 | AG91: =R91*$M91 -> 0 | AH91: =R91*$N91 -> 0 | AI91: =S91*$M91 -> 0 | AJ91: =S91*$N91 -> 0 | AK91: =T91*$M91 -> 0 | AL91: =T91*$N91 -> 0 | AM91: =U91*$M91 -> 0 | AN91: =U91*$N91 -> 0 | AO91: =V91*$M91 -> 0 | AP91: =V91*$N91 -> 0 | AQ91: =W91*$M91 -> 0 | AR91: =W91*$N91 -> 0 | AS91: =X91*$M91 -> 0 | AT91: =X91*$N91 -> 0 | AU91: =Y91*$M91 -> 0 | AV91: =Y91*$N91 -> 0 | AW91: =Z91*$M91 -> 0 | AX91: =Z91*$N91 -> 0
A92: MC-16 | B92: Clearing debris from stumped coffee | C92: ከጉንድል ቡና ጭራሮ ማንሳት | D92: Rejuvenation | E92: ha | F92: Industry average | G92: =IFERROR(INDEX('Benchmark Data'!$AC$7:$AC$130,MATCH($A92,'Benchmark Data'!$A$7:$A$130,0)),0) -> 10 | H92: =IFERROR(INDEX('Benchmark Data'!$AD$7:$AD$130,MATCH($A92,'Benchmark Data'!$A$7:$A$130,0)),0) -> 300 | I92: =G92*H92 -> 3000 | K92: =IFERROR(INDEX('Benchmark Data'!$AE$7:$AE$130,MATCH($A92,'Benchmark Data'!$A$7:$A$130,0)),0) -> 1 | L92: =J92*K92 -> 0 | M92: =L92*G92 -> 0 | N92: =L92*I92 -> 0
A93: MC-16 | B93: Clearing debris from stumped coffee | C93: ከጉንድል ቡና ጭራሮ ማንሳት | D93: Rejuvenation | E93: ha | F93: +25% | G93: =G92 -> 10 | H93: =H92*(1+Settings!$C$8) -> 375 | I93: =G93*H93 -> 3750 | J93: =J92 -> 0 | K93: =K92 -> 1 | L93: =J93*K93 -> 0 | M93: =L93*G93 -> 0 | N93: =L93*I93 -> 0
A94: MC-16 | B94: Clearing debris from stumped coffee | C94: ከጉንድል ቡና ጭራሮ ማንሳት | D94: Rejuvenation | E94: ha | F94: +50% | G94: =G92 -> 10 | H94: =H92*(1+Settings!$C$9) -> 450 | I94: =G94*H94 -> 4500 | J94: =J92 -> 0 | K94: =K92 -> 1 | L94: =J94*K94 -> 0 | M94: =L94*G94 -> 0 | N94: =L94*I94 -> 0
A95: MC-16 | B95: Clearing debris from stumped coffee | C95: ከጉንድል ቡና ጭራሮ ማንሳት | D95: Rejuvenation | E95: ha | F95: Expert input | G95: =G92 -> 10 | H95: =H92 -> 300 | I95: =G95*H95 -> 3000 | J95: =J92 -> 0 | K95: =K92 -> 1 | L95: =J95*K95 -> 0 | M95: =L95*G95 -> 0 | N95: =L95*I95 -> 0
A96: MC-16 | B96: Clearing debris from stumped coffee | C96: ከጉንድል ቡና ጭራሮ ማንሳት | D96: Rejuvenation | E96: ha | F96: Chaka Buna plan | G96: =CHOOSE(IF(OR($C$3="Expert input",$I$92=0),4,IF($C$3="+25%",2,IF($C$3="+50%",3,1))),G92,G93,G94,G95) -> 10 | H96: =CHOOSE(IF(OR($C$3="Expert input",$I$92=0),4,IF($C$3="+25%",2,IF($C$3="+50%",3,1))),H92,H93,H94,H95) -> 300 | I96: =G96*H96 -> 3000 | J96: =J92 -> 0 | K96: =CHOOSE(IF(OR($C$3="Expert input",$I$92=0),4,IF($C$3="+25%",2,IF($C$3="+50%",3,1))),K92,K93,K94,K95) -> 1 | L96: =J96*K96 -> 0 | M96: =L96*G96 -> 0 | N96: =L96*I96 -> 0 | R96: 0.5 | S96: 0.5 | AA96: =O96*$M96 -> 0 | AB96: =O96*$N96 -> 0 | AC96: =P96*$M96 -> 0 | AD96: =P96*$N96 -> 0 | AE96: =Q96*$M96 -> 0 | AF96: =Q96*$N96 -> 0 | AG96: =R96*$M96 -> 0 | AH96: =R96*$N96 -> 0 | AI96: =S96*$M96 -> 0 | AJ96: =S96*$N96 -> 0 | AK96: =T96*$M96 -> 0 | AL96: =T96*$N96 -> 0 | AM96: =U96*$M96 -> 0 | AN96: =U96*$N96 -> 0 | AO96: =V96*$M96 -> 0 | AP96: =V96*$N96 -> 0 | AQ96: =W96*$M96 -> 0 | AR96: =W96*$N96 -> 0 | AS96: =X96*$M96 -> 0 | AT96: =X96*$N96 -> 0 | AU96: =Y96*$M96 -> 0 | AV96: =Y96*$N96 -> 0 | AW96: =Z96*$M96 -> 0 | AX96: =Z96*$N96 -> 0
A97: MC-17 | B97: Uprooting old trees | C97: የቡና እግር ነቀላ | D97: Rejuvenation | E97: tree | F97: Industry average | G97: =IFERROR(INDEX('Benchmark Data'!$AC$7:$AC$130,MATCH($A97,'Benchmark Data'!$A$7:$A$130,0)),0) -> 0.01 | H97: =IFERROR(INDEX('Benchmark Data'!$AD$7:$AD$130,MATCH($A97,'Benchmark Data'!$A$7:$A$130,0)),0) -> 300 | I97: =G97*H97 -> 3 | K97: =IFERROR(INDEX('Benchmark Data'!$AE$7:$AE$130,MATCH($A97,'Benchmark Data'!$A$7:$A$130,0)),0) -> 1 | L97: =J97*K97 -> 0 | M97: =L97*G97 -> 0 | N97: =L97*I97 -> 0
A98: MC-17 | B98: Uprooting old trees | C98: የቡና እግር ነቀላ | D98: Rejuvenation | E98: tree | F98: +25% | G98: =G97 -> 0.01 | H98: =H97*(1+Settings!$C$8) -> 375 | I98: =G98*H98 -> 3.75 | J98: =J97 -> 0 | K98: =K97 -> 1 | L98: =J98*K98 -> 0 | M98: =L98*G98 -> 0 | N98: =L98*I98 -> 0
A99: MC-17 | B99: Uprooting old trees | C99: የቡና እግር ነቀላ | D99: Rejuvenation | E99: tree | F99: +50% | G99: =G97 -> 0.01 | H99: =H97*(1+Settings!$C$9) -> 450 | I99: =G99*H99 -> 4.5 | J99: =J97 -> 0 | K99: =K97 -> 1 | L99: =J99*K99 -> 0 | M99: =L99*G99 -> 0 | N99: =L99*I99 -> 0
A100: MC-17 | B100: Uprooting old trees | C100: የቡና እግር ነቀላ | D100: Rejuvenation | E100: tree | F100: Expert input | G100: =G97 -> 0.01 | H100: =H97 -> 300 | I100: =G100*H100 -> 3 | J100: =J97 -> 0 | K100: =K97 -> 1 | L100: =J100*K100 -> 0 | M100: =L100*G100 -> 0 | N100: =L100*I100 -> 0
A101: MC-17 | B101: Uprooting old trees | C101: የቡና እግር ነቀላ | D101: Rejuvenation | E101: tree | F101: Chaka Buna plan | G101: =CHOOSE(IF(OR($C$3="Expert input",$I$97=0),4,IF($C$3="+25%",2,IF($C$3="+50%",3,1))),G97,G98,G99,G100) -> 0.01 | H101: =CHOOSE(IF(OR($C$3="Expert input",$I$97=0),4,IF($C$3="+25%",2,IF($C$3="+50%",3,1))),H97,H98,H99,H100) -> 300 | I101: =G101*H101 -> 3 | J101: =J97 -> 0 | K101: =CHOOSE(IF(OR($C$3="Expert input",$I$97=0),4,IF($C$3="+25%",2,IF($C$3="+50%",3,1))),K97,K98,K99,K100) -> 1 | L101: =J101*K101 -> 0 | M101: =L101*G101 -> 0 | N101: =L101*I101 -> 0 | R101: 0.34 | S101: 0.33 | T101: 0.33 | AA101: =O101*$M101 -> 0 | AB101: =O101*$N101 -> 0 | AC101: =P101*$M101 -> 0 | AD101: =P101*$N101 -> 0 | AE101: =Q101*$M101 -> 0 | AF101: =Q101*$N101 -> 0 | AG101: =R101*$M101 -> 0 | AH101: =R101*$N101 -> 0 | AI101: =S101*$M101 -> 0 | AJ101: =S101*$N101 -> 0 | AK101: =T101*$M101 -> 0 | AL101: =T101*$N101 -> 0 | AM101: =U101*$M101 -> 0 | AN101: =U101*$N101 -> 0 | AO101: =V101*$M101 -> 0 | AP101: =V101*$N101 -> 0 | AQ101: =W101*$M101 -> 0 | AR101: =W101*$N101 -> 0 | AS101: =X101*$M101 -> 0 | AT101: =X101*$N101 -> 0 | AU101: =Y101*$M101 -> 0 | AV101: =Y101*$N101 -> 0 | AW101: =Z101*$M101 -> 0 | AX101: =Z101*$N101 -> 0
A102: MC-18 | B102: Shade tree regulation | C102: ጥላ ዛፍ ቅነሳ | D102: Shade & vegetation | E102: ha | F102: Industry average | G102: =IFERROR(INDEX('Benchmark Data'!$AC$7:$AC$130,MATCH($A102,'Benchmark Data'!$A$7:$A$130,0)),0) -> 10 | H102: =IFERROR(INDEX('Benchmark Data'!$AD$7:$AD$130,MATCH($A102,'Benchmark Data'!$A$7:$A$130,0)),0) -> 80 | I102: =G102*H102 -> 800 | J102: =$E$7 -> 0 | K102: =IFERROR(INDEX('Benchmark Data'!$AE$7:$AE$130,MATCH($A102,'Benchmark Data'!$A$7:$A$130,0)),0) -> 1 | L102: =J102*K102 -> 0 | M102: =L102*G102 -> 0 | N102: =L102*I102 -> 0
A103: MC-18 | B103: Shade tree regulation | C103: ጥላ ዛፍ ቅነሳ | D103: Shade & vegetation | E103: ha | F103: +25% | G103: =G102 -> 10 | H103: =H102*(1+Settings!$C$8) -> 100 | I103: =G103*H103 -> 1000 | J103: =J102 -> 0 | K103: =K102 -> 1 | L103: =J103*K103 -> 0 | M103: =L103*G103 -> 0 | N103: =L103*I103 -> 0
A104: MC-18 | B104: Shade tree regulation | C104: ጥላ ዛፍ ቅነሳ | D104: Shade & vegetation | E104: ha | F104: +50% | G104: =G102 -> 10 | H104: =H102*(1+Settings!$C$9) -> 120 | I104: =G104*H104 -> 1200 | J104: =J102 -> 0 | K104: =K102 -> 1 | L104: =J104*K104 -> 0 | M104: =L104*G104 -> 0 | N104: =L104*I104 -> 0
...

Sheet Infilling
A1: Infilling – activity plan and budget
A2: ="Farm: "&Settings!$C$6&" | Plan year: "&Settings!$C$7 -> Farm: Chaka Buna Estate (Silva Forest Coffee) | Plan year: 2019 EFY (2026/27) – confirm
B3: Plan basis (drop-down) ► | C3: Industry average | D3: Sets the Chaka Buna plan row of every activity on this tab. Activities with no industry-average rate always use the Expert input row.
B5: GENERAL INFORMATION | F5: CATEGORY TOTALS
B6: Metric (English) | C6: Metric (Amharic) | D6: Unit | E6: Quantity | F6: Rate scenario | M6: Total man-days | N6: Total cost (birr) | O6: Plan phasing (% of cost) | AA6: Plan monthly totals
B7: Total coffee area | C7: ጠቅላላ የመሬት (ሄ/ር) | D7: ha | F7: Industry average | M7: =SUMIF($F$17:$F$81,"Industry average",M$17:M$81) -> 0 | N7: =SUMIF($F$17:$F$81,"Industry average",N$17:N$81) -> 0
B8: Trees to infill | C8: ሞተ ከዳ ቁጥር | D8: no. | F8: +25% | M8: =SUMIF($F$17:$F$81,"+25%",M$17:M$81) -> 0 | N8: =SUMIF($F$17:$F$81,"+25%",N$17:N$81) -> 0
B9: Average trees per ha (trees to infill ÷ area) | C9: የቡና እግር አማካይ (ሄ/ር) | D9: trees/ha | E9: =IFERROR($E$8/$E$7,0) -> 0 | F9: +50% | M9: =SUMIF($F$17:$F$81,"+50%",M$17:M$81) -> 0 | N9: =SUMIF($F$17:$F$81,"+50%",N$17:N$81) -> 0
F10: Expert input | M10: =SUMIF($F$17:$F$81,"Expert input",M$17:M$81) -> 0 | N10: =SUMIF($F$17:$F$81,"Expert input",N$17:N$81) -> 0
F11: Chaka Buna plan – counts in Summary | M11: =SUMIF($F$17:$F$81,"Chaka Buna plan",M$17:M$81) -> 0 | N11: =SUMIF($F$17:$F$81,"Chaka Buna plan",N$17:N$81) -> 0 | O11: =IFERROR(AB11/$N$11,0) -> 0 | P11: =IFERROR(AD11/$N$11,0) -> 0 | Q11: =IFERROR(AF11/$N$11,0) -> 0 | R11: =IFERROR(AH11/$N$11,0) -> 0 | S11: =IFERROR(AJ11/$N$11,0) -> 0 | T11: =IFERROR(AL11/$N$11,0) -> 0 | U11: =IFERROR(AN11/$N$11,0) -> 0 | V11: =IFERROR(AP11/$N$11,0) -> 0 | W11: =IFERROR(AR11/$N$11,0) -> 0 | X11: =IFERROR(AT11/$N$11,0) -> 0 | Y11: =IFERROR(AV11/$N$11,0) -> 0 | Z11: =IFERROR(AX11/$N$11,0) -> 0 | AA11: =SUM(AA17:AA81) -> 0 | AB11: =SUM(AB17:AB81) -> 0 | AC11: =SUM(AC17:AC81) -> 0 | AD11: =SUM(AD17:AD81) -> 0 | AE11: =SUM(AE17:AE81) -> 0 | AF11: =SUM(AF17:AF81) -> 0 | AG11: =SUM(AG17:AG81) -> 0 | AH11: =SUM(AH17:AH81) -> 0 | ... AX11: =SUM(AX17:AX81) -> 0
A15: ACTIVITY | F15: RATE (cost per unit = man-days × wage) | J15: QUANTITY | L15: TOTALS (calculated) | O15: PHASING – % of annual (input on the Chaka Buna plan row) | AA15: MONTHLY MAN-DAYS AND COST (Chaka Buna plan row)
A16: Code | B16: Activity | C16: Activity (Amharic) | D16: Sub-group | E16: Unit | F16: Rate scenario | G16: Man-days per unit | H16: Wage per man-day (birr) | I16: Cost per unit (birr) | J16: Activity quantity per round | K16: Frequency (times / year) | L16: Total activity quantity | M16: Total man-days per activity | N16: Total cost per activity (birr) | O16: Tikimt (Oct) | P16: Hidar (Nov) | Q16: Tahsas (Dec) | R16: Tir (Jan) | S16: Yekatit (Feb) | T16: Megabit (Mar) | U16: Miyazya (Apr) | V16: Ginbot (May) | W16: Sene (Jun) | X16: Hamle (Jul) | Y16: Nehase (Aug) | Z16: Meskerem (Sep) | AA16: Tikimt (Oct) – man-days | AB16: Tikimt (Oct) – cost | AC16: Hidar (Nov) – man-days | AD16: Hidar (Nov) – cost | AE16: Tahsas (Dec) – man-days | AF16: Tahsas (Dec) – cost | AG16: Tir (Jan) – man-days | AH16: Tir (Jan) – cost | AI16: Yekatit (Feb) – man-days | AJ16: Yekatit (Feb) – cost | AK16: Megabit (Mar) – man-days | AL16: Megabit (Mar) – cost | AM16: Miyazya (Apr) – man-days | AN16: Miyazya (Apr) – cost | AO16: Ginbot (May) – man-days | AP16: Ginbot (May) – cost | AQ16: Sene (Jun) – man-days | AR16: Sene (Jun) – cost | AS16: Hamle (Jul) – man-days | AT16: Hamle (Jul) – cost | AU16: Nehase (Aug) – man-days | AV16: Nehase (Aug) – cost | AW16: Meskerem (Sep) – man-days | AX16: Meskerem (Sep) – cost
A17: IF-01 | B17: Peg preparation & transport | C17: ችካል ዝግጅትና ማጓጓዝ | D17: Site preparation | E17: peg | F17: Industry average | G17: =IFERROR(INDEX('Benchmark Data'!$AC$7:$AC$130,MATCH($A17,'Benchmark Data'!$A$7:$A$130,0)),0) -> 0.0061111111 | H17: =IFERROR(INDEX('Benchmark Data'!$AD$7:$AD$130,MATCH($A17,'Benchmark Data'!$A$7:$A$130,0)),0) -> 106.36364 | I17: =G17*H17 -> 0.65 | J17: =$E$8 -> 0 | K17: =IFERROR(INDEX('Benchmark Data'!$AE$7:$AE$130,MATCH($A17,'Benchmark Data'!$A$7:$A$130,0)),0) -> 1 | L17: =J17*K17 -> 0 | M17: =L17*G17 -> 0 | N17: =L17*I17 -> 0
A18: IF-01 | B18: Peg preparation & transport | C18: ችካል ዝግጅትና ማጓጓዝ | D18: Site preparation | E18: peg | F18: +25% | G18: =G17 -> 0.0061111111 | H18: =H17*(1+Settings!$C$8) -> 132.95455 | I18: =G18*H18 -> 0.8125 | J18: =J17 -> 0 | K18: =K17 -> 1 | L18: =J18*K18 -> 0 | M18: =L18*G18 -> 0 | N18: =L18*I18 -> 0
A19: IF-01 | B19: Peg preparation & transport | C19: ችካል ዝግጅትና ማጓጓዝ | D19: Site preparation | E19: peg | F19: +50% | G19: =G17 -> 0.0061111111 | H19: =H17*(1+Settings!$C$9) -> 159.54545 | I19: =G19*H19 -> 0.975 | J19: =J17 -> 0 | K19: =K17 -> 1 | L19: =J19*K19 -> 0 | M19: =L19*G19 -> 0 | N19: =L19*I19 -> 0
A20: IF-01 | B20: Peg preparation & transport | C20: ችካል ዝግጅትና ማጓጓዝ | D20: Site preparation | E20: peg | F20: Expert input | G20: =G17 -> 0.0061111111 | H20: =H17 -> 106.36364 | I20: =G20*H20 -> 0.65 | J20: =J17 -> 0 | K20: =K17 -> 1 | L20: =J20*K20 -> 0 | M20: =L20*G20 -> 0 | N20: =L20*I20 -> 0
A21: IF-01 | B21: Peg preparation & transport | C21: ችካል ዝግጅትና ማጓጓዝ | D21: Site preparation | E21: peg | F21: Chaka Buna plan | G21: =CHOOSE(IF(OR($C$3="Expert input",$I$17=0),4,IF($C$3="+25%",2,IF($C$3="+50%",3,1))),G17,G18,G19,G20) -> 0.0061111111 | H21: =CHOOSE(IF(OR($C$3="Expert input",$I$17=0),4,IF($C$3="+25%",2,IF($C$3="+50%",3,1))),H17,H18,H19,H20) -> 106.36364 | I21: =G21*H21 -> 0.65 | J21: =J17 -> 0 | K21: =CHOOSE(IF(OR($C$3="Expert input",$I$17=0),4,IF($C$3="+25%",2,IF($C$3="+50%",3,1))),K17,K18,K19,K20) -> 1 | L21: =J21*K21 -> 0 | M21: =L21*G21 -> 0 | N21: =L21*I21 -> 0 | T21: 0.33 | U21: 0.5 | V21: 0.17 | AA21: =O21*$M21 -> 0 | AB21: =O21*$N21 -> 0 | AC21: =P21*$M21 -> 0 | AD21: =P21*$N21 -> 0 | AE21: =Q21*$M21 -> 0 | AF21: =Q21*$N21 -> 0 | AG21: =R21*$M21 -> 0 | AH21: =R21*$N21 -> 0 | AI21: =S21*$M21 -> 0 | AJ21: =S21*$N21 -> 0 | AK21: =T21*$M21 -> 0 | AL21: =T21*$N21 -> 0 | AM21: =U21*$M21 -> 0 | AN21: =U21*$N21 -> 0 | AO21: =V21*$M21 -> 0 | AP21: =V21*$N21 -> 0 | AQ21: =W21*$M21 -> 0 | AR21: =W21*$N21 -> 0 | AS21: =X21*$M21 -> 0 | AT21: =X21*$N21 -> 0 | AU21: =Y21*$M21 -> 0 | AV21: =Y21*$N21 -> 0 | AW21: =Z21*$M21 -> 0 | AX21: =Z21*$N21 -> 0
A22: IF-02 | B22: Layout & pegging | C22: ቅየሳና ችካል መቸከል | D22: Site preparation | E22: peg | F22: Industry average | G22: =IFERROR(INDEX('Benchmark Data'!$AC$7:$AC$130,MATCH($A22,'Benchmark Data'!$A$7:$A$130,0)),0) -> 0.0066666667 | H22: =IFERROR(INDEX('Benchmark Data'!$AD$7:$AD$130,MATCH($A22,'Benchmark Data'!$A$7:$A$130,0)),0) -> 97.5 | I22: =G22*H22 -> 0.65 | J22: =$E$8 -> 0 | K22: =IFERROR(INDEX('Benchmark Data'!$AE$7:$AE$130,MATCH($A22,'Benchmark Data'!$A$7:$A$130,0)),0) -> 1 | L22: =J22*K22 -> 0 | M22: =L22*G22 -> 0 | N22: =L22*I22 -> 0
A23: IF-02 | B23: Layout & pegging | C23: ቅየሳና ችካል መቸከል | D23: Site preparation | E23: peg | F23: +25% | G23: =G22 -> 0.0066666667 | H23: =H22*(1+Settings!$C$8) -> 121.875 | I23: =G23*H23 -> 0.8125 | J23: =J22 -> 0 | K23: =K22 -> 1 | L23: =J23*K23 -> 0 | M23: =L23*G23 -> 0 | N23: =L23*I23 -> 0
A24: IF-02 | B24: Layout & pegging | C24: ቅየሳና ችካል መቸከል | D24: Site preparation | E24: peg | F24: +50% | G24: =G22 -> 0.0066666667 | H24: =H22*(1+Settings!$C$9) -> 146.25 | I24: =G24*H24 -> 0.975 | J24: =J22 -> 0 | K24: =K22 -> 1 | L24: =J24*K24 -> 0 | M24: =L24*G24 -> 0 | N24: =L24*I24 -> 0
A25: IF-02 | B25: Layout & pegging | C25: ቅየሳና ችካል መቸከል | D25: Site preparation | E25: peg | F25: Expert input | G25: =G22 -> 0.0066666667 | H25: =H22 -> 97.5 | I25: =G25*H25 -> 0.65 | J25: =J22 -> 0 | K25: =K22 -> 1 | L25: =J25*K25 -> 0 | M25: =L25*G25 -> 0 | N25: =L25*I25 -> 0
A26: IF-02 | B26: Layout & pegging | C26: ቅየሳና ችካል መቸከል | D26: Site preparation | E26: peg | F26: Chaka Buna plan | G26: =CHOOSE(IF(OR($C$3="Expert input",$I$22=0),4,IF($C$3="+25%",2,IF($C$3="+50%",3,1))),G22,G23,G24,G25) -> 0.0066666667 | H26: =CHOOSE(IF(OR($C$3="Expert input",$I$22=0),4,IF($C$3="+25%",2,IF($C$3="+50%",3,1))),H22,H23,H24,H25) -> 97.5 | I26: =G26*H26 -> 0.65 | J26: =J22 -> 0 | K26: =CHOOSE(IF(OR($C$3="Expert input",$I$22=0),4,IF($C$3="+25%",2,IF($C$3="+50%",3,1))),K22,K23,K24,K25) -> 1 | L26: =J26*K26 -> 0 | M26: =L26*G26 -> 0 | N26: =L26*I26 -> 0 | T26: 0.33 | U26: 0.33 | V26: 0.17 | X26: 0.17 | AA26: =O26*$M26 -> 0 | AB26: =O26*$N26 -> 0 | AC26: =P26*$M26 -> 0 | AD26: =P26*$N26 -> 0 | AE26: =Q26*$M26 -> 0 | AF26: =Q26*$N26 -> 0 | AG26: =R26*$M26 -> 0 | AH26: =R26*$N26 -> 0 | AI26: =S26*$M26 -> 0 | AJ26: =S26*$N26 -> 0 | AK26: =T26*$M26 -> 0 | AL26: =T26*$N26 -> 0 | AM26: =U26*$M26 -> 0 | AN26: =U26*$N26 -> 0 | AO26: =V26*$M26 -> 0 | AP26: =V26*$N26 -> 0 | AQ26: =W26*$M26 -> 0 | AR26: =W26*$N26 -> 0 | AS26: =X26*$M26 -> 0 | AT26: =X26*$N26 -> 0 | AU26: =Y26*$M26 -> 0 | AV26: =Y26*$N26 -> 0 | AW26: =Z26*$M26 -> 0 | AX26: =Z26*$N26 -> 0
A27: IF-03 | B27: Holing | C27: ጉድጓድ ቁፋሮ | D27: Site preparation | E27: hole | F27: Industry average | G27: =IFERROR(INDEX('Benchmark Data'!$AC$7:$AC$130,MATCH($A27,'Benchmark Data'!$A$7:$A$130,0)),0) -> 0.012777778 | H27: =IFERROR(INDEX('Benchmark Data'!$AD$7:$AD$130,MATCH($A27,'Benchmark Data'!$A$7:$A$130,0)),0) -> 169.56522 | I27: =G27*H27 -> 2.1666667 | J27: =$E$8 -> 0 | K27: =IFERROR(INDEX('Benchmark Data'!$AE$7:$AE$130,MATCH($A27,'Benchmark Data'!$A$7:$A$130,0)),0) -> 1 | L27: =J27*K27 -> 0 | M27: =L27*G27 -> 0 | N27: =L27*I27 -> 0
A28: IF-03 | B28: Holing | C28: ጉድጓድ ቁፋሮ | D28: Site preparation | E28: hole | F28: +25% | G28: =G27 -> 0.012777778 | H28: =H27*(1+Settings!$C$8) -> 211.95652 | I28: =G28*H28 -> 2.7083333 | J28: =J27 -> 0 | K28: =K27 -> 1 | L28: =J28*K28 -> 0 | M28: =L28*G28 -> 0 | N28: =L28*I28 -> 0
A29: IF-03 | B29: Holing | C29: ጉድጓድ ቁፋሮ | D29: Site preparation | E29: hole | F29: +50% | G29: =G27 -> 0.012777778 | H29: =H27*(1+Settings!$C$9) -> 254.34783 | I29: =G29*H29 -> 3.25 | J29: =J27 -> 0 | K29: =K27 -> 1 | L29: =J29*K29 -> 0 | M29: =L29*G29 -> 0 | N29: =L29*I29 -> 0
A30: IF-03 | B30: Holing | C30: ጉድጓድ ቁፋሮ | D30: Site preparation | E30: hole | F30: Expert input | G30: =G27 -> 0.012777778 | H30: =H27 -> 169.56522 | I30: =G30*H30 -> 2.1666667 | J30: =J27 -> 0 | K30: =K27 -> 1 | L30: =J30*K30 -> 0 | M30: =L30*G30 -> 0 | N30: =L30*I30 -> 0
A31: IF-03 | B31: Holing | C31: ጉድጓድ ቁፋሮ | D31: Site preparation | E31: hole | F31: Chaka Buna plan | G31: =CHOOSE(IF(OR($C$3="Expert input",$I$27=0),4,IF($C$3="+25%",2,IF($C$3="+50%",3,1))),G27,G28,G29,G30) -> 0.012777778 | H31: =CHOOSE(IF(OR($C$3="Expert input",$I$27=0),4,IF($C$3="+25%",2,IF($C$3="+50%",3,1))),H27,H28,H29,H30) -> 169.56522 | I31: =G31*H31 -> 2.1666667 | J31: =J27 -> 0 | K31: =CHOOSE(IF(OR($C$3="Expert input",$I$27=0),4,IF($C$3="+25%",2,IF($C$3="+50%",3,1))),K27,K28,K29,K30) -> 1 | L31: =J31*K31 -> 0 | M31: =L31*G31 -> 0 | N31: =L31*I31 -> 0 | S31: 0.17 | T31: 0.83 | AA31: =O31*$M31 -> 0 | AB31: =O31*$N31 -> 0 | AC31: =P31*$M31 -> 0 | AD31: =P31*$N31 -> 0 | AE31: =Q31*$M31 -> 0 | AF31: =Q31*$N31 -> 0 | AG31: =R31*$M31 -> 0 | AH31: =R31*$N31 -> 0 | AI31: =S31*$M31 -> 0 | AJ31: =S31*$N31 -> 0 | AK31: =T31*$M31 -> 0 | AL31: =T31*$N31 -> 0 | AM31: =U31*$M31 -> 0 | AN31: =U31*$N31 -> 0 | AO31: =V31*$M31 -> 0 | AP31: =V31*$N31 -> 0 | AQ31: =W31*$M31 -> 0 | AR31: =W31*$N31 -> 0 | AS31: =X31*$M31 -> 0 | AT31: =X31*$N31 -> 0 | AU31: =Y31*$M31 -> 0 | AV31: =Y31*$N31 -> 0 | AW31: =Z31*$M31 -> 0 | AX31: =Z31*$N31 -> 0
A32: IF-04 | B32: Refilling holes | C32: አፈር ምለሳ | D32: Site preparation | E32: hole | F32: Industry average | G32: =IFERROR(INDEX('Benchmark Data'!$AC$7:$AC$130,MATCH($A32,'Benchmark Data'!$A$7:$A$130,0)),0) -> 0.0083333333 | H32: =IFERROR(INDEX('Benchmark Data'!$AD$7:$AD$130,MATCH($A32,'Benchmark Data'!$A$7:$A$130,0)),0) -> 78 | I32: =G32*H32 -> 0.65 | J32: =$E$8 -> 0 | K32: =IFERROR(INDEX('Benchmark Data'!$AE$7:$AE$130,MATCH($A32,'Benchmark Data'!$A$7:$A$130,0)),0) -> 1 | L32: =J32*K32 -> 0 | M32: =L32*G32 -> 0 | N32: =L32*I32 -> 0
A33: IF-04 | B33: Refilling holes | C33: አፈር ምለሳ | D33: Site preparation | E33: hole | F33: +25% | G33: =G32 -> 0.0083333333 | H33: =H32*(1+Settings!$C$8) -> 97.5 | I33: =G33*H33 -> 0.8125 | J33: =J32 -> 0 | K33: =K32 -> 1 | L33: =J33*K33 -> 0 | M33: =L33*G33 -> 0 | N33: =L33*I33 -> 0
A34: IF-04 | B34: Refilling holes | C34: አፈር ምለሳ | D34: Site preparation | E34: hole | F34: +50% | G34: =G32 -> 0.0083333333 | H34: =H32*(1+Settings!$C$9) -> 117 | I34: =G34*H34 -> 0.975 | J34: =J32 -> 0 | K34: =K32 -> 1 | L34: =J34*K34 -> 0 | M34: =L34*G34 -> 0 | N34: =L34*I34 -> 0
A35: IF-04 | B35: Refilling holes | C35: አፈር ምለሳ | D35: Site preparation | E35: hole | F35: Expert input | G35: =G32 -> 0.0083333333 | H35: =H32 -> 78 | I35: =G35*H35 -> 0.65 | J35: =J32 -> 0 | K35: =K32 -> 1 | L35: =J35*K35 -> 0 | M35: =L35*G35 -> 0 | N35: =L35*I35 -> 0
A36: IF-04 | B36: Refilling holes | C36: አፈር ምለሳ | D36: Site preparation | E36: hole | F36: Chaka Buna plan | G36: =CHOOSE(IF(OR($C$3="Expert input",$I$32=0),4,IF($C$3="+25%",2,IF($C$3="+50%",3,1))),G32,G33,G34,G35) -> 0.0083333333 | H36: =CHOOSE(IF(OR($C$3="Expert input",$I$32=0),4,IF($C$3="+25%",2,IF($C$3="+50%",3,1))),H32,H33,H34,H35) -> 78 | I36: =G36*H36 -> 0.65 | J36: =J32 -> 0 | K36: =CHOOSE(IF(OR($C$3="Expert input",$I$32=0),4,IF($C$3="+25%",2,IF($C$3="+50%",3,1))),K32,K33,K34,K35) -> 1 | L36: =J36*K36 -> 0 | M36: =L36*G36 -> 0 | N36: =L36*I36 -> 0 | U36: 0.83 | V36: 0.17 | AA36: =O36*$M36 -> 0 | AB36: =O36*$N36 -> 0 | AC36: =P36*$M36 -> 0 | AD36: =P36*$N36 -> 0 | AE36: =Q36*$M36 -> 0 | AF36: =Q36*$N36 -> 0 | AG36: =R36*$M36 -> 0 | AH36: =R36*$N36 -> 0 | AI36: =S36*$M36 -> 0 | AJ36: =S36*$N36 -> 0 | AK36: =T36*$M36 -> 0 | AL36: =T36*$N36 -> 0 | AM36: =U36*$M36 -> 0 | AN36: =U36*$N36 -> 0 | AO36: =V36*$M36 -> 0 | AP36: =V36*$N36 -> 0 | AQ36: =W36*$M36 -> 0 | AR36: =W36*$N36 -> 0 | AS36: =X36*$M36 -> 0 | AT36: =X36*$N36 -> 0 | AU36: =Y36*$M36 -> 0 | AV36: =Y36*$N36 -> 0 | AW36: =Z36*$M36 -> 0 | AX36: =Z36*$N36 -> 0
A37: IF-05 | B37: Seedling counting | C37: ቡና ችግኝ ቆጠራ | D37: Planting | E37: seedling | F37: Industry average | G37: =IFERROR(INDEX('Benchmark Data'!$AC$7:$AC$130,MATCH($A37,'Benchmark Data'!$A$7:$A$130,0)),0) -> 0 | H37: =IFERROR(INDEX('Benchmark Data'!$AD$7:$AD$130,MATCH($A37,'Benchmark Data'!$A$7:$A$130,0)),0) -> 0 | I37: =G37*H37 -> 0 | J37: =$E$8 -> 0 | K37: =IFERROR(INDEX('Benchmark Data'!$AE$7:$AE$130,MATCH($A37,'Benchmark Data'!$A$7:$A$130,0)),0) -> 1 | L37: =J37*K37 -> 0 | M37: =L37*G37 -> 0 | N37: =L37*I37 -> 0
A38: IF-05 | B38: Seedling counting | C38: ቡና ችግኝ ቆጠራ | D38: Planting | E38: seedling | F38: +25% | G38: =G37 -> 0 | H38: =H37*(1+Settings!$C$8) -> 0 | I38: =G38*H38 -> 0 | J38: =J37 -> 0 | K38: =K37 -> 1 | L38: =J38*K38 -> 0 | M38: =L38*G38 -> 0 | N38: =L38*I38 -> 0
A39: IF-05 | B39: Seedling counting | C39: ቡና ችግኝ ቆጠራ | D39: Planting | E39: seedling | F39: +50% | G39: =G37 -> 0 | H39: =H37*(1+Settings!$C$9) -> 0 | I39: =G39*H39 -> 0 | J39: =J37 -> 0 | K39: =K37 -> 1 | L39: =J39*K39 -> 0 | M39: =L39*G39 -> 0 | N39: =L39*I39 -> 0
A40: IF-05 | B40: Seedling counting | C40: ቡና ችግኝ ቆጠራ | D40: Planting | E40: seedling | F40: Expert input | I40: =G40*H40 -> 0 | J40: =J37 -> 0 | K40: 1 | L40: =J40*K40 -> 0 | M40: =L40*G40 -> 0 | N40: =L40*I40 -> 0
A41: IF-05 | B41: Seedling counting | C41: ቡና ችግኝ ቆጠራ | D41: Planting | E41: seedling | F41: Chaka Buna plan | G41: =CHOOSE(IF(OR($C$3="Expert input",$I$37=0),4,IF($C$3="+25%",2,IF($C$3="+50%",3,1))),G37,G38,G39,G40) -> 0 | H41: =CHOOSE(IF(OR($C$3="Expert input",$I$37=0),4,IF($C$3="+25%",2,IF($C$3="+50%",3,1))),H37,H38,H39,H40) -> 0 | I41: =G41*H41 -> 0 | J41: =J37 -> 0 | K41: =CHOOSE(IF(OR($C$3="Expert input",$I$37=0),4,IF($C$3="+25%",2,IF($C$3="+50%",3,1))),K37,K38,K39,K40) -> 1 | L41: =J41*K41 -> 0 | M41: =L41*G41 -> 0 | N41: =L41*I41 -> 0 | AA41: =O41*$M41 -> 0 | AB41: =O41*$N41 -> 0 | AC41: =P41*$M41 -> 0 | AD41: =P41*$N41 -> 0 | AE41: =Q41*$M41 -> 0 | AF41: =Q41*$N41 -> 0 | AG41: =R41*$M41 -> 0 | AH41: =R41*$N41 -> 0 | AI41: =S41*$M41 -> 0 | AJ41: =S41*$N41 -> 0 | AK41: =T41*$M41 -> 0 | AL41: =T41*$N41 -> 0 | AM41: =U41*$M41 -> 0 | AN41: =U41*$N41 -> 0 | AO41: =V41*$M41 -> 0 | AP41: =V41*$N41 -> 0 | AQ41: =W41*$M41 -> 0 | AR41: =W41*$N41 -> 0 | AS41: =X41*$M41 -> 0 | AT41: =X41*$N41 -> 0 | AU41: =Y41*$M41 -> 0 | AV41: =Y41*$N41 -> 0 | AW41: =Z41*$M41 -> 0 | AX41: =Z41*$N41 -> 0
A42: IF-06 | B42: Seedling transport | C42: ቡና ችግኝ ማጓጓዝ | D42: Planting | E42: seedling | F42: Industry average | G42: =IFERROR(INDEX('Benchmark Data'!$AC$7:$AC$130,MATCH($A42,'Benchmark Data'!$A$7:$A$130,0)),0) -> 0.015 | H42: =IFERROR(INDEX('Benchmark Data'!$AD$7:$AD$130,MATCH($A42,'Benchmark Data'!$A$7:$A$130,0)),0) -> 133.33333 | I42: =G42*H42 -> 2 | J42: =$E$8 -> 0 | K42: =IFERROR(INDEX('Benchmark Data'!$AE$7:$AE$130,MATCH($A42,'Benchmark Data'!$A$7:$A$130,0)),0) -> 1 | L42: =J42*K42 -> 0 | M42: =L42*G42 -> 0 | N42: =L42*I42 -> 0
A43: IF-06 | B43: Seedling transport | C43: ቡና ችግኝ ማጓጓዝ | D43: Planting | E43: seedling | F43: +25% | G43: =G42 -> 0.015 | H43: =H42*(1+Settings!$C$8) -> 166.66667 | I43: =G43*H43 -> 2.5 | J43: =J42 -> 0 | K43: =K42 -> 1 | L43: =J43*K43 -> 0 | M43: =L43*G43 -> 0 | N43: =L43*I43 -> 0
A44: IF-06 | B44: Seedling transport | C44: ቡና ችግኝ ማጓጓዝ | D44: Planting | E44: seedling | F44: +50% | G44: =G42 -> 0.015 | H44: =H42*(1+Settings!$C$9) -> 200 | I44: =G44*H44 -> 3 | J44: =J42 -> 0 | K44: =K42 -> 1 | L44: =J44*K44 -> 0 | M44: =L44*G44 -> 0 | N44: =L44*I44 -> 0
A45: IF-06 | B45: Seedling transport | C45: ቡና ችግኝ ማጓጓዝ | D45: Planting | E45: seedling | F45: Expert input | G45: =G42 -> 0.015 | H45: =H42 -> 133.33333 | I45: =G45*H45 -> 2 | J45: =J42 -> 0 | K45: =K42 -> 1 | L45: =J45*K45 -> 0 | M45: =L45*G45 -> 0 | N45: =L45*I45 -> 0
A46: IF-06 | B46: Seedling transport | C46: ቡና ችግኝ ማጓጓዝ | D46: Planting | E46: seedling | F46: Chaka Buna plan | G46: =CHOOSE(IF(OR($C$3="Expert input",$I$42=0),4,IF($C$3="+25%",2,IF($C$3="+50%",3,1))),G42,G43,G44,G45) -> 0.015 | H46: =CHOOSE(IF(OR($C$3="Expert input",$I$42=0),4,IF($C$3="+25%",2,IF($C$3="+50%",3,1))),H42,H43,H44,H45) -> 133.33333 | I46: =G46*H46 -> 2 | J46: =J42 -> 0 | K46: =CHOOSE(IF(OR($C$3="Expert input",$I$42=0),4,IF($C$3="+25%",2,IF($C$3="+50%",3,1))),K42,K43,K44,K45) -> 1 | L46: =J46*K46 -> 0 | M46: =L46*G46 -> 0 | N46: =L46*I46 -> 0 | U46: 0.12 | V46: 0.54 | W46: 0.17 | X46: 0.17 | AA46: =O46*$M46 -> 0 | AB46: =O46*$N46 -> 0 | AC46: =P46*$M46 -> 0 | AD46: =P46*$N46 -> 0 | AE46: =Q46*$M46 -> 0 | AF46: =Q46*$N46 -> 0 | AG46: =R46*$M46 -> 0 | AH46: =R46*$N46 -> 0 | AI46: =S46*$M46 -> 0 | AJ46: =S46*$N46 -> 0 | AK46: =T46*$M46 -> 0 | AL46: =T46*$N46 -> 0 | AM46: =U46*$M46 -> 0 | AN46: =U46*$N46 -> 0 | AO46: =V46*$M46 -> 0 | AP46: =V46*$N46 -> 0 | AQ46: =W46*$M46 -> 0 | AR46: =W46*$N46 -> 0 | AS46: =X46*$M46 -> 0 | AT46: =X46*$N46 -> 0 | AU46: =Y46*$M46 -> 0 | AV46: =Y46*$N46 -> 0 | AW46: =Z46*$M46 -> 0 | AX46: =Z46*$N46 -> 0
A47: IF-07 | B47: Coffee planting | C47: ቡና ተከላ | D47: Planting | E47: seedling | F47: Industry average | G47: =IFERROR(INDEX('Benchmark Data'!$AC$7:$AC$130,MATCH($A47,'Benchmark Data'!$A$7:$A$130,0)),0) -> 0.01 | H47: =IFERROR(INDEX('Benchmark Data'!$AD$7:$AD$130,MATCH($A47,'Benchmark Data'!$A$7:$A$130,0)),0) -> 133.33333 | I47: =G47*H47 -> 1.3333333 | J47: =$E$8 -> 0 | K47: =IFERROR(INDEX('Benchmark Data'!$AE$7:$AE$130,MATCH($A47,'Benchmark Data'!$A$7:$A$130,0)),0) -> 1 | L47: =J47*K47 -> 0 | M47: =L47*G47 -> 0 | N47: =L47*I47 -> 0
A48: IF-07 | B48: Coffee planting | C48: ቡና ተከላ | D48: Planting | E48: seedling | F48: +25% | G48: =G47 -> 0.01 | H48: =H47*(1+Settings!$C$8) -> 166.66667 | I48: =G48*H48 -> 1.6666667 | J48: =J47 -> 0 | K48: =K47 -> 1 | L48: =J48*K48 -> 0 | M48: =L48*G48 -> 0 | N48: =L48*I48 -> 0
A49: IF-07 | B49: Coffee planting | C49: ቡና ተከላ | D49: Planting | E49: seedling | F49: +50% | G49: =G47 -> 0.01 | H49: =H47*(1+Settings!$C$9) -> 200 | I49: =G49*H49 -> 2 | J49: =J47 -> 0 | K49: =K47 -> 1 | L49: =J49*K49 -> 0 | M49: =L49*G49 -> 0 | N49: =L49*I49 -> 0
A50: IF-07 | B50: Coffee planting | C50: ቡና ተከላ | D50: Planting | E50: seedling | F50: Expert input | G50: =G47 -> 0.01 | H50: =H47 -> 133.33333 | I50: =G50*H50 -> 1.3333333 | J50: =J47 -> 0 | K50: =K47 -> 1 | L50: =J50*K50 -> 0 | M50: =L50*G50 -> 0 | N50: =L50*I50 -> 0
A51: IF-07 | B51: Coffee planting | C51: ቡና ተከላ | D51: Planting | E51: seedling | F51: Chaka Buna plan | G51: =CHOOSE(IF(OR($C$3="Expert input",$I$47=0),4,IF($C$3="+25%",2,IF($C$3="+50%",3,1))),G47,G48,G49,G50) -> 0.01 | H51: =CHOOSE(IF(OR($C$3="Expert input",$I$47=0),4,IF($C$3="+25%",2,IF($C$3="+50%",3,1))),H47,H48,H49,H50) -> 133.33333 | I51: =G51*H51 -> 1.3333333 | J51: =J47 -> 0 | K51: =CHOOSE(IF(OR($C$3="Expert input",$I$47=0),4,IF($C$3="+25%",2,IF($C$3="+50%",3,1))),K47,K48,K49,K50) -> 1 | L51: =J51*K51 -> 0 | M51: =L51*G51 -> 0 | N51: =L51*I51 -> 0 | V51: 0.45 | W51: 0.38 | X51: 0.17 | AA51: =O51*$M51 -> 0 | AB51: =O51*$N51 -> 0 | AC51: =P51*$M51 -> 0 | AD51: =P51*$N51 -> 0 | AE51: =Q51*$M51 -> 0 | AF51: =Q51*$N51 -> 0 | AG51: =R51*$M51 -> 0 | AH51: =R51*$N51 -> 0 | AI51: =S51*$M51 -> 0 | AJ51: =S51*$N51 -> 0 | AK51: =T51*$M51 -> 0 | AL51: =T51*$N51 -> 0 | AM51: =U51*$M51 -> 0 | AN51: =U51*$N51 -> 0 | AO51: =V51*$M51 -> 0 | AP51: =V51*$N51 -> 0 | AQ51: =W51*$M51 -> 0 | AR51: =W51*$N51 -> 0 | AS51: =X51*$M51 -> 0 | AT51: =X51*$N51 -> 0 | AU51: =Y51*$M51 -> 0 | AV51: =Y51*$N51 -> 0 | AW51: =Z51*$M51 -> 0 | AX51: =Z51*$N51 -> 0
A52: IF-08 | B52: Ring weeding of planted seedlings | C52: ችግኝ ቡና ዙሪያ ማረም | D52: Planting | E52: seedling | F52: Industry average | G52: =IFERROR(INDEX('Benchmark Data'!$AC$7:$AC$130,MATCH($A52,'Benchmark Data'!$A$7:$A$130,0)),0) -> 0.01 | H52: =IFERROR(INDEX('Benchmark Data'!$AD$7:$AD$130,MATCH($A52,'Benchmark Data'!$A$7:$A$130,0)),0) -> 150 | I52: =G52*H52 -> 1.5 | J52: =$E$8 -> 0 | K52: =IFERROR(INDEX('Benchmark Data'!$AE$7:$AE$130,MATCH($A52,'Benchmark Data'!$A$7:$A$130,0)),0) -> 1 | L52: =J52*K52 -> 0 | M52: =L52*G52 -> 0 | N52: =L52*I52 -> 0
A53: IF-08 | B53: Ring weeding of planted seedlings | C53: ችግኝ ቡና ዙሪያ ማረም | D53: Planting | E53: seedling | F53: +25% | G53: =G52 -> 0.01 | H53: =H52*(1+Settings!$C$8) -> 187.5 | I53: =G53*H53 -> 1.875 | J53: =J52 -> 0 | K53: =K52 -> 1 | L53: =J53*K53 -> 0 | M53: =L53*G53 -> 0 | N53: =L53*I53 -> 0
A54: IF-08 | B54: Ring weeding of planted seedlings | C54: ችግኝ ቡና ዙሪያ ማረም | D54: Planting | E54: seedling | F54: +50% | G54: =G52 -> 0.01 | H54: =H52*(1+Settings!$C$9) -> 225 | I54: =G54*H54 -> 2.25 | J54: =J52 -> 0 | K54: =K52 -> 1 | L54: =J54*K54 -> 0 | M54: =L54*G54 -> 0 | N54: =L54*I54 -> 0
A55: IF-08 | B55: Ring weeding of planted seedlings | C55: ችግኝ ቡና ዙሪያ ማረም | D55: Planting | E55: seedling | F55: Expert input | G55: =G52 -> 0.01 | H55: =H52 -> 150 | I55: =G55*H55 -> 1.5 | J55: =J52 -> 0 | K55: =K52 -> 1 | L55: =J55*K55 -> 0 | M55: =L55*G55 -> 0 | N55: =L55*I55 -> 0
A56: IF-08 | B56: Ring weeding of planted seedlings | C56: ችግኝ ቡና ዙሪያ ማረም | D56: Planting | E56: seedling | F56: Chaka Buna plan | G56: =CHOOSE(IF(OR($C$3="Expert input",$I$52=0),4,IF($C$3="+25%",2,IF($C$3="+50%",3,1))),G52,G53,G54,G55) -> 0.01 | H56: =CHOOSE(IF(OR($C$3="Expert input",$I$52=0),4,IF($C$3="+25%",2,IF($C$3="+50%",3,1))),H52,H53,H54,H55) -> 150 | I56: =G56*H56 -> 1.5 | J56: =J52 -> 0 | K56: =CHOOSE(IF(OR($C$3="Expert input",$I$52=0),4,IF($C$3="+25%",2,IF($C$3="+50%",3,1))),K52,K53,K54,K55) -> 1 | L56: =J56*K56 -> 0 | M56: =L56*G56 -> 0 | N56: =L56*I56 -> 0 | Y56: 0.5 | Z56: 0.5 | AA56: =O56*$M56 -> 0 | AB56: =O56*$N56 -> 0 | AC56: =P56*$M56 -> 0 | AD56: =P56*$N56 -> 0 | AE56: =Q56*$M56 -> 0 | AF56: =Q56*$N56 -> 0 | AG56: =R56*$M56 -> 0 | AH56: =R56*$N56 -> 0 | AI56: =S56*$M56 -> 0 | AJ56: =S56*$N56 -> 0 | AK56: =T56*$M56 -> 0 | AL56: =T56*$N56 -> 0 | AM56: =U56*$M56 -> 0 | AN56: =U56*$N56 -> 0 | AO56: =V56*$M56 -> 0 | AP56: =V56*$N56 -> 0 | AQ56: =W56*$M56 -> 0 | AR56: =W56*$N56 -> 0 | AS56: =X56*$M56 -> 0 | AT56: =X56*$N56 -> 0 | AU56: =Y56*$M56 -> 0 | AV56: =Y56*$N56 -> 0 | AW56: =Z56*$M56 -> 0 | AX56: =Z56*$N56 -> 0
A57: IF-09 | B57: Permanent shade tree planting | C57: ቋሚ ጥላ ዛፍ ተከላ | D57: Shade | E57: seedling | F57: Industry average | G57: =IFERROR(INDEX('Benchmark Data'!$AC$7:$AC$130,MATCH($A57,'Benchmark Data'!$A$7:$A$130,0)),0) -> 0.01 | H57: =IFERROR(INDEX('Benchmark Data'!$AD$7:$AD$130,MATCH($A57,'Benchmark Data'!$A$7:$A$130,0)),0) -> 150 | I57: =G57*H57 -> 1.5 | K57: =IFERROR(INDEX('Benchmark Data'!$AE$7:$AE$130,MATCH($A57,'Benchmark Data'!$A$7:$A$130,0)),0) -> 1 | L57: =J57*K57 -> 0 | M57: =L57*G57 -> 0 | N57: =L57*I57 -> 0
A58: IF-09 | B58: Permanent shade tree planting | C58: ቋሚ ጥላ ዛፍ ተከላ | D58: Shade | E58: seedling | F58: +25% | G58: =G57 -> 0.01 | H58: =H57*(1+Settings!$C$8) -> 187.5 | I58: =G58*H58 -> 1.875 | J58: =J57 -> 0 | K58: =K57 -> 1 | L58: =J58*K58 -> 0 | M58: =L58*G58 -> 0 | N58: =L58*I58 -> 0
A59: IF-09 | B59: Permanent shade tree planting | C59: ቋሚ ጥላ ዛፍ ተከላ | D59: Shade | E59: seedling | F59: +50% | G59: =G57 -> 0.01 | H59: =H57*(1+Settings!$C$9) -> 225 | I59: =G59*H59 -> 2.25 | J59: =J57 -> 0 | K59: =K57 -> 1 | L59: =J59*K59 -> 0 | M59: =L59*G59 -> 0 | N59: =L59*I59 -> 0
A60: IF-09 | B60: Permanent shade tree planting | C60: ቋሚ ጥላ ዛፍ ተከላ | D60: Shade | E60: seedling | F60: Expert input | G60: =G57 -> 0.01 | H60: =H57 -> 150 | I60: =G60*H60 -> 1.5 | J60: =J57 -> 0 | K60: =K57 -> 1 | L60: =J60*K60 -> 0 | M60: =L60*G60 -> 0 | N60: =L60*I60 -> 0
A61: IF-09 | B61: Permanent shade tree planting | C61: ቋሚ ጥላ ዛፍ ተከላ | D61: Shade | E61: seedling | F61: Chaka Buna plan | G61: =CHOOSE(IF(OR($C$3="Expert input",$I$57=0),4,IF($C$3="+25%",2,IF($C$3="+50%",3,1))),G57,G58,G59,G60) -> 0.01 | H61: =CHOOSE(IF(OR($C$3="Expert input",$I$57=0),4,IF($C$3="+25%",2,IF($C$3="+50%",3,1))),H57,H58,H59,H60) -> 150 | I61: =G61*H61 -> 1.5 | J61: =J57 -> 0 | K61: =CHOOSE(IF(OR($C$3="Expert input",$I$57=0),4,IF($C$3="+25%",2,IF($C$3="+50%",3,1))),K57,K58,K59,K60) -> 1 | L61: =J61*K61 -> 0 | M61: =L61*G61 -> 0 | N61: =L61*I61 -> 0 | W61: 1 | AA61: =O61*$M61 -> 0 | AB61: =O61*$N61 -> 0 | AC61: =P61*$M61 -> 0 | AD61: =P61*$N61 -> 0 | AE61: =Q61*$M61 -> 0 | AF61: =Q61*$N61 -> 0 | AG61: =R61*$M61 -> 0 | AH61: =R61*$N61 -> 0 | AI61: =S61*$M61 -> 0 | AJ61: =S61*$N61 -> 0 | AK61: =T61*$M61 -> 0 | AL61: =T61*$N61 -> 0 | AM61: =U61*$M61 -> 0 | AN61: =U61*$N61 -> 0 | AO61: =V61*$M61 -> 0 | AP61: =V61*$N61 -> 0 | AQ61: =W61*$M61 -> 0 | AR61: =W61*$N61 -> 0 | AS61: =X61*$M61 -> 0 | AT61: =X61*$N61 -> 0 | AU61: =Y61*$M61 -> 0 | AV61: =Y61*$N61 -> 0 | AW61: =Z61*$M61 -> 0 | AX61: =Z61*$N61 -> 0
A62: IF-10 | B62: Grevillea planting | C62: ግራቪሊያ ተከላ | D62: Shade | E62: seedling | F62: Industry average | G62: =IFERROR(INDEX('Benchmark Data'!$AC$7:$AC$130,MATCH($A62,'Benchmark Data'!$A$7:$A$130,0)),0) -> 0.02 | H62: =IFERROR(INDEX('Benchmark Data'!$AD$7:$AD$130,MATCH($A62,'Benchmark Data'!$A$7:$A$130,0)),0) -> 150 | I62: =G62*H62 -> 3 | K62: =IFERROR(INDEX('Benchmark Data'!$AE$7:$AE$130,MATCH($A62,'Benchmark Data'!$A$7:$A$130,0)),0) -> 1 | L62: =J62*K62 -> 0 | M62: =L62*G62 -> 0 | N62: =L62*I62 -> 0
A63: IF-10 | B63: Grevillea planting | C63: ግራቪሊያ ተከላ | D63: Shade | E63: seedling | F63: +25% | G63: =G62 -> 0.02 | H63: =H62*(1+Settings!$C$8) -> 187.5 | I63: =G63*H63 -> 3.75 | J63: =J62 -> 0 | K63: =K62 -> 1 | L63: =J63*K63 -> 0 | M63: =L63*G63 -> 0 | N63: =L63*I63 -> 0
A64: IF-10 | B64: Grevillea planting | C64: ግራቪሊያ ተከላ | D64: Shade | E64: seedling | F64: +50% | G64: =G62 -> 0.02 | H64: =H62*(1+Settings!$C$9) -> 225 | I64: =G64*H64 -> 4.5 | J64: =J62 -> 0 | K64: =K62 -> 1 | L64: =J64*K64 -> 0 | M64: =L64*G64 -> 0 | N64: =L64*I64 -> 0
A65: IF-10 | B65: Grevillea planting | C65: ግራቪሊያ ተከላ | D65: Shade | E65: seedling | F65: Expert input | G65: =G62 -> 0.02 | H65: =H62 -> 150 | I65: =G65*H65 -> 3 | J65: =J62 -> 0 | K65: =K62 -> 1 | L65: =J65*K65 -> 0 | M65: =L65*G65 -> 0 | N65: =L65*I65 -> 0
A66: IF-10 | B66: Grevillea planting | C66: ግራቪሊያ ተከላ | D66: Shade | E66: seedling | F66: Chaka Buna plan | G66: =CHOOSE(IF(OR($C$3="Expert input",$I$62=0),4,IF($C$3="+25%",2,IF($C$3="+50%",3,1))),G62,G63,G64,G65) -> 0.02 | H66: =CHOOSE(IF(OR($C$3="Expert input",$I$62=0),4,IF($C$3="+25%",2,IF($C$3="+50%",3,1))),H62,H63,H64,H65) -> 150 | I66: =G66*H66 -> 3 | J66: =J62 -> 0 | K66: =CHOOSE(IF(OR($C$3="Expert input",$I$62=0),4,IF($C$3="+25%",2,IF($C$3="+50%",3,1))),K62,K63,K64,K65) -> 1 | L66: =J66*K66 -> 0 | M66: =L66*G66 -> 0 | N66: =L66*I66 -> 0 | W66: 1 | AA66: =O66*$M66 -> 0 | AB66: =O66*$N66 -> 0 | AC66: =P66*$M66 -> 0 | AD66: =P66*$N66 -> 0 | AE66: =Q66*$M66 -> 0 | AF66: =Q66*$N66 -> 0 | AG66: =R66*$M66 -> 0 | AH66: =R66*$N66 -> 0 | AI66: =S66*$M66 -> 0 | AJ66: =S66*$N66 -> 0 | AK66: =T66*$M66 -> 0 | AL66: =T66*$N66 -> 0 | AM66: =U66*$M66 -> 0 | AN66: =U66*$N66 -> 0 | AO66: =V66*$M66 -> 0 | AP66: =V66*$N66 -> 0 | AQ66: =W66*$M66 -> 0 | AR66: =W66*$N66 -> 0 | AS66: =X66*$M66 -> 0 | AT66: =X66*$N66 -> 0 | AU66: =Y66*$M66 -> 0 | AV66: =Y66*$N66 -> 0 | AW66: =Z66*$M66 -> 0 | AX66: =Z66*$N66 -> 0
A67: IF-11 | B67: Watchman tower construction | C67: የጥበቃ ማማ ስራ | D67: Protection | E67: no. | F67: Industry average | G67: =IFERROR(INDEX('Benchmark Data'!$AC$7:$AC$130,MATCH($A67,'Benchmark Data'!$A$7:$A$130,0)),0) -> 0 | H67: =IFERROR(INDEX('Benchmark Data'!$AD$7:$AD$130,MATCH($A67,'Benchmark Data'!$A$7:$A$130,0)),0) -> 0 | I67: =G67*H67 -> 0 | K67: =IFERROR(INDEX('Benchmark Data'!$AE$7:$AE$130,MATCH($A67,'Benchmark Data'!$A$7:$A$130,0)),0) -> 1 | L67: =J67*K67 -> 0 | M67: =L67*G67 -> 0 | N67: =L67*I67 -> 0
A68: IF-11 | B68: Watchman tower construction | C68: የጥበቃ ማማ ስራ | D68: Protection | E68: no. | F68: +25% | G68: =G67 -> 0 | H68: =H67*(1+Settings!$C$8) -> 0 | I68: =G68*H68 -> 0 | J68: =J67 -> 0 | K68: =K67 -> 1 | L68: =J68*K68 -> 0 | M68: =L68*G68 -> 0 | N68: =L68*I68 -> 0
A69: IF-11 | B69: Watchman tower construction | C69: የጥበቃ ማማ ስራ | D69: Protection | E69: no. | F69: +50% | G69: =G67 -> 0 | H69: =H67*(1+Settings!$C$9) -> 0 | I69: =G69*H69 -> 0 | J69: =J67 -> 0 | K69: =K67 -> 1 | L69: =J69*K69 -> 0 | M69: =L69*G69 -> 0 | N69: =L69*I69 -> 0
A70: IF-11 | B70: Watchman tower construction | C70: የጥበቃ ማማ ስራ | D70: Protection | E70: no. | F70: Expert input | G70: =IFERROR(INDEX('Benchmark Data'!$AH$7:$AH$130,MATCH($A70,'Benchmark Data'!$A$7:$A$130,0)),0) -> 1 | H70: =IFERROR(INDEX('Benchmark Data'!$AI$7:$AI$130,MATCH($A70,'Benchmark Data'!$A$7:$A$130,0)),0) -> 2500 | I70: =G70*H70 -> 2500 | J70: =J67 -> 0 | K70: =IFERROR(INDEX('Benchmark Data'!$AJ$7:$AJ$130,MATCH($A70,'Benchmark Data'!$A$7:$A$130,0)),0) -> 1 | L70: =J70*K70 -> 0 | M70: =L70*G70 -> 0 | N70: =L70*I70 -> 0
A71: IF-11 | B71: Watchman tower construction | C71: የጥበቃ ማማ ስራ | D71: Protection | E71: no. | F71: Chaka Buna plan | G71: =CHOOSE(IF(OR($C$3="Expert input",$I$67=0),4,IF($C$3="+25%",2,IF($C$3="+50%",3,1))),G67,G68,G69,G70) -> 1 | H71: =CHOOSE(IF(OR($C$3="Expert input",$I$67=0),4,IF($C$3="+25%",2,IF($C$3="+50%",3,1))),H67,H68,H69,H70) -> 2500 | I71: =G71*H71 -> 2500 | J71: =J67 -> 0 | K71: =CHOOSE(IF(OR($C$3="Expert input",$I$67=0),4,IF($C$3="+25%",2,IF($C$3="+50%",3,1))),K67,K68,K69,K70) -> 1 | L71: =J71*K71 -> 0 | M71: =L71*G71 -> 0 | N71: =L71*I71 -> 0 | T71: 1 | AA71: =O71*$M71 -> 0 | AB71: =O71*$N71 -> 0 | AC71: =P71*$M71 -> 0 | AD71: =P71*$N71 -> 0 | AE71: =Q71*$M71 -> 0 | AF71: =Q71*$N71 -> 0 | AG71: =R71*$M71 -> 0 | AH71: =R71*$N71 -> 0 | AI71: =S71*$M71 -> 0 | AJ71: =S71*$N71 -> 0 | AK71: =T71*$M71 -> 0 | AL71: =T71*$N71 -> 0 | AM71: =U71*$M71 -> 0 | AN71: =U71*$N71 -> 0 | AO71: =V71*$M71 -> 0 | AP71: =V71*$N71 -> 0 | AQ71: =W71*$M71 -> 0 | AR71: =W71*$N71 -> 0 | AS71: =X71*$M71 -> 0 | AT71: =X71*$N71 -> 0 | AU71: =Y71*$M71 -> 0 | AV71: =Y71*$N71 -> 0 | AW71: =Z71*$M71 -> 0 | AX71: =Z71*$N71 -> 0
A72: IF-12 | B72: Temporary guard | C72: ጊዚያዊ ጥበቃ | D72: Protection | E72: man-day | F72: Industry average | G72: =IFERROR(INDEX('Benchmark Data'!$AC$7:$AC$130,MATCH($A72,'Benchmark Data'!$A$7:$A$130,0)),0) -> 0 | H72: =IFERROR(INDEX('Benchmark Data'!$AD$7:$AD$130,MATCH($A72,'Benchmark Data'!$A$7:$A$130,0)),0) -> 0 | I72: =G72*H72 -> 0 | K72: =IFERROR(INDEX('Benchmark Data'!$AE$7:$AE$130,MATCH($A72,'Benchmark Data'!$A$7:$A$130,0)),0) -> 1 | L72: =J72*K72 -> 0 | M72: =L72*G72 -> 0 | N72: =L72*I72 -> 0
A73: IF-12 | B73: Temporary guard | C73: ጊዚያዊ ጥበቃ | D73: Protection | E73: man-day | F73: +25% | G73: =G72 -> 0 | H73: =H72*(1+Settings!$C$8) -> 0 | I73: =G73*H73 -> 0 | J73: =J72 -> 0 | K73: =K72 -> 1 | L73: =J73*K73 -> 0 | M73: =L73*G73 -> 0 | N73: =L73*I73 -> 0
A74: IF-12 | B74: Temporary guard | C74: ጊዚያዊ ጥበቃ | D74: Protection | E74: man-day | F74: +50% | G74: =G72 -> 0 | H74: =H72*(1+Settings!$C$9) -> 0 | I74: =G74*H74 -> 0 | J74: =J72 -> 0 | K74: =K72 -> 1 | L74: =J74*K74 -> 0 | M74: =L74*G74 -> 0 | N74: =L74*I74 -> 0
A75: IF-12 | B75: Temporary guard | C75: ጊዚያዊ ጥበቃ | D75: Protection | E75: man-day | F75: Expert input | G75: =IFERROR(INDEX('Benchmark Data'!$AH$7:$AH$130,MATCH($A75,'Benchmark Data'!$A$7:$A$130,0)),0) -> 1 | H75: =IFERROR(INDEX('Benchmark Data'!$AI$7:$AI$130,MATCH($A75,'Benchmark Data'!$A$7:$A$130,0)),0) -> 500 | I75: =G75*H75 -> 500 | J75: =J72 -> 0 | K75: =IFERROR(INDEX('Benchmark Data'!$AJ$7:$AJ$130,MATCH($A75,'Benchmark Data'!$A$7:$A$130,0)),0) -> 20 | L75: =J75*K75 -> 0 | M75: =L75*G75 -> 0 | N75: =L75*I75 -> 0
A76: IF-12 | B76: Temporary guard | C76: ጊዚያዊ ጥበቃ | D76: Protection | E76: man-day | F76: Chaka Buna plan | G76: =CHOOSE(IF(OR($C$3="Expert input",$I$72=0),4,IF($C$3="+25%",2,IF($C$3="+50%",3,1))),G72,G73,G74,G75) -> 1 | H76: =CHOOSE(IF(OR($C$3="Expert input",$I$72=0),4,IF($C$3="+25%",2,IF($C$3="+50%",3,1))),H72,H73,H74,H75) -> 500 | I76: =G76*H76 -> 500 | J76: =J72 -> 0 | K76: =CHOOSE(IF(OR($C$3="Expert input",$I$72=0),4,IF($C$3="+25%",2,IF($C$3="+50%",3,1))),K72,K73,K74,K75) -> 20 | L76: =J76*K76 -> 0 | M76: =L76*G76 -> 0 | N76: =L76*I76 -> 0 | T76: 0.25 | U76: 0.25 | V76: 0.25 | W76: 0.25 | AA76: =O76*$M76 -> 0 | AB76: =O76*$N76 -> 0 | AC76: =P76*$M76 -> 0 | AD76: =P76*$N76 -> 0 | AE76: =Q76*$M76 -> 0 | AF76: =Q76*$N76 -> 0 | AG76: =R76*$M76 -> 0 | AH76: =R76*$N76 -> 0 | AI76: =S76*$M76 -> 0 | AJ76: =S76*$N76 -> 0 | AK76: =T76*$M76 -> 0 | AL76: =T76*$N76 -> 0 | AM76: =U76*$M76 -> 0 | AN76: =U76*$N76 -> 0 | AO76: =V76*$M76 -> 0 | AP76: =V76*$N76 -> 0 | AQ76: =W76*$M76 -> 0 | AR76: =W76*$N76 -> 0 | AS76: =X76*$M76 -> 0 | AT76: =X76*$N76 -> 0 | AU76: =Y76*$M76 -> 0 | AV76: =Y76*$N76 -> 0 | AW76: =Z76*$M76 -> 0 | AX76: =Z76*$N76 -> 0
A77: IF-13 | B77: Establishment survival count (3 months after planting) | D77: SPX addition – no B-Agro benchmark | E77: seedling | F77: Industry average | G77: =IFERROR(INDEX('Benchmark Data'!$AC$7:$AC$130,MATCH($A77,'Benchmark Data'!$A$7:$A$130,0)),0) -> 0 | H77: =IFERROR(INDEX('Benchmark Data'!$AD$7:$AD$130,MATCH($A77,'Benchmark Data'!$A$7:$A$130,0)),0) -> 0 | I77: =G77*H77 -> 0 | J77: =$E$8 -> 0 | K77: =IFERROR(INDEX('Benchmark Data'!$AE$7:$AE$130,MATCH($A77,'Benchmark Data'!$A$7:$A$130,0)),0) -> 1 | L77: =J77*K77 -> 0 | M77: =L77*G77 -> 0 | N77: =L77*I77 -> 0
A78: IF-13 | B78: Establishment survival count (3 months after planting) | D78: SPX addition – no B-Agro benchmark | E78: seedling | F78: +25% | G78: =G77 -> 0 | H78: =H77*(1+Settings!$C$8) -> 0 | I78: =G78*H78 -> 0 | J78: =J77 -> 0 | K78: =K77 -> 1 | L78: =J78*K78 -> 0 | M78: =L78*G78 -> 0 | N78: =L78*I78 -> 0
A79: IF-13 | B79: Establishment survival count (3 months after planting) | D79: SPX addition – no B-Agro benchmark | E79: seedling | F79: +50% | G79: =G77 -> 0 | H79: =H77*(1+Settings!$C$9) -> 0 | I79: =G79*H79 -> 0 | J79: =J77 -> 0 | K79: =K77 -> 1 | L79: =J79*K79 -> 0 | M79: =L79*G79 -> 0 | N79: =L79*I79 -> 0
A80: IF-13 | B80: Establishment survival count (3 months after planting) | D80: SPX addition – no B-Agro benchmark | E80: seedling | F80: Expert input | I80: =G80*H80 -> 0 | J80: =J77 -> 0 | K80: 1 | L80: =J80*K80 -> 0 | M80: =L80*G80 -> 0 | N80: =L80*I80 -> 0
A81: IF-13 | B81: Establishment survival count (3 months after planting) | D81: SPX addition – no B-Agro benchmark | E81: seedling | F81: Chaka Buna plan | G81: =CHOOSE(IF(OR($C$3="Expert input",$I$77=0),4,IF($C$3="+25%",2,IF($C$3="+50%",3,1))),G77,G78,G79,G80) -> 0 | H81: =CHOOSE(IF(OR($C$3="Expert input",$I$77=0),4,IF($C$3="+25%",2,IF($C$3="+50%",3,1))),H77,H78,H79,H80) -> 0 | I81: =G81*H81 -> 0 | J81: =J77 -> 0 | K81: =CHOOSE(IF(OR($C$3="Expert input",$I$77=0),4,IF($C$3="+25%",2,IF($C$3="+50%",3,1))),K77,K78,K79,K80) -> 1 | L81: =J81*K81 -> 0 | M81: =L81*G81 -> 0 | N81: =L81*I81 -> 0 | AA81: =O81*$M81 -> 0 | AB81: =O81*$N81 -> 0 | AC81: =P81*$M81 -> 0 | AD81: =P81*$N81 -> 0 | AE81: =Q81*$M81 -> 0 | AF81: =Q81*$N81 -> 0 | AG81: =R81*$M81 -> 0 | AH81: =R81*$N81 -> 0 | AI81: =S81*$M81 -> 0 | AJ81: =S81*$N81 -> 0 | AK81: =T81*$M81 -> 0 | AL81: =T81*$N81 -> 0 | AM81: =U81*$M81 -> 0 | AN81: =U81*$N81 -> 0 | AO81: =V81*$M81 -> 0 | AP81: =V81*$N81 -> 0 | AQ81: =W81*$M81 -> 0 | AR81: =W81*$N81 -> 0 | AS81: =X81*$M81 -> 0 | AT81: =X81*$N81 -> 0 | AU81: =Y81*$M81 -> 0 | AV81: =Y81*$N81 -> 0 | AW81: =Z81*$M81 -> 0 | AX81: =Z81*$N81 -> 0

Sheet Harvesting
A1: Harvesting & Related – activity plan and budget
A2: ="Farm: "&Settings!$C$6&" | Plan year: "&Settings!$C$7 -> Farm: Chaka Buna Estate (Silva Forest Coffee) | Plan year: 2019 EFY (2026/27) – confirm
B3: Plan basis (drop-down) ► | C3: Industry average | D3: Sets the Chaka Buna plan row of every activity on this tab. Activities with no industry-average rate always use the Expert input row.
B5: GENERAL INFORMATION | F5: CATEGORY TOTALS
B6: Metric (English) | C6: Metric (Amharic) | D6: Unit | E6: Quantity | F6: Rate scenario | M6: Total man-days | N6: Total cost (birr) | O6: Plan phasing (% of cost) | AA6: Plan monthly totals
B7: Productive trees | C7: ምርታማ የቡና እግር ቁጥር | D7: no. | F7: Industry average | M7: =SUMIF($F$17:$F$156,"Industry average",M$17:M$156) -> 0 | N7: =SUMIF($F$17:$F$156,"Industry average",N$17:N$156) -> 0
B8: Gross plantation area | C8: ጠቅላላ የቦታ ስፋት (ሄ/ር) | D8: ha | F8: +25% | M8: =SUMIF($F$17:$F$156,"+25%",M$17:M$156) -> 0 | N8: =SUMIF($F$17:$F$156,"+25%",N$17:N$156) -> 0
B9: Average productivity | C9: ምርታማነት አማካይ (ኩ/ል/ሄ/ር) | D9: qt clean coffee/ha | F9: +50% | M9: =SUMIF($F$17:$F$156,"+50%",M$17:M$156) -> 0 | N9: =SUMIF($F$17:$F$156,"+50%",N$17:N$156) -> 0
B10: Total clean coffee production | C10: አጠቃላይ የሚመረት ንፁህ ቡና (ኩ/ል) | D10: qt | E10: =IFERROR($E$9*$E$8,0) -> 0 | F10: Expert input | M10: =SUMIF($F$17:$F$156,"Expert input",M$17:M$156) -> 0 | N10: =SUMIF($F$17:$F$156,"Expert input",N$17:N$156) -> 0
B11: Red cherry to pick | C11: ቀይ ቡና | D11: kg | F11: Chaka Buna plan – counts in Summary | M11: =SUMIF($F$17:$F$156,"Chaka Buna plan",M$17:M$156) -> 0 | N11: =SUMIF($F$17:$F$156,"Chaka Buna plan",N$17:N$156) -> 0 | O11: =IFERROR(AB11/$N$11,0) -> 0 | P11: =IFERROR(AD11/$N$11,0) -> 0 | Q11: =IFERROR(AF11/$N$11,0) -> 0 | R11: =IFERROR(AH11/$N$11,0) -> 0 | S11: =IFERROR(AJ11/$N$11,0) -> 0 | T11: =IFERROR(AL11/$N$11,0) -> 0 | U11: =IFERROR(AN11/$N$11,0) -> 0 | V11: =IFERROR(AP11/$N$11,0) -> 0 | W11: =IFERROR(AR11/$N$11,0) -> 0 | X11: =IFERROR(AT11/$N$11,0) -> 0 | Y11: =IFERROR(AV11/$N$11,0) -> 0 | Z11: =IFERROR(AX11/$N$11,0) -> 0 | AA11: =SUM(AA17:AA156) -> 0 | AB11: =SUM(AB17:AB156) -> 0 | AC11: =SUM(AC17:AC156) -> 0 | AD11: =SUM(AD17:AD156) -> 0 | AE11: =SUM(AE17:AE156) -> 0 | AF11: =SUM(AF17:AF156) -> 0 | AG11: =SUM(AG17:AG156) -> 0 | AH11: =SUM(AH17:AH156) -> 0 | ... AX11: =SUM(AX17:AX156) -> 0
B12: Drying beds | C12: የቡና ማስጫ አልጋ | D12: bed
B13: Dry cherry bags | C13: ደረቅ ቡና ኬሻ | D13: bag
A15: ACTIVITY | F15: RATE (cost per unit = man-days × wage) | J15: QUANTITY | L15: TOTALS (calculated) | O15: PHASING – % of annual (input on the Chaka Buna plan row) | AA15: MONTHLY MAN-DAYS AND COST (Chaka Buna plan row)
A16: Code | B16: Activity | C16: Activity (Amharic) | D16: Sub-group | E16: Unit | F16: Rate scenario | G16: Man-days per unit | H16: Wage per man-day (birr) | I16: Cost per unit (birr) | J16: Activity quantity per round | K16: Frequency (times / year) | L16: Total activity quantity | M16: Total man-days per activity | N16: Total cost per activity (birr) | O16: Tikimt (Oct) | P16: Hidar (Nov) | Q16: Tahsas (Dec) | R16: Tir (Jan) | S16: Yekatit (Feb) | T16: Megabit (Mar) | U16: Miyazya (Apr) | V16: Ginbot (May) | W16: Sene (Jun) | X16: Hamle (Jul) | Y16: Nehase (Aug) | Z16: Meskerem (Sep) | AA16: Tikimt (Oct) – man-days | AB16: Tikimt (Oct) – cost | AC16: Hidar (Nov) – man-days | AD16: Hidar (Nov) – cost | AE16: Tahsas (Dec) – man-days | AF16: Tahsas (Dec) – cost | AG16: Tir (Jan) – man-days | AH16: Tir (Jan) – cost | AI16: Yekatit (Feb) – man-days | AJ16: Yekatit (Feb) – cost | AK16: Megabit (Mar) – man-days | AL16: Megabit (Mar) – cost | AM16: Miyazya (Apr) – man-days | AN16: Miyazya (Apr) – cost | AO16: Ginbot (May) – man-days | AP16: Ginbot (May) – cost | AQ16: Sene (Jun) – man-days | AR16: Sene (Jun) – cost | AS16: Hamle (Jul) – man-days | AT16: Hamle (Jul) – cost | AU16: Nehase (Aug) – man-days | AV16: Nehase (Aug) – cost | AW16: Meskerem (Sep) – man-days | AX16: Meskerem (Sep) – cost
A17: HR-01 | B17: Watchman tower construction / repair | C17: የጥበቃ ማማ ስራ/እድሳት | D17: Harvest preparation | E17: no. | F17: Industry average | G17: =IFERROR(INDEX('Benchmark Data'!$AC$7:$AC$130,MATCH($A17,'Benchmark Data'!$A$7:$A$130,0)),0) -> 1.3333333 | H17: =IFERROR(INDEX('Benchmark Data'!$AD$7:$AD$130,MATCH($A17,'Benchmark Data'!$A$7:$A$130,0)),0) -> 1500 | I17: =G17*H17 -> 2000 | K17: =IFERROR(INDEX('Benchmark Data'!$AE$7:$AE$130,MATCH($A17,'Benchmark Data'!$A$7:$A$130,0)),0) -> 1 | L17: =J17*K17 -> 0 | M17: =L17*G17 -> 0 | N17: =L17*I17 -> 0
A18: HR-01 | B18: Watchman tower construction / repair | C18: የጥበቃ ማማ ስራ/እድሳት | D18: Harvest preparation | E18: no. | F18: +25% | G18: =G17 -> 1.3333333 | H18: =H17*(1+Settings!$C$8) -> 1875 | I18: =G18*H18 -> 2500 | J18: =J17 -> 0 | K18: =K17 -> 1 | L18: =J18*K18 -> 0 | M18: =L18*G18 -> 0 | N18: =L18*I18 -> 0
A19: HR-01 | B19: Watchman tower construction / repair | C19: የጥበቃ ማማ ስራ/እድሳት | D19: Harvest preparation | E19: no. | F19: +50% | G19: =G17 -> 1.3333333 | H19: =H17*(1+Settings!$C$9) -> 2250 | I19: =G19*H19 -> 3000 | J19: =J17 -> 0 | K19: =K17 -> 1 | L19: =J19*K19 -> 0 | M19: =L19*G19 -> 0 | N19: =L19*I19 -> 0
A20: HR-01 | B20: Watchman tower construction / repair | C20: የጥበቃ ማማ ስራ/እድሳት | D20: Harvest preparation | E20: no. | F20: Expert input | G20: =G17 -> 1.3333333 | H20: =H17 -> 1500 | I20: =G20*H20 -> 2000 | J20: =J17 -> 0 | K20: =K17 -> 1 | L20: =J20*K20 -> 0 | M20: =L20*G20 -> 0 | N20: =L20*I20 -> 0
A21: HR-01 | B21: Watchman tower construction / repair | C21: የጥበቃ ማማ ስራ/እድሳት | D21: Harvest preparation | E21: no. | F21: Chaka Buna plan | G21: =CHOOSE(IF(OR($C$3="Expert input",$I$17=0),4,IF($C$3="+25%",2,IF($C$3="+50%",3,1))),G17,G18,G19,G20) -> 1.3333333 | H21: =CHOOSE(IF(OR($C$3="Expert input",$I$17=0),4,IF($C$3="+25%",2,IF($C$3="+50%",3,1))),H17,H18,H19,H20) -> 1500 | I21: =G21*H21 -> 2000 | J21: =J17 -> 0 | K21: =CHOOSE(IF(OR($C$3="Expert input",$I$17=0),4,IF($C$3="+25%",2,IF($C$3="+50%",3,1))),K17,K18,K19,K20) -> 1 | L21: =J21*K21 -> 0 | M21: =L21*G21 -> 0 | N21: =L21*I21 -> 0 | O21: 0.54 | Y21: 0.13 | Z21: 0.33 | AA21: =O21*$M21 -> 0 | AB21: =O21*$N21 -> 0 | AC21: =P21*$M21 -> 0 | AD21: =P21*$N21 -> 0 | AE21: =Q21*$M21 -> 0 | AF21: =Q21*$N21 -> 0 | AG21: =R21*$M21 -> 0 | AH21: =R21*$N21 -> 0 | AI21: =S21*$M21 -> 0 | AJ21: =S21*$N21 -> 0 | AK21: =T21*$M21 -> 0 | AL21: =T21*$N21 -> 0 | AM21: =U21*$M21 -> 0 | AN21: =U21*$N21 -> 0 | AO21: =V21*$M21 -> 0 | AP21: =V21*$N21 -> 0 | AQ21: =W21*$M21 -> 0 | AR21: =W21*$N21 -> 0 | AS21: =X21*$M21 -> 0 | AT21: =X21*$N21 -> 0 | AU21: =Y21*$M21 -> 0 | AV21: =Y21*$N21 -> 0 | AW21: =Z21*$M21 -> 0 | AX21: =Z21*$N21 -> 0
A22: HR-02 | B22: Fence material preparation & transport | C22: ለአጥር ቁሳቁስ ዝግጅት | D22: Harvest preparation | E22: load | F22: Industry average | G22: =IFERROR(INDEX('Benchmark Data'!$AC$7:$AC$130,MATCH($A22,'Benchmark Data'!$A$7:$A$130,0)),0) -> 0.33333333 | H22: =IFERROR(INDEX('Benchmark Data'!$AD$7:$AD$130,MATCH($A22,'Benchmark Data'!$A$7:$A$130,0)),0) -> 240 | I22: =G22*H22 -> 80 | K22: =IFERROR(INDEX('Benchmark Data'!$AE$7:$AE$130,MATCH($A22,'Benchmark Data'!$A$7:$A$130,0)),0) -> 1 | L22: =J22*K22 -> 0 | M22: =L22*G22 -> 0 | N22: =L22*I22 -> 0
A23: HR-02 | B23: Fence material preparation & transport | C23: ለአጥር ቁሳቁስ ዝግጅት | D23: Harvest preparation | E23: load | F23: +25% | G23: =G22 -> 0.33333333 | H23: =H22*(1+Settings!$C$8) -> 300 | I23: =G23*H23 -> 100 | J23: =J22 -> 0 | K23: =K22 -> 1 | L23: =J23*K23 -> 0 | M23: =L23*G23 -> 0 | N23: =L23*I23 -> 0
A24: HR-02 | B24: Fence material preparation & transport | C24: ለአጥር ቁሳቁስ ዝግጅት | D24: Harvest preparation | E24: load | F24: +50% | G24: =G22 -> 0.33333333 | H24: =H22*(1+Settings!$C$9) -> 360 | I24: =G24*H24 -> 120 | J24: =J22 -> 0 | K24: =K22 -> 1 | L24: =J24*K24 -> 0 | M24: =L24*G24 -> 0 | N24: =L24*I24 -> 0
A25: HR-02 | B25: Fence material preparation & transport | C25: ለአጥር ቁሳቁስ ዝግጅት | D25: Harvest preparation | E25: load | F25: Expert input | G25: =G22 -> 0.33333333 | H25: =H22 -> 240 | I25: =G25*H25 -> 80 | J25: =J22 -> 0 | K25: =K22 -> 1 | L25: =J25*K25 -> 0 | M25: =L25*G25 -> 0 | N25: =L25*I25 -> 0
A26: HR-02 | B26: Fence material preparation & transport | C26: ለአጥር ቁሳቁስ ዝግጅት | D26: Harvest preparation | E26: load | F26: Chaka Buna plan | G26: =CHOOSE(IF(OR($C$3="Expert input",$I$22=0),4,IF($C$3="+25%",2,IF($C$3="+50%",3,1))),G22,G23,G24,G25) -> 0.33333333 | H26: =CHOOSE(IF(OR($C$3="Expert input",$I$22=0),4,IF($C$3="+25%",2,IF($C$3="+50%",3,1))),H22,H23,H24,H25) -> 240 | I26: =G26*H26 -> 80 | J26: =J22 -> 0 | K26: =CHOOSE(IF(OR($C$3="Expert input",$I$22=0),4,IF($C$3="+25%",2,IF($C$3="+50%",3,1))),K22,K23,K24,K25) -> 1 | L26: =J26*K26 -> 0 | M26: =L26*G26 -> 0 | N26: =L26*I26 -> 0 | O26: 0.41 | W26: 0.17 | X26: 0.17 | Y26: 0.25 | AA26: =O26*$M26 -> 0 | AB26: =O26*$N26 -> 0 | AC26: =P26*$M26 -> 0 | AD26: =P26*$N26 -> 0 | AE26: =Q26*$M26 -> 0 | AF26: =Q26*$N26 -> 0 | AG26: =R26*$M26 -> 0 | AH26: =R26*$N26 -> 0 | AI26: =S26*$M26 -> 0 | AJ26: =S26*$N26 -> 0 | AK26: =T26*$M26 -> 0 | AL26: =T26*$N26 -> 0 | AM26: =U26*$M26 -> 0 | AN26: =U26*$N26 -> 0 | AO26: =V26*$M26 -> 0 | AP26: =V26*$N26 -> 0 | AQ26: =W26*$M26 -> 0 | AR26: =W26*$N26 -> 0 | AS26: =X26*$M26 -> 0 | AT26: =X26*$N26 -> 0 | AU26: =Y26*$M26 -> 0 | AV26: =Y26*$N26 -> 0 | AW26: =Z26*$M26 -> 0 | AX26: =Z26*$N26 -> 0
A27: HR-03 | B27: Drying area fencing | C27: አውድማ አጥር ማሳጠር | D27: Harvest preparation | E27: m | F27: Industry average | G27: =IFERROR(INDEX('Benchmark Data'!$AC$7:$AC$130,MATCH($A27,'Benchmark Data'!$A$7:$A$130,0)),0) -> 0.1 | H27: =IFERROR(INDEX('Benchmark Data'!$AD$7:$AD$130,MATCH($A27,'Benchmark Data'!$A$7:$A$130,0)),0) -> 100 | I27: =G27*H27 -> 10 | K27: =IFERROR(INDEX('Benchmark Data'!$AE$7:$AE$130,MATCH($A27,'Benchmark Data'!$A$7:$A$130,0)),0) -> 1 | L27: =J27*K27 -> 0 | M27: =L27*G27 -> 0 | N27: =L27*I27 -> 0
A28: HR-03 | B28: Drying area fencing | C28: አውድማ አጥር ማሳጠር | D28: Harvest preparation | E28: m | F28: +25% | G28: =G27 -> 0.1 | H28: =H27*(1+Settings!$C$8) -> 125 | I28: =G28*H28 -> 12.5 | J28: =J27 -> 0 | K28: =K27 -> 1 | L28: =J28*K28 -> 0 | M28: =L28*G28 -> 0 | N28: =L28*I28 -> 0
A29: HR-03 | B29: Drying area fencing | C29: አውድማ አጥር ማሳጠር | D29: Harvest preparation | E29: m | F29: +50% | G29: =G27 -> 0.1 | H29: =H27*(1+Settings!$C$9) -> 150 | I29: =G29*H29 -> 15 | J29: =J27 -> 0 | K29: =K27 -> 1 | L29: =J29*K29 -> 0 | M29: =L29*G29 -> 0 | N29: =L29*I29 -> 0
A30: HR-03 | B30: Drying area fencing | C30: አውድማ አጥር ማሳጠር | D30: Harvest preparation | E30: m | F30: Expert input | G30: =G27 -> 0.1 | H30: =H27 -> 100 | I30: =G30*H30 -> 10 | J30: =J27 -> 0 | K30: =K27 -> 1 | L30: =J30*K30 -> 0 | M30: =L30*G30 -> 0 | N30: =L30*I30 -> 0
A31: HR-03 | B31: Drying area fencing | C31: አውድማ አጥር ማሳጠር | D31: Harvest preparation | E31: m | F31: Chaka Buna plan | G31: =CHOOSE(IF(OR($C$3="Expert input",$I$27=0),4,IF($C$3="+25%",2,IF($C$3="+50%",3,1))),G27,G28,G29,G30) -> 0.1 | H31: =CHOOSE(IF(OR($C$3="Expert input",$I$27=0),4,IF($C$3="+25%",2,IF($C$3="+50%",3,1))),H27,H28,H29,H30) -> 100 | I31: =G31*H31 -> 10 | J31: =J27 -> 0 | K31: =CHOOSE(IF(OR($C$3="Expert input",$I$27=0),4,IF($C$3="+25%",2,IF($C$3="+50%",3,1))),K27,K28,K29,K30) -> 1 | L31: =J31*K31 -> 0 | M31: =L31*G31 -> 0 | N31: =L31*I31 -> 0 | X31: 0.5 | Y31: 0.5 | AA31: =O31*$M31 -> 0 | AB31: =O31*$N31 -> 0 | AC31: =P31*$M31 -> 0 | AD31: =P31*$N31 -> 0 | AE31: =Q31*$M31 -> 0 | AF31: =Q31*$N31 -> 0 | AG31: =R31*$M31 -> 0 | AH31: =R31*$N31 -> 0 | AI31: =S31*$M31 -> 0 | AJ31: =S31*$N31 -> 0 | AK31: =T31*$M31 -> 0 | AL31: =T31*$N31 -> 0 | AM31: =U31*$M31 -> 0 | AN31: =U31*$N31 -> 0 | AO31: =V31*$M31 -> 0 | AP31: =V31*$N31 -> 0 | AQ31: =W31*$M31 -> 0 | AR31: =W31*$N31 -> 0 | AS31: =X31*$M31 -> 0 | AT31: =X31*$N31 -> 0 | AU31: =Y31*$M31 -> 0 | AV31: =Y31*$N31 -> 0 | AW31: =Z31*$M31 -> 0 | AX31: =Z31*$N31 -> 0
A32: HR-04 | B32: Drying site clearing | C32: የቡና ማድረቂያ ቦታ ማፅዳት | D32: Harvest preparation | E32: ha | F32: Industry average | G32: =IFERROR(INDEX('Benchmark Data'!$AC$7:$AC$130,MATCH($A32,'Benchmark Data'!$A$7:$A$130,0)),0) -> 13.666667 | H32: =IFERROR(INDEX('Benchmark Data'!$AD$7:$AD$130,MATCH($A32,'Benchmark Data'!$A$7:$A$130,0)),0) -> 160.97561 | I32: =G32*H32 -> 2200 | K32: =IFERROR(INDEX('Benchmark Data'!$AE$7:$AE$130,MATCH($A32,'Benchmark Data'!$A$7:$A$130,0)),0) -> 1 | L32: =J32*K32 -> 0 | M32: =L32*G32 -> 0 | N32: =L32*I32 -> 0
A33: HR-04 | B33: Drying site clearing | C33: የቡና ማድረቂያ ቦታ ማፅዳት | D33: Harvest preparation | E33: ha | F33: +25% | G33: =G32 -> 13.666667 | H33: =H32*(1+Settings!$C$8) -> 201.21951 | I33: =G33*H33 -> 2750 | J33: =J32 -> 0 | K33: =K32 -> 1 | L33: =J33*K33 -> 0 | M33: =L33*G33 -> 0 | N33: =L33*I33 -> 0
A34: HR-04 | B34: Drying site clearing | C34: የቡና ማድረቂያ ቦታ ማፅዳት | D34: Harvest preparation | E34: ha | F34: +50% | G34: =G32 -> 13.666667 | H34: =H32*(1+Settings!$C$9) -> 241.46341 | I34: =G34*H34 -> 3300 | J34: =J32 -> 0 | K34: =K32 -> 1 | L34: =J34*K34 -> 0 | M34: =L34*G34 -> 0 | N34: =L34*I34 -> 0
A35: HR-04 | B35: Drying site clearing | C35: የቡና ማድረቂያ ቦታ ማፅዳት | D35: Harvest preparation | E35: ha | F35: Expert input | G35: =G32 -> 13.666667 | H35: =H32 -> 160.97561 | I35: =G35*H35 -> 2200 | J35: =J32 -> 0 | K35: =K32 -> 1 | L35: =J35*K35 -> 0 | M35: =L35*G35 -> 0 | N35: =L35*I35 -> 0
