Workbook

Sheet README
B2: Cropfort — Coffee Field OS Template (Plain, Farm-Agnostic)
B4: Purpose
B5: This is Cropfort's own standard operating template — blank, reusable for any farm on the platform. It is not specific to any owner, manager, or field operator; those identities are filled in when the template is instantiated for a real farm. The activity taxonomy (Tier 1 Core / Tier 2 Projects / Tier 3 Interventions) is Cropfort's own product standard and stays in the template as-is.
B7: Sheet Map, in the order they are used
B8: Activity List
B9: The full activity taxonomy, tier-tagged. Add, edit or re-tier activities here — every other sheet reads from this.
B10: Master
B11: Farm name, Term Start Date (drives every date on the workbook), and the block registry — hectares, variety, planting date, tree count. Fill this in first.
B12: Benchmark Rate Survey
B13: Two-adjacent-farm rate survey per activity. Lock the survey once entered; the average shows as a light-shade recommendation; override it and route for approval by the mandated person at the owning company. Approved rates feed the Labor Rate Card directly.
B14: Labor Rate Card
B15: Final piece rate per activity: Benchmark Approved Rate if one exists, otherwise mandays-norm x wage rate entered directly.
... B51: 4. The Monthly Client Report's narrative fields are placeholders for a person (or an AI drafting pass a person reviews) to fill in — the sheet does not write prose on its own.

Sheet Activity List
A1: Activity ID | B1: Tier | C1: Category | D1: Activity Name | E1: Unit of Measure | F1: Source / Notes | G1: Default Tick
A2: T1-001 | B2: Tier 1 — Core Services | C2: Nursery | D2: Land Clearing | E2: ha | F2: Cropfort Core Services standard | G2: Y
A3: T1-002 | B3: Tier 1 — Core Services | C3: Nursery | D3: Tree Felling | E3: ha | F3: Cropfort Core Services standard | G3: Y
A4: T1-003 | B4: Tier 1 — Core Services | C4: Nursery | D4: Soil Heaping | E4: m3 | F4: Cropfort Core Services standard | G4: Y
A5: T1-004 | B5: Tier 1 — Core Services | C5: Nursery | D5: Polytube Cutting | E5: kg | F5: Cropfort Core Services standard | G5: Y
A6: T1-005 | B6: Tier 1 — Core Services | C6: Nursery | D6: Polytube Filling | E6: seedling | F6: Cropfort Core Services standard | G6: Y
A7: T1-006 | B7: Tier 1 — Core Services | C7: Nursery | D7: Seedbed Preparation | E7: bed | F7: Cropfort Core Services standard | G7: Y
A8: T1-007 | B8: Tier 1 — Core Services | C8: Nursery | D8: Polytube Arranging | E8: bed | F8: Cropfort Core Services standard | G8: Y
A9: T1-008 | B9: Tier 1 — Core Services | C9: Nursery | D9: Seed Sowing | E9: bed | F9: Cropfort Core Services standard | G9: Y
A10: T1-009 | B10: Tier 1 — Core Services | C10: Nursery | D10: Mulch Material Preparation | E10: bed | F10: Cropfort Core Services standard | G10: Y
A11: T1-010 | B11: Tier 1 — Core Services | C11: Nursery | D11: Mulch Application | E11: bed | F11: Cropfort Core Services standard | G11: Y
A12: T1-011 | B12: Tier 1 — Core Services | C12: Nursery | D12: Shade Material Preparation | E12: bed | F12: Cropfort Core Services standard | G12: Y
... A135: T3-035 | B135: Tier 3 — Interventions | C135: B. Technical and Laboratory Services | D135: Buyer Hosting at SpiralLabs | E135: event | F135: Cropfort Interventions standard | G135: N

Sheet Master
A1: Master — Farm and Block Registry
A2: Farm Name:
A3: Term Start Date (Year 1, Month 1): | E3: All Annual Election windows and the per-block Calendar are calculated from this one date — set it once and everything downstream follows.
A5: Block ID | B5: Block Name | C5: Hectares | D5: Variety Planted | E5: Planting Date | F5: Tree Count | G5: Status | H5: Notes
H6: Add one row per block. Each block also needs its own Calendar tab, generated to match.
A13: This is the Cropfort platform template — blank on purpose. Every field here is filled in when the template is instantiated for a real farm. Adding a block row does not, on its own, create that block's Calendar tab or its Annual Election rows; those are generated to match whenever a block is added.

Sheet Benchmark Rate Survey
A1: Benchmark Rate Survey — Annual
A2: Survey the piece rate paid for each activity at two adjacent farms, lock it in once entered, and let that guide — but not dictate — this farm's own rate. The recommended rate is the plain average, shown in light shade; override it in the Proposed Rate column. Nothing is binding until the mandated approver for this farm's owning company signs off, after which the rate is locked for the year.
A4: Activity ID | B4: Activity Name | C4: Unit | D4: Neighbor Farm 1 (Name) | E4: Neighbor Farm 1 Rate (ETB/unit) | F4: Neighbor Farm 2 (Name) | G4: Neighbor Farm 2 Rate (ETB/unit) | H4: Survey Locked (Y/N) | I4: Recommended Rate (avg, light shade) | J4: Proposed Rate (override) | K4: Status | L4: Approver Name | M4: Approval Date | N4: Valid Until | O4: Approved Rate
A5: ='Activity List'!A2 -> T1-001 | B5: ='Activity List'!D2 -> Land Clearing | C5: ='Activity List'!E2 -> ha | H5: N | I5: =IFERROR(AVERAGE(E5,G5),"") | J5: =I5 | K5: Draft | N5: =IF(M5="","",EDATE(M5,12)) | O5: =IF(K5="Approved",J5,"")
A6: ='Activity List'!A3 -> T1-002 | B6: ='Activity List'!D3 -> Tree Felling | C6: ='Activity List'!E3 -> ha | H6: N | I6: =IFERROR(AVERAGE(E6,G6),"") | J6: =I6 | K6: Draft | N6: =IF(M6="","",EDATE(M6,12)) | O6: =IF(K6="Approved",J6,"")
A7: ='Activity List'!A4 -> T1-003 | B7: ='Activity List'!D4 -> Soil Heaping | C7: ='Activity List'!E4 -> m3 | H7: N | I7: =IFERROR(AVERAGE(E7,G7),"") | J7: =I7 | K7: Draft | N7: =IF(M7="","",EDATE(M7,12)) | O7: =IF(K7="Approved",J7,"")
A8: ='Activity List'!A5 -> T1-004 | B8: ='Activity List'!D5 -> Polytube Cutting | C8: ='Activity List'!E5 -> kg | H8: N | I8: =IFERROR(AVERAGE(E8,G8),"") | J8: =I8 | K8: Draft | N8: =IF(M8="","",EDATE(M8,12)) | O8: =IF(K8="Approved",J8,"")
A9: ='Activity List'!A6 -> T1-005 | B9: ='Activity List'!D6 -> Polytube Filling | C9: ='Activity List'!E6 -> seedling | H9: N | I9: =IFERROR(AVERAGE(E9,G9),"") | J9: =I9 | K9: Draft | N9: =IF(M9="","",EDATE(M9,12)) | O9: =IF(K9="Approved",J9,"")
A10: ='Activity List'!A7 -> T1-006 | B10: ='Activity List'!D7 -> Seedbed Preparation | C10: ='Activity List'!E7 -> bed | H10: N | I10: =IFERROR(AVERAGE(E10,G10),"") | J10: =I10 | K10: Draft | N10: =IF(M10="","",EDATE(M10,12)) | O10: =IF(K10="Approved",J10,"")
A11: ='Activity List'!A8 -> T1-007 | B11: ='Activity List'!D8 -> Polytube Arranging | C11: ='Activity List'!E8 -> bed | H11: N | I11: =IFERROR(AVERAGE(E11,G11),"") | J11: =I11 | K11: Draft | N11: =IF(M11="","",EDATE(M11,12)) | O11: =IF(K11="Approved",J11,"")
A12: ='Activity List'!A9 -> T1-008 | B12: ='Activity List'!D9 -> Seed Sowing | C12: ='Activity List'!E9 -> bed | H12: N | I12: =IFERROR(AVERAGE(E12,G12),"") | J12: =I12 | K12: Draft | N12: =IF(M12="","",EDATE(M12,12)) | O12: =IF(K12="Approved",J12,"")
A13: ='Activity List'!A10 -> T1-009 | B13: ='Activity List'!D10 -> Mulch Material Preparation | C13: ='Activity List'!E10 -> bed | H13: N | I13: =IFERROR(AVERAGE(E13,G13),"") | J13: =I13 | K13: Draft | N13: =IF(M13="","",EDATE(M13,12)) | O13: =IF(K13="Approved",J13,"")
A14: ='Activity List'!A11 -> T1-010 | B14: ='Activity List'!D11 -> Mulch Application | C14: ='Activity List'!E11 -> bed | H14: N | I14: =IFERROR(AVERAGE(E14,G14),"") | J14: =I14 | K14: Draft | N14: =IF(M14="","",EDATE(M14,12)) | O14: =IF(K14="Approved",J14,"")
A15: ='Activity List'!A12 -> T1-011 | B15: ='Activity List'!D12 -> Shade Material Preparation | C15: ='Activity List'!E12 -> bed | H15: N | I15: =IFERROR(AVERAGE(E15,G15),"") | J15: =I15 | K15: Draft | N15: =IF(M15="","",EDATE(M15,12)) | O15: =IF(K15="Approved",J15,"")
A16: ='Activity List'!A13 -> T1-012 | B16: ='Activity List'!D13 -> Shade Construction | C16: ='Activity List'!E13 -> bed | H16: N | I16: =IFERROR(AVERAGE(E16,G16),"") | J16: =I16 | K16: Draft | N16: =IF(M16="","",EDATE(M16,12)) | O16: =IF(K16="Approved",J16,"")
... A138: ='Activity List'!A135 -> T3-035 | B138: ='Activity List'!D135 -> Buyer Hosting at SpiralLabs | C138: ='Activity List'!E135 -> event | H138: N | I138: =IFERROR(AVERAGE(E138,G138),"") | J138: =I138 | K138: Draft | N138: =IF(M138="","",EDATE(M138,12)) | O138: =IF(K138="Approved",J138,"")
A140: Workflow: (1) enter both neighbor rates, set Survey Locked to Y once confirmed — treat that row's neighbor rate cells as historical from that point and do not edit them again this cycle; a fresh survey next year gets new rows, not overwritten ones. (2) Proposed Rate defaults to the Recommended average; overwrite it directly to set this farm's own figure — that replaces the link with a plain value, same convention used on the Annual Election bundle tick. (3) Set Status to 'Approved' only once the mandated approver for this farm's owning company has actually signed off — Approver Name and Approval Date are that record. (4) Approved Rate is blank until Status = Approved; the Labor Rate Card reads only this column, never Proposed Rate directly, so nothing reaches the live rate card without approval. Valid Until is one year from Approval Date; a rate can still be revised for an individual activity mid-year if a real change is decided — that revision gets its own new row, not an edit to this one, so the history stays intact.

Sheet Labor Rate Card
A1: Activity ID | B1: Activity Name | C1: Unit | D1: Labor Norm (manday / unit) | E1: Wage Rate (ETB / manday) | F1: Computed Cost / Unit (norm x wage) | G1: Final Labor Cost / Unit (ETB) | H1: Status / Source
A2: ='Activity List'!A2 -> T1-001 | B2: ='Activity List'!D2 -> Land Clearing | C2: ='Activity List'!E2 -> ha | F2: =IF(OR(D2="",E2=""),0,D2*E2) -> 0 | G2: =IF('Benchmark Rate Survey'!O5<>"",'Benchmark Rate Survey'!O5,F2) -> 0 | H2: TBD — norm/wage not yet entered; or awaiting Benchmark Rate Survey approval
A3: ='Activity List'!A3 -> T1-002 | B3: ='Activity List'!D3 -> Tree Felling | C3: ='Activity List'!E3 -> ha | F3: =IF(OR(D3="",E3=""),0,D3*E3) -> 0 | G3: =IF('Benchmark Rate Survey'!O6<>"",'Benchmark Rate Survey'!O6,F3) -> 0 | H3: TBD — norm/wage not yet entered; or awaiting Benchmark Rate Survey approval
A4: ='Activity List'!A4 -> T1-003 | B4: ='Activity List'!D4 -> Soil Heaping | C4: ='Activity List'!E4 -> m3 | F4: =IF(OR(D4="",E4=""),0,D4*E4) -> 0 | G4: =IF('Benchmark Rate Survey'!O7<>"",'Benchmark Rate Survey'!O7,F4) -> 0 | H4: TBD — norm/wage not yet entered; or awaiting Benchmark Rate Survey approval
A5: ='Activity List'!A5 -> T1-004 | B5: ='Activity List'!D5 -> Polytube Cutting | C5: ='Activity List'!E5 -> kg | F5: =IF(OR(D5="",E5=""),0,D5*E5) -> 0 | G5: =IF('Benchmark Rate Survey'!O8<>"",'Benchmark Rate Survey'!O8,F5) -> 0 | H5: TBD — norm/wage not yet entered; or awaiting Benchmark Rate Survey approval
A6: ='Activity List'!A6 -> T1-005 | B6: ='Activity List'!D6 -> Polytube Filling | C6: ='Activity List'!E6 -> seedling | F6: =IF(OR(D6="",E6=""),0,D6*E6) -> 0 | G6: =IF('Benchmark Rate Survey'!O9<>"",'Benchmark Rate Survey'!O9,F6) -> 0 | H6: TBD — norm/wage not yet entered; or awaiting Benchmark Rate Survey approval
A7: ='Activity List'!A7 -> T1-006 | B7: ='Activity List'!D7 -> Seedbed Preparation | C7: ='Activity List'!E7 -> bed | F7: =IF(OR(D7="",E7=""),0,D7*E7) -> 0 | G7: =IF('Benchmark Rate Survey'!O10<>"",'Benchmark Rate Survey'!O10,F7) -> 0 | H7: TBD — norm/wage not yet entered; or awaiting Benchmark Rate Survey approval
A8: ='Activity List'!A8 -> T1-007 | B8: ='Activity List'!D8 -> Polytube Arranging | C8: ='Activity List'!E8 -> bed | F8: =IF(OR(D8="",E8=""),0,D8*E8) -> 0 | G8: =IF('Benchmark Rate Survey'!O11<>"",'Benchmark Rate Survey'!O11,F8) -> 0 | H8: TBD — norm/wage not yet entered; or awaiting Benchmark Rate Survey approval
A9: ='Activity List'!A9 -> T1-008 | B9: ='Activity List'!D9 -> Seed Sowing | C9: ='Activity List'!E9 -> bed | F9: =IF(OR(D9="",E9=""),0,D9*E9) -> 0 | G9: =IF('Benchmark Rate Survey'!O12<>"",'Benchmark Rate Survey'!O12,F9) -> 0 | H9: TBD — norm/wage not yet entered; or awaiting Benchmark Rate Survey approval
A10: ='Activity List'!A10 -> T1-009 | B10: ='Activity List'!D10 -> Mulch Material Preparation | C10: ='Activity List'!E10 -> bed | F10: =IF(OR(D10="",E10=""),0,D10*E10) -> 0 | G10: =IF('Benchmark Rate Survey'!O13<>"",'Benchmark Rate Survey'!O13,F10) -> 0 | H10: TBD — norm/wage not yet entered; or awaiting Benchmark Rate Survey approval
A11: ='Activity List'!A11 -> T1-010 | B11: ='Activity List'!D11 -> Mulch Application | C11: ='Activity List'!E11 -> bed | F11: =IF(OR(D11="",E11=""),0,D11*E11) -> 0 | G11: =IF('Benchmark Rate Survey'!O14<>"",'Benchmark Rate Survey'!O14,F11) -> 0 | H11: TBD — norm/wage not yet entered; or awaiting Benchmark Rate Survey approval
A12: ='Activity List'!A12 -> T1-011 | B12: ='Activity List'!D12 -> Shade Material Preparation | C12: ='Activity List'!E12 -> bed | F12: =IF(OR(D12="",E12=""),0,D12*E12) -> 0 | G12: =IF('Benchmark Rate Survey'!O15<>"",'Benchmark Rate Survey'!O15,F12) -> 0 | H12: TBD — norm/wage not yet entered; or awaiting Benchmark Rate Survey approval
A13: ='Activity List'!A13 -> T1-012 | B13: ='Activity List'!D13 -> Shade Construction | C13: ='Activity List'!E13 -> bed | F13: =IF(OR(D13="",E13=""),0,D13*E13) -> 0 | G13: =IF('Benchmark Rate Survey'!O16<>"",'Benchmark Rate Survey'!O16,F13) -> 0 | H13: TBD — norm/wage not yet entered; or awaiting Benchmark Rate Survey approval
... A135: ='Activity List'!A135 -> T3-035 | B135: ='Activity List'!D135 -> Buyer Hosting at SpiralLabs | C135: ='Activity List'!E135 -> event | F135: =IF(OR(D135="",E135=""),0,D135*E135) -> 0 | G135: =IF('Benchmark Rate Survey'!O138<>"",'Benchmark Rate Survey'!O138,F135) -> 0 | H135: TBD — norm/wage not yet entered; or awaiting Benchmark Rate Survey approval
A137: Final Labor Cost/Unit is what every downstream sheet reads. It takes the Benchmark Rate Survey's Approved Rate when one exists for that activity; otherwise it falls back to the norm x wage figure entered directly here. Columns D and E are for activities costed the traditional way (mandays x wage), independent of benchmarking — use whichever route applies to a given activity.

Sheet Material Rate Card
A1: Material ID | B1: Material Name | C1: Unit | D1: Rate (ETB / unit) | E1: Status / Source
E2: Add one row per material input
E3: Add one row per material input
E4: Add one row per material input
E5: Add one row per material input
E6: Add one row per material input
E7: Add one row per material input
E8: Add one row per material input
E9: Add one row per material input
E10: Add one row per material input
E11: Add one row per material input

Sheet Outsourced Services Rate Card
A1: Service ID | B1: Service Name | C1: Unit | D1: Indicative Rate (ETB / unit) | E1: Status / Source
E2: Add one row per outsourced service
E3: Add one row per outsourced service
E4: Add one row per outsourced service
E5: Add one row per outsourced service
E6: Add one row per outsourced service
E7: Add one row per outsourced service
E8: Add one row per outsourced service
E9: Add one row per outsourced service
E10: Add one row per outsourced service
E11: Add one row per outsourced service

Sheet Fee Schedule
B1: Fee Schedule — 3-Year Vision (36 Months)
B2: What the farm owner pays for management, separate from the farm's own operating costs (labor, materials, services) tracked elsewhere in this workbook. Confirmed lines are guaranteed annual fees; Elective lines activate only from the month entered, per the standing election for that tier.
B4: CONFIRMED FEE LINES (annual, guaranteed)
B5: Core Services (Tier 1), Annual Fee
B7: ELECTIVE FEE LINES (annual if fully elected; activates from month entered)
B8: Elective Line | C8: Annual Fee | D8: Activation Month (1-36)
B9: Tier 2 — A. Annual Harvest Management
B10: Tier 2 — B. Coffee Operations
B11: Tier 2 — C. Export and Commercial Operations
B12: Tier 2 — D. Asset Development
B13: Tier 3 — A. Institutional and Strategic Interventions
B14: Tier 3 — B. Technical and Laboratory Services
B16: MONTHLY SCHEDULE
B17: Month # | C17: Month | D17: A. Annual Harvest Mana | E17: B. Coffee Operations | F17: C. Export and Commerci | G17: D. Asset Development | H17: A. Institutional and S | I17: B. Technical and Labor | J17: Confirmed | K17: Elective Subtotal | L17: Total Monthly Fee | M17: Cumulative Total
B18: 1 | C18: =EDATE(Master!$B$3,0) -> 0 | D18: =IF(OR($D$9="",B18<$D$9),0,$C$9/12) -> 0 | E18: =IF(OR($D$10="",B18<$D$10),0,$C$10/12) -> 0 | F18: =IF(OR($D$11="",B18<$D$11),0,$C$11/12) -> 0 | G18: =IF(OR($D$12="",B18<$D$12),0,$C$12/12) -> 0 | H18: =IF(OR($D$13="",B18<$D$13),0,$C$13/12) -> 0 | I18: =IF(OR($D$14="",B18<$D$14),0,$C$14/12) -> 0 | J18: =IF($C$5="",0,$C$5/12) -> 0 | K18: =SUM(D18:I18) -> 0 | L18: =J18+K18 -> 0 | M18: =L18 -> 0
B19: 2 | C19: =EDATE(Master!$B$3,1) -> 31 | D19: =IF(OR($D$9="",B19<$D$9),0,$C$9/12) -> 0 | E19: =IF(OR($D$10="",B19<$D$10),0,$C$10/12) -> 0 | F19: =IF(OR($D$11="",B19<$D$11),0,$C$11/12) -> 0 | G19: =IF(OR($D$12="",B19<$D$12),0,$C$12/12) -> 0 | H19: =IF(OR($D$13="",B19<$D$13),0,$C$13/12) -> 0 | I19: =IF(OR($D$14="",B19<$D$14),0,$C$14/12) -> 0 | J19: =IF($C$5="",0,$C$5/12) -> 0 | K19: =SUM(D19:I19) -> 0 | L19: =J19+K19 -> 0 | M19: =M18+L19 -> 0
B20: 3 | C20: =EDATE(Master!$B$3,2) -> 60 | D20: =IF(OR($D$9="",B20<$D$9),0,$C$9/12) -> 0 | E20: =IF(OR($D$10="",B20<$D$10),0,$C$10/12) -> 0 | F20: =IF(OR($D$11="",B20<$D$11),0,$C$11/12) -> 0 | G20: =IF(OR($D$12="",B20<$D$12),0,$C$12/12) -> 0 | H20: =IF(OR($D$13="",B20<$D$13),0,$C$13/12) -> 0 | I20: =IF(OR($D$14="",B20<$D$14),0,$C$14/12) -> 0 | J20: =IF($C$5="",0,$C$5/12) -> 0 | K20: =SUM(D20:I20) -> 0 | L20: =J20+K20 -> 0 | M20: =M19+L20 -> 0
B21: 4 | C21: =EDATE(Master!$B$3,3) -> 91 | D21: =IF(OR($D$9="",B21<$D$9),0,$C$9/12) -> 0 | E21: =IF(OR($D$10="",B21<$D$10),0,$C$10/12) -> 0 | F21: =IF(OR($D$11="",B21<$D$11),0,$C$11/12) -> 0 | G21: =IF(OR($D$12="",B21<$D$12),0,$C$12/12) -> 0 | H21: =IF(OR($D$13="",B21<$D$13),0,$C$13/12) -> 0 | I21: =IF(OR($D$14="",B21<$D$14),0,$C$14/12) -> 0 | J21: =IF($C$5="",0,$C$5/12) -> 0 | K21: =SUM(D21:I21) -> 0 | L21: =J21+K21 -> 0 | M21: =M20+L21 -> 0
B22: 5 | C22: =EDATE(Master!$B$3,4) -> 121 | D22: =IF(OR($D$9="",B22<$D$9),0,$C$9/12) -> 0 | E22: =IF(OR($D$10="",B22<$D$10),0,$C$10/12) -> 0 | F22: =IF(OR($D$11="",B22<$D$11),0,$C$11/12) -> 0 | G22: =IF(OR($D$12="",B22<$D$12),0,$C$12/12) -> 0 | H22: =IF(OR($D$13="",B22<$D$13),0,$C$13/12) -> 0 | I22: =IF(OR($D$14="",B22<$D$14),0,$C$14/12) -> 0 | J22: =IF($C$5="",0,$C$5/12) -> 0 | K22: =SUM(D22:I22) -> 0 | L22: =J22+K22 -> 0 | M22: =M21+L22 -> 0
B23: 6 | C23: =EDATE(Master!$B$3,5) -> 152 | D23: =IF(OR($D$9="",B23<$D$9),0,$C$9/12) -> 0 | E23: =IF(OR($D$10="",B23<$D$10),0,$C$10/12) -> 0 | F23: =IF(OR($D$11="",B23<$D$11),0,$C$11/12) -> 0 | G23: =IF(OR($D$12="",B23<$D$12),0,$C$12/12) -> 0 | H23: =IF(OR($D$13="",B23<$D$13),0,$C$13/12) -> 0 | I23: =IF(OR($D$14="",B23<$D$14),0,$C$14/12) -> 0 | J23: =IF($C$5="",0,$C$5/12) -> 0 | K23: =SUM(D23:I23) -> 0 | L23: =J23+K23 -> 0 | M23: =M22+L23 -> 0
B24: 7 | C24: =EDATE(Master!$B$3,6) -> 182 | D24: =IF(OR($D$9="",B24<$D$9),0,$C$9/12) -> 0 | E24: =IF(OR($D$10="",B24<$D$10),0,$C$10/12) -> 0 | F24: =IF(OR($D$11="",B24<$D$11),0,$C$11/12) -> 0 | G24: =IF(OR($D$12="",B24<$D$12),0,$C$12/12) -> 0 | H24: =IF(OR($D$13="",B24<$D$13),0,$C$13/12) -> 0 | I24: =IF(OR($D$14="",B24<$D$14),0,$C$14/12) -> 0 | J24: =IF($C$5="",0,$C$5/12) -> 0 | K24: =SUM(D24:I24) -> 0 | L24: =J24+K24 -> 0 | M24: =M23+L24 -> 0
B25: 8 | C25: =EDATE(Master!$B$3,7) -> 213 | D25: =IF(OR($D$9="",B25<$D$9),0,$C$9/12) -> 0 | E25: =IF(OR($D$10="",B25<$D$10),0,$C$10/12) -> 0 | F25: =IF(OR($D$11="",B25<$D$11),0,$C$11/12) -> 0 | G25: =IF(OR($D$12="",B25<$D$12),0,$C$12/12) -> 0 | H25: =IF(OR($D$13="",B25<$D$13),0,$C$13/12) -> 0 | I25: =IF(OR($D$14="",B25<$D$14),0,$C$14/12) -> 0 | J25: =IF($C$5="",0,$C$5/12) -> 0 | K25: =SUM(D25:I25) -> 0 | L25: =J25+K25 -> 0 | M25: =M24+L25 -> 0
B26: 9 | C26: =EDATE(Master!$B$3,8) -> 244 | D26: =IF(OR($D$9="",B26<$D$9),0,$C$9/12) -> 0 | E26: =IF(OR($D$10="",B26<$D$10),0,$C$10/12) -> 0 | F26: =IF(OR($D$11="",B26<$D$11),0,$C$11/12) -> 0 | G26: =IF(OR($D$12="",B26<$D$12),0,$C$12/12) -> 0 | H26: =IF(OR($D$13="",B26<$D$13),0,$C$13/12) -> 0 | I26: =IF(OR($D$14="",B26<$D$14),0,$C$14/12) -> 0 | J26: =IF($C$5="",0,$C$5/12) -> 0 | K26: =SUM(D26:I26) -> 0 | L26: =J26+K26 -> 0 | M26: =M25+L26 -> 0
B27: 10 | C27: =EDATE(Master!$B$3,9) -> 274 | D27: =IF(OR($D$9="",B27<$D$9),0,$C$9/12) -> 0 | E27: =IF(OR($D$10="",B27<$D$10),0,$C$10/12) -> 0 | F27: =IF(OR($D$11="",B27<$D$11),0,$C$11/12) -> 0 | G27: =IF(OR($D$12="",B27<$D$12),0,$C$12/12) -> 0 | H27: =IF(OR($D$13="",B27<$D$13),0,$C$13/12) -> 0 | I27: =IF(OR($D$14="",B27<$D$14),0,$C$14/12) -> 0 | J27: =IF($C$5="",0,$C$5/12) -> 0 | K27: =SUM(D27:I27) -> 0 | L27: =J27+K27 -> 0 | M27: =M26+L27 -> 0
B28: 11 | C28: =EDATE(Master!$B$3,10) -> 305 | D28: =IF(OR($D$9="",B28<$D$9),0,$C$9/12) -> 0 | E28: =IF(OR($D$10="",B28<$D$10),0,$C$10/12) -> 0 | F28: =IF(OR($D$11="",B28<$D$11),0,$C$11/12) -> 0 | G28: =IF(OR($D$12="",B28<$D$12),0,$C$12/12) -> 0 | H28: =IF(OR($D$13="",B28<$D$13),0,$C$13/12) -> 0 | I28: =IF(OR($D$14="",B28<$D$14),0,$C$14/12) -> 0 | J28: =IF($C$5="",0,$C$5/12) -> 0 | K28: =SUM(D28:I28) -> 0 | L28: =J28+K28 -> 0 | M28: =M27+L28 -> 0
B29: 12 | C29: =EDATE(Master!$B$3,11) -> 335 | D29: =IF(OR($D$9="",B29<$D$9),0,$C$9/12) -> 0 | E29: =IF(OR($D$10="",B29<$D$10),0,$C$10/12) -> 0 | F29: =IF(OR($D$11="",B29<$D$11),0,$C$11/12) -> 0 | G29: =IF(OR($D$12="",B29<$D$12),0,$C$12/12) -> 0 | H29: =IF(OR($D$13="",B29<$D$13),0,$C$13/12) -> 0 | I29: =IF(OR($D$14="",B29<$D$14),0,$C$14/12) -> 0 | J29: =IF($C$5="",0,$C$5/12) -> 0 | K29: =SUM(D29:I29) -> 0 | L29: =J29+K29 -> 0 | M29: =M28+L29 -> 0
B30: 13 | C30: =EDATE(Master!$B$3,12) -> 366 | D30: =IF(OR($D$9="",B30<$D$9),0,$C$9/12) -> 0 | E30: =IF(OR($D$10="",B30<$D$10),0,$C$10/12) -> 0 | F30: =IF(OR($D$11="",B30<$D$11),0,$C$11/12) -> 0 | G30: =IF(OR($D$12="",B30<$D$12),0,$C$12/12) -> 0 | H30: =IF(OR($D$13="",B30<$D$13),0,$C$13/12) -> 0 | I30: =IF(OR($D$14="",B30<$D$14),0,$C$14/12) -> 0 | J30: =IF($C$5="",0,$C$5/12) -> 0 | K30: =SUM(D30:I30) -> 0 | L30: =J30+K30 -> 0 | M30: =M29+L30 -> 0
B31: 14 | C31: =EDATE(Master!$B$3,13) -> 397 | D31: =IF(OR($D$9="",B31<$D$9),0,$C$9/12) -> 0 | E31: =IF(OR($D$10="",B31<$D$10),0,$C$10/12) -> 0 | F31: =IF(OR($D$11="",B31<$D$11),0,$C$11/12) -> 0 | G31: =IF(OR($D$12="",B31<$D$12),0,$C$12/12) -> 0 | H31: =IF(OR($D$13="",B31<$D$13),0,$C$13/12) -> 0 | I31: =IF(OR($D$14="",B31<$D$14),0,$C$14/12) -> 0 | J31: =IF($C$5="",0,$C$5/12) -> 0 | K31: =SUM(D31:I31) -> 0 | L31: =J31+K31 -> 0 | M31: =M30+L31 -> 0
B32: 15 | C32: =EDATE(Master!$B$3,14) -> 425 | D32: =IF(OR($D$9="",B32<$D$9),0,$C$9/12) -> 0 | E32: =IF(OR($D$10="",B32<$D$10),0,$C$10/12) -> 0 | F32: =IF(OR($D$11="",B32<$D$11),0,$C$11/12) -> 0 | G32: =IF(OR($D$12="",B32<$D$12),0,$C$12/12) -> 0 | H32: =IF(OR($D$13="",B32<$D$13),0,$C$13/12) -> 0 | I32: =IF(OR($D$14="",B32<$D$14),0,$C$14/12) -> 0 | J32: =IF($C$5="",0,$C$5/12) -> 0 | K32: =SUM(D32:I32) -> 0 | L32: =J32+K32 -> 0 | M32: =M31+L32 -> 0
B33: 16 | C33: =EDATE(Master!$B$3,15) -> 456 | D33: =IF(OR($D$9="",B33<$D$9),0,$C$9/12) -> 0 | E33: =IF(OR($D$10="",B33<$D$10),0,$C$10/12) -> 0 | F33: =IF(OR($D$11="",B33<$D$11),0,$C$11/12) -> 0 | G33: =IF(OR($D$12="",B33<$D$12),0,$C$12/12) -> 0 | H33: =IF(OR($D$13="",B33<$D$13),0,$C$13/12) -> 0 | I33: =IF(OR($D$14="",B33<$D$14),0,$C$14/12) -> 0 | J33: =IF($C$5="",0,$C$5/12) -> 0 | K33: =SUM(D33:I33) -> 0 | L33: =J33+K33 -> 0 | M33: =M32+L33 -> 0
B34: 17 | C34: =EDATE(Master!$B$3,16) -> 486 | D34: =IF(OR($D$9="",B34<$D$9),0,$C$9/12) -> 0 | E34: =IF(OR($D$10="",B34<$D$10),0,$C$10/12) -> 0 | F34: =IF(OR($D$11="",B34<$D$11),0,$C$11/12) -> 0 | G34: =IF(OR($D$12="",B34<$D$12),0,$C$12/12) -> 0 | H34: =IF(OR($D$13="",B34<$D$13),0,$C$13/12) -> 0 | I34: =IF(OR($D$14="",B34<$D$14),0,$C$14/12) -> 0 | J34: =IF($C$5="",0,$C$5/12) -> 0 | K34: =SUM(D34:I34) -> 0 | L34: =J34+K34 -> 0 | M34: =M33+L34 -> 0
B35: 18 | C35: =EDATE(Master!$B$3,17) -> 517 | D35: =IF(OR($D$9="",B35<$D$9),0,$C$9/12) -> 0 | E35: =IF(OR($D$10="",B35<$D$10),0,$C$10/12) -> 0 | F35: =IF(OR($D$11="",B35<$D$11),0,$C$11/12) -> 0 | G35: =IF(OR($D$12="",B35<$D$12),0,$C$12/12) -> 0 | H35: =IF(OR($D$13="",B35<$D$13),0,$C$13/12) -> 0 | I35: =IF(OR($D$14="",B35<$D$14),0,$C$14/12) -> 0 | J35: =IF($C$5="",0,$C$5/12) -> 0 | K35: =SUM(D35:I35) -> 0 | L35: =J35+K35 -> 0 | M35: =M34+L35 -> 0
B36: 19 | C36: =EDATE(Master!$B$3,18) -> 547 | D36: =IF(OR($D$9="",B36<$D$9),0,$C$9/12) -> 0 | E36: =IF(OR($D$10="",B36<$D$10),0,$C$10/12) -> 0 | F36: =IF(OR($D$11="",B36<$D$11),0,$C$11/12) -> 0 | G36: =IF(OR($D$12="",B36<$D$12),0,$C$12/12) -> 0 | H36: =IF(OR($D$13="",B36<$D$13),0,$C$13/12) -> 0 | I36: =IF(OR($D$14="",B36<$D$14),0,$C$14/12) -> 0 | J36: =IF($C$5="",0,$C$5/12) -> 0 | K36: =SUM(D36:I36) -> 0 | L36: =J36+K36 -> 0 | M36: =M35+L36 -> 0
B37: 20 | C37: =EDATE(Master!$B$3,19) -> 578 | D37: =IF(OR($D$9="",B37<$D$9),0,$C$9/12) -> 0 | E37: =IF(OR($D$10="",B37<$D$10),0,$C$10/12) -> 0 | F37: =IF(OR($D$11="",B37<$D$11),0,$C$11/12) -> 0 | G37: =IF(OR($D$12="",B37<$D$12),0,$C$12/12) -> 0 | H37: =IF(OR($D$13="",B37<$D$13),0,$C$13/12) -> 0 | I37: =IF(OR($D$14="",B37<$D$14),0,$C$14/12) -> 0 | J37: =IF($C$5="",0,$C$5/12) -> 0 | K37: =SUM(D37:I37) -> 0 | L37: =J37+K37 -> 0 | M37: =M36+L37 -> 0
B38: 21 | C38: =EDATE(Master!$B$3,20) -> 609 | D38: =IF(OR($D$9="",B38<$D$9),0,$C$9/12) -> 0 | E38: =IF(OR($D$10="",B38<$D$10),0,$C$10/12) -> 0 | F38: =IF(OR($D$11="",B38<$D$11),0,$C$11/12) -> 0 | G38: =IF(OR($D$12="",B38<$D$12),0,$C$12/12) -> 0 | H38: =IF(OR($D$13="",B38<$D$13),0,$C$13/12) -> 0 | I38: =IF(OR($D$14="",B38<$D$14),0,$C$14/12) -> 0 | J38: =IF($C$5="",0,$C$5/12) -> 0 | K38: =SUM(D38:I38) -> 0 | L38: =J38+K38 -> 0 | M38: =M37+L38 -> 0
B39: 22 | C39: =EDATE(Master!$B$3,21) -> 639 | D39: =IF(OR($D$9="",B39<$D$9),0,$C$9/12) -> 0 | E39: =IF(OR($D$10="",B39<$D$10),0,$C$10/12) -> 0 | F39: =IF(OR($D$11="",B39<$D$11),0,$C$11/12) -> 0 | G39: =IF(OR($D$12="",B39<$D$12),0,$C$12/12) -> 0 | H39: =IF(OR($D$13="",B39<$D$13),0,$C$13/12) -> 0 | I39: =IF(OR($D$14="",B39<$D$14),0,$C$14/12) -> 0 | J39: =IF($C$5="",0,$C$5/12) -> 0 | K39: =SUM(D39:I39) -> 0 | L39: =J39+K39 -> 0 | M39: =M38+L39 -> 0
B40: 23 | C40: =EDATE(Master!$B$3,22) -> 670 | D40: =IF(OR($D$9="",B40<$D$9),0,$C$9/12) -> 0 | E40: =IF(OR($D$10="",B40<$D$10),0,$C$10/12) -> 0 | F40: =IF(OR($D$11="",B40<$D$11),0,$C$11/12) -> 0 | G40: =IF(OR($D$12="",B40<$D$12),0,$C$12/12) -> 0 | H40: =IF(OR($D$13="",B40<$D$13),0,$C$13/12) -> 0 | I40: =IF(OR($D$14="",B40<$D$14),0,$C$14/12) -> 0 | J40: =IF($C$5="",0,$C$5/12) -> 0 | K40: =SUM(D40:I40) -> 0 | L40: =J40+K40 -> 0 | M40: =M39+L40 -> 0
B41: 24 | C41: =EDATE(Master!$B$3,23) -> 700 | D41: =IF(OR($D$9="",B41<$D$9),0,$C$9/12) -> 0 | E41: =IF(OR($D$10="",B41<$D$10),0,$C$10/12) -> 0 | F41: =IF(OR($D$11="",B41<$D$11),0,$C$11/12) -> 0 | G41: =IF(OR($D$12="",B41<$D$12),0,$C$12/12) -> 0 | H41: =IF(OR($D$13="",B41<$D$13),0,$C$13/12) -> 0 | I41: =IF(OR($D$14="",B41<$D$14),0,$C$14/12) -> 0 | J41: =IF($C$5="",0,$C$5/12) -> 0 | K41: =SUM(D41:I41) -> 0 | L41: =J41+K41 -> 0 | M41: =M40+L41 -> 0
B42: 25 | C42: =EDATE(Master!$B$3,24) -> 731 | D42: =IF(OR($D$9="",B42<$D$9),0,$C$9/12) -> 0 | E42: =IF(OR($D$10="",B42<$D$10),0,$C$10/12) -> 0 | F42: =IF(OR($D$11="",B42<$D$11),0,$C$11/12) -> 0 | G42: =IF(OR($D$12="",B42<$D$12),0,$C$12/12) -> 0 | H42: =IF(OR($D$13="",B42<$D$13),0,$C$13/12) -> 0 | I42: =IF(OR($D$14="",B42<$D$14),0,$C$14/12) -> 0 | J42: =IF($C$5="",0,$C$5/12) -> 0 | K42: =SUM(D42:I42) -> 0 | L42: =J42+K42 -> 0 | M42: =M41+L42 -> 0
B43: 26 | C43: =EDATE(Master!$B$3,25) -> 762 | D43: =IF(OR($D$9="",B43<$D$9),0,$C$9/12) -> 0 | E43: =IF(OR($D$10="",B43<$D$10),0,$C$10/12) -> 0 | F43: =IF(OR($D$11="",B43<$D$11),0,$C$11/12) -> 0 | G43: =IF(OR($D$12="",B43<$D$12),0,$C$12/12) -> 0 | H43: =IF(OR($D$13="",B43<$D$13),0,$C$13/12) -> 0 | I43: =IF(OR($D$14="",B43<$D$14),0,$C$14/12) -> 0 | J43: =IF($C$5="",0,$C$5/12) -> 0 | K43: =SUM(D43:I43) -> 0 | L43: =J43+K43 -> 0 | M43: =M42+L43 -> 0
B44: 27 | C44: =EDATE(Master!$B$3,26) -> 790 | D44: =IF(OR($D$9="",B44<$D$9),0,$C$9/12) -> 0 | E44: =IF(OR($D$10="",B44<$D$10),0,$C$10/12) -> 0 | F44: =IF(OR($D$11="",B44<$D$11),0,$C$11/12) -> 0 | G44: =IF(OR($D$12="",B44<$D$12),0,$C$12/12) -> 0 | H44: =IF(OR($D$13="",B44<$D$13),0,$C$13/12) -> 0 | I44: =IF(OR($D$14="",B44<$D$14),0,$C$14/12) -> 0 | J44: =IF($C$5="",0,$C$5/12) -> 0 | K44: =SUM(D44:I44) -> 0 | L44: =J44+K44 -> 0 | M44: =M43+L44 -> 0
B45: 28 | C45: =EDATE(Master!$B$3,27) -> 821 | D45: =IF(OR($D$9="",B45<$D$9),0,$C$9/12) -> 0 | E45: =IF(OR($D$10="",B45<$D$10),0,$C$10/12) -> 0 | F45: =IF(OR($D$11="",B45<$D$11),0,$C$11/12) -> 0 | G45: =IF(OR($D$12="",B45<$D$12),0,$C$12/12) -> 0 | H45: =IF(OR($D$13="",B45<$D$13),0,$C$13/12) -> 0 | I45: =IF(OR($D$14="",B45<$D$14),0,$C$14/12) -> 0 | J45: =IF($C$5="",0,$C$5/12) -> 0 | K45: =SUM(D45:I45) -> 0 | L45: =J45+K45 -> 0 | M45: =M44+L45 -> 0
B46: 29 | C46: =EDATE(Master!$B$3,28) -> 851 | D46: =IF(OR($D$9="",B46<$D$9),0,$C$9/12) -> 0 | E46: =IF(OR($D$10="",B46<$D$10),0,$C$10/12) -> 0 | F46: =IF(OR($D$11="",B46<$D$11),0,$C$11/12) -> 0 | G46: =IF(OR($D$12="",B46<$D$12),0,$C$12/12) -> 0 | H46: =IF(OR($D$13="",B46<$D$13),0,$C$13/12) -> 0 | I46: =IF(OR($D$14="",B46<$D$14),0,$C$14/12) -> 0 | J46: =IF($C$5="",0,$C$5/12) -> 0 | K46: =SUM(D46:I46) -> 0 | L46: =J46+K46 -> 0 | M46: =M45+L46 -> 0
B47: 30 | C47: =EDATE(Master!$B$3,29) -> 882 | D47: =IF(OR($D$9="",B47<$D$9),0,$C$9/12) -> 0 | E47: =IF(OR($D$10="",B47<$D$10),0,$C$10/12) -> 0 | F47: =IF(OR($D$11="",B47<$D$11),0,$C$11/12) -> 0 | G47: =IF(OR($D$12="",B47<$D$12),0,$C$12/12) -> 0 | H47: =IF(OR($D$13="",B47<$D$13),0,$C$13/12) -> 0 | I47: =IF(OR($D$14="",B47<$D$14),0,$C$14/12) -> 0 | J47: =IF($C$5="",0,$C$5/12) -> 0 | K47: =SUM(D47:I47) -> 0 | L47: =J47+K47 -> 0 | M47: =M46+L47 -> 0
B48: 31 | C48: =EDATE(Master!$B$3,30) -> 912 | D48: =IF(OR($D$9="",B48<$D$9),0,$C$9/12) -> 0 | E48: =IF(OR($D$10="",B48<$D$10),0,$C$10/12) -> 0 | F48: =IF(OR($D$11="",B48<$D$11),0,$C$11/12) -> 0 | G48: =IF(OR($D$12="",B48<$D$12),0,$C$12/12) -> 0 | H48: =IF(OR($D$13="",B48<$D$13),0,$C$13/12) -> 0 | I48: =IF(OR($D$14="",B48<$D$14),0,$C$14/12) -> 0 | J48: =IF($C$5="",0,$C$5/12) -> 0 | K48: =SUM(D48:I48) -> 0 | L48: =J48+K48 -> 0 | M48: =M47+L48 -> 0
B49: 32 | C49: =EDATE(Master!$B$3,31) -> 943 | D49: =IF(OR($D$9="",B49<$D$9),0,$C$9/12) -> 0 | E49: =IF(OR($D$10="",B49<$D$10),0,$C$10/12) -> 0 | F49: =IF(OR($D$11="",B49<$D$11),0,$C$11/12) -> 0 | G49: =IF(OR($D$12="",B49<$D$12),0,$C$12/12) -> 0 | H49: =IF(OR($D$13="",B49<$D$13),0,$C$13/12) -> 0 | I49: =IF(OR($D$14="",B49<$D$14),0,$C$14/12) -> 0 | J49: =IF($C$5="",0,$C$5/12) -> 0 | K49: =SUM(D49:I49) -> 0 | L49: =J49+K49 -> 0 | M49: =M48+L49 -> 0
B50: 33 | C50: =EDATE(Master!$B$3,32) -> 974 | D50: =IF(OR($D$9="",B50<$D$9),0,$C$9/12) -> 0 | E50: =IF(OR($D$10="",B50<$D$10),0,$C$10/12) -> 0 | F50: =IF(OR($D$11="",B50<$D$11),0,$C$11/12) -> 0 | G50: =IF(OR($D$12="",B50<$D$12),0,$C$12/12) -> 0 | H50: =IF(OR($D$13="",B50<$D$13),0,$C$13/12) -> 0 | I50: =IF(OR($D$14="",B50<$D$14),0,$C$14/12) -> 0 | J50: =IF($C$5="",0,$C$5/12) -> 0 | K50: =SUM(D50:I50) -> 0 | L50: =J50+K50 -> 0 | M50: =M49+L50 -> 0
B51: 34 | C51: =EDATE(Master!$B$3,33) -> 1004 | D51: =IF(OR($D$9="",B51<$D$9),0,$C$9/12) -> 0 | E51: =IF(OR($D$10="",B51<$D$10),0,$C$10/12) -> 0 | F51: =IF(OR($D$11="",B51<$D$11),0,$C$11/12) -> 0 | G51: =IF(OR($D$12="",B51<$D$12),0,$C$12/12) -> 0 | H51: =IF(OR($D$13="",B51<$D$13),0,$C$13/12) -> 0 | I51: =IF(OR($D$14="",B51<$D$14),0,$C$14/12) -> 0 | J51: =IF($C$5="",0,$C$5/12) -> 0 | K51: =SUM(D51:I51) -> 0 | L51: =J51+K51 -> 0 | M51: =M50+L51 -> 0
B52: 35 | C52: =EDATE(Master!$B$3,34) -> 1035 | D52: =IF(OR($D$9="",B52<$D$9),0,$C$9/12) -> 0 | E52: =IF(OR($D$10="",B52<$D$10),0,$C$10/12) -> 0 | F52: =IF(OR($D$11="",B52<$D$11),0,$C$11/12) -> 0 | G52: =IF(OR($D$12="",B52<$D$12),0,$C$12/12) -> 0 | H52: =IF(OR($D$13="",B52<$D$13),0,$C$13/12) -> 0 | I52: =IF(OR($D$14="",B52<$D$14),0,$C$14/12) -> 0 | J52: =IF($C$5="",0,$C$5/12) -> 0 | K52: =SUM(D52:I52) -> 0 | L52: =J52+K52 -> 0 | M52: =M51+L52 -> 0
B53: 36 | C53: =EDATE(Master!$B$3,35) -> 1065 | D53: =IF(OR($D$9="",B53<$D$9),0,$C$9/12) -> 0 | E53: =IF(OR($D$10="",B53<$D$10),0,$C$10/12) -> 0 | F53: =IF(OR($D$11="",B53<$D$11),0,$C$11/12) -> 0 | G53: =IF(OR($D$12="",B53<$D$12),0,$C$12/12) -> 0 | H53: =IF(OR($D$13="",B53<$D$13),0,$C$13/12) -> 0 | I53: =IF(OR($D$14="",B53<$D$14),0,$C$14/12) -> 0 | J53: =IF($C$5="",0,$C$5/12) -> 0 | K53: =SUM(D53:I53) -> 0 | L53: =J53+K53 -> 0 | M53: =M52+L53 -> 0
B55: Column headings D onward, in order, match the six Elective Fee Lines above the table. Activation Month uses the same Month # numbering as this table (1 = the month of Master's Term Start Date); a blank Activation Month means that line is never billed. This sheet is the fee Cropfort's manager invoices the farm owner — it does not include the farm's own operating costs, which are the labor, material and service budgets tracked on their own sheets and paid directly from the farm owner's Project Account.

Sheet Annual Election
A1: Annual Election — Year 1
A2: Core Bundle Tick (Y elects every Tier 1 activity at once):
A3: Tier 1 (Core): tick the bundle above to elect all at once, or overwrite an individual row's Elected cell directly to remove or add it one by one. Tier 2 (Projects) and Tier 3 (Interventions) have no bundle and no default — every row is elected individually, only once the commercial agreement for that work has been settled outside the platform.
A4: Block ID | B4: Activity ID | C4: Category | D4: Activity Name | E4: Default Window Start | F4: Default Window End | G4: Planned Duration (days) | H4: Effective End Date (auto) | I4: Elected (Y/N)
A5: =Master!A$6 -> 0 | B5: ='Activity List'!A2 -> T1-001 | C5: ='Activity List'!C2 -> Nursery | D5: ='Activity List'!D2 -> Land Clearing | E5: =IF(Master!$B$3="","",EDATE(Master!$B$3,0)) | F5: =IF(Master!$B$3="","",EDATE(Master!$B$3,6)-1) | H5: =IF(E5="","",IF(G5="",F5,E5+G5-1)) | I5: ='Annual Election'!$D$2 -> 0
A6: =Master!A$6 -> 0 | B6: ='Activity List'!A3 -> T1-002 | C6: ='Activity List'!C3 -> Nursery | D6: ='Activity List'!D3 -> Tree Felling | E6: =IF(Master!$B$3="","",EDATE(Master!$B$3,0)) | F6: =IF(Master!$B$3="","",EDATE(Master!$B$3,6)-1) | H6: =IF(E6="","",IF(G6="",F6,E6+G6-1)) | I6: ='Annual Election'!$D$2 -> 0
A7: =Master!A$6 -> 0 | B7: ='Activity List'!A4 -> T1-003 | C7: ='Activity List'!C4 -> Nursery | D7: ='Activity List'!D4 -> Soil Heaping | E7: =IF(Master!$B$3="","",EDATE(Master!$B$3,0)) | F7: =IF(Master!$B$3="","",EDATE(Master!$B$3,6)-1) | H7: =IF(E7="","",IF(G7="",F7,E7+G7-1)) | I7: ='Annual Election'!$D$2 -> 0
A8: =Master!A$6 -> 0 | B8: ='Activity List'!A5 -> T1-004 | C8: ='Activity List'!C5 -> Nursery | D8: ='Activity List'!D5 -> Polytube Cutting | E8: =IF(Master!$B$3="","",EDATE(Master!$B$3,0)) | F8: =IF(Master!$B$3="","",EDATE(Master!$B$3,6)-1) | H8: =IF(E8="","",IF(G8="",F8,E8+G8-1)) | I8: ='Annual Election'!$D$2 -> 0
A9: =Master!A$6 -> 0 | B9: ='Activity List'!A6 -> T1-005 | C9: ='Activity List'!C6 -> Nursery | D9: ='Activity List'!D6 -> Polytube Filling | E9: =IF(Master!$B$3="","",EDATE(Master!$B$3,0)) | F9: =IF(Master!$B$3="","",EDATE(Master!$B$3,6)-1) | H9: =IF(E9="","",IF(G9="",F9,E9+G9-1)) | I9: ='Annual Election'!$D$2 -> 0
A10: =Master!A$6 -> 0 | B10: ='Activity List'!A7 -> T1-006 | C10: ='Activity List'!C7 -> Nursery | D10: ='Activity List'!D7 -> Seedbed Preparation | E10: =IF(Master!$B$3="","",EDATE(Master!$B$3,0)) | F10: =IF(Master!$B$3="","",EDATE(Master!$B$3,6)-1) | H10: =IF(E10="","",IF(G10="",F10,E10+G10-1)) | I10: ='Annual Election'!$D$2 -> 0
A11: =Master!A$6 -> 0 | B11: ='Activity List'!A8 -> T1-007 | C11: ='Activity List'!C8 -> Nursery | D11: ='Activity List'!D8 -> Polytube Arranging | E11: =IF(Master!$B$3="","",EDATE(Master!$B$3,0)) | F11: =IF(Master!$B$3="","",EDATE(Master!$B$3,6)-1) | H11: =IF(E11="","",IF(G11="",F11,E11+G11-1)) | I11: ='Annual Election'!$D$2 -> 0
A12: =Master!A$6 -> 0 | B12: ='Activity List'!A9 -> T1-008 | C12: ='Activity List'!C9 -> Nursery | D12: ='Activity List'!D9 -> Seed Sowing | E12: =IF(Master!$B$3="","",EDATE(Master!$B$3,0)) | F12: =IF(Master!$B$3="","",EDATE(Master!$B$3,6)-1) | H12: =IF(E12="","",IF(G12="",F12,E12+G12-1)) | I12: ='Annual Election'!$D$2 -> 0
A13: =Master!A$6 -> 0 | B13: ='Activity List'!A10 -> T1-009 | C13: ='Activity List'!C10 -> Nursery | D13: ='Activity List'!D10 -> Mulch Material Preparation | E13: =IF(Master!$B$3="","",EDATE(Master!$B$3,0)) | F13: =IF(Master!$B$3="","",EDATE(Master!$B$3,6)-1) | H13: =IF(E13="","",IF(G13="",F13,E13+G13-1)) | I13: ='Annual Election'!$D$2 -> 0
A14: =Master!A$6 -> 0 | B14: ='Activity List'!A11 -> T1-010 | C14: ='Activity List'!C11 -> Nursery | D14: ='Activity List'!D11 -> Mulch Application | E14: =IF(Master!$B$3="","",EDATE(Master!$B$3,0)) | F14: =IF(Master!$B$3="","",EDATE(Master!$B$3,6)-1) | H14: =IF(E14="","",IF(G14="",F14,E14+G14-1)) | I14: ='Annual Election'!$D$2 -> 0
A15: =Master!A$6 -> 0 | B15: ='Activity List'!A12 -> T1-011 | C15: ='Activity List'!C12 -> Nursery | D15: ='Activity List'!D12 -> Shade Material Preparation | E15: =IF(Master!$B$3="","",EDATE(Master!$B$3,0)) | F15: =IF(Master!$B$3="","",EDATE(Master!$B$3,6)-1) | H15: =IF(E15="","",IF(G15="",F15,E15+G15-1)) | I15: ='Annual Election'!$D$2 -> 0
A16: =Master!A$6 -> 0 | B16: ='Activity List'!A13 -> T1-012 | C16: ='Activity List'!C13 -> Nursery | D16: ='Activity List'!D13 -> Shade Construction | E16: =IF(Master!$B$3="","",EDATE(Master!$B$3,0)) | F16: =IF(Master!$B$3="","",EDATE(Master!$B$3,6)-1) | H16: =IF(E16="","",IF(G16="",F16,E16+G16-1)) | I16: ='Annual Election'!$D$2 -> 0
... A20: =Master!A$6 -> 0 | B20: ='Activity List'!A17 -> T1-016 | C20: ='Activity List'!C17 -> Nursery | D20: ='Activity List'!D17 -> Shade Removal | E20: =IF(Master!$B$3="","",EDATE(Master!$B$3,0)) | F20: =IF(Master!$B$3="","",EDATE(Master!$B$3,6)-1) | H20: =IF(E20="","",IF(G20="",F20,E20+G20-1)) | I20: ='Annual Election'!$D$2 -> 0
A21: =Master!A$6 -> 0 | B21: ='Activity List'!A18 -> T1-017 | C21: ='Activity List'!C18 -> Young Coffee | D21: ='Activity List'!D18 -> Hoeing (Young Coffee) | E21: =IF(Master!$B$3="","",EDATE(Master!$B$3,0)) | F21: =IF(Master!$B$3="","",EDATE(Master!$B$3,12)-1) | H21: =IF(E21="","",IF(G21="",F21,E21+G21-1)) | I21: ='Annual Election'!$D$2 -> 0
A22: =Master!A$6 -> 0 | B22: ='Activity List'!A19 -> T1-018 | C22: ='Activity List'!C19 -> Young Coffee | D22: ='Activity List'!D19 -> Fertilizing (Young Coffee) | E22: =IF(Master!$B$3="","",EDATE(Master!$B$3,0)) | F22: =IF(Master!$B$3="","",EDATE(Master!$B$3,12)-1) | H22: =IF(E22="","",IF(G22="",F22,E22+G22-1)) | I22: ='Annual Election'!$D$2 -> 0
A23: =Master!A$6 -> 0 | B23: ='Activity List'!A20 -> T1-019 | C23: ='Activity List'!C20 -> Young Coffee | D23: ='Activity List'!D20 -> Ring Weeding of Seedlings | E23: =IF(Master!$B$3="","",EDATE(Master!$B$3,0)) | F23: =IF(Master!$B$3="","",EDATE(Master!$B$3,12)-1) | H23: =IF(E23="","",IF(G23="",F23,E23+G23-1)) | I23: ='Annual Election'!$D$2 -> 0
A24: =Master!A$6 -> 0 | B24: ='Activity List'!A21 -> T1-020 | C24: ='Activity List'!C21 -> Young Coffee | D24: ='Activity List'!D21 -> Shade Tree Regulation | E24: =IF(Master!$B$3="","",EDATE(Master!$B$3,0)) | F24: =IF(Master!$B$3="","",EDATE(Master!$B$3,12)-1) | H24: =IF(E24="","",IF(G24="",F24,E24+G24-1)) | I24: ='Annual Election'!$D$2 -> 0
A25: =Master!A$6 -> 0 | B25: ='Activity List'!A22 -> T1-021 | C25: ='Activity List'!C22 -> Young Coffee | D25: ='Activity List'!D22 -> Compost Preparation | E25: =IF(Master!$B$3="","",EDATE(Master!$B$3,0)) | F25: =IF(Master!$B$3="","",EDATE(Master!$B$3,12)-1) | H25: =IF(E25="","",IF(G25="",F25,E25+G25-1)) | I25: ='Annual Election'!$D$2 -> 0
A26: =Master!A$6 -> 0 | B26: ='Activity List'!A23 -> T1-022 | C26: ='Activity List'!C23 -> Young Coffee | D26: ='Activity List'!D23 -> Ridge Construction | E26: =IF(Master!$B$3="","",EDATE(Master!$B$3,0)) | F26: =IF(Master!$B$3="","",EDATE(Master!$B$3,12)-1) | H26: =IF(E26="","",IF(G26="",F26,E26+G26-1)) | I26: ='Annual Election'!$D$2 -> 0
A27: =Master!A$6 -> 0 | B27: ='Activity List'!A24 -> T1-023 | C27: ='Activity List'!C24 -> Matured Coffee | D27: ='Activity List'!D24 -> Manual Weeding | E27: =IF(Master!$B$3="","",EDATE(Master!$B$3,0)) | F27: =IF(Master!$B$3="","",EDATE(Master!$B$3,12)-1) | H27: =IF(E27="","",IF(G27="",F27,E27+G27-1)) | I27: ='Annual Election'!$D$2 -> 0
A28: =Master!A$6 -> 0 | B28: ='Activity List'!A25 -> T1-024 | C28: ='Activity List'!C25 -> Matured Coffee | D28: ='Activity List'!D25 -> Chemical Weeding | E28: =IF(Master!$B$3="","",EDATE(Master!$B$3,0)) | F28: =IF(Master!$B$3="","",EDATE(Master!$B$3,12)-1) | H28: =IF(E28="","",IF(G28="",F28,E28+G28-1)) | I28: ='Annual Election'!$D$2 -> 0
A29: =Master!A$6 -> 0 | B29: ='Activity List'!A26 -> T1-025 | C29: ='Activity List'!C26 -> Matured Coffee | D29: ='Activity List'!D26 -> Pruning (Matured Coffee) | E29: =IF(Master!$B$3="","",EDATE(Master!$B$3,0)) | F29: =IF(Master!$B$3="","",EDATE(Master!$B$3,12)-1) | H29: =IF(E29="","",IF(G29="",F29,E29+G29-1)) | I29: ='Annual Election'!$D$2 -> 0
A30: =Master!A$6 -> 0 | B30: ='Activity List'!A27 -> T1-026 | C30: ='Activity List'!C27 -> Matured Coffee | D30: ='Activity List'!D27 -> Topping (Matured Coffee) | E30: =IF(Master!$B$3="","",EDATE(Master!$B$3,0)) | F30: =IF(Master!$B$3="","",EDATE(Master!$B$3,12)-1) | H30: =IF(E30="","",IF(G30="",F30,E30+G30-1)) | I30: ='Annual Election'!$D$2 -> 0
A31: =Master!A$6 -> 0 | B31: ='Activity List'!A28 -> T1-027 | C31: ='Activity List'!C28 -> Matured Coffee | D31: ='Activity List'!D28 -> Handling and Desuckering | E31: =IF(Master!$B$3="","",EDATE(Master!$B$3,0)) | F31: =IF(Master!$B$3="","",EDATE(Master!$B$3,12)-1) | H31: =IF(E31="","",IF(G31="",F31,E31+G31-1)) | I31: ='Annual Election'!$D$2 -> 0
A32: =Master!A$6 -> 0 | B32: ='Activity List'!A29 -> T1-028 | C32: ='Activity List'!C29 -> Matured Coffee | D32: ='Activity List'!D29 -> Coffee Tree Support/Staking | E32: =IF(Master!$B$3="","",EDATE(Master!$B$3,0)) | F32: =IF(Master!$B$3="","",EDATE(Master!$B$3,12)-1) | H32: =IF(E32="","",IF(G32="",F32,E32+G32-1)) | I32: ='Annual Election'!$D$2 -> 0
A33: =Master!A$6 -> 0 | B33: ='Activity List'!A30 -> T1-029 | C33: ='Activity List'!C30 -> Matured Coffee | D33: ='Activity List'!D30 -> Watchman Tower (Matured Block) | E33: =IF(Master!$B$3="","",EDATE(Master!$B$3,0)) | F33: =IF(Master!$B$3="","",EDATE(Master!$B$3,12)-1) | H33: =IF(E33="","",IF(G33="",F33,E33+G33-1)) | I33: ='Annual Election'!$D$2 -> 0
A34: =Master!A$6 -> 0 | B34: ='Activity List'!A31 -> T1-030 | C34: ='Activity List'!C31 -> Infilling | D34: ='Activity List'!D31 -> Infill Peg Preparation | E34: =IF(Master!$B$3="","",EDATE(Master!$B$3,8)) | F34: =IF(Master!$B$3="","",EDATE(Master!$B$3,11)-1) | H34: =IF(E34="","",IF(G34="",F34,E34+G34-1)) | I34: ='Annual Election'!$D$2 -> 0
A35: =Master!A$6 -> 0 | B35: ='Activity List'!A32 -> T1-031 | C35: ='Activity List'!C32 -> Infilling | D35: ='Activity List'!D32 -> Infill Layout and Pegging | E35: =IF(Master!$B$3="","",EDATE(Master!$B$3,8)) | F35: =IF(Master!$B$3="","",EDATE(Master!$B$3,11)-1) | H35: =IF(E35="","",IF(G35="",F35,E35+G35-1)) | I35: ='Annual Election'!$D$2 -> 0
A36: =Master!A$6 -> 0 | B36: ='Activity List'!A33 -> T1-032 | C36: ='Activity List'!C33 -> Infilling | D36: ='Activity List'!D33 -> Infill Hole Digging | E36: =IF(Master!$B$3="","",EDATE(Master!$B$3,8)) | F36: =IF(Master!$B$3="","",EDATE(Master!$B$3,11)-1) | H36: =IF(E36="","",IF(G36="",F36,E36+G36-1)) | I36: ='Annual Election'!$D$2 -> 0
A37: =Master!A$6 -> 0 | B37: ='Activity List'!A34 -> T1-033 | C37: ='Activity List'!C34 -> Infilling | D37: ='Activity List'!D34 -> Infill Hole Refilling | E37: =IF(Master!$B$3="","",EDATE(Master!$B$3,8)) | F37: =IF(Master!$B$3="","",EDATE(Master!$B$3,11)-1) | H37: =IF(E37="","",IF(G37="",F37,E37+G37-1)) | I37: ='Annual Election'!$D$2 -> 0
A38: =Master!A$6 -> 0 | B38: ='Activity List'!A35 -> T1-034 | C38: ='Activity List'!C35 -> Infilling | D38: ='Activity List'!D35 -> Infill Watchman Tower Prep | E38: =IF(Master!$B$3="","",EDATE(Master!$B$3,8)) | F38: =IF(Master!$B$3="","",EDATE(Master!$B$3,11)-1) | H38: =IF(E38="","",IF(G38="",F38,E38+G38-1)) | I38: ='Annual Election'!$D$2 -> 0
A39: =Master!A$6 -> 0 | B39: ='Activity List'!A36 -> T1-035 | C39: ='Activity List'!C36 -> Infilling | D39: ='Activity List'!D36 -> Infill Seedling Transport | E39: =IF(Master!$B$3="","",EDATE(Master!$B$3,8)) | F39: =IF(Master!$B$3="","",EDATE(Master!$B$3,11)-1) | H39: =IF(E39="","",IF(G39="",F39,E39+G39-1)) | I39: ='Annual Election'!$D$2 -> 0
A40: =Master!A$6 -> 0 | B40: ='Activity List'!A37 -> T1-036 | C40: ='Activity List'!C37 -> Infilling | D40: ='Activity List'!D37 -> Infill Planting | E40: =IF(Master!$B$3="","",EDATE(Master!$B$3,8)) | F40: =IF(Master!$B$3="","",EDATE(Master!$B$3,11)-1) | H40: =IF(E40="","",IF(G40="",F40,E40+G40-1)) | I40: ='Annual Election'!$D$2 -> 0
A41: =Master!A$6 -> 0 | B41: ='Activity List'!A38 -> T1-037 | C41: ='Activity List'!C38 -> Picking & Related | D41: ='Activity List'!D38 -> Harvest Watchman Tower Prep | E41: =IF(Master!$B$3="","",EDATE(Master!$B$3,0)) | F41: =IF(Master!$B$3="","",EDATE(Master!$B$3,7)-1) | H41: =IF(E41="","",IF(G41="",F41,E41+G41-1)) | I41: ='Annual Election'!$D$2 -> 0
A42: =Master!A$6 -> 0 | B42: ='Activity List'!A39 -> T1-038 | C42: ='Activity List'!C39 -> Picking & Related | D42: ='Activity List'!D39 -> Drying Bed Material Prep and Transport | E42: =IF(Master!$B$3="","",EDATE(Master!$B$3,0)) | F42: =IF(Master!$B$3="","",EDATE(Master!$B$3,7)-1) | H42: =IF(E42="","",IF(G42="",F42,E42+G42-1)) | I42: ='Annual Election'!$D$2 -> 0
A43: =Master!A$6 -> 0 | B43: ='Activity List'!A40 -> T1-039 | C43: ='Activity List'!C40 -> Picking & Related | D43: ='Activity List'!D40 -> Drying Bed Site Cleaning | E43: =IF(Master!$B$3="","",EDATE(Master!$B$3,0)) | F43: =IF(Master!$B$3="","",EDATE(Master!$B$3,7)-1) | H43: =IF(E43="","",IF(G43="",F43,E43+G43-1)) | I43: ='Annual Election'!$D$2 -> 0
A44: =Master!A$6 -> 0 | B44: ='Activity List'!A41 -> T1-040 | C44: ='Activity List'!C41 -> Picking & Related | D44: ='Activity List'!D41 -> Drying Bed Construction | E44: =IF(Master!$B$3="","",EDATE(Master!$B$3,0)) | F44: =IF(Master!$B$3="","",EDATE(Master!$B$3,7)-1) | H44: =IF(E44="","",IF(G44="",F44,E44+G44-1)) | I44: ='Annual Election'!$D$2 -> 0
A45: =Master!A$6 -> 0 | B45: ='Activity List'!A42 -> T1-041 | C45: ='Activity List'!C42 -> Picking & Related | D45: ='Activity List'!D42 -> Selective Picking, Red Cherry | E45: =IF(Master!$B$3="","",EDATE(Master!$B$3,0)) | F45: =IF(Master!$B$3="","",EDATE(Master!$B$3,7)-1) | H45: =IF(E45="","",IF(G45="",F45,E45+G45-1)) | I45: ='Annual Election'!$D$2 -> 0
A46: =Master!A$6 -> 0 | B46: ='Activity List'!A43 -> T1-042 | C46: ='Activity List'!C43 -> Picking & Related | D46: ='Activity List'!D43 -> Cherry Drying on Bed | E46: =IF(Master!$B$3="","",EDATE(Master!$B$3,0)) | F46: =IF(Master!$B$3="","",EDATE(Master!$B$3,7)-1) | H46: =IF(E46="","",IF(G46="",F46,E46+G46-1)) | I46: ='Annual Election'!$D$2 -> 0
A47: =Master!A$6 -> 0 | B47: ='Activity List'!A44 -> T1-043 | C47: ='Activity List'!C44 -> Picking & Related | D47: ='Activity List'!D44 -> Drying Bed Maintenance | E47: =IF(Master!$B$3="","",EDATE(Master!$B$3,0)) | F47: =IF(Master!$B$3="","",EDATE(Master!$B$3,7)-1) | H47: =IF(E47="","",IF(G47="",F47,E47+G47-1)) | I47: ='Annual Election'!$D$2 -> 0
A48: =Master!A$6 -> 0 | B48: ='Activity List'!A45 -> T1-044 | C48: ='Activity List'!C45 -> Picking & Related | D48: ='Activity List'!D45 -> Weighing and Arranging Dry Coffee | E48: =IF(Master!$B$3="","",EDATE(Master!$B$3,0)) | F48: =IF(Master!$B$3="","",EDATE(Master!$B$3,7)-1) | H48: =IF(E48="","",IF(G48="",F48,E48+G48-1)) | I48: ='Annual Election'!$D$2 -> 0
A49: =Master!A$6 -> 0 | B49: ='Activity List'!A46 -> T1-045 | C49: ='Activity List'!C46 -> Picking & Related | D49: ='Activity List'!D46 -> Loading Dry Coffee, Farm 1 to 2 | E49: =IF(Master!$B$3="","",EDATE(Master!$B$3,0)) | F49: =IF(Master!$B$3="","",EDATE(Master!$B$3,7)-1) | H49: =IF(E49="","",IF(G49="",F49,E49+G49-1)) | I49: ='Annual Election'!$D$2 -> 0
A50: =Master!A$6 -> 0 | B50: ='Activity List'!A47 -> T1-046 | C50: ='Activity List'!C47 -> Picking & Related | D50: ='Activity List'!D47 -> Loading Dry Coffee, Farm to Hulling | E50: =IF(Master!$B$3="","",EDATE(Master!$B$3,0)) | F50: =IF(Master!$B$3="","",EDATE(Master!$B$3,7)-1) | H50: =IF(E50="","",IF(G50="",F50,E50+G50-1)) | I50: ='Annual Election'!$D$2 -> 0
A51: =Master!A$6 -> 0 | B51: ='Activity List'!A48 -> T1-047 | C51: ='Activity List'!C48 -> Picking & Related | D51: ='Activity List'!D48 -> Transport Vehicle Rental | E51: =IF(Master!$B$3="","",EDATE(Master!$B$3,0)) | F51: =IF(Master!$B$3="","",EDATE(Master!$B$3,7)-1) | H51: =IF(E51="","",IF(G51="",F51,E51+G51-1)) | I51: ='Annual Election'!$D$2 -> 0
A52: =Master!A$6 -> 0 | B52: ='Activity List'!A49 -> T1-048 | C52: ='Activity List'!C49 -> Picking & Related | D52: ='Activity List'!D49 -> Unloading Dry Coffee at Hulling | E52: =IF(Master!$B$3="","",EDATE(Master!$B$3,0)) | F52: =IF(Master!$B$3="","",EDATE(Master!$B$3,7)-1) | H52: =IF(E52="","",IF(G52="",F52,E52+G52-1)) | I52: ='Annual Election'!$D$2 -> 0
... A56: =Master!A$6 -> 0 | B56: ='Activity List'!A53 -> T1-052 | C56: ='Activity List'!C53 -> Picking & Related | D56: ='Activity List'!D53 -> Drying Bed Removal | E56: =IF(Master!$B$3="","",EDATE(Master!$B$3,0)) | F56: =IF(Master!$B$3="","",EDATE(Master!$B$3,7)-1) | H56: =IF(E56="","",IF(G56="",F56,E56+G56-1)) | I56: ='Annual Election'!$D$2 -> 0
A57: =Master!A$6 -> 0 | B57: ='Activity List'!A54 -> T2-001 | C57: ='Activity List'!C54 -> A. Annual Harvest Management | D57: ='Activity List'!D54 -> Harvest Planning | E57: =IF(Master!$B$3="","",EDATE(Master!$B$3,0)) | F57: =IF(Master!$B$3="","",EDATE(Master!$B$3,7)-1) | H57: =IF(E57="","",IF(G57="",F57,E57+G57-1)) | I57: N
A58: =Master!A$6 -> 0 | B58: ='Activity List'!A55 -> T2-002 | C58: ='Activity List'!C55 -> A. Annual Harvest Management | D58: ='Activity List'!D55 -> Labour Mobilisation | E58: =IF(Master!$B$3="","",EDATE(Master!$B$3,0)) | F58: =IF(Master!$B$3="","",EDATE(Master!$B$3,7)-1) | H58: =IF(E58="","",IF(G58="",F58,E58+G58-1)) | I58: N
A59: =Master!A$6 -> 0 | B59: ='Activity List'!A56 -> T2-003 | C59: ='Activity List'!C56 -> A. Annual Harvest Management | D59: ='Activity List'!D56 -> Harvest Supervision | E59: =IF(Master!$B$3="","",EDATE(Master!$B$3,0)) | F59: =IF(Master!$B$3="","",EDATE(Master!$B$3,7)-1) | H59: =IF(E59="","",IF(G59="",F59,E59+G59-1)) | I59: N
A60: =Master!A$6 -> 0 | B60: ='Activity List'!A57 -> T2-004 | C60: ='Activity List'!C57 -> A. Annual Harvest Management | D60: ='Activity List'!D57 -> Daily Production Monitoring | E60: =IF(Master!$B$3="","",EDATE(Master!$B$3,0)) | F60: =IF(Master!$B$3="","",EDATE(Master!$B$3,7)-1) | H60: =IF(E60="","",IF(G60="",F60,E60+G60-1)) | I60: N
A61: =Master!A$6 -> 0 | B61: ='Activity List'!A58 -> T2-005 | C61: ='Activity List'!C58 -> A. Annual Harvest Management | D61: ='Activity List'!D58 -> Quality Monitoring (Harvest) | E61: =IF(Master!$B$3="","",EDATE(Master!$B$3,0)) | F61: =IF(Master!$B$3="","",EDATE(Master!$B$3,7)-1) | H61: =IF(E61="","",IF(G61="",F61,E61+G61-1)) | I61: N
A62: =Master!A$6 -> 0 | B62: ='Activity List'!A59 -> T2-006 | C62: ='Activity List'!C59 -> A. Annual Harvest Management | D62: ='Activity List'!D59 -> Cherry Movement Coordination | E62: =IF(Master!$B$3="","",EDATE(Master!$B$3,0)) | F62: =IF(Master!$B$3="","",EDATE(Master!$B$3,7)-1) | H62: =IF(E62="","",IF(G62="",F62,E62+G62-1)) | I62: N
A63: =Master!A$6 -> 0 | B63: ='Activity List'!A60 -> T2-007 | C63: ='Activity List'!C60 -> A. Annual Harvest Management | D63: ='Activity List'!D60 -> Daily Harvest Reporting | E63: =IF(Master!$B$3="","",EDATE(Master!$B$3,0)) | F63: =IF(Master!$B$3="","",EDATE(Master!$B$3,7)-1) | H63: =IF(E63="","",IF(G63="",F63,E63+G63-1)) | I63: N
A64: =Master!A$6 -> 0 | B64: ='Activity List'!A61 -> T2-008 | C64: ='Activity List'!C61 -> A. Annual Harvest Management | D64: ='Activity List'!D61 -> Yield Reconciliation | E64: =IF(Master!$B$3="","",EDATE(Master!$B$3,0)) | F64: =IF(Master!$B$3="","",EDATE(Master!$B$3,7)-1) | H64: =IF(E64="","",IF(G64="",F64,E64+G64-1)) | I64: N
A65: =Master!A$6 -> 0 | B65: ='Activity List'!A62 -> T2-009 | C65: ='Activity List'!C62 -> A. Annual Harvest Management | D65: ='Activity List'!D62 -> Harvest Close-Out | E65: =IF(Master!$B$3="","",EDATE(Master!$B$3,0)) | F65: =IF(Master!$B$3="","",EDATE(Master!$B$3,7)-1) | H65: =IF(E65="","",IF(G65="",F65,E65+G65-1)) | I65: N
A66: =Master!A$6 -> 0 | B66: ='Activity List'!A63 -> T2-010 | C66: ='Activity List'!C63 -> B. Coffee Operations | D66: ='Activity List'!D63 -> Cherry Reception | E66: =IF(Master!$B$3="","",EDATE(Master!$B$3,1)) | F66: =IF(Master!$B$3="","",EDATE(Master!$B$3,8)-1) | H66: =IF(E66="","",IF(G66="",F66,E66+G66-1)) | I66: N
A67: =Master!A$6 -> 0 | B67: ='Activity List'!A64 -> T2-011 | C67: ='Activity List'!C64 -> B. Coffee Operations | D67: ='Activity List'!D64 -> Washing Supervision | E67: =IF(Master!$B$3="","",EDATE(Master!$B$3,1)) | F67: =IF(Master!$B$3="","",EDATE(Master!$B$3,8)-1) | H67: =IF(E67="","",IF(G67="",F67,E67+G67-1)) | I67: N
A68: =Master!A$6 -> 0 | B68: ='Activity List'!A65 -> T2-012 | C68: ='Activity List'!C65 -> B. Coffee Operations | D68: ='Activity List'!D65 -> Fermentation Supervision | E68: =IF(Master!$B$3="","",EDATE(Master!$B$3,1)) | F68: =IF(Master!$B$3="","",EDATE(Master!$B$3,8)-1) | H68: =IF(E68="","",IF(G68="",F68,E68+G68-1)) | I68: N
A69: =Master!A$6 -> 0 | B69: ='Activity List'!A66 -> T2-013 | C69: ='Activity List'!C66 -> B. Coffee Operations | D69: ='Activity List'!D66 -> Drying Supervision | E69: =IF(Master!$B$3="","",EDATE(Master!$B$3,1)) | F69: =IF(Master!$B$3="","",EDATE(Master!$B$3,8)-1) | H69: =IF(E69="","",IF(G69="",F69,E69+G69-1)) | I69: N
A70: =Master!A$6 -> 0 | B70: ='Activity List'!A67 -> T2-014 | C70: ='Activity List'!C67 -> B. Coffee Operations | D70: ='Activity List'!D67 -> Moisture Management | E70: =IF(Master!$B$3="","",EDATE(Master!$B$3,1)) | F70: =IF(Master!$B$3="","",EDATE(Master!$B$3,8)-1) | H70: =IF(E70="","",IF(G70="",F70,E70+G70-1)) | I70: N
A71: =Master!A$6 -> 0 | B71: ='Activity List'!A68 -> T2-015 | C71: ='Activity List'!C68 -> B. Coffee Operations | D71: ='Activity List'!D68 -> Parchment Storage | E71: =IF(Master!$B$3="","",EDATE(Master!$B$3,1)) | F71: =IF(Master!$B$3="","",EDATE(Master!$B$3,8)-1) | H71: =IF(E71="","",IF(G71="",F71,E71+G71-1)) | I71: N
A72: =Master!A$6 -> 0 | B72: ='Activity List'!A69 -> T2-016 | C72: ='Activity List'!C69 -> B. Coffee Operations | D72: ='Activity List'!D69 -> Warehouse Management | E72: =IF(Master!$B$3="","",EDATE(Master!$B$3,1)) | F72: =IF(Master!$B$3="","",EDATE(Master!$B$3,8)-1) | H72: =IF(E72="","",IF(G72="",F72,E72+G72-1)) | I72: N
A73: =Master!A$6 -> 0 | B73: ='Activity List'!A70 -> T2-017 | C73: ='Activity List'!C70 -> B. Coffee Operations | D73: ='Activity List'!D70 -> Inventory Reconciliation | E73: =IF(Master!$B$3="","",EDATE(Master!$B$3,1)) | F73: =IF(Master!$B$3="","",EDATE(Master!$B$3,8)-1) | H73: =IF(E73="","",IF(G73="",F73,E73+G73-1)) | I73: N
A74: =Master!A$6 -> 0 | B74: ='Activity List'!A71 -> T2-018 | C74: ='Activity List'!C71 -> B. Coffee Operations | D74: ='Activity List'!D71 -> Internal Transport Coordination | E74: =IF(Master!$B$3="","",EDATE(Master!$B$3,1)) | F74: =IF(Master!$B$3="","",EDATE(Master!$B$3,8)-1) | H74: =IF(E74="","",IF(G74="",F74,E74+G74-1)) | I74: N
A75: =Master!A$6 -> 0 | B75: ='Activity List'!A72 -> T2-019 | C75: ='Activity List'!C72 -> B. Coffee Operations | D75: ='Activity List'!D72 -> Hulling Supervision | E75: =IF(Master!$B$3="","",EDATE(Master!$B$3,1)) | F75: =IF(Master!$B$3="","",EDATE(Master!$B$3,8)-1) | H75: =IF(E75="","",IF(G75="",F75,E75+G75-1)) | I75: N
A76: =Master!A$6 -> 0 | B76: ='Activity List'!A73 -> T2-020 | C76: ='Activity List'!C73 -> B. Coffee Operations | D76: ='Activity List'!D73 -> Stock Management | E76: =IF(Master!$B$3="","",EDATE(Master!$B$3,1)) | F76: =IF(Master!$B$3="","",EDATE(Master!$B$3,8)-1) | H76: =IF(E76="","",IF(G76="",F76,E76+G76-1)) | I76: N
A77: =Master!A$6 -> 0 | B77: ='Activity List'!A74 -> T2-021 | C77: ='Activity List'!C74 -> B. Coffee Operations | D77: ='Activity List'!D74 -> Loss Control | E77: =IF(Master!$B$3="","",EDATE(Master!$B$3,1)) | F77: =IF(Master!$B$3="","",EDATE(Master!$B$3,8)-1) | H77: =IF(E77="","",IF(G77="",F77,E77+G77-1)) | I77: N
A78: =Master!A$6 -> 0 | B78: ='Activity List'!A75 -> T2-022 | C78: ='Activity List'!C75 -> C. Export & Commercial Operations | D78: ='Activity List'!D75 -> Export Grading Coordination | E78: =IF(Master!$B$3="","",EDATE(Master!$B$3,3)) | F78: =IF(Master!$B$3="","",EDATE(Master!$B$3,10)-1) | H78: =IF(E78="","",IF(G78="",F78,E78+G78-1)) | I78: N
A79: =Master!A$6 -> 0 | B79: ='Activity List'!A76 -> T2-023 | C79: ='Activity List'!C76 -> C. Export & Commercial Operations | D79: ='Activity List'!D76 -> Quality Inspection Coordination | E79: =IF(Master!$B$3="","",EDATE(Master!$B$3,3)) | F79: =IF(Master!$B$3="","",EDATE(Master!$B$3,10)-1) | H79: =IF(E79="","",IF(G79="",F79,E79+G79-1)) | I79: N
A80: =Master!A$6 -> 0 | B80: ='Activity List'!A77 -> T2-024 | C80: ='Activity List'!C77 -> C. Export & Commercial Operations | D80: ='Activity List'!D77 -> Sample Preparation | E80: =IF(Master!$B$3="","",EDATE(Master!$B$3,3)) | F80: =IF(Master!$B$3="","",EDATE(Master!$B$3,10)-1) | H80: =IF(E80="","",IF(G80="",F80,E80+G80-1)) | I80: N
A81: =Master!A$6 -> 0 | B81: ='Activity List'!A78 -> T2-025 | C81: ='Activity List'!C78 -> C. Export & Commercial Operations | D81: ='Activity List'!D78 -> Client Correspondence | E81: =IF(Master!$B$3="","",EDATE(Master!$B$3,3)) | F81: =IF(Master!$B$3="","",EDATE(Master!$B$3,10)-1) | H81: =IF(E81="","",IF(G81="",F81,E81+G81-1)) | I81: N
A82: =Master!A$6 -> 0 | B82: ='Activity List'!A79 -> T2-026 | C82: ='Activity List'!C79 -> C. Export & Commercial Operations | D82: ='Activity List'!D79 -> Contract Administration | E82: =IF(Master!$B$3="","",EDATE(Master!$B$3,3)) | F82: =IF(Master!$B$3="","",EDATE(Master!$B$3,10)-1) | H82: =IF(E82="","",IF(G82="",F82,E82+G82-1)) | I82: N
A83: =Master!A$6 -> 0 | B83: ='Activity List'!A80 -> T2-027 | C83: ='Activity List'!C80 -> C. Export & Commercial Operations | D83: ='Activity List'!D80 -> Buyer Coordination | E83: =IF(Master!$B$3="","",EDATE(Master!$B$3,3)) | F83: =IF(Master!$B$3="","",EDATE(Master!$B$3,10)-1) | H83: =IF(E83="","",IF(G83="",F83,E83+G83-1)) | I83: N
A84: =Master!A$6 -> 0 | B84: ='Activity List'!A81 -> T2-028 | C84: ='Activity List'!C81 -> C. Export & Commercial Operations | D84: ='Activity List'!D81 -> Letters of Credit Coordination | E84: =IF(Master!$B$3="","",EDATE(Master!$B$3,3)) | F84: =IF(Master!$B$3="","",EDATE(Master!$B$3,10)-1) | H84: =IF(E84="","",IF(G84="",F84,E84+G84-1)) | I84: N
A85: =Master!A$6 -> 0 | B85: ='Activity List'!A82 -> T2-029 | C85: ='Activity List'!C82 -> C. Export & Commercial Operations | D85: ='Activity List'!D82 -> Export Documentation | E85: =IF(Master!$B$3="","",EDATE(Master!$B$3,3)) | F85: =IF(Master!$B$3="","",EDATE(Master!$B$3,10)-1) | H85: =IF(E85="","",IF(G85="",F85,E85+G85-1)) | I85: N
A86: =Master!A$6 -> 0 | B86: ='Activity List'!A83 -> T2-030 | C86: ='Activity List'!C83 -> C. Export & Commercial Operations | D86: ='Activity List'!D83 -> Shipping Coordination | E86: =IF(Master!$B$3="","",EDATE(Master!$B$3,3)) | F86: =IF(Master!$B$3="","",EDATE(Master!$B$3,10)-1) | H86: =IF(E86="","",IF(G86="",F86,E86+G86-1)) | I86: N
A87: =Master!A$6 -> 0 | B87: ='Activity List'!A84 -> T2-031 | C87: ='Activity List'!C84 -> C. Export & Commercial Operations | D87: ='Activity List'!D84 -> Export Compliance | E87: =IF(Master!$B$3="","",EDATE(Master!$B$3,3)) | F87: =IF(Master!$B$3="","",EDATE(Master!$B$3,10)-1) | H87: =IF(E87="","",IF(G87="",F87,E87+G87-1)) | I87: N
A88: =Master!A$6 -> 0 | B88: ='Activity List'!A85 -> T2-032 | C88: ='Activity List'!C85 -> C. Export & Commercial Operations | D88: ='Activity List'!D85 -> Shipment Follow-Up | E88: =IF(Master!$B$3="","",EDATE(Master!$B$3,3)) | F88: =IF(Master!$B$3="","",EDATE(Master!$B$3,10)-1) | H88: =IF(E88="","",IF(G88="",F88,E88+G88-1)) | I88: N
A89: =Master!A$6 -> 0 | B89: ='Activity List'!A86 -> T2-033 | C89: ='Activity List'!C86 -> C. Export & Commercial Operations | D89: ='Activity List'!D86 -> Export Proceeds Receipt and Reconciliation | E89: =IF(Master!$B$3="","",EDATE(Master!$B$3,3)) | F89: =IF(Master!$B$3="","",EDATE(Master!$B$3,10)-1) | H89: =IF(E89="","",IF(G89="",F89,E89+G89-1)) | I89: N
A90: =Master!A$6 -> 0 | B90: ='Activity List'!A87 -> T2-034 | C90: ='Activity List'!C87 -> D. Asset Development | D90: ='Activity List'!D87 -> Washing Station Rehabilitation | I90: N
A91: =Master!A$6 -> 0 | B91: ='Activity List'!A88 -> T2-035 | C91: ='Activity List'!C88 -> D. Asset Development | D91: ='Activity List'!D88 -> Huller Rehabilitation | I91: N
A92: =Master!A$6 -> 0 | B92: ='Activity List'!A89 -> T2-036 | C92: ='Activity List'!C89 -> D. Asset Development | D92: ='Activity List'!D89 -> Irrigation Systems | I92: N
A93: =Master!A$6 -> 0 | B93: ='Activity List'!A90 -> T2-037 | C93: ='Activity List'!C90 -> D. Asset Development | D93: ='Activity List'!D90 -> On-Farm Water Systems Development | I93: N
A94: =Master!A$6 -> 0 | B94: ='Activity List'!A91 -> T2-038 | C94: ='Activity List'!C91 -> D. Asset Development | D94: ='Activity List'!D91 -> Roads | I94: N
A95: =Master!A$6 -> 0 | B95: ='Activity List'!A92 -> T2-039 | C95: ='Activity List'!C92 -> D. Asset Development | D95: ='Activity List'!D92 -> Buildings | I95: N
A96: =Master!A$6 -> 0 | B96: ='Activity List'!A93 -> T2-040 | C96: ='Activity List'!C93 -> D. Asset Development | D96: ='Activity List'!D93 -> Staff Housing | I96: N
A97: =Master!A$6 -> 0 | B97: ='Activity List'!A94 -> T2-041 | C97: ='Activity List'!C94 -> D. Asset Development | D97: ='Activity List'!D94 -> Workshops | I97: N
A98: =Master!A$6 -> 0 | B98: ='Activity List'!A95 -> T2-042 | C98: ='Activity List'!C95 -> D. Asset Development | D98: ='Activity List'!D95 -> Machinery Procurement | I98: N
A99: =Master!A$6 -> 0 | B99: ='Activity List'!A96 -> T2-043 | C99: ='Activity List'!C96 -> D. Asset Development | D99: ='Activity List'!D96 -> Utilities | I99: N
A100: =Master!A$6 -> 0 | B100: ='Activity List'!A97 -> T2-044 | C100: ='Activity List'!C97 -> D. Asset Development | D100: ='Activity List'!D97 -> Solar Systems (incl. Staff Welfare) | I100: N
A101: =Master!A$6 -> 0 | B101: ='Activity List'!A98 -> T2-045 | C101: ='Activity List'!C98 -> D. Asset Development | D101: ='Activity List'!D98 -> Farm Expansion | I101: N
... A129: =Master!A$6 -> 0 | B129: ='Activity List'!A126 -> T3-026 | C129: ='Activity List'!C126 -> A. Institutional and Strategic Interventions | D129: ='Activity List'!D126 -> Coordination of Specialist Advisers | I129: N
A130: =Master!A$6 -> 0 | B130: ='Activity List'!A127 -> T3-027 | C130: ='Activity List'!C127 -> B. Technical and Laboratory Services | D130: ='Activity List'!D127 -> Soil Sampling and Analysis | E130: =IF(Master!$B$3="","",EDATE(Master!$B$3,0)) | F130: =IF(Master!$B$3="","",EDATE(Master!$B$3,12)-1) | H130: =IF(E130="","",IF(G130="",F130,E130+G130-1)) | I130: N
A131: =Master!A$6 -> 0 | B131: ='Activity List'!A128 -> T3-028 | C131: ='Activity List'!C128 -> B. Technical and Laboratory Services | D131: ='Activity List'!D128 -> Soil Fertility and Nutrient Status Reporting | E131: =IF(Master!$B$3="","",EDATE(Master!$B$3,0)) | F131: =IF(Master!$B$3="","",EDATE(Master!$B$3,12)-1) | H131: =IF(E131="","",IF(G131="",F131,E131+G131-1)) | I131: N
A132: =Master!A$6 -> 0 | B132: ='Activity List'!A129 -> T3-029 | C132: ='Activity List'!C129 -> B. Technical and Laboratory Services | D132: ='Activity List'!D129 -> Liming and Soil Amendment Recommendations | E132: =IF(Master!$B$3="","",EDATE(Master!$B$3,0)) | F132: =IF(Master!$B$3="","",EDATE(Master!$B$3,12)-1) | H132: =IF(E132="","",IF(G132="",F132,E132+G132-1)) | I132: N
A133: =Master!A$6 -> 0 | B133: ='Activity List'!A130 -> T3-030 | C133: ='Activity List'!C130 -> B. Technical and Laboratory Services | D133: ='Activity List'!D130 -> GPS Farm Boundary and Block Mapping | E133: =IF(Master!$B$3="","",EDATE(Master!$B$3,0)) | F133: =IF(Master!$B$3="","",EDATE(Master!$B$3,3)-1) | H133: =IF(E133="","",IF(G133="",F133,E133+G133-1)) | I133: N
...

Sheet Activity Plan
A1: Block ID | B1: Block Name | C1: Activity ID | D1: Activity Name | E1: Tier | F1: Unit | G1: Tick (Y/N) | H1: Planned Qty | I1: Labor Rate / Unit (ETB) | J1: Planned Labor Cost (ETB) | K1: Window Start (helper) | L1: Window End (helper) | M1: Weeks Spanned (helper) | N1: Weekly Allocation (ETB, helper)
A2: =Master!A$6 -> 0 | B2: =Master!B$6 -> 0 | C2: ='Activity List'!A2 -> T1-001 | D2: ='Activity List'!D2 -> Land Clearing | E2: ='Activity List'!B2 -> Tier 1 — Core Services | F2: ='Activity List'!E2 -> ha | G2: ='Annual Election'!I5 -> 0 | I2: =IFERROR(INDEX('Labor Rate Card'!$G$2:$G$135,MATCH(C2,'Labor Rate Card'!$A$2:$A$135,0)),0) -> 0 | J2: =IF(G2="Y",H2*I2,0) -> 0 | K2: ='Annual Election'!E5 | L2: ='Annual Election'!H5 | M2: =IF(OR(K2="",L2=""),"",ROUNDUP((L2-K2+1)/7,0)) | N2: =IF(OR(J2="",M2="",M2=0),0,J2/M2) -> 0
A3: =Master!A$6 -> 0 | B3: =Master!B$6 -> 0 | C3: ='Activity List'!A3 -> T1-002 | D3: ='Activity List'!D3 -> Tree Felling | E3: ='Activity List'!B3 -> Tier 1 — Core Services | F3: ='Activity List'!E3 -> ha | G3: ='Annual Election'!I6 -> 0 | I3: =IFERROR(INDEX('Labor Rate Card'!$G$2:$G$135,MATCH(C3,'Labor Rate Card'!$A$2:$A$135,0)),0) -> 0 | J3: =IF(G3="Y",H3*I3,0) -> 0 | K3: ='Annual Election'!E6 | L3: ='Annual Election'!H6 | M3: =IF(OR(K3="",L3=""),"",ROUNDUP((L3-K3+1)/7,0)) | N3: =IF(OR(J3="",M3="",M3=0),0,J3/M3) -> 0
A4: =Master!A$6 -> 0 | B4: =Master!B$6 -> 0 | C4: ='Activity List'!A4 -> T1-003 | D4: ='Activity List'!D4 -> Soil Heaping | E4: ='Activity List'!B4 -> Tier 1 — Core Services | F4: ='Activity List'!E4 -> m3 | G4: ='Annual Election'!I7 -> 0 | I4: =IFERROR(INDEX('Labor Rate Card'!$G$2:$G$135,MATCH(C4,'Labor Rate Card'!$A$2:$A$135,0)),0) -> 0 | J4: =IF(G4="Y",H4*I4,0) -> 0 | K4: ='Annual Election'!E7 | L4: ='Annual Election'!H7 | M4: =IF(OR(K4="",L4=""),"",ROUNDUP((L4-K4+1)/7,0)) | N4: =IF(OR(J4="",M4="",M4=0),0,J4/M4) -> 0
A5: =Master!A$6 -> 0 | B5: =Master!B$6 -> 0 | C5: ='Activity List'!A5 -> T1-004 | D5: ='Activity List'!D5 -> Polytube Cutting | E5: ='Activity List'!B5 -> Tier 1 — Core Services | F5: ='Activity List'!E5 -> kg | G5: ='Annual Election'!I8 -> 0 | I5: =IFERROR(INDEX('Labor Rate Card'!$G$2:$G$135,MATCH(C5,'Labor Rate Card'!$A$2:$A$135,0)),0) -> 0 | J5: =IF(G5="Y",H5*I5,0) -> 0 | K5: ='Annual Election'!E8 | L5: ='Annual Election'!H8 | M5: =IF(OR(K5="",L5=""),"",ROUNDUP((L5-K5+1)/7,0)) | N5: =IF(OR(J5="",M5="",M5=0),0,J5/M5) -> 0
A6: =Master!A$6 -> 0 | B6: =Master!B$6 -> 0 | C6: ='Activity List'!A6 -> T1-005 | D6: ='Activity List'!D6 -> Polytube Filling | E6: ='Activity List'!B6 -> Tier 1 — Core Services | F6: ='Activity List'!E6 -> seedling | G6: ='Annual Election'!I9 -> 0 | I6: =IFERROR(INDEX('Labor Rate Card'!$G$2:$G$135,MATCH(C6,'Labor Rate Card'!$A$2:$A$135,0)),0) -> 0 | J6: =IF(G6="Y",H6*I6,0) -> 0 | K6: ='Annual Election'!E9 | L6: ='Annual Election'!H9 | M6: =IF(OR(K6="",L6=""),"",ROUNDUP((L6-K6+1)/7,0)) | N6: =IF(OR(J6="",M6="",M6=0),0,J6/M6) -> 0
A7: =Master!A$6 -> 0 | B7: =Master!B$6 -> 0 | C7: ='Activity List'!A7 -> T1-006 | D7: ='Activity List'!D7 -> Seedbed Preparation | E7: ='Activity List'!B7 -> Tier 1 — Core Services | F7: ='Activity List'!E7 -> bed | G7: ='Annual Election'!I10 -> 0 | I7: =IFERROR(INDEX('Labor Rate Card'!$G$2:$G$135,MATCH(C7,'Labor Rate Card'!$A$2:$A$135,0)),0) -> 0 | J7: =IF(G7="Y",H7*I7,0) -> 0 | K7: ='Annual Election'!E10 | L7: ='Annual Election'!H10 | M7: =IF(OR(K7="",L7=""),"",ROUNDUP((L7-K7+1)/7,0)) | N7: =IF(OR(J7="",M7="",M7=0),0,J7/M7) -> 0
A8: =Master!A$6 -> 0 | B8: =Master!B$6 -> 0 | C8: ='Activity List'!A8 -> T1-007 | D8: ='Activity List'!D8 -> Polytube Arranging | E8: ='Activity List'!B8 -> Tier 1 — Core Services | F8: ='Activity List'!E8 -> bed | G8: ='Annual Election'!I11 -> 0 | I8: =IFERROR(INDEX('Labor Rate Card'!$G$2:$G$135,MATCH(C8,'Labor Rate Card'!$A$2:$A$135,0)),0) -> 0 | J8: =IF(G8="Y",H8*I8,0) -> 0 | K8: ='Annual Election'!E11 | L8: ='Annual Election'!H11 | M8: =IF(OR(K8="",L8=""),"",ROUNDUP((L8-K8+1)/7,0)) | N8: =IF(OR(J8="",M8="",M8=0),0,J8/M8) -> 0
A9: =Master!A$6 -> 0 | B9: =Master!B$6 -> 0 | C9: ='Activity List'!A9 -> T1-008 | D9: ='Activity List'!D9 -> Seed Sowing | E9: ='Activity List'!B9 -> Tier 1 — Core Services | F9: ='Activity List'!E9 -> bed | G9: ='Annual Election'!I12 -> 0 | I9: =IFERROR(INDEX('Labor Rate Card'!$G$2:$G$135,MATCH(C9,'Labor Rate Card'!$A$2:$A$135,0)),0) -> 0 | J9: =IF(G9="Y",H9*I9,0) -> 0 | K9: ='Annual Election'!E12 | L9: ='Annual Election'!H12 | M9: =IF(OR(K9="",L9=""),"",ROUNDUP((L9-K9+1)/7,0)) | N9: =IF(OR(J9="",M9="",M9=0),0,J9/M9) -> 0
A10: =Master!A$6 -> 0 | B10: =Master!B$6 -> 0 | C10: ='Activity List'!A10 -> T1-009 | D10: ='Activity List'!D10 -> Mulch Material Preparation | E10: ='Activity List'!B10 -> Tier 1 — Core Services | F10: ='Activity List'!E10 -> bed | G10: ='Annual Election'!I13 -> 0 | I10: =IFERROR(INDEX('Labor Rate Card'!$G$2:$G$135,MATCH(C10,'Labor Rate Card'!$A$2:$A$135,0)),0) -> 0 | J10: =IF(G10="Y",H10*I10,0) -> 0 | K10: ='Annual Election'!E13 | L10: ='Annual Election'!H13 | M10: =IF(OR(K10="",L10=""),"",ROUNDUP((L10-K10+1)/7,0)) | N10: =IF(OR(J10="",M10="",M10=0),0,J10/M10) -> 0
A11: =Master!A$6 -> 0 | B11: =Master!B$6 -> 0 | C11: ='Activity List'!A11 -> T1-010 | D11: ='Activity List'!D11 -> Mulch Application | E11: ='Activity List'!B11 -> Tier 1 — Core Services | F11: ='Activity List'!E11 -> bed | G11: ='Annual Election'!I14 -> 0 | I11: =IFERROR(INDEX('Labor Rate Card'!$G$2:$G$135,MATCH(C11,'Labor Rate Card'!$A$2:$A$135,0)),0) -> 0 | J11: =IF(G11="Y",H11*I11,0) -> 0 | K11: ='Annual Election'!E14 | L11: ='Annual Election'!H14 | M11: =IF(OR(K11="",L11=""),"",ROUNDUP((L11-K11+1)/7,0)) | N11: =IF(OR(J11="",M11="",M11=0),0,J11/M11) -> 0
A12: =Master!A$6 -> 0 | B12: =Master!B$6 -> 0 | C12: ='Activity List'!A12 -> T1-011 | D12: ='Activity List'!D12 -> Shade Material Preparation | E12: ='Activity List'!B12 -> Tier 1 — Core Services | F12: ='Activity List'!E12 -> bed | G12: ='Annual Election'!I15 -> 0 | I12: =IFERROR(INDEX('Labor Rate Card'!$G$2:$G$135,MATCH(C12,'Labor Rate Card'!$A$2:$A$135,0)),0) -> 0 | J12: =IF(G12="Y",H12*I12,0) -> 0 | K12: ='Annual Election'!E15 | L12: ='Annual Election'!H15 | M12: =IF(OR(K12="",L12=""),"",ROUNDUP((L12-K12+1)/7,0)) | N12: =IF(OR(J12="",M12="",M12=0),0,J12/M12) -> 0
A13: =Master!A$6 -> 0 | B13: =Master!B$6 -> 0 | C13: ='Activity List'!A13 -> T1-012 | D13: ='Activity List'!D13 -> Shade Construction | E13: ='Activity List'!B13 -> Tier 1 — Core Services | F13: ='Activity List'!E13 -> bed | G13: ='Annual Election'!I16 -> 0 | I13: =IFERROR(INDEX('Labor Rate Card'!$G$2:$G$135,MATCH(C13,'Labor Rate Card'!$A$2:$A$135,0)),0) -> 0 | J13: =IF(G13="Y",H13*I13,0) -> 0 | K13: ='Annual Election'!E16 | L13: ='Annual Election'!H16 | M13: =IF(OR(K13="",L13=""),"",ROUNDUP((L13-K13+1)/7,0)) | N13: =IF(OR(J13="",M13="",M13=0),0,J13/M13) -> 0
... A135: =Master!A$6 -> 0 | B135: =Master!B$6 -> 0 | C135: ='Activity List'!A135 -> T3-035 | D135: ='Activity List'!D135 -> Buyer Hosting at SpiralLabs | E135: ='Activity List'!B135 -> Tier 3 — Interventions | F135: ='Activity List'!E135 -> event | G135: ='Annual Election'!I138 -> N | I135: =IFERROR(INDEX('Labor Rate Card'!$G$2:$G$135,MATCH(C135,'Labor Rate Card'!$A$2:$A$135,0)),0) -> 0 | J135: =IF(G135="Y",H135*I135,0) -> 0 | K135: ='Annual Election'!E138 -> 0 | L135: ='Annual Election'!H138 -> 0 | M135: =IF(OR(K135="",L135=""),"",ROUNDUP((L135-K135+1)/7,0)) -> 1 | N135: =IF(OR(J135="",M135="",M135=0),0,J135/M135) -> 0
A137: Tick (Y/N) now reads from the Annual Election sheet — election happens there first. Planned Qty is the magnitude of work for this block: how many hectares, trees, beds etc. this activity actually needs, entered once elected. Columns K-N are helper columns (window, weeks spanned, weekly allocation) feeding the Weekly Cash Flow sheet. To plan a second block: generate a matching set of Election and Activity Plan rows for that block, plus its own Calendar tab.

Sheet Supervisor Progress
A1: Block ID | B1: Activity ID | C1: Activity Name | D1: Planned Qty | E1: Window Start | F1: Effective End | G1: % Complete (25/50/75/100) | H1: Actual Qty Done | I1: Labor Cost Booked (ETB) | J1: Variance Qty (Planned - Actual) | K1: Last Movement Date (update manually when % changes) | L1: Weeks Since Movement | M1: Stall Flag (2+ weeks) | N1: Rollover Qty (if window closed, <100%) | O1: Rollover Flag | P1: Flagged Activity (helper, for report)
A2: ='Activity Plan'!A2 -> 0 | B2: ='Activity Plan'!C2 -> T1-001 | C2: ='Activity Plan'!D2 -> Land Clearing | D2: ='Activity Plan'!H2 -> 0 | E2: ='Annual Election'!E5 | F2: ='Annual Election'!H5 | H2: =IF(OR(D2="",G2=""),"",D2*G2/100) | I2: =IF(H2="","",H2*'Activity Plan'!I2) | J2: =IF(H2="","",D2-H2) | L2: =IF(K2="","",(TODAY()-K2)/7) | M2: =IF(AND(L2<>"",L2>=2,G2<100),"AT RISK — no progress in 2+ weeks","") | N2: =IF(AND(F2<>"",TODAY()>F2,OR(G2="",G2<100)),D2-IF(H2="",0,H2),0) -> 0 | O2: =IF(N2>0,"ROLL OVER — create a new Election/Activity Plan entry for the shortfall","") | P2: =IF(M2<>"",C2,"")
A3: ='Activity Plan'!A3 -> 0 | B3: ='Activity Plan'!C3 -> T1-002 | C3: ='Activity Plan'!D3 -> Tree Felling | D3: ='Activity Plan'!H3 -> 0 | E3: ='Annual Election'!E6 | F3: ='Annual Election'!H6 | H3: =IF(OR(D3="",G3=""),"",D3*G3/100) | I3: =IF(H3="","",H3*'Activity Plan'!I3) | J3: =IF(H3="","",D3-H3) | L3: =IF(K3="","",(TODAY()-K3)/7) | M3: =IF(AND(L3<>"",L3>=2,G3<100),"AT RISK — no progress in 2+ weeks","") | N3: =IF(AND(F3<>"",TODAY()>F3,OR(G3="",G3<100)),D3-IF(H3="",0,H3),0) -> 0 | O3: =IF(N3>0,"ROLL OVER — create a new Election/Activity Plan entry for the shortfall","") | P3: =IF(M3<>"",C3,"")
A4: ='Activity Plan'!A4 -> 0 | B4: ='Activity Plan'!C4 -> T1-003 | C4: ='Activity Plan'!D4 -> Soil Heaping | D4: ='Activity Plan'!H4 -> 0 | E4: ='Annual Election'!E7 | F4: ='Annual Election'!H7 | H4: =IF(OR(D4="",G4=""),"",D4*G4/100) | I4: =IF(H4="","",H4*'Activity Plan'!I4) | J4: =IF(H4="","",D4-H4) | L4: =IF(K4="","",(TODAY()-K4)/7) | M4: =IF(AND(L4<>"",L4>=2,G4<100),"AT RISK — no progress in 2+ weeks","") | N4: =IF(AND(F4<>"",TODAY()>F4,OR(G4="",G4<100)),D4-IF(H4="",0,H4),0) -> 0 | O4: =IF(N4>0,"ROLL OVER — create a new Election/Activity Plan entry for the shortfall","") | P4: =IF(M4<>"",C4,"")
A5: ='Activity Plan'!A5 -> 0 | B5: ='Activity Plan'!C5 -> T1-004 | C5: ='Activity Plan'!D5 -> Polytube Cutting | D5: ='Activity Plan'!H5 -> 0 | E5: ='Annual Election'!E8 | F5: ='Annual Election'!H8 | H5: =IF(OR(D5="",G5=""),"",D5*G5/100) | I5: =IF(H5="","",H5*'Activity Plan'!I5) | J5: =IF(H5="","",D5-H5) | L5: =IF(K5="","",(TODAY()-K5)/7) | M5: =IF(AND(L5<>"",L5>=2,G5<100),"AT RISK — no progress in 2+ weeks","") | N5: =IF(AND(F5<>"",TODAY()>F5,OR(G5="",G5<100)),D5-IF(H5="",0,H5),0) -> 0 | O5: =IF(N5>0,"ROLL OVER — create a new Election/Activity Plan entry for the shortfall","") | P5: =IF(M5<>"",C5,"")
A6: ='Activity Plan'!A6 -> 0 | B6: ='Activity Plan'!C6 -> T1-005 | C6: ='Activity Plan'!D6 -> Polytube Filling | D6: ='Activity Plan'!H6 -> 0 | E6: ='Annual Election'!E9 | F6: ='Annual Election'!H9 | H6: =IF(OR(D6="",G6=""),"",D6*G6/100) | I6: =IF(H6="","",H6*'Activity Plan'!I6) | J6: =IF(H6="","",D6-H6) | L6: =IF(K6="","",(TODAY()-K6)/7) | M6: =IF(AND(L6<>"",L6>=2,G6<100),"AT RISK — no progress in 2+ weeks","") | N6: =IF(AND(F6<>"",TODAY()>F6,OR(G6="",G6<100)),D6-IF(H6="",0,H6),0) -> 0 | O6: =IF(N6>0,"ROLL OVER — create a new Election/Activity Plan entry for the shortfall","") | P6: =IF(M6<>"",C6,"")
A7: ='Activity Plan'!A7 -> 0 | B7: ='Activity Plan'!C7 -> T1-006 | C7: ='Activity Plan'!D7 -> Seedbed Preparation | D7: ='Activity Plan'!H7 -> 0 | E7: ='Annual Election'!E10 | F7: ='Annual Election'!H10 | H7: =IF(OR(D7="",G7=""),"",D7*G7/100) | I7: =IF(H7="","",H7*'Activity Plan'!I7) | J7: =IF(H7="","",D7-H7) | L7: =IF(K7="","",(TODAY()-K7)/7) | M7: =IF(AND(L7<>"",L7>=2,G7<100),"AT RISK — no progress in 2+ weeks","") | N7: =IF(AND(F7<>"",TODAY()>F7,OR(G7="",G7<100)),D7-IF(H7="",0,H7),0) -> 0 | O7: =IF(N7>0,"ROLL OVER — create a new Election/Activity Plan entry for the shortfall","") | P7: =IF(M7<>"",C7,"")
A8: ='Activity Plan'!A8 -> 0 | B8: ='Activity Plan'!C8 -> T1-007 | C8: ='Activity Plan'!D8 -> Polytube Arranging | D8: ='Activity Plan'!H8 -> 0 | E8: ='Annual Election'!E11 | F8: ='Annual Election'!H11 | H8: =IF(OR(D8="",G8=""),"",D8*G8/100) | I8: =IF(H8="","",H8*'Activity Plan'!I8) | J8: =IF(H8="","",D8-H8) | L8: =IF(K8="","",(TODAY()-K8)/7) | M8: =IF(AND(L8<>"",L8>=2,G8<100),"AT RISK — no progress in 2+ weeks","") | N8: =IF(AND(F8<>"",TODAY()>F8,OR(G8="",G8<100)),D8-IF(H8="",0,H8),0) -> 0 | O8: =IF(N8>0,"ROLL OVER — create a new Election/Activity Plan entry for the shortfall","") | P8: =IF(M8<>"",C8,"")
A9: ='Activity Plan'!A9 -> 0 | B9: ='Activity Plan'!C9 -> T1-008 | C9: ='Activity Plan'!D9 -> Seed Sowing | D9: ='Activity Plan'!H9 -> 0 | E9: ='Annual Election'!E12 | F9: ='Annual Election'!H12 | H9: =IF(OR(D9="",G9=""),"",D9*G9/100) | I9: =IF(H9="","",H9*'Activity Plan'!I9) | J9: =IF(H9="","",D9-H9) | L9: =IF(K9="","",(TODAY()-K9)/7) | M9: =IF(AND(L9<>"",L9>=2,G9<100),"AT RISK — no progress in 2+ weeks","") | N9: =IF(AND(F9<>"",TODAY()>F9,OR(G9="",G9<100)),D9-IF(H9="",0,H9),0) -> 0 | O9: =IF(N9>0,"ROLL OVER — create a new Election/Activity Plan entry for the shortfall","") | P9: =IF(M9<>"",C9,"")
A10: ='Activity Plan'!A10 -> 0 | B10: ='Activity Plan'!C10 -> T1-009 | C10: ='Activity Plan'!D10 -> Mulch Material Preparation | D10: ='Activity Plan'!H10 -> 0 | E10: ='Annual Election'!E13 | F10: ='Annual Election'!H13 | H10: =IF(OR(D10="",G10=""),"",D10*G10/100) | I10: =IF(H10="","",H10*'Activity Plan'!I10) | J10: =IF(H10="","",D10-H10) | L10: =IF(K10="","",(TODAY()-K10)/7) | M10: =IF(AND(L10<>"",L10>=2,G10<100),"AT RISK — no progress in 2+ weeks","") | N10: =IF(AND(F10<>"",TODAY()>F10,OR(G10="",G10<100)),D10-IF(H10="",0,H10),0) -> 0 | O10: =IF(N10>0,"ROLL OVER — create a new Election/Activity Plan entry for the shortfall","") | P10: =IF(M10<>"",C10,"")
A11: ='Activity Plan'!A11 -> 0 | B11: ='Activity Plan'!C11 -> T1-010 | C11: ='Activity Plan'!D11 -> Mulch Application | D11: ='Activity Plan'!H11 -> 0 | E11: ='Annual Election'!E14 | F11: ='Annual Election'!H14 | H11: =IF(OR(D11="",G11=""),"",D11*G11/100) | I11: =IF(H11="","",H11*'Activity Plan'!I11) | J11: =IF(H11="","",D11-H11) | L11: =IF(K11="","",(TODAY()-K11)/7) | M11: =IF(AND(L11<>"",L11>=2,G11<100),"AT RISK — no progress in 2+ weeks","") | N11: =IF(AND(F11<>"",TODAY()>F11,OR(G11="",G11<100)),D11-IF(H11="",0,H11),0) -> 0 | O11: =IF(N11>0,"ROLL OVER — create a new Election/Activity Plan entry for the shortfall","") | P11: =IF(M11<>"",C11,"")
A12: ='Activity Plan'!A12 -> 0 | B12: ='Activity Plan'!C12 -> T1-011 | C12: ='Activity Plan'!D12 -> Shade Material Preparation | D12: ='Activity Plan'!H12 -> 0 | E12: ='Annual Election'!E15 | F12: ='Annual Election'!H15 | H12: =IF(OR(D12="",G12=""),"",D12*G12/100) | I12: =IF(H12="","",H12*'Activity Plan'!I12) | J12: =IF(H12="","",D12-H12) | L12: =IF(K12="","",(TODAY()-K12)/7) | M12: =IF(AND(L12<>"",L12>=2,G12<100),"AT RISK — no progress in 2+ weeks","") | N12: =IF(AND(F12<>"",TODAY()>F12,OR(G12="",G12<100)),D12-IF(H12="",0,H12),0) -> 0 | O12: =IF(N12>0,"ROLL OVER — create a new Election/Activity Plan entry for the shortfall","") | P12: =IF(M12<>"",C12,"")
A13: ='Activity Plan'!A13 -> 0 | B13: ='Activity Plan'!C13 -> T1-012 | C13: ='Activity Plan'!D13 -> Shade Construction | D13: ='Activity Plan'!H13 -> 0 | E13: ='Annual Election'!E16 | F13: ='Annual Election'!H16 | H13: =IF(OR(D13="",G13=""),"",D13*G13/100) | I13: =IF(H13="","",H13*'Activity Plan'!I13) | J13: =IF(H13="","",D13-H13) | L13: =IF(K13="","",(TODAY()-K13)/7) | M13: =IF(AND(L13<>"",L13>=2,G13<100),"AT RISK — no progress in 2+ weeks","") | N13: =IF(AND(F13<>"",TODAY()>F13,OR(G13="",G13<100)),D13-IF(H13="",0,H13),0) -> 0 | O13: =IF(N13>0,"ROLL OVER — create a new Election/Activity Plan entry for the shortfall","") | P13: =IF(M13<>"",C13,"")
... A135: ='Activity Plan'!A135 -> 0 | B135: ='Activity Plan'!C135 -> T3-035 | C135: ='Activity Plan'!D135 -> Buyer Hosting at SpiralLabs | D135: ='Activity Plan'!H135 -> 0 | E135: ='Annual Election'!E138 -> 0 | F135: ='Annual Election'!H138 -> 0 | H135: =IF(OR(D135="",G135=""),"",D135*G135/100) | I135: =IF(H135="","",H135*'Activity Plan'!I135) | J135: =IF(H135="","",D135-H135) | L135: =IF(K135="","",(TODAY()-K135)/7) | M135: =IF(AND(L135<>"",L135>=2,G135<100),"AT RISK — no progress in 2+ weeks","") | N135: =IF(AND(F135<>"",TODAY()>F135,OR(G135="",G135<100)),D135-IF(H135="",0,H135),0) -> 0 | O135: =IF(N135>0,"ROLL OVER — create a new Election/Activity Plan entry for the shortfall","") | P135: =IF(M135<>"",C135,"")
A137: % Complete is entered by the field supervisor, weekly, against the Field Ticket record — not a guess. Update Last Movement Date by hand whenever % actually changes; the Stall Flag and rollover logic both depend on that date being kept current. Rollover Qty and Rollover Flag are calculated warnings, not automatic actions — plain formulas cannot create new rows on their own, so a flagged rollover still needs a new Annual Election / Activity Plan entry created by hand for the shortfall, in the next appropriate window.

Sheet Labor Budget
A1: Block ID | B1: Block Name | C1: Tier 1 — Core Services Labor Cost (ETB) | D1: Tier 2 — Projects Labor Cost (ETB) | E1: Tier 3 — Interventions Labor Cost (ETB) | F1: Block Total Labor Cost (ETB)
A2: =Master!A$6 -> 0 | B2: =Master!B$6 -> 0 | C2: =SUMIFS('Activity Plan'!$J$2:$J$135,'Activity Plan'!$A$2:$A$135,A2,'Activity Plan'!$E$2:$E$135,"Tier 1 — Core Services") -> 0 | D2: =SUMIFS('Activity Plan'!$J$2:$J$135,'Activity Plan'!$A$2:$A$135,A2,'Activity Plan'!$E$2:$E$135,"Tier 2 — Projects") -> 0 | E2: =SUMIFS('Activity Plan'!$J$2:$J$135,'Activity Plan'!$A$2:$A$135,A2,'Activity Plan'!$E$2:$E$135,"Tier 3 — Interventions") -> 0 | F2: =SUM(C2:E2) -> 0
B3: Farm Total | C3: =SUM(C2:C2) -> 0 | D3: =SUM(D2:D2) -> 0 | E3: =SUM(E2:E2) -> 0 | F3: =SUM(F2:F2) -> 0
A5: Add a row per block as Master grows; copy the formulas across.

Sheet Material Budget
A1: Block ID | B1: Activity ID | C1: Activity Name | D1: Material ID | E1: Material Norm (qty / activity unit) | F1: Material Rate (ETB / qty) | G1: Planned Activity Qty (from Activity Plan) | H1: Planned Material Qty | I1: Planned Material Cost (ETB) | J1: Window Start (helper) | K1: Window End (helper) | L1: Months Spanned (helper) | M1: Monthly Allocation (ETB, helper)
A2: =Master!A$6 -> 0 | C2: =IFERROR(INDEX('Activity List'!$D$2:$D$135,MATCH(B2,'Activity List'!$A$2:$A$135,0)),"") | F2: =IFERROR(INDEX('Material Rate Card'!$D$2:$D$11,MATCH(D2,'Material Rate Card'!$A$2:$A$11,0)),0) -> 0 | G2: =IFERROR(SUMIFS('Activity Plan'!$H$2:$H$135,'Activity Plan'!$A$2:$A$135,A2,'Activity Plan'!$C$2:$C$135,B2),0) -> 0 | H2: =G2*E2 -> 0 | I2: =H2*F2 -> 0 | J2: =IFERROR(INDEX('Annual Election'!$E$2:$E$138,MATCH(B2,'Annual Election'!$B$2:$B$138,0)),"") | K2: =IFERROR(INDEX('Annual Election'!$H$2:$H$138,MATCH(B2,'Annual Election'!$B$2:$B$138,0)),"") | L2: =IF(OR(J2="",K2=""),"",DATEDIF(J2,K2,"m")+1) | M2: =IF(OR(I2="",L2="",L2=0),0,I2/L2) -> 0
A3: =Master!A$6 -> 0 | C3: =IFERROR(INDEX('Activity List'!$D$2:$D$135,MATCH(B3,'Activity List'!$A$2:$A$135,0)),"") | F3: =IFERROR(INDEX('Material Rate Card'!$D$2:$D$11,MATCH(D3,'Material Rate Card'!$A$2:$A$11,0)),0) -> 0 | G3: =IFERROR(SUMIFS('Activity Plan'!$H$2:$H$135,'Activity Plan'!$A$2:$A$135,A3,'Activity Plan'!$C$2:$C$135,B3),0) -> 0 | H3: =G3*E3 -> 0 | I3: =H3*F3 -> 0 | J3: =IFERROR(INDEX('Annual Election'!$E$2:$E$138,MATCH(B3,'Annual Election'!$B$2:$B$138,0)),"") | K3: =IFERROR(INDEX('Annual Election'!$H$2:$H$138,MATCH(B3,'Annual Election'!$B$2:$B$138,0)),"") | L3: =IF(OR(J3="",K3=""),"",DATEDIF(J3,K3,"m")+1) | M3: =IF(OR(I3="",L3="",L3=0),0,I3/L3) -> 0
A4: =Master!A$6 -> 0 | C4: =IFERROR(INDEX('Activity List'!$D$2:$D$135,MATCH(B4,'Activity List'!$A$2:$A$135,0)),"") | F4: =IFERROR(INDEX('Material Rate Card'!$D$2:$D$11,MATCH(D4,'Material Rate Card'!$A$2:$A$11,0)),0) -> 0 | G4: =IFERROR(SUMIFS('Activity Plan'!$H$2:$H$135,'Activity Plan'!$A$2:$A$135,A4,'Activity Plan'!$C$2:$C$135,B4),0) -> 0 | H4: =G4*E4 -> 0 | I4: =H4*F4 -> 0 | J4: =IFERROR(INDEX('Annual Election'!$E$2:$E$138,MATCH(B4,'Annual Election'!$B$2:$B$138,0)),"") | K4: =IFERROR(INDEX('Annual Election'!$H$2:$H$138,MATCH(B4,'Annual Election'!$B$2:$B$138,0)),"") | L4: =IF(OR(J4="",K4=""),"",DATEDIF(J4,K4,"m")+1) | M4: =IF(OR(I4="",L4="",L4=0),0,I4/L4) -> 0
A5: =Master!A$6 -> 0 | C5: =IFERROR(INDEX('Activity List'!$D$2:$D$135,MATCH(B5,'Activity List'!$A$2:$A$135,0)),"") | F5: =IFERROR(INDEX('Material Rate Card'!$D$2:$D$11,MATCH(D5,'Material Rate Card'!$A$2:$A$11,0)),0) -> 0 | G5: =IFERROR(SUMIFS('Activity Plan'!$H$2:$H$135,'Activity Plan'!$A$2:$A$135,A5,'Activity Plan'!$C$2:$C$135,B5),0) -> 0 | H5: =G5*E5 -> 0 | I5: =H5*F5 -> 0 | J5: =IFERROR(INDEX('Annual Election'!$E$2:$E$138,MATCH(B5,'Annual Election'!$B$2:$B$138,0)),"") | K5: =IFERROR(INDEX('Annual Election'!$H$2:$H$138,MATCH(B5,'Annual Election'!$B$2:$B$138,0)),"") | L5: =IF(OR(J5="",K5=""),"",DATEDIF(J5,K5,"m")+1) | M5: =IF(OR(I5="",L5="",L5=0),0,I5/L5) -> 0
A6: =Master!A$6 -> 0 | C6: =IFERROR(INDEX('Activity List'!$D$2:$D$135,MATCH(B6,'Activity List'!$A$2:$A$135,0)),"") | F6: =IFERROR(INDEX('Material Rate Card'!$D$2:$D$11,MATCH(D6,'Material Rate Card'!$A$2:$A$11,0)),0) -> 0 | G6: =IFERROR(SUMIFS('Activity Plan'!$H$2:$H$135,'Activity Plan'!$A$2:$A$135,A6,'Activity Plan'!$C$2:$C$135,B6),0) -> 0 | H6: =G6*E6 -> 0 | I6: =H6*F6 -> 0 | J6: =IFERROR(INDEX('Annual Election'!$E$2:$E$138,MATCH(B6,'Annual Election'!$B$2:$B$138,0)),"") | K6: =IFERROR(INDEX('Annual Election'!$H$2:$H$138,MATCH(B6,'Annual Election'!$B$2:$B$138,0)),"") | L6: =IF(OR(J6="",K6=""),"",DATEDIF(J6,K6,"m")+1) | M6: =IF(OR(I6="",L6="",L6=0),0,I6/L6) -> 0
A7: =Master!A$6 -> 0 | C7: =IFERROR(INDEX('Activity List'!$D$2:$D$135,MATCH(B7,'Activity List'!$A$2:$A$135,0)),"") | F7: =IFERROR(INDEX('Material Rate Card'!$D$2:$D$11,MATCH(D7,'Material Rate Card'!$A$2:$A$11,0)),0) -> 0 | G7: =IFERROR(SUMIFS('Activity Plan'!$H$2:$H$135,'Activity Plan'!$A$2:$A$135,A7,'Activity Plan'!$C$2:$C$135,B7),0) -> 0 | H7: =G7*E7 -> 0 | I7: =H7*F7 -> 0 | J7: =IFERROR(INDEX('Annual Election'!$E$2:$E$138,MATCH(B7,'Annual Election'!$B$2:$B$138,0)),"") | K7: =IFERROR(INDEX('Annual Election'!$H$2:$H$138,MATCH(B7,'Annual Election'!$B$2:$B$138,0)),"") | L7: =IF(OR(J7="",K7=""),"",DATEDIF(J7,K7,"m")+1) | M7: =IF(OR(I7="",L7="",L7=0),0,I7/L7) -> 0
A8: =Master!A$6 -> 0 | C8: =IFERROR(INDEX('Activity List'!$D$2:$D$135,MATCH(B8,'Activity List'!$A$2:$A$135,0)),"") | F8: =IFERROR(INDEX('Material Rate Card'!$D$2:$D$11,MATCH(D8,'Material Rate Card'!$A$2:$A$11,0)),0) -> 0 | G8: =IFERROR(SUMIFS('Activity Plan'!$H$2:$H$135,'Activity Plan'!$A$2:$A$135,A8,'Activity Plan'!$C$2:$C$135,B8),0) -> 0 | H8: =G8*E8 -> 0 | I8: =H8*F8 -> 0 | J8: =IFERROR(INDEX('Annual Election'!$E$2:$E$138,MATCH(B8,'Annual Election'!$B$2:$B$138,0)),"") | K8: =IFERROR(INDEX('Annual Election'!$H$2:$H$138,MATCH(B8,'Annual Election'!$B$2:$B$138,0)),"") | L8: =IF(OR(J8="",K8=""),"",DATEDIF(J8,K8,"m")+1) | M8: =IF(OR(I8="",L8="",L8=0),0,I8/L8) -> 0
A9: =Master!A$6 -> 0 | C9: =IFERROR(INDEX('Activity List'!$D$2:$D$135,MATCH(B9,'Activity List'!$A$2:$A$135,0)),"") | F9: =IFERROR(INDEX('Material Rate Card'!$D$2:$D$11,MATCH(D9,'Material Rate Card'!$A$2:$A$11,0)),0) -> 0 | G9: =IFERROR(SUMIFS('Activity Plan'!$H$2:$H$135,'Activity Plan'!$A$2:$A$135,A9,'Activity Plan'!$C$2:$C$135,B9),0) -> 0 | H9: =G9*E9 -> 0 | I9: =H9*F9 -> 0 | J9: =IFERROR(INDEX('Annual Election'!$E$2:$E$138,MATCH(B9,'Annual Election'!$B$2:$B$138,0)),"") | K9: =IFERROR(INDEX('Annual Election'!$H$2:$H$138,MATCH(B9,'Annual Election'!$B$2:$B$138,0)),"") | L9: =IF(OR(J9="",K9=""),"",DATEDIF(J9,K9,"m")+1) | M9: =IF(OR(I9="",L9="",L9=0),0,I9/L9) -> 0
A10: =Master!A$6 -> 0 | C10: =IFERROR(INDEX('Activity List'!$D$2:$D$135,MATCH(B10,'Activity List'!$A$2:$A$135,0)),"") | F10: =IFERROR(INDEX('Material Rate Card'!$D$2:$D$11,MATCH(D10,'Material Rate Card'!$A$2:$A$11,0)),0) -> 0 | G10: =IFERROR(SUMIFS('Activity Plan'!$H$2:$H$135,'Activity Plan'!$A$2:$A$135,A10,'Activity Plan'!$C$2:$C$135,B10),0) -> 0 | H10: =G10*E10 -> 0 | I10: =H10*F10 -> 0 | J10: =IFERROR(INDEX('Annual Election'!$E$2:$E$138,MATCH(B10,'Annual Election'!$B$2:$B$138,0)),"") | K10: =IFERROR(INDEX('Annual Election'!$H$2:$H$138,MATCH(B10,'Annual Election'!$B$2:$B$138,0)),"") | L10: =IF(OR(J10="",K10=""),"",DATEDIF(J10,K10,"m")+1) | M10: =IF(OR(I10="",L10="",L10=0),0,I10/L10) -> 0
A11: =Master!A$6 -> 0 | C11: =IFERROR(INDEX('Activity List'!$D$2:$D$135,MATCH(B11,'Activity List'!$A$2:$A$135,0)),"") | F11: =IFERROR(INDEX('Material Rate Card'!$D$2:$D$11,MATCH(D11,'Material Rate Card'!$A$2:$A$11,0)),0) -> 0 | G11: =IFERROR(SUMIFS('Activity Plan'!$H$2:$H$135,'Activity Plan'!$A$2:$A$135,A11,'Activity Plan'!$C$2:$C$135,B11),0) -> 0 | H11: =G11*E11 -> 0 | I11: =H11*F11 -> 0 | J11: =IFERROR(INDEX('Annual Election'!$E$2:$E$138,MATCH(B11,'Annual Election'!$B$2:$B$138,0)),"") | K11: =IFERROR(INDEX('Annual Election'!$H$2:$H$138,MATCH(B11,'Annual Election'!$B$2:$B$138,0)),"") | L11: =IF(OR(J11="",K11=""),"",DATEDIF(J11,K11,"m")+1) | M11: =IF(OR(I11="",L11="",L11=0),0,I11/L11) -> 0
A13: Add one row per activity-material link, entering the Activity ID and its consumption norm. Columns J-M (Window Start/End, Months Spanned, Monthly Allocation) are helper columns feeding the Monthly Cost Summary — they read the activity's window straight from Annual Election.

Sheet Service Budget
A1: Block ID | B1: Activity ID | C1: Activity Name | D1: Service ID | E1: Service Norm (qty / activity unit) | F1: Service Rate (ETB / qty) | G1: Planned Activity Qty (from Activity Plan) | H1: Planned Service Qty | I1: Planned Service Cost (ETB) | J1: Window Start (helper) | K1: Window End (helper) | L1: Months Spanned (helper) | M1: Monthly Allocation (ETB, helper)
A2: =Master!A$6 -> 0 | C2: =IFERROR(INDEX('Activity List'!$D$2:$D$135,MATCH(B2,'Activity List'!$A$2:$A$135,0)),"") | F2: =IFERROR(INDEX('Outsourced Services Rate Card'!$D$2:$D$11,MATCH(D2,'Outsourced Services Rate Card'!$A$2:$A$11,0)),0) -> 0 | G2: =IFERROR(SUMIFS('Activity Plan'!$H$2:$H$135,'Activity Plan'!$A$2:$A$135,A2,'Activity Plan'!$C$2:$C$135,B2),0) -> 0 | H2: =G2*E2 -> 0 | I2: =H2*F2 -> 0 | J2: =IFERROR(INDEX('Annual Election'!$E$2:$E$138,MATCH(B2,'Annual Election'!$B$2:$B$138,0)),"") | K2: =IFERROR(INDEX('Annual Election'!$H$2:$H$138,MATCH(B2,'Annual Election'!$B$2:$B$138,0)),"") | L2: =IF(OR(J2="",K2=""),"",DATEDIF(J2,K2,"m")+1) | M2: =IF(OR(I2="",L2="",L2=0),0,I2/L2) -> 0
A3: =Master!A$6 -> 0 | C3: =IFERROR(INDEX('Activity List'!$D$2:$D$135,MATCH(B3,'Activity List'!$A$2:$A$135,0)),"") | F3: =IFERROR(INDEX('Outsourced Services Rate Card'!$D$2:$D$11,MATCH(D3,'Outsourced Services Rate Card'!$A$2:$A$11,0)),0) -> 0 | G3: =IFERROR(SUMIFS('Activity Plan'!$H$2:$H$135,'Activity Plan'!$A$2:$A$135,A3,'Activity Plan'!$C$2:$C$135,B3),0) -> 0 | H3: =G3*E3 -> 0 | I3: =H3*F3 -> 0 | J3: =IFERROR(INDEX('Annual Election'!$E$2:$E$138,MATCH(B3,'Annual Election'!$B$2:$B$138,0)),"") | K3: =IFERROR(INDEX('Annual Election'!$H$2:$H$138,MATCH(B3,'Annual Election'!$B$2:$B$138,0)),"") | L3: =IF(OR(J3="",K3=""),"",DATEDIF(J3,K3,"m")+1) | M3: =IF(OR(I3="",L3="",L3=0),0,I3/L3) -> 0
A4: =Master!A$6 -> 0 | C4: =IFERROR(INDEX('Activity List'!$D$2:$D$135,MATCH(B4,'Activity List'!$A$2:$A$135,0)),"") | F4: =IFERROR(INDEX('Outsourced Services Rate Card'!$D$2:$D$11,MATCH(D4,'Outsourced Services Rate Card'!$A$2:$A$11,0)),0) -> 0 | G4: =IFERROR(SUMIFS('Activity Plan'!$H$2:$H$135,'Activity Plan'!$A$2:$A$135,A4,'Activity Plan'!$C$2:$C$135,B4),0) -> 0 | H4: =G4*E4 -> 0 | I4: =H4*F4 -> 0 | J4: =IFERROR(INDEX('Annual Election'!$E$2:$E$138,MATCH(B4,'Annual Election'!$B$2:$B$138,0)),"") | K4: =IFERROR(INDEX('Annual Election'!$H$2:$H$138,MATCH(B4,'Annual Election'!$B$2:$B$138,0)),"") | L4: =IF(OR(J4="",K4=""),"",DATEDIF(J4,K4,"m")+1) | M4: =IF(OR(I4="",L4="",L4=0),0,I4/L4) -> 0
A5: =Master!A$6 -> 0 | C5: =IFERROR(INDEX('Activity List'!$D$2:$D$135,MATCH(B5,'Activity List'!$A$2:$A$135,0)),"") | F5: =IFERROR(INDEX('Outsourced Services Rate Card'!$D$2:$D$11,MATCH(D5,'Outsourced Services Rate Card'!$A$2:$A$11,0)),0) -> 0 | G5: =IFERROR(SUMIFS('Activity Plan'!$H$2:$H$135,'Activity Plan'!$A$2:$A$135,A5,'Activity Plan'!$C$2:$C$135,B5),0) -> 0 | H5: =G5*E5 -> 0 | I5: =H5*F5 -> 0 | J5: =IFERROR(INDEX('Annual Election'!$E$2:$E$138,MATCH(B5,'Annual Election'!$B$2:$B$138,0)),"") | K5: =IFERROR(INDEX('Annual Election'!$H$2:$H$138,MATCH(B5,'Annual Election'!$B$2:$B$138,0)),"") | L5: =IF(OR(J5="",K5=""),"",DATEDIF(J5,K5,"m")+1) | M5: =IF(OR(I5="",L5="",L5=0),0,I5/L5) -> 0
A6: =Master!A$6 -> 0 | C6: =IFERROR(INDEX('Activity List'!$D$2:$D$135,MATCH(B6,'Activity List'!$A$2:$A$135,0)),"") | F6: =IFERROR(INDEX('Outsourced Services Rate Card'!$D$2:$D$11,MATCH(D6,'Outsourced Services Rate Card'!$A$2:$A$11,0)),0) -> 0 | G6: =IFERROR(SUMIFS('Activity Plan'!$H$2:$H$135,'Activity Plan'!$A$2:$A$135,A6,'Activity Plan'!$C$2:$C$135,B6),0) -> 0 | H6: =G6*E6 -> 0 | I6: =H6*F6 -> 0 | J6: =IFERROR(INDEX('Annual Election'!$E$2:$E$138,MATCH(B6,'Annual Election'!$B$2:$B$138,0)),"") | K6: =IFERROR(INDEX('Annual Election'!$H$2:$H$138,MATCH(B6,'Annual Election'!$B$2:$B$138,0)),"") | L6: =IF(OR(J6="",K6=""),"",DATEDIF(J6,K6,"m")+1) | M6: =IF(OR(I6="",L6="",L6=0),0,I6/L6) -> 0
A7: =Master!A$6 -> 0 | C7: =IFERROR(INDEX('Activity List'!$D$2:$D$135,MATCH(B7,'Activity List'!$A$2:$A$135,0)),"") | F7: =IFERROR(INDEX('Outsourced Services Rate Card'!$D$2:$D$11,MATCH(D7,'Outsourced Services Rate Card'!$A$2:$A$11,0)),0) -> 0 | G7: =IFERROR(SUMIFS('Activity Plan'!$H$2:$H$135,'Activity Plan'!$A$2:$A$135,A7,'Activity Plan'!$C$2:$C$135,B7),0) -> 0 | H7: =G7*E7 -> 0 | I7: =H7*F7 -> 0 | J7: =IFERROR(INDEX('Annual Election'!$E$2:$E$138,MATCH(B7,'Annual Election'!$B$2:$B$138,0)),"") | K7: =IFERROR(INDEX('Annual Election'!$H$2:$H$138,MATCH(B7,'Annual Election'!$B$2:$B$138,0)),"") | L7: =IF(OR(J7="",K7=""),"",DATEDIF(J7,K7,"m")+1) | M7: =IF(OR(I7="",L7="",L7=0),0,I7/L7) -> 0
A8: =Master!A$6 -> 0 | C8: =IFERROR(INDEX('Activity List'!$D$2:$D$135,MATCH(B8,'Activity List'!$A$2:$A$135,0)),"") | F8: =IFERROR(INDEX('Outsourced Services Rate Card'!$D$2:$D$11,MATCH(D8,'Outsourced Services Rate Card'!$A$2:$A$11,0)),0) -> 0 | G8: =IFERROR(SUMIFS('Activity Plan'!$H$2:$H$135,'Activity Plan'!$A$2:$A$135,A8,'Activity Plan'!$C$2:$C$135,B8),0) -> 0 | H8: =G8*E8 -> 0 | I8: =H8*F8 -> 0 | J8: =IFERROR(INDEX('Annual Election'!$E$2:$E$138,MATCH(B8,'Annual Election'!$B$2:$B$138,0)),"") | K8: =IFERROR(INDEX('Annual Election'!$H$2:$H$138,MATCH(B8,'Annual Election'!$B$2:$B$138,0)),"") | L8: =IF(OR(J8="",K8=""),"",DATEDIF(J8,K8,"m")+1) | M8: =IF(OR(I8="",L8="",L8=0),0,I8/L8) -> 0
A9: =Master!A$6 -> 0 | C9: =IFERROR(INDEX('Activity List'!$D$2:$D$135,MATCH(B9,'Activity List'!$A$2:$A$135,0)),"") | F9: =IFERROR(INDEX('Outsourced Services Rate Card'!$D$2:$D$11,MATCH(D9,'Outsourced Services Rate Card'!$A$2:$A$11,0)),0) -> 0 | G9: =IFERROR(SUMIFS('Activity Plan'!$H$2:$H$135,'Activity Plan'!$A$2:$A$135,A9,'Activity Plan'!$C$2:$C$135,B9),0) -> 0 | H9: =G9*E9 -> 0 | I9: =H9*F9 -> 0 | J9: =IFERROR(INDEX('Annual Election'!$E$2:$E$138,MATCH(B9,'Annual Election'!$B$2:$B$138,0)),"") | K9: =IFERROR(INDEX('Annual Election'!$H$2:$H$138,MATCH(B9,'Annual Election'!$B$2:$B$138,0)),"") | L9: =IF(OR(J9="",K9=""),"",DATEDIF(J9,K9,"m")+1) | M9: =IF(OR(I9="",L9="",L9=0),0,I9/L9) -> 0
A10: =Master!A$6 -> 0 | C10: =IFERROR(INDEX('Activity List'!$D$2:$D$135,MATCH(B10,'Activity List'!$A$2:$A$135,0)),"") | F10: =IFERROR(INDEX('Outsourced Services Rate Card'!$D$2:$D$11,MATCH(D10,'Outsourced Services Rate Card'!$A$2:$A$11,0)),0) -> 0 | G10: =IFERROR(SUMIFS('Activity Plan'!$H$2:$H$135,'Activity Plan'!$A$2:$A$135,A10,'Activity Plan'!$C$2:$C$135,B10),0) -> 0 | H10: =G10*E10 -> 0 | I10: =H10*F10 -> 0 | J10: =IFERROR(INDEX('Annual Election'!$E$2:$E$138,MATCH(B10,'Annual Election'!$B$2:$B$138,0)),"") | K10: =IFERROR(INDEX('Annual Election'!$H$2:$H$138,MATCH(B10,'Annual Election'!$B$2:$B$138,0)),"") | L10: =IF(OR(J10="",K10=""),"",DATEDIF(J10,K10,"m")+1) | M10: =IF(OR(I10="",L10="",L10=0),0,I10/L10) -> 0
A11: =Master!A$6 -> 0 | C11: =IFERROR(INDEX('Activity List'!$D$2:$D$135,MATCH(B11,'Activity List'!$A$2:$A$135,0)),"") | F11: =IFERROR(INDEX('Outsourced Services Rate Card'!$D$2:$D$11,MATCH(D11,'Outsourced Services Rate Card'!$A$2:$A$11,0)),0) -> 0 | G11: =IFERROR(SUMIFS('Activity Plan'!$H$2:$H$135,'Activity Plan'!$A$2:$A$135,A11,'Activity Plan'!$C$2:$C$135,B11),0) -> 0 | H11: =G11*E11 -> 0 | I11: =H11*F11 -> 0 | J11: =IFERROR(INDEX('Annual Election'!$E$2:$E$138,MATCH(B11,'Annual Election'!$B$2:$B$138,0)),"") | K11: =IFERROR(INDEX('Annual Election'!$H$2:$H$138,MATCH(B11,'Annual Election'!$B$2:$B$138,0)),"") | L11: =IF(OR(J11="",K11=""),"",DATEDIF(J11,K11,"m")+1) | M11: =IF(OR(I11="",L11="",L11=0),0,I11/L11) -> 0
A13: Add one row per activity-service link, entering the Activity ID and its consumption norm. Columns J-M are helper columns feeding the Monthly Cost Summary.

Sheet Monthly Cost Summary
A1: Month # | B1: Month | C1: Material Cost (ETB) | D1: Service Cost (ETB) | E1: Total Inputs + Services (ETB)
A2: 1 | B2: =IF(Master!$B$3="","",EDATE(Master!$B$3,0)) | C2: =IF(B2="",0,SUMPRODUCT(('Material Budget'!$J$2:$J$11<=EOMONTH(B2,0))*('Material Budget'!$K$2:$K$11>=EOMONTH(B2,-1)+1)*'Material Budget'!$M$2:$M$11)) -> 0 | D2: =IF(B2="",0,SUMPRODUCT(('Service Budget'!$J$2:$J$11<=EOMONTH(B2,0))*('Service Budget'!$K$2:$K$11>=EOMONTH(B2,-1)+1)*'Service Budget'!$M$2:$M$11)) -> 0 | E2: =C2+D2 -> 0
A3: 2 | B3: =IF(Master!$B$3="","",EDATE(Master!$B$3,1)) | C3: =IF(B3="",0,SUMPRODUCT(('Material Budget'!$J$2:$J$11<=EOMONTH(B3,0))*('Material Budget'!$K$2:$K$11>=EOMONTH(B3,-1)+1)*'Material Budget'!$M$2:$M$11)) -> 0 | D3: =IF(B3="",0,SUMPRODUCT(('Service Budget'!$J$2:$J$11<=EOMONTH(B3,0))*('Service Budget'!$K$2:$K$11>=EOMONTH(B3,-1)+1)*'Service Budget'!$M$2:$M$11)) -> 0 | E3: =C3+D3 -> 0
A4: 3 | B4: =IF(Master!$B$3="","",EDATE(Master!$B$3,2)) | C4: =IF(B4="",0,SUMPRODUCT(('Material Budget'!$J$2:$J$11<=EOMONTH(B4,0))*('Material Budget'!$K$2:$K$11>=EOMONTH(B4,-1)+1)*'Material Budget'!$M$2:$M$11)) -> 0 | D4: =IF(B4="",0,SUMPRODUCT(('Service Budget'!$J$2:$J$11<=EOMONTH(B4,0))*('Service Budget'!$K$2:$K$11>=EOMONTH(B4,-1)+1)*'Service Budget'!$M$2:$M$11)) -> 0 | E4: =C4+D4 -> 0
A5: 4 | B5: =IF(Master!$B$3="","",EDATE(Master!$B$3,3)) | C5: =IF(B5="",0,SUMPRODUCT(('Material Budget'!$J$2:$J$11<=EOMONTH(B5,0))*('Material Budget'!$K$2:$K$11>=EOMONTH(B5,-1)+1)*'Material Budget'!$M$2:$M$11)) -> 0 | D5: =IF(B5="",0,SUMPRODUCT(('Service Budget'!$J$2:$J$11<=EOMONTH(B5,0))*('Service Budget'!$K$2:$K$11>=EOMONTH(B5,-1)+1)*'Service Budget'!$M$2:$M$11)) -> 0 | E5: =C5+D5 -> 0
A6: 5 | B6: =IF(Master!$B$3="","",EDATE(Master!$B$3,4)) | C6: =IF(B6="",0,SUMPRODUCT(('Material Budget'!$J$2:$J$11<=EOMONTH(B6,0))*('Material Budget'!$K$2:$K$11>=EOMONTH(B6,-1)+1)*'Material Budget'!$M$2:$M$11)) -> 0 | D6: =IF(B6="",0,SUMPRODUCT(('Service Budget'!$J$2:$J$11<=EOMONTH(B6,0))*('Service Budget'!$K$2:$K$11>=EOMONTH(B6,-1)+1)*'Service Budget'!$M$2:$M$11)) -> 0 | E6: =C6+D6 -> 0
A7: 6 | B7: =IF(Master!$B$3="","",EDATE(Master!$B$3,5)) | C7: =IF(B7="",0,SUMPRODUCT(('Material Budget'!$J$2:$J$11<=EOMONTH(B7,0))*('Material Budget'!$K$2:$K$11>=EOMONTH(B7,-1)+1)*'Material Budget'!$M$2:$M$11)) -> 0 | D7: =IF(B7="",0,SUMPRODUCT(('Service Budget'!$J$2:$J$11<=EOMONTH(B7,0))*('Service Budget'!$K$2:$K$11>=EOMONTH(B7,-1)+1)*'Service Budget'!$M$2:$M$11)) -> 0 | E7: =C7+D7 -> 0
A8: 7 | B8: =IF(Master!$B$3="","",EDATE(Master!$B$3,6)) | C8: =IF(B8="",0,SUMPRODUCT(('Material Budget'!$J$2:$J$11<=EOMONTH(B8,0))*('Material Budget'!$K$2:$K$11>=EOMONTH(B8,-1)+1)*'Material Budget'!$M$2:$M$11)) -> 0 | D8: =IF(B8="",0,SUMPRODUCT(('Service Budget'!$J$2:$J$11<=EOMONTH(B8,0))*('Service Budget'!$K$2:$K$11>=EOMONTH(B8,-1)+1)*'Service Budget'!$M$2:$M$11)) -> 0 | E8: =C8+D8 -> 0
A9: 8 | B9: =IF(Master!$B$3="","",EDATE(Master!$B$3,7)) | C9: =IF(B9="",0,SUMPRODUCT(('Material Budget'!$J$2:$J$11<=EOMONTH(B9,0))*('Material Budget'!$K$2:$K$11>=EOMONTH(B9,-1)+1)*'Material Budget'!$M$2:$M$11)) -> 0 | D9: =IF(B9="",0,SUMPRODUCT(('Service Budget'!$J$2:$J$11<=EOMONTH(B9,0))*('Service Budget'!$K$2:$K$11>=EOMONTH(B9,-1)+1)*'Service Budget'!$M$2:$M$11)) -> 0 | E9: =C9+D9 -> 0
A10: 9 | B10: =IF(Master!$B$3="","",EDATE(Master!$B$3,8)) | C10: =IF(B10="",0,SUMPRODUCT(('Material Budget'!$J$2:$J$11<=EOMONTH(B10,0))*('Material Budget'!$K$2:$K$11>=EOMONTH(B10,-1)+1)*'Material Budget'!$M$2:$M$11)) -> 0 | D10: =IF(B10="",0,SUMPRODUCT(('Service Budget'!$J$2:$J$11<=EOMONTH(B10,0))*('Service Budget'!$K$2:$K$11>=EOMONTH(B10,-1)+1)*'Service Budget'!$M$2:$M$11)) -> 0 | E10: =C10+D10 -> 0
A11: 10 | B11: =IF(Master!$B$3="","",EDATE(Master!$B$3,9)) | C11: =IF(B11="",0,SUMPRODUCT(('Material Budget'!$J$2:$J$11<=EOMONTH(B11,0))*('Material Budget'!$K$2:$K$11>=EOMONTH(B11,-1)+1)*'Material Budget'!$M$2:$M$11)) -> 0 | D11: =IF(B11="",0,SUMPRODUCT(('Service Budget'!$J$2:$J$11<=EOMONTH(B11,0))*('Service Budget'!$K$2:$K$11>=EOMONTH(B11,-1)+1)*'Service Budget'!$M$2:$M$11)) -> 0 | E11: =C11+D11 -> 0
A12: 11 | B12: =IF(Master!$B$3="","",EDATE(Master!$B$3,10)) | C12: =IF(B12="",0,SUMPRODUCT(('Material Budget'!$J$2:$J$11<=EOMONTH(B12,0))*('Material Budget'!$K$2:$K$11>=EOMONTH(B12,-1)+1)*'Material Budget'!$M$2:$M$11)) -> 0 | D12: =IF(B12="",0,SUMPRODUCT(('Service Budget'!$J$2:$J$11<=EOMONTH(B12,0))*('Service Budget'!$K$2:$K$11>=EOMONTH(B12,-1)+1)*'Service Budget'!$M$2:$M$11)) -> 0 | E12: =C12+D12 -> 0
A13: 12 | B13: =IF(Master!$B$3="","",EDATE(Master!$B$3,11)) | C13: =IF(B13="",0,SUMPRODUCT(('Material Budget'!$J$2:$J$11<=EOMONTH(B13,0))*('Material Budget'!$K$2:$K$11>=EOMONTH(B13,-1)+1)*'Material Budget'!$M$2:$M$11)) -> 0 | D13: =IF(B13="",0,SUMPRODUCT(('Service Budget'!$J$2:$J$11<=EOMONTH(B13,0))*('Service Budget'!$K$2:$K$11>=EOMONTH(B13,-1)+1)*'Service Budget'!$M$2:$M$11)) -> 0 | E13: =C13+D13 -> 0
B14: Year Total | C14: =SUM(C2:C13) -> 0 | D14: =SUM(D2:D13) -> 0 | E14: =SUM(E2:E13) -> 0
A16: Each Material/Service Budget row's cost is spread evenly across the months its activity window touches (the Monthly Allocation helper column), then summed here by month. This treats materials and services as monthly figures, matching how they're actually ordered and engaged — never given a false weekly precision.

Sheet Weekly Cash Flow
A1: Weekly Cash Flow — Year 1
A2: Labor is real weekly cost, prorated across each ticked activity's own window. Inputs and services are monthly figures (Monthly Cost Summary) split evenly across the weeks that fall in each month — an honest cash-flow allocation, not fabricated weekly precision. Use the cumulative column to size the Project Account reserve.
A4: Week # | B4: Week Start | C4: Week End | D4: Labor Cost (ETB) | E4: Inputs + Services Cost (ETB) | F4: Total Weekly Cost (ETB) | G4: Cumulative Total (ETB)
A5: 1 | B5: =IF(Master!$B$3="","",Master!$B$3+(0*7)) | C5: =IF(B5="","",MIN(B5+6,Master!$B$3+364)) | D5: =IF(B5="",0,SUMPRODUCT(('Activity Plan'!$K$2:$K$135<=C5)*('Activity Plan'!$L$2:$L$135>=B5)*'Activity Plan'!$N$2:$N$135)) -> 0 | E5: =IF(B5="",0,IFERROR(INDEX('Monthly Cost Summary'!$E$2:$E$13,MATCH(TEXT(B5,"yyyymm"),TEXT('Monthly Cost Summary'!$B$2:$B$13,"yyyymm"),0))/COUNTIFS('Weekly Cash Flow'!$B$5:$B$57,">="&EOMONTH(B5,-1)+1,'Weekly Cash Flow'!$B$5:$B$57,"<="&EOMONTH(B5,0)),0)) -> 0 | F5: =D5+E5 -> 0 | G5: =F5 -> 0
A6: 2 | B6: =IF(Master!$B$3="","",Master!$B$3+(1*7)) | C6: =IF(B6="","",MIN(B6+6,Master!$B$3+364)) | D6: =IF(B6="",0,SUMPRODUCT(('Activity Plan'!$K$2:$K$135<=C6)*('Activity Plan'!$L$2:$L$135>=B6)*'Activity Plan'!$N$2:$N$135)) -> 0 | E6: =IF(B6="",0,IFERROR(INDEX('Monthly Cost Summary'!$E$2:$E$13,MATCH(TEXT(B6,"yyyymm"),TEXT('Monthly Cost Summary'!$B$2:$B$13,"yyyymm"),0))/COUNTIFS('Weekly Cash Flow'!$B$5:$B$57,">="&EOMONTH(B6,-1)+1,'Weekly Cash Flow'!$B$5:$B$57,"<="&EOMONTH(B6,0)),0)) -> 0 | F6: =D6+E6 -> 0 | G6: =G5+F6 -> 0
A7: 3 | B7: =IF(Master!$B$3="","",Master!$B$3+(2*7)) | C7: =IF(B7="","",MIN(B7+6,Master!$B$3+364)) | D7: =IF(B7="",0,SUMPRODUCT(('Activity Plan'!$K$2:$K$135<=C7)*('Activity Plan'!$L$2:$L$135>=B7)*'Activity Plan'!$N$2:$N$135)) -> 0 | E7: =IF(B7="",0,IFERROR(INDEX('Monthly Cost Summary'!$E$2:$E$13,MATCH(TEXT(B7,"yyyymm"),TEXT('Monthly Cost Summary'!$B$2:$B$13,"yyyymm"),0))/COUNTIFS('Weekly Cash Flow'!$B$5:$B$57,">="&EOMONTH(B7,-1)+1,'Weekly Cash Flow'!$B$5:$B$57,"<="&EOMONTH(B7,0)),0)) -> 0 | F7: =D7+E7 -> 0 | G7: =G6+F7 -> 0
A8: 4 | B8: =IF(Master!$B$3="","",Master!$B$3+(3*7)) | C8: =IF(B8="","",MIN(B8+6,Master!$B$3+364)) | D8: =IF(B8="",0,SUMPRODUCT(('Activity Plan'!$K$2:$K$135<=C8)*('Activity Plan'!$L$2:$L$135>=B8)*'Activity Plan'!$N$2:$N$135)) -> 0 | E8: =IF(B8="",0,IFERROR(INDEX('Monthly Cost Summary'!$E$2:$E$13,MATCH(TEXT(B8,"yyyymm"),TEXT('Monthly Cost Summary'!$B$2:$B$13,"yyyymm"),0))/COUNTIFS('Weekly Cash Flow'!$B$5:$B$57,">="&EOMONTH(B8,-1)+1,'Weekly Cash Flow'!$B$5:$B$57,"<="&EOMONTH(B8,0)),0)) -> 0 | F8: =D8+E8 -> 0 | G8: =G7+F8 -> 0
A9: 5 | B9: =IF(Master!$B$3="","",Master!$B$3+(4*7)) | C9: =IF(B9="","",MIN(B9+6,Master!$B$3+364)) | D9: =IF(B9="",0,SUMPRODUCT(('Activity Plan'!$K$2:$K$135<=C9)*('Activity Plan'!$L$2:$L$135>=B9)*'Activity Plan'!$N$2:$N$135)) -> 0 | E9: =IF(B9="",0,IFERROR(INDEX('Monthly Cost Summary'!$E$2:$E$13,MATCH(TEXT(B9,"yyyymm"),TEXT('Monthly Cost Summary'!$B$2:$B$13,"yyyymm"),0))/COUNTIFS('Weekly Cash Flow'!$B$5:$B$57,">="&EOMONTH(B9,-1)+1,'Weekly Cash Flow'!$B$5:$B$57,"<="&EOMONTH(B9,0)),0)) -> 0 | F9: =D9+E9 -> 0 | G9: =G8+F9 -> 0
A10: 6 | B10: =IF(Master!$B$3="","",Master!$B$3+(5*7)) | C10: =IF(B10="","",MIN(B10+6,Master!$B$3+364)) | D10: =IF(B10="",0,SUMPRODUCT(('Activity Plan'!$K$2:$K$135<=C10)*('Activity Plan'!$L$2:$L$135>=B10)*'Activity Plan'!$N$2:$N$135)) -> 0 | E10: =IF(B10="",0,IFERROR(INDEX('Monthly Cost Summary'!$E$2:$E$13,MATCH(TEXT(B10,"yyyymm"),TEXT('Monthly Cost Summary'!$B$2:$B$13,"yyyymm"),0))/COUNTIFS('Weekly Cash Flow'!$B$5:$B$57,">="&EOMONTH(B10,-1)+1,'Weekly Cash Flow'!$B$5:$B$57,"<="&EOMONTH(B10,0)),0)) -> 0 | F10: =D10+E10 -> 0 | G10: =G9+F10 -> 0
A11: 7 | B11: =IF(Master!$B$3="","",Master!$B$3+(6*7)) | C11: =IF(B11="","",MIN(B11+6,Master!$B$3+364)) | D11: =IF(B11="",0,SUMPRODUCT(('Activity Plan'!$K$2:$K$135<=C11)*('Activity Plan'!$L$2:$L$135>=B11)*'Activity Plan'!$N$2:$N$135)) -> 0 | E11: =IF(B11="",0,IFERROR(INDEX('Monthly Cost Summary'!$E$2:$E$13,MATCH(TEXT(B11,"yyyymm"),TEXT('Monthly Cost Summary'!$B$2:$B$13,"yyyymm"),0))/COUNTIFS('Weekly Cash Flow'!$B$5:$B$57,">="&EOMONTH(B11,-1)+1,'Weekly Cash Flow'!$B$5:$B$57,"<="&EOMONTH(B11,0)),0)) -> 0 | F11: =D11+E11 -> 0 | G11: =G10+F11 -> 0
A12: 8 | B12: =IF(Master!$B$3="","",Master!$B$3+(7*7)) | C12: =IF(B12="","",MIN(B12+6,Master!$B$3+364)) | D12: =IF(B12="",0,SUMPRODUCT(('Activity Plan'!$K$2:$K$135<=C12)*('Activity Plan'!$L$2:$L$135>=B12)*'Activity Plan'!$N$2:$N$135)) -> 0 | E12: =IF(B12="",0,IFERROR(INDEX('Monthly Cost Summary'!$E$2:$E$13,MATCH(TEXT(B12,"yyyymm"),TEXT('Monthly Cost Summary'!$B$2:$B$13,"yyyymm"),0))/COUNTIFS('Weekly Cash Flow'!$B$5:$B$57,">="&EOMONTH(B12,-1)+1,'Weekly Cash Flow'!$B$5:$B$57,"<="&EOMONTH(B12,0)),0)) -> 0 | F12: =D12+E12 -> 0 | G12: =G11+F12 -> 0
A13: 9 | B13: =IF(Master!$B$3="","",Master!$B$3+(8*7)) | C13: =IF(B13="","",MIN(B13+6,Master!$B$3+364)) | D13: =IF(B13="",0,SUMPRODUCT(('Activity Plan'!$K$2:$K$135<=C13)*('Activity Plan'!$L$2:$L$135>=B13)*'Activity Plan'!$N$2:$N$135)) -> 0 | E13: =IF(B13="",0,IFERROR(INDEX('Monthly Cost Summary'!$E$2:$E$13,MATCH(TEXT(B13,"yyyymm"),TEXT('Monthly Cost Summary'!$B$2:$B$13,"yyyymm"),0))/COUNTIFS('Weekly Cash Flow'!$B$5:$B$57,">="&EOMONTH(B13,-1)+1,'Weekly Cash Flow'!$B$5:$B$57,"<="&EOMONTH(B13,0)),0)) -> 0 | F13: =D13+E13 -> 0 | G13: =G12+F13 -> 0
A14: 10 | B14: =IF(Master!$B$3="","",Master!$B$3+(9*7)) | C14: =IF(B14="","",MIN(B14+6,Master!$B$3+364)) | D14: =IF(B14="",0,SUMPRODUCT(('Activity Plan'!$K$2:$K$135<=C14)*('Activity Plan'!$L$2:$L$135>=B14)*'Activity Plan'!$N$2:$N$135)) -> 0 | E14: =IF(B14="",0,IFERROR(INDEX('Monthly Cost Summary'!$E$2:$E$13,MATCH(TEXT(B14,"yyyymm"),TEXT('Monthly Cost Summary'!$B$2:$B$13,"yyyymm"),0))/COUNTIFS('Weekly Cash Flow'!$B$5:$B$57,">="&EOMONTH(B14,-1)+1,'Weekly Cash Flow'!$B$5:$B$57,"<="&EOMONTH(B14,0)),0)) -> 0 | F14: =D14+E14 -> 0 | G14: =G13+F14 -> 0
A15: 11 | B15: =IF(Master!$B$3="","",Master!$B$3+(10*7)) | C15: =IF(B15="","",MIN(B15+6,Master!$B$3+364)) | D15: =IF(B15="",0,SUMPRODUCT(('Activity Plan'!$K$2:$K$135<=C15)*('Activity Plan'!$L$2:$L$135>=B15)*'Activity Plan'!$N$2:$N$135)) -> 0 | E15: =IF(B15="",0,IFERROR(INDEX('Monthly Cost Summary'!$E$2:$E$13,MATCH(TEXT(B15,"yyyymm"),TEXT('Monthly Cost Summary'!$B$2:$B$13,"yyyymm"),0))/COUNTIFS('Weekly Cash Flow'!$B$5:$B$57,">="&EOMONTH(B15,-1)+1,'Weekly Cash Flow'!$B$5:$B$57,"<="&EOMONTH(B15,0)),0)) -> 0 | F15: =D15+E15 -> 0 | G15: =G14+F15 -> 0
A16: 12 | B16: =IF(Master!$B$3="","",Master!$B$3+(11*7)) | C16: =IF(B16="","",MIN(B16+6,Master!$B$3+364)) | D16: =IF(B16="",0,SUMPRODUCT(('Activity Plan'!$K$2:$K$135<=C16)*('Activity Plan'!$L$2:$L$135>=B16)*'Activity Plan'!$N$2:$N$135)) -> 0 | E16: =IF(B16="",0,IFERROR(INDEX('Monthly Cost Summary'!$E$2:$E$13,MATCH(TEXT(B16,"yyyymm"),TEXT('Monthly Cost Summary'!$B$2:$B$13,"yyyymm"),0))/COUNTIFS('Weekly Cash Flow'!$B$5:$B$57,">="&EOMONTH(B16,-1)+1,'Weekly Cash Flow'!$B$5:$B$57,"<="&EOMONTH(B16,0)),0)) -> 0 | F16: =D16+E16 -> 0 | G16: =G15+F16 -> 0
A17: 13 | B17: =IF(Master!$B$3="","",Master!$B$3+(12*7)) | C17: =IF(B17="","",MIN(B17+6,Master!$B$3+364)) | D17: =IF(B17="",0,SUMPRODUCT(('Activity Plan'!$K$2:$K$135<=C17)*('Activity Plan'!$L$2:$L$135>=B17)*'Activity Plan'!$N$2:$N$135)) -> 0 | E17: =IF(B17="",0,IFERROR(INDEX('Monthly Cost Summary'!$E$2:$E$13,MATCH(TEXT(B17,"yyyymm"),TEXT('Monthly Cost Summary'!$B$2:$B$13,"yyyymm"),0))/COUNTIFS('Weekly Cash Flow'!$B$5:$B$57,">="&EOMONTH(B17,-1)+1,'Weekly Cash Flow'!$B$5:$B$57,"<="&EOMONTH(B17,0)),0)) -> 0 | F17: =D17+E17 -> 0 | G17: =G16+F17 -> 0
A18: 14 | B18: =IF(Master!$B$3="","",Master!$B$3+(13*7)) | C18: =IF(B18="","",MIN(B18+6,Master!$B$3+364)) | D18: =IF(B18="",0,SUMPRODUCT(('Activity Plan'!$K$2:$K$135<=C18)*('Activity Plan'!$L$2:$L$135>=B18)*'Activity Plan'!$N$2:$N$135)) -> 0 | E18: =IF(B18="",0,IFERROR(INDEX('Monthly Cost Summary'!$E$2:$E$13,MATCH(TEXT(B18,"yyyymm"),TEXT('Monthly Cost Summary'!$B$2:$B$13,"yyyymm"),0))/COUNTIFS('Weekly Cash Flow'!$B$5:$B$57,">="&EOMONTH(B18,-1)+1,'Weekly Cash Flow'!$B$5:$B$57,"<="&EOMONTH(B18,0)),0)) -> 0 | F18: =D18+E18 -> 0 | G18: =G17+F18 -> 0
A19: 15 | B19: =IF(Master!$B$3="","",Master!$B$3+(14*7)) | C19: =IF(B19="","",MIN(B19+6,Master!$B$3+364)) | D19: =IF(B19="",0,SUMPRODUCT(('Activity Plan'!$K$2:$K$135<=C19)*('Activity Plan'!$L$2:$L$135>=B19)*'Activity Plan'!$N$2:$N$135)) -> 0 | E19: =IF(B19="",0,IFERROR(INDEX('Monthly Cost Summary'!$E$2:$E$13,MATCH(TEXT(B19,"yyyymm"),TEXT('Monthly Cost Summary'!$B$2:$B$13,"yyyymm"),0))/COUNTIFS('Weekly Cash Flow'!$B$5:$B$57,">="&EOMONTH(B19,-1)+1,'Weekly Cash Flow'!$B$5:$B$57,"<="&EOMONTH(B19,0)),0)) -> 0 | F19: =D19+E19 -> 0 | G19: =G18+F19 -> 0
A20: 16 | B20: =IF(Master!$B$3="","",Master!$B$3+(15*7)) | C20: =IF(B20="","",MIN(B20+6,Master!$B$3+364)) | D20: =IF(B20="",0,SUMPRODUCT(('Activity Plan'!$K$2:$K$135<=C20)*('Activity Plan'!$L$2:$L$135>=B20)*'Activity Plan'!$N$2:$N$135)) -> 0 | E20: =IF(B20="",0,IFERROR(INDEX('Monthly Cost Summary'!$E$2:$E$13,MATCH(TEXT(B20,"yyyymm"),TEXT('Monthly Cost Summary'!$B$2:$B$13,"yyyymm"),0))/COUNTIFS('Weekly Cash Flow'!$B$5:$B$57,">="&EOMONTH(B20,-1)+1,'Weekly Cash Flow'!$B$5:$B$57,"<="&EOMONTH(B20,0)),0)) -> 0 | F20: =D20+E20 -> 0 | G20: =G19+F20 -> 0
A21: 17 | B21: =IF(Master!$B$3="","",Master!$B$3+(16*7)) | C21: =IF(B21="","",MIN(B21+6,Master!$B$3+364)) | D21: =IF(B21="",0,SUMPRODUCT(('Activity Plan'!$K$2:$K$135<=C21)*('Activity Plan'!$L$2:$L$135>=B21)*'Activity Plan'!$N$2:$N$135)) -> 0 | E21: =IF(B21="",0,IFERROR(INDEX('Monthly Cost Summary'!$E$2:$E$13,MATCH(TEXT(B21,"yyyymm"),TEXT('Monthly Cost Summary'!$B$2:$B$13,"yyyymm"),0))/COUNTIFS('Weekly Cash Flow'!$B$5:$B$57,">="&EOMONTH(B21,-1)+1,'Weekly Cash Flow'!$B$5:$B$57,"<="&EOMONTH(B21,0)),0)) -> 0 | F21: =D21+E21 -> 0 | G21: =G20+F21 -> 0
A22: 18 | B22: =IF(Master!$B$3="","",Master!$B$3+(17*7)) | C22: =IF(B22="","",MIN(B22+6,Master!$B$3+364)) | D22: =IF(B22="",0,SUMPRODUCT(('Activity Plan'!$K$2:$K$135<=C22)*('Activity Plan'!$L$2:$L$135>=B22)*'Activity Plan'!$N$2:$N$135)) -> 0 | E22: =IF(B22="",0,IFERROR(INDEX('Monthly Cost Summary'!$E$2:$E$13,MATCH(TEXT(B22,"yyyymm"),TEXT('Monthly Cost Summary'!$B$2:$B$13,"yyyymm"),0))/COUNTIFS('Weekly Cash Flow'!$B$5:$B$57,">="&EOMONTH(B22,-1)+1,'Weekly Cash Flow'!$B$5:$B$57,"<="&EOMONTH(B22,0)),0)) -> 0 | F22: =D22+E22 -> 0 | G22: =G21+F22 -> 0
A23: 19 | B23: =IF(Master!$B$3="","",Master!$B$3+(18*7)) | C23: =IF(B23="","",MIN(B23+6,Master!$B$3+364)) | D23: =IF(B23="",0,SUMPRODUCT(('Activity Plan'!$K$2:$K$135<=C23)*('Activity Plan'!$L$2:$L$135>=B23)*'Activity Plan'!$N$2:$N$135)) -> 0 | E23: =IF(B23="",0,IFERROR(INDEX('Monthly Cost Summary'!$E$2:$E$13,MATCH(TEXT(B23,"yyyymm"),TEXT('Monthly Cost Summary'!$B$2:$B$13,"yyyymm"),0))/COUNTIFS('Weekly Cash Flow'!$B$5:$B$57,">="&EOMONTH(B23,-1)+1,'Weekly Cash Flow'!$B$5:$B$57,"<="&EOMONTH(B23,0)),0)) -> 0 | F23: =D23+E23 -> 0 | G23: =G22+F23 -> 0
A24: 20 | B24: =IF(Master!$B$3="","",Master!$B$3+(19*7)) | C24: =IF(B24="","",MIN(B24+6,Master!$B$3+364)) | D24: =IF(B24="",0,SUMPRODUCT(('Activity Plan'!$K$2:$K$135<=C24)*('Activity Plan'!$L$2:$L$135>=B24)*'Activity Plan'!$N$2:$N$135)) -> 0 | E24: =IF(B24="",0,IFERROR(INDEX('Monthly Cost Summary'!$E$2:$E$13,MATCH(TEXT(B24,"yyyymm"),TEXT('Monthly Cost Summary'!$B$2:$B$13,"yyyymm"),0))/COUNTIFS('Weekly Cash Flow'!$B$5:$B$57,">="&EOMONTH(B24,-1)+1,'Weekly Cash Flow'!$B$5:$B$57,"<="&EOMONTH(B24,0)),0)) -> 0 | F24: =D24+E24 -> 0 | G24: =G23+F24 -> 0
A25: 21 | B25: =IF(Master!$B$3="","",Master!$B$3+(20*7)) | C25: =IF(B25="","",MIN(B25+6,Master!$B$3+364)) | D25: =IF(B25="",0,SUMPRODUCT(('Activity Plan'!$K$2:$K$135<=C25)*('Activity Plan'!$L$2:$L$135>=B25)*'Activity Plan'!$N$2:$N$135)) -> 0 | E25: =IF(B25="",0,IFERROR(INDEX('Monthly Cost Summary'!$E$2:$E$13,MATCH(TEXT(B25,"yyyymm"),TEXT('Monthly Cost Summary'!$B$2:$B$13,"yyyymm"),0))/COUNTIFS('Weekly Cash Flow'!$B$5:$B$57,">="&EOMONTH(B25,-1)+1,'Weekly Cash Flow'!$B$5:$B$57,"<="&EOMONTH(B25,0)),0)) -> 0 | F25: =D25+E25 -> 0 | G25: =G24+F25 -> 0
A26: 22 | B26: =IF(Master!$B$3="","",Master!$B$3+(21*7)) | C26: =IF(B26="","",MIN(B26+6,Master!$B$3+364)) | D26: =IF(B26="",0,SUMPRODUCT(('Activity Plan'!$K$2:$K$135<=C26)*('Activity Plan'!$L$2:$L$135>=B26)*'Activity Plan'!$N$2:$N$135)) -> 0 | E26: =IF(B26="",0,IFERROR(INDEX('Monthly Cost Summary'!$E$2:$E$13,MATCH(TEXT(B26,"yyyymm"),TEXT('Monthly Cost Summary'!$B$2:$B$13,"yyyymm"),0))/COUNTIFS('Weekly Cash Flow'!$B$5:$B$57,">="&EOMONTH(B26,-1)+1,'Weekly Cash Flow'!$B$5:$B$57,"<="&EOMONTH(B26,0)),0)) -> 0 | F26: =D26+E26 -> 0 | G26: =G25+F26 -> 0
A27: 23 | B27: =IF(Master!$B$3="","",Master!$B$3+(22*7)) | C27: =IF(B27="","",MIN(B27+6,Master!$B$3+364)) | D27: =IF(B27="",0,SUMPRODUCT(('Activity Plan'!$K$2:$K$135<=C27)*('Activity Plan'!$L$2:$L$135>=B27)*'Activity Plan'!$N$2:$N$135)) -> 0 | E27: =IF(B27="",0,IFERROR(INDEX('Monthly Cost Summary'!$E$2:$E$13,MATCH(TEXT(B27,"yyyymm"),TEXT('Monthly Cost Summary'!$B$2:$B$13,"yyyymm"),0))/COUNTIFS('Weekly Cash Flow'!$B$5:$B$57,">="&EOMONTH(B27,-1)+1,'Weekly Cash Flow'!$B$5:$B$57,"<="&EOMONTH(B27,0)),0)) -> 0 | F27: =D27+E27 -> 0 | G27: =G26+F27 -> 0
A28: 24 | B28: =IF(Master!$B$3="","",Master!$B$3+(23*7)) | C28: =IF(B28="","",MIN(B28+6,Master!$B$3+364)) | D28: =IF(B28="",0,SUMPRODUCT(('Activity Plan'!$K$2:$K$135<=C28)*('Activity Plan'!$L$2:$L$135>=B28)*'Activity Plan'!$N$2:$N$135)) -> 0 | E28: =IF(B28="",0,IFERROR(INDEX('Monthly Cost Summary'!$E$2:$E$13,MATCH(TEXT(B28,"yyyymm"),TEXT('Monthly Cost Summary'!$B$2:$B$13,"yyyymm"),0))/COUNTIFS('Weekly Cash Flow'!$B$5:$B$57,">="&EOMONTH(B28,-1)+1,'Weekly Cash Flow'!$B$5:$B$57,"<="&EOMONTH(B28,0)),0)) -> 0 | F28: =D28+E28 -> 0 | G28: =G27+F28 -> 0
A29: 25 | B29: =IF(Master!$B$3="","",Master!$B$3+(24*7)) | C29: =IF(B29="","",MIN(B29+6,Master!$B$3+364)) | D29: =IF(B29="",0,SUMPRODUCT(('Activity Plan'!$K$2:$K$135<=C29)*('Activity Plan'!$L$2:$L$135>=B29)*'Activity Plan'!$N$2:$N$135)) -> 0 | E29: =IF(B29="",0,IFERROR(INDEX('Monthly Cost Summary'!$E$2:$E$13,MATCH(TEXT(B29,"yyyymm"),TEXT('Monthly Cost Summary'!$B$2:$B$13,"yyyymm"),0))/COUNTIFS('Weekly Cash Flow'!$B$5:$B$57,">="&EOMONTH(B29,-1)+1,'Weekly Cash Flow'!$B$5:$B$57,"<="&EOMONTH(B29,0)),0)) -> 0 | F29: =D29+E29 -> 0 | G29: =G28+F29 -> 0
A30: 26 | B30: =IF(Master!$B$3="","",Master!$B$3+(25*7)) | C30: =IF(B30="","",MIN(B30+6,Master!$B$3+364)) | D30: =IF(B30="",0,SUMPRODUCT(('Activity Plan'!$K$2:$K$135<=C30)*('Activity Plan'!$L$2:$L$135>=B30)*'Activity Plan'!$N$2:$N$135)) -> 0 | E30: =IF(B30="",0,IFERROR(INDEX('Monthly Cost Summary'!$E$2:$E$13,MATCH(TEXT(B30,"yyyymm"),TEXT('Monthly Cost Summary'!$B$2:$B$13,"yyyymm"),0))/COUNTIFS('Weekly Cash Flow'!$B$5:$B$57,">="&EOMONTH(B30,-1)+1,'Weekly Cash Flow'!$B$5:$B$57,"<="&EOMONTH(B30,0)),0)) -> 0 | F30: =D30+E30 -> 0 | G30: =G29+F30 -> 0
A31: 27 | B31: =IF(Master!$B$3="","",Master!$B$3+(26*7)) | C31: =IF(B31="","",MIN(B31+6,Master!$B$3+364)) | D31: =IF(B31="",0,SUMPRODUCT(('Activity Plan'!$K$2:$K$135<=C31)*('Activity Plan'!$L$2:$L$135>=B31)*'Activity Plan'!$N$2:$N$135)) -> 0 | E31: =IF(B31="",0,IFERROR(INDEX('Monthly Cost Summary'!$E$2:$E$13,MATCH(TEXT(B31,"yyyymm"),TEXT('Monthly Cost Summary'!$B$2:$B$13,"yyyymm"),0))/COUNTIFS('Weekly Cash Flow'!$B$5:$B$57,">="&EOMONTH(B31,-1)+1,'Weekly Cash Flow'!$B$5:$B$57,"<="&EOMONTH(B31,0)),0)) -> 0 | F31: =D31+E31 -> 0 | G31: =G30+F31 -> 0
A32: 28 | B32: =IF(Master!$B$3="","",Master!$B$3+(27*7)) | C32: =IF(B32="","",MIN(B32+6,Master!$B$3+364)) | D32: =IF(B32="",0,SUMPRODUCT(('Activity Plan'!$K$2:$K$135<=C32)*('Activity Plan'!$L$2:$L$135>=B32)*'Activity Plan'!$N$2:$N$135)) -> 0 | E32: =IF(B32="",0,IFERROR(INDEX('Monthly Cost Summary'!$E$2:$E$13,MATCH(TEXT(B32,"yyyymm"),TEXT('Monthly Cost Summary'!$B$2:$B$13,"yyyymm"),0))/COUNTIFS('Weekly Cash Flow'!$B$5:$B$57,">="&EOMONTH(B32,-1)+1,'Weekly Cash Flow'!$B$5:$B$57,"<="&EOMONTH(B32,0)),0)) -> 0 | F32: =D32+E32 -> 0 | G32: =G31+F32 -> 0
A33: 29 | B33: =IF(Master!$B$3="","",Master!$B$3+(28*7)) | C33: =IF(B33="","",MIN(B33+6,Master!$B$3+364)) | D33: =IF(B33="",0,SUMPRODUCT(('Activity Plan'!$K$2:$K$135<=C33)*('Activity Plan'!$L$2:$L$135>=B33)*'Activity Plan'!$N$2:$N$135)) -> 0 | E33: =IF(B33="",0,IFERROR(INDEX('Monthly Cost Summary'!$E$2:$E$13,MATCH(TEXT(B33,"yyyymm"),TEXT('Monthly Cost Summary'!$B$2:$B$13,"yyyymm"),0))/COUNTIFS('Weekly Cash Flow'!$B$5:$B$57,">="&EOMONTH(B33,-1)+1,'Weekly Cash Flow'!$B$5:$B$57,"<="&EOMONTH(B33,0)),0)) -> 0 | F33: =D33+E33 -> 0 | G33: =G32+F33 -> 0
A34: 30 | B34: =IF(Master!$B$3="","",Master!$B$3+(29*7)) | C34: =IF(B34="","",MIN(B34+6,Master!$B$3+364)) | D34: =IF(B34="",0,SUMPRODUCT(('Activity Plan'!$K$2:$K$135<=C34)*('Activity Plan'!$L$2:$L$135>=B34)*'Activity Plan'!$N$2:$N$135)) -> 0 | E34: =IF(B34="",0,IFERROR(INDEX('Monthly Cost Summary'!$E$2:$E$13,MATCH(TEXT(B34,"yyyymm"),TEXT('Monthly Cost Summary'!$B$2:$B$13,"yyyymm"),0))/COUNTIFS('Weekly Cash Flow'!$B$5:$B$57,">="&EOMONTH(B34,-1)+1,'Weekly Cash Flow'!$B$5:$B$57,"<="&EOMONTH(B34,0)),0)) -> 0 | F34: =D34+E34 -> 0 | G34: =G33+F34 -> 0
A35: 31 | B35: =IF(Master!$B$3="","",Master!$B$3+(30*7)) | C35: =IF(B35="","",MIN(B35+6,Master!$B$3+364)) | D35: =IF(B35="",0,SUMPRODUCT(('Activity Plan'!$K$2:$K$135<=C35)*('Activity Plan'!$L$2:$L$135>=B35)*'Activity Plan'!$N$2:$N$135)) -> 0 | E35: =IF(B35="",0,IFERROR(INDEX('Monthly Cost Summary'!$E$2:$E$13,MATCH(TEXT(B35,"yyyymm"),TEXT('Monthly Cost Summary'!$B$2:$B$13,"yyyymm"),0))/COUNTIFS('Weekly Cash Flow'!$B$5:$B$57,">="&EOMONTH(B35,-1)+1,'Weekly Cash Flow'!$B$5:$B$57,"<="&EOMONTH(B35,0)),0)) -> 0 | F35: =D35+E35 -> 0 | G35: =G34+F35 -> 0
A36: 32 | B36: =IF(Master!$B$3="","",Master!$B$3+(31*7)) | C36: =IF(B36="","",MIN(B36+6,Master!$B$3+364)) | D36: =IF(B36="",0,SUMPRODUCT(('Activity Plan'!$K$2:$K$135<=C36)*('Activity Plan'!$L$2:$L$135>=B36)*'Activity Plan'!$N$2:$N$135)) -> 0 | E36: =IF(B36="",0,IFERROR(INDEX('Monthly Cost Summary'!$E$2:$E$13,MATCH(TEXT(B36,"yyyymm"),TEXT('Monthly Cost Summary'!$B$2:$B$13,"yyyymm"),0))/COUNTIFS('Weekly Cash Flow'!$B$5:$B$57,">="&EOMONTH(B36,-1)+1,'Weekly Cash Flow'!$B$5:$B$57,"<="&EOMONTH(B36,0)),0)) -> 0 | F36: =D36+E36 -> 0 | G36: =G35+F36 -> 0
A37: 33 | B37: =IF(Master!$B$3="","",Master!$B$3+(32*7)) | C37: =IF(B37="","",MIN(B37+6,Master!$B$3+364)) | D37: =IF(B37="",0,SUMPRODUCT(('Activity Plan'!$K$2:$K$135<=C37)*('Activity Plan'!$L$2:$L$135>=B37)*'Activity Plan'!$N$2:$N$135)) -> 0 | E37: =IF(B37="",0,IFERROR(INDEX('Monthly Cost Summary'!$E$2:$E$13,MATCH(TEXT(B37,"yyyymm"),TEXT('Monthly Cost Summary'!$B$2:$B$13,"yyyymm"),0))/COUNTIFS('Weekly Cash Flow'!$B$5:$B$57,">="&EOMONTH(B37,-1)+1,'Weekly Cash Flow'!$B$5:$B$57,"<="&EOMONTH(B37,0)),0)) -> 0 | F37: =D37+E37 -> 0 | G37: =G36+F37 -> 0
A38: 34 | B38: =IF(Master!$B$3="","",Master!$B$3+(33*7)) | C38: =IF(B38="","",MIN(B38+6,Master!$B$3+364)) | D38: =IF(B38="",0,SUMPRODUCT(('Activity Plan'!$K$2:$K$135<=C38)*('Activity Plan'!$L$2:$L$135>=B38)*'Activity Plan'!$N$2:$N$135)) -> 0 | E38: =IF(B38="",0,IFERROR(INDEX('Monthly Cost Summary'!$E$2:$E$13,MATCH(TEXT(B38,"yyyymm"),TEXT('Monthly Cost Summary'!$B$2:$B$13,"yyyymm"),0))/COUNTIFS('Weekly Cash Flow'!$B$5:$B$57,">="&EOMONTH(B38,-1)+1,'Weekly Cash Flow'!$B$5:$B$57,"<="&EOMONTH(B38,0)),0)) -> 0 | F38: =D38+E38 -> 0 | G38: =G37+F38 -> 0
A39: 35 | B39: =IF(Master!$B$3="","",Master!$B$3+(34*7)) | C39: =IF(B39="","",MIN(B39+6,Master!$B$3+364)) | D39: =IF(B39="",0,SUMPRODUCT(('Activity Plan'!$K$2:$K$135<=C39)*('Activity Plan'!$L$2:$L$135>=B39)*'Activity Plan'!$N$2:$N$135)) -> 0 | E39: =IF(B39="",0,IFERROR(INDEX('Monthly Cost Summary'!$E$2:$E$13,MATCH(TEXT(B39,"yyyymm"),TEXT('Monthly Cost Summary'!$B$2:$B$13,"yyyymm"),0))/COUNTIFS('Weekly Cash Flow'!$B$5:$B$57,">="&EOMONTH(B39,-1)+1,'Weekly Cash Flow'!$B$5:$B$57,"<="&EOMONTH(B39,0)),0)) -> 0 | F39: =D39+E39 -> 0 | G39: =G38+F39 -> 0
A40: 36 | B40: =IF(Master!$B$3="","",Master!$B$3+(35*7)) | C40: =IF(B40="","",MIN(B40+6,Master!$B$3+364)) | D40: =IF(B40="",0,SUMPRODUCT(('Activity Plan'!$K$2:$K$135<=C40)*('Activity Plan'!$L$2:$L$135>=B40)*'Activity Plan'!$N$2:$N$135)) -> 0 | E40: =IF(B40="",0,IFERROR(INDEX('Monthly Cost Summary'!$E$2:$E$13,MATCH(TEXT(B40,"yyyymm"),TEXT('Monthly Cost Summary'!$B$2:$B$13,"yyyymm"),0))/COUNTIFS('Weekly Cash Flow'!$B$5:$B$57,">="&EOMONTH(B40,-1)+1,'Weekly Cash Flow'!$B$5:$B$57,"<="&EOMONTH(B40,0)),0)) -> 0 | F40: =D40+E40 -> 0 | G40: =G39+F40 -> 0
A41: 37 | B41: =IF(Master!$B$3="","",Master!$B$3+(36*7)) | C41: =IF(B41="","",MIN(B41+6,Master!$B$3+364)) | D41: =IF(B41="",0,SUMPRODUCT(('Activity Plan'!$K$2:$K$135<=C41)*('Activity Plan'!$L$2:$L$135>=B41)*'Activity Plan'!$N$2:$N$135)) -> 0 | E41: =IF(B41="",0,IFERROR(INDEX('Monthly Cost Summary'!$E$2:$E$13,MATCH(TEXT(B41,"yyyymm"),TEXT('Monthly Cost Summary'!$B$2:$B$13,"yyyymm"),0))/COUNTIFS('Weekly Cash Flow'!$B$5:$B$57,">="&EOMONTH(B41,-1)+1,'Weekly Cash Flow'!$B$5:$B$57,"<="&EOMONTH(B41,0)),0)) -> 0 | F41: =D41+E41 -> 0 | G41: =G40+F41 -> 0
A42: 38 | B42: =IF(Master!$B$3="","",Master!$B$3+(37*7)) | C42: =IF(B42="","",MIN(B42+6,Master!$B$3+364)) | D42: =IF(B42="",0,SUMPRODUCT(('Activity Plan'!$K$2:$K$135<=C42)*('Activity Plan'!$L$2:$L$135>=B42)*'Activity Plan'!$N$2:$N$135)) -> 0 | E42: =IF(B42="",0,IFERROR(INDEX('Monthly Cost Summary'!$E$2:$E$13,MATCH(TEXT(B42,"yyyymm"),TEXT('Monthly Cost Summary'!$B$2:$B$13,"yyyymm"),0))/COUNTIFS('Weekly Cash Flow'!$B$5:$B$57,">="&EOMONTH(B42,-1)+1,'Weekly Cash Flow'!$B$5:$B$57,"<="&EOMONTH(B42,0)),0)) -> 0 | F42: =D42+E42 -> 0 | G42: =G41+F42 -> 0
A43: 39 | B43: =IF(Master!$B$3="","",Master!$B$3+(38*7)) | C43: =IF(B43="","",MIN(B43+6,Master!$B$3+364)) | D43: =IF(B43="",0,SUMPRODUCT(('Activity Plan'!$K$2:$K$135<=C43)*('Activity Plan'!$L$2:$L$135>=B43)*'Activity Plan'!$N$2:$N$135)) -> 0 | E43: =IF(B43="",0,IFERROR(INDEX('Monthly Cost Summary'!$E$2:$E$13,MATCH(TEXT(B43,"yyyymm"),TEXT('Monthly Cost Summary'!$B$2:$B$13,"yyyymm"),0))/COUNTIFS('Weekly Cash Flow'!$B$5:$B$57,">="&EOMONTH(B43,-1)+1,'Weekly Cash Flow'!$B$5:$B$57,"<="&EOMONTH(B43,0)),0)) -> 0 | F43: =D43+E43 -> 0 | G43: =G42+F43 -> 0
A44: 40 | B44: =IF(Master!$B$3="","",Master!$B$3+(39*7)) | C44: =IF(B44="","",MIN(B44+6,Master!$B$3+364)) | D44: =IF(B44="",0,SUMPRODUCT(('Activity Plan'!$K$2:$K$135<=C44)*('Activity Plan'!$L$2:$L$135>=B44)*'Activity Plan'!$N$2:$N$135)) -> 0 | E44: =IF(B44="",0,IFERROR(INDEX('Monthly Cost Summary'!$E$2:$E$13,MATCH(TEXT(B44,"yyyymm"),TEXT('Monthly Cost Summary'!$B$2:$B$13,"yyyymm"),0))/COUNTIFS('Weekly Cash Flow'!$B$5:$B$57,">="&EOMONTH(B44,-1)+1,'Weekly Cash Flow'!$B$5:$B$57,"<="&EOMONTH(B44,0)),0)) -> 0 | F44: =D44+E44 -> 0 | G44: =G43+F44 -> 0
A45: 41 | B45: =IF(Master!$B$3="","",Master!$B$3+(40*7)) | C45: =IF(B45="","",MIN(B45+6,Master!$B$3+364)) | D45: =IF(B45="",0,SUMPRODUCT(('Activity Plan'!$K$2:$K$135<=C45)*('Activity Plan'!$L$2:$L$135>=B45)*'Activity Plan'!$N$2:$N$135)) -> 0 | E45: =IF(B45="",0,IFERROR(INDEX('Monthly Cost Summary'!$E$2:$E$13,MATCH(TEXT(B45,"yyyymm"),TEXT('Monthly Cost Summary'!$B$2:$B$13,"yyyymm"),0))/COUNTIFS('Weekly Cash Flow'!$B$5:$B$57,">="&EOMONTH(B45,-1)+1,'Weekly Cash Flow'!$B$5:$B$57,"<="&EOMONTH(B45,0)),0)) -> 0 | F45: =D45+E45 -> 0 | G45: =G44+F45 -> 0
A46: 42 | B46: =IF(Master!$B$3="","",Master!$B$3+(41*7)) | C46: =IF(B46="","",MIN(B46+6,Master!$B$3+364)) | D46: =IF(B46="",0,SUMPRODUCT(('Activity Plan'!$K$2:$K$135<=C46)*('Activity Plan'!$L$2:$L$135>=B46)*'Activity Plan'!$N$2:$N$135)) -> 0 | E46: =IF(B46="",0,IFERROR(INDEX('Monthly Cost Summary'!$E$2:$E$13,MATCH(TEXT(B46,"yyyymm"),TEXT('Monthly Cost Summary'!$B$2:$B$13,"yyyymm"),0))/COUNTIFS('Weekly Cash Flow'!$B$5:$B$57,">="&EOMONTH(B46,-1)+1,'Weekly Cash Flow'!$B$5:$B$57,"<="&EOMONTH(B46,0)),0)) -> 0 | F46: =D46+E46 -> 0 | G46: =G45+F46 -> 0
A47: 43 | B47: =IF(Master!$B$3="","",Master!$B$3+(42*7)) | C47: =IF(B47="","",MIN(B47+6,Master!$B$3+364)) | D47: =IF(B47="",0,SUMPRODUCT(('Activity Plan'!$K$2:$K$135<=C47)*('Activity Plan'!$L$2:$L$135>=B47)*'Activity Plan'!$N$2:$N$135)) -> 0 | E47: =IF(B47="",0,IFERROR(INDEX('Monthly Cost Summary'!$E$2:$E$13,MATCH(TEXT(B47,"yyyymm"),TEXT('Monthly Cost Summary'!$B$2:$B$13,"yyyymm"),0))/COUNTIFS('Weekly Cash Flow'!$B$5:$B$57,">="&EOMONTH(B47,-1)+1,'Weekly Cash Flow'!$B$5:$B$57,"<="&EOMONTH(B47,0)),0)) -> 0 | F47: =D47+E47 -> 0 | G47: =G46+F47 -> 0
A48: 44 | B48: =IF(Master!$B$3="","",Master!$B$3+(43*7)) | C48: =IF(B48="","",MIN(B48+6,Master!$B$3+364)) | D48: =IF(B48="",0,SUMPRODUCT(('Activity Plan'!$K$2:$K$135<=C48)*('Activity Plan'!$L$2:$L$135>=B48)*'Activity Plan'!$N$2:$N$135)) -> 0 | E48: =IF(B48="",0,IFERROR(INDEX('Monthly Cost Summary'!$E$2:$E$13,MATCH(TEXT(B48,"yyyymm"),TEXT('Monthly Cost Summary'!$B$2:$B$13,"yyyymm"),0))/COUNTIFS('Weekly Cash Flow'!$B$5:$B$57,">="&EOMONTH(B48,-1)+1,'Weekly Cash Flow'!$B$5:$B$57,"<="&EOMONTH(B48,0)),0)) -> 0 | F48: =D48+E48 -> 0 | G48: =G47+F48 -> 0
A49: 45 | B49: =IF(Master!$B$3="","",Master!$B$3+(44*7)) | C49: =IF(B49="","",MIN(B49+6,Master!$B$3+364)) | D49: =IF(B49="",0,SUMPRODUCT(('Activity Plan'!$K$2:$K$135<=C49)*('Activity Plan'!$L$2:$L$135>=B49)*'Activity Plan'!$N$2:$N$135)) -> 0 | E49: =IF(B49="",0,IFERROR(INDEX('Monthly Cost Summary'!$E$2:$E$13,MATCH(TEXT(B49,"yyyymm"),TEXT('Monthly Cost Summary'!$B$2:$B$13,"yyyymm"),0))/COUNTIFS('Weekly Cash Flow'!$B$5:$B$57,">="&EOMONTH(B49,-1)+1,'Weekly Cash Flow'!$B$5:$B$57,"<="&EOMONTH(B49,0)),0)) -> 0 | F49: =D49+E49 -> 0 | G49: =G48+F49 -> 0
A50: 46 | B50: =IF(Master!$B$3="","",Master!$B$3+(45*7)) | C50: =IF(B50="","",MIN(B50+6,Master!$B$3+364)) | D50: =IF(B50="",0,SUMPRODUCT(('Activity Plan'!$K$2:$K$135<=C50)*('Activity Plan'!$L$2:$L$135>=B50)*'Activity Plan'!$N$2:$N$135)) -> 0 | E50: =IF(B50="",0,IFERROR(INDEX('Monthly Cost Summary'!$E$2:$E$13,MATCH(TEXT(B50,"yyyymm"),TEXT('Monthly Cost Summary'!$B$2:$B$13,"yyyymm"),0))/COUNTIFS('Weekly Cash Flow'!$B$5:$B$57,">="&EOMONTH(B50,-1)+1,'Weekly Cash Flow'!$B$5:$B$57,"<="&EOMONTH(B50,0)),0)) -> 0 | F50: =D50+E50 -> 0 | G50: =G49+F50 -> 0
A51: 47 | B51: =IF(Master!$B$3="","",Master!$B$3+(46*7)) | C51: =IF(B51="","",MIN(B51+6,Master!$B$3+364)) | D51: =IF(B51="",0,SUMPRODUCT(('Activity Plan'!$K$2:$K$135<=C51)*('Activity Plan'!$L$2:$L$135>=B51)*'Activity Plan'!$N$2:$N$135)) -> 0 | E51: =IF(B51="",0,IFERROR(INDEX('Monthly Cost Summary'!$E$2:$E$13,MATCH(TEXT(B51,"yyyymm"),TEXT('Monthly Cost Summary'!$B$2:$B$13,"yyyymm"),0))/COUNTIFS('Weekly Cash Flow'!$B$5:$B$57,">="&EOMONTH(B51,-1)+1,'Weekly Cash Flow'!$B$5:$B$57,"<="&EOMONTH(B51,0)),0)) -> 0 | F51: =D51+E51 -> 0 | G51: =G50+F51 -> 0
A52: 48 | B52: =IF(Master!$B$3="","",Master!$B$3+(47*7)) | C52: =IF(B52="","",MIN(B52+6,Master!$B$3+364)) | D52: =IF(B52="",0,SUMPRODUCT(('Activity Plan'!$K$2:$K$135<=C52)*('Activity Plan'!$L$2:$L$135>=B52)*'Activity Plan'!$N$2:$N$135)) -> 0 | E52: =IF(B52="",0,IFERROR(INDEX('Monthly Cost Summary'!$E$2:$E$13,MATCH(TEXT(B52,"yyyymm"),TEXT('Monthly Cost Summary'!$B$2:$B$13,"yyyymm"),0))/COUNTIFS('Weekly Cash Flow'!$B$5:$B$57,">="&EOMONTH(B52,-1)+1,'Weekly Cash Flow'!$B$5:$B$57,"<="&EOMONTH(B52,0)),0)) -> 0 | F52: =D52+E52 -> 0 | G52: =G51+F52 -> 0
A53: 49 | B53: =IF(Master!$B$3="","",Master!$B$3+(48*7)) | C53: =IF(B53="","",MIN(B53+6,Master!$B$3+364)) | D53: =IF(B53="",0,SUMPRODUCT(('Activity Plan'!$K$2:$K$135<=C53)*('Activity Plan'!$L$2:$L$135>=B53)*'Activity Plan'!$N$2:$N$135)) -> 0 | E53: =IF(B53="",0,IFERROR(INDEX('Monthly Cost Summary'!$E$2:$E$13,MATCH(TEXT(B53,"yyyymm"),TEXT('Monthly Cost Summary'!$B$2:$B$13,"yyyymm"),0))/COUNTIFS('Weekly Cash Flow'!$B$5:$B$57,">="&EOMONTH(B53,-1)+1,'Weekly Cash Flow'!$B$5:$B$57,"<="&EOMONTH(B53,0)),0)) -> 0 | F53: =D53+E53 -> 0 | G53: =G52+F53 -> 0
A54: 50 | B54: =IF(Master!$B$3="","",Master!$B$3+(49*7)) | C54: =IF(B54="","",MIN(B54+6,Master!$B$3+364)) | D54: =IF(B54="",0,SUMPRODUCT(('Activity Plan'!$K$2:$K$135<=C54)*('Activity Plan'!$L$2:$L$135>=B54)*'Activity Plan'!$N$2:$N$135)) -> 0 | E54: =IF(B54="",0,IFERROR(INDEX('Monthly Cost Summary'!$E$2:$E$13,MATCH(TEXT(B54,"yyyymm"),TEXT('Monthly Cost Summary'!$B$2:$B$13,"yyyymm"),0))/COUNTIFS('Weekly Cash Flow'!$B$5:$B$57,">="&EOMONTH(B54,-1)+1,'Weekly Cash Flow'!$B$5:$B$57,"<="&EOMONTH(B54,0)),0)) -> 0 | F54: =D54+E54 -> 0 | G54: =G53+F54 -> 0
A55: 51 | B55: =IF(Master!$B$3="","",Master!$B$3+(50*7)) | C55: =IF(B55="","",MIN(B55+6,Master!$B$3+364)) | D55: =IF(B55="",0,SUMPRODUCT(('Activity Plan'!$K$2:$K$135<=C55)*('Activity Plan'!$L$2:$L$135>=B55)*'Activity Plan'!$N$2:$N$135)) -> 0 | E55: =IF(B55="",0,IFERROR(INDEX('Monthly Cost Summary'!$E$2:$E$13,MATCH(TEXT(B55,"yyyymm"),TEXT('Monthly Cost Summary'!$B$2:$B$13,"yyyymm"),0))/COUNTIFS('Weekly Cash Flow'!$B$5:$B$57,">="&EOMONTH(B55,-1)+1,'Weekly Cash Flow'!$B$5:$B$57,"<="&EOMONTH(B55,0)),0)) -> 0 | F55: =D55+E55 -> 0 | G55: =G54+F55 -> 0
A56: 52 | B56: =IF(Master!$B$3="","",Master!$B$3+(51*7)) | C56: =IF(B56="","",MIN(B56+6,Master!$B$3+364)) | D56: =IF(B56="",0,SUMPRODUCT(('Activity Plan'!$K$2:$K$135<=C56)*('Activity Plan'!$L$2:$L$135>=B56)*'Activity Plan'!$N$2:$N$135)) -> 0 | E56: =IF(B56="",0,IFERROR(INDEX('Monthly Cost Summary'!$E$2:$E$13,MATCH(TEXT(B56,"yyyymm"),TEXT('Monthly Cost Summary'!$B$2:$B$13,"yyyymm"),0))/COUNTIFS('Weekly Cash Flow'!$B$5:$B$57,">="&EOMONTH(B56,-1)+1,'Weekly Cash Flow'!$B$5:$B$57,"<="&EOMONTH(B56,0)),0)) -> 0 | F56: =D56+E56 -> 0 | G56: =G55+F56 -> 0
A57: 53 | B57: =IF(Master!$B$3="","",Master!$B$3+(52*7)) | C57: =IF(B57="","",MIN(B57+6,Master!$B$3+364)) | D57: =IF(B57="",0,SUMPRODUCT(('Activity Plan'!$K$2:$K$135<=C57)*('Activity Plan'!$L$2:$L$135>=B57)*'Activity Plan'!$N$2:$N$135)) -> 0 | E57: =IF(B57="",0,IFERROR(INDEX('Monthly Cost Summary'!$E$2:$E$13,MATCH(TEXT(B57,"yyyymm"),TEXT('Monthly Cost Summary'!$B$2:$B$13,"yyyymm"),0))/COUNTIFS('Weekly Cash Flow'!$B$5:$B$57,">="&EOMONTH(B57,-1)+1,'Weekly Cash Flow'!$B$5:$B$57,"<="&EOMONTH(B57,0)),0)) -> 0 | F57: =D57+E57 -> 0 | G57: =G56+F57 -> 0
A59: 53 weeks covers the 365-day year with the last week short by a few days. If Term Start is blank, every row reads zero — set Master's Term Start Date first. Column E's self-reference (COUNTIFS against this sheet's own Week Start column) counts how many weeks fall in that same calendar month, so the monthly total splits evenly across them.

Sheet Total Budget Summary
A1: Total Budget Summary
A3: Block ID | B3: Block Name | C3: Labor Budget (ETB) | D3: Material Budget (ETB) | E3: Service Budget (ETB) | F3: Total Budget (ETB)
A4: =Master!A$6 -> 0 | B4: =Master!B$6 -> 0 | C4: ='Labor Budget'!F2 -> 0 | D4: =SUMIFS('Material Budget'!$I$2:$I$11,'Material Budget'!$A$2:$A$11,A4) -> 0 | E4: =SUMIFS('Service Budget'!$I$2:$I$11,'Service Budget'!$A$2:$A$11,A4) -> 0 | F4: =SUM(C4:E4) -> 0
B5: Farm Total | C5: =SUM(C4:C4) -> 0 | D5: =SUM(D4:D4) -> 0 | E5: =SUM(E4:E4) -> 0 | F5: =SUM(F4:F4) -> 0
A8: By Tier
A9: Tier | B9: Labor Budget (ETB) | C9: Material Budget (ETB) | D9: Service Budget (ETB) | E9: Total (ETB)
A10: Tier 1 — Core Services | B10: ='Labor Budget'!C2 -> 0 | C10: =SUMIFS('Material Budget'!$I$2:$I$11,'Material Budget'!$B$2:$B$11,"T1-*") -> 0 | D10: =SUMIFS('Service Budget'!$I$2:$I$11,'Service Budget'!$B$2:$B$11,"T1-*") -> 0 | E10: =SUM(B10:D10) -> 0
A11: Tier 2 — Projects | B11: ='Labor Budget'!D2 -> 0 | C11: =SUMIFS('Material Budget'!$I$2:$I$11,'Material Budget'!$B$2:$B$11,"T2-*") -> 0 | D11: =SUMIFS('Service Budget'!$I$2:$I$11,'Service Budget'!$B$2:$B$11,"T2-*") -> 0 | E11: =SUM(B11:D11) -> 0
A12: Tier 3 — Interventions | B12: ='Labor Budget'!E2 -> 0 | C12: =SUMIFS('Material Budget'!$I$2:$I$11,'Material Budget'!$B$2:$B$11,"T3-*") -> 0 | D12: =SUMIFS('Service Budget'!$I$2:$I$11,'Service Budget'!$B$2:$B$11,"T3-*") -> 0 | E12: =SUM(B12:D12) -> 0
A13: Grand Total | B13: =SUM(B10:B12) -> 0 | C13: =SUM(C10:C12) -> 0 | D13: =SUM(D10:D12) -> 0 | E13: =SUM(E10:E12) -> 0
A15: This is the farm's own operating cost — labor, materials and services paid from the farm owner's Project Account. It is separate from the Fee Schedule, which is what the farm owner pays Cropfort's manager for running this program.

Sheet Calendar - Block 1
A1: Calendar - Block 1 — Year 1 (365 days from Term Start)
A2: Shading reads live off the Annual Election sheet for this block — elect the Core bundle or an individual activity there, and its row shades automatically here for the duration assigned. If Master's Term Start Date is blank, the day headers below will show blank/zero until it's set.
A4: Block ID | B4: Activity ID | C4: Activity Name | D4: Category | E4: =Master!$B$3+0 -> 0 | F4: =Master!$B$3+1 -> 1 | G4: =Master!$B$3+2 -> 2 | H4: =Master!$B$3+3 -> 3 | I4: =Master!$B$3+4 -> 4 | J4: =Master!$B$3+5 -> 5 | K4: =Master!$B$3+6 -> 6 | L4: =Master!$B$3+7 -> 7 | M4: =Master!$B$3+8 -> 8 | N4: =Master!$B$3+9 -> 9 | O4: =Master!$B$3+10 -> 10 | P4: =Master!$B$3+11 -> 11 | Q4: =Master!$B$3+12 -> 12 | R4: =Master!$B$3+13 -> 13 | S4: =Master!$B$3+14 -> 14 | T4: =Master!$B$3+15 -> 15 | U4: =Master!$B$3+16 -> 16 | V4: =Master!$B$3+17 -> 17 | W4: =Master!$B$3+18 -> 18 | X4: =Master!$B$3+19 -> 19 | Y4: =Master!$B$3+20 -> 20 | Z4: =Master!$B$3+21 -> 21 | AA4: =Master!$B$3+22 -> 22 | AB4: =Master!$B$3+23 -> 23 | AC4: =Master!$B$3+24 -> 24 | AD4: =Master!$B$3+25 -> 25 | AE4: =Master!$B$3+26 -> 26 | AF4: =Master!$B$3+27 -> 27 | AG4: =Master!$B$3+28 -> 28 | AH4: =Master!$B$3+29 -> 29 | AI4: =Master!$B$3+30 -> 30 | AJ4: =Master!$B$3+31 -> 31 | AK4: =Master!$B$3+32 -> 32 | AL4: =Master!$B$3+33 -> 33 | AM4: =Master!$B$3+34 -> 34 | AN4: =Master!$B$3+35 -> 35 | AO4: =Master!$B$3+36 -> 36 | AP4: =Master!$B$3+37 -> 37 | AQ4: =Master!$B$3+38 -> 38 | AR4: =Master!$B$3+39 -> 39 | AS4: =Master!$B$3+40 -> 40 | AT4: =Master!$B$3+41 -> 41 | AU4: =Master!$B$3+42 -> 42 | AV4: =Master!$B$3+43 -> 43 | AW4: =Master!$B$3+44 -> 44 | AX4: =Master!$B$3+45 -> 45 | AY4: =Master!$B$3+46 -> 46 | AZ4: =Master!$B$3+47 -> 47 | BA4: =Master!$B$3+48 -> 48 | BB4: =Master!$B$3+49 -> 49 | BC4: =Master!$B$3+50 -> 50 | BD4: =Master!$B$3+51 -> 51 | BE4: =Master!$B$3+52 -> 52 | BF4: =Master!$B$3+53 -> 53 | BG4: =Master!$B$3+54 -> 54 | BH4: =Master!$B$3+55 -> 55 | BI4: =Master!$B$3+56 -> 56 | BJ4: =Master!$B$3+57 -> 57 | BK4: =Master!$B$3+58 -> 58 | BL4: =Master!$B$3+59 -> 59 | BM4: =Master!$B$3+60 -> 60 | BN4: =Master!$B$3+61 -> 61 | BO4: =Master!$B$3+62 -> 62 | BP4: =Master!$B$3+63 -> 63 | BQ4: =Master!$B$3+64 -> 64 | BR4: =Master!$B$3+65 -> 65 | BS4: =Master!$B$3+66 -> 66 | BT4: =Master!$B$3+67 -> 67 | BU4: =Master!$B$3+68 -> 68 | BV4: =Master!$B$3+69 -> 69 | BW4: =Master!$B$3+70 -> 70 | BX4: =Master!$B$3+71 -> 71 | BY4: =Master!$B$3+72 -> 72 | BZ4: =Master!$B$3+73 -> 73 | CA4: =Master!$B$3+74 -> 74 | CB4: =Master!$B$3+75 -> 75 | CC4: =Master!$B$3+76 -> 76 | CD4: =Master!$B$3+77 -> 77 | CE4: =Master!$B$3+78 -> 78 | CF4: =Master!$B$3+79 -> 79 | CG4: =Master!$B$3+80 -> 80 | CH4: =Master!$B$3+81 -> 81 | CI4: =Master!$B$3+82 -> 82 | CJ4: =Master!$B$3+83 -> 83 | CK4: =Master!$B$3+84 -> 84 | CL4: =Master!$B$3+85 -> 85 | CM4: =Master!$B$3+86 -> 86 | CN4: =Master!$B$3+87 -> 87 | CO4: =Master!$B$3+88 -> 88 | CP4: =Master!$B$3+89 -> 89 | CQ4: =Master!$B$3+90 -> 90 | CR4: =Master!$B$3+91 -> 91 | CS4: =Master!$B$3+92 -> 92 | CT4: =Master!$B$3+93 -> 93 | CU4: =Master!$B$3+94 -> 94 | CV4: =Master!$B$3+95 -> 95 | CW4: =Master!$B$3+96 -> 96 | CX4: =Master!$B$3+97 -> 97 | CY4: =Master!$B$3+98 -> 98 | CZ4: =Master!$B$3+99 -> 99 | DA4: =Master!$B$3+100 -> 100 | DB4: =Master!$B$3+101 -> 101 | DC4: =Master!$B$3+102 -> 102 | DD4: =Master!$B$3+103 -> 103 | DE4: =Master!$B$3+104 -> 104 | DF4: =Master!$B$3+105 -> 105 | DG4: =Master!$B$3+106 -> 106 | DH4: =Master!$B$3+107 -> 107 | DI4: =Master!$B$3+108 -> 108 | DJ4: =Master!$B$3+109 -> 109 | DK4: =Master!$B$3+110 -> 110 | DL4: =Master!$B$3+111 -> 111 | DM4: =Master!$B$3+112 -> 112 | DN4: =Master!$B$3+113 -> 113 | DO4: =Master!$B$3+114 -> 114 | DP4: =Master!$B$3+115 -> 115 | DQ4: =Master!$B$3+116 -> 116 | DR4: =Master!$B$3+117 -> 117 | DS4: =Master!$B$3+118 -> 118 | DT4: =Master!$B$3+119 -> 119 | DU4: =Master!$B$3+120 -> 120 | DV4: =Master!$B$3+121 -> 121 | DW4: =Master!$B$3+122 -> 122 | DX4: =Master!$B$3+123 -> 123 | DY4: =Master!$B$3+124 -> 124 | DZ4: =Master!$B$3+125 -> 125 | EA4: =Master!$B$3+126 -> 126 | EB4: =Master!$B$3+127 -> 127 | EC4: =Master!$B$3+128 -> 128 | ED4: =Master!$B$3+129 -> 129 | EE4: =Master!$B$3+130 -> 130 | EF4: =Master!$B$3+131 -> 131 | EG4: =Master!$B$3+132 -> 132 | EH4: =Master!$B$3+133 -> 133 | EI4: =Master!$B$3+134 -> 134 | EJ4: =Master!$B$3+135 -> 135 | EK4: =Master!$B$3+136 -> 136 | EL4: =Master!$B$3+137 -> 137 | EM4: =Master!$B$3+138 -> 138 | EN4: =Master!$B$3+139 -> 139 | EO4: =Master!$B$3+140 -> 140 | EP4: =Master!$B$3+141 -> 141 | EQ4: =Master!$B$3+142 -> 142 | ER4: =Master!$B$3+143 -> 143 | ES4: =Master!$B$3+144 -> 144 | ET4: =Master!$B$3+145 -> 145 | EU4: =Master!$B$3+146 -> 146 | EV4: =Master!$B$3+147 -> 147 | EW4: =Master!$B$3+148 -> 148 | EX4: =Master!$B$3+149 -> 149 | EY4: =Master!$B$3+150 -> 150 | EZ4: =Master!$B$3+151 -> 151 | FA4: =Master!$B$3+152 -> 152 | FB4: =Master!$B$3+153 -> 153 | FC4: =Master!$B$3+154 -> 154 | FD4: =Master!$B$3+155 -> 155 | FE4: =Master!$B$3+156 -> 156 | FF4: =Master!$B$3+157 -> 157 | FG4: =Master!$B$3+158 -> 158 | FH4: =Master!$B$3+159 -> 159 | FI4: =Master!$B$3+160 -> 160 | FJ4: =Master!$B$3+161 -> 161 | FK4: =Master!$B$3+162 -> 162 | FL4: =Master!$B$3+163 -> 163 | FM4: =Master!$B$3+164 -> 164 | FN4: =Master!$B$3+165 -> 165 | FO4: =Master!$B$3+166 -> 166 | FP4: =Master!$B$3+167 -> 167 | FQ4: =Master!$B$3+168 -> 168 | FR4: =Master!$B$3+169 -> 169 | FS4: =Master!$B$3+170 -> 170 | FT4: =Master!$B$3+171 -> 171 | FU4: =Master!$B$3+172 -> 172 | FV4: =Master!$B$3+173 -> 173 | FW4: =Master!$B$3+174 -> 174 | FX4: =Master!$B$3+175 -> 175 | FY4: =Master!$B$3+176 -> 176 | FZ4: =Master!$B$3+177 -> 177 | GA4: =Master!$B$3+178 -> 178 | GB4: =Master!$B$3+179 -> 179 | GC4: =Master!$B$3+180 -> 180 | GD4: =Master!$B$3+181 -> 181 | GE4: =Master!$B$3+182 -> 182 | GF4: =Master!$B$3+183 -> 183 | GG4: =Master!$B$3+184 -> 184 | GH4: =Master!$B$3+185 -> 185 | GI4: =Master!$B$3+186 -> 186 | GJ4: =Master!$B$3+187 -> 187 | GK4: =Master!$B$3+188 -> 188 | GL4: =Master!$B$3+189 -> 189 | GM4: =Master!$B$3+190 -> 190 | GN4: =Master!$B$3+191 -> 191 | GO4: =Master!$B$3+192 -> 192 | GP4: =Master!$B$3+193 -> 193 | GQ4: =Master!$B$3+194 -> 194 | GR4: =Master!$B$3+195 -> 195 | GS4: =Master!$B$3+196 -> 196 | GT4: =Master!$B$3+197 -> 197 | GU4: =Master!$B$3+198 -> 198 | GV4: =Master!$B$3+199 -> 199 | GW4: =Master!$B$3+200 -> 200 | GX4: =Master!$B$3+201 -> 201 | GY4: =Master!$B$3+202 -> 202 | GZ4: =Master!$B$3+203 -> 203 | HA4: =Master!$B$3+204 -> 204 | HB4: =Master!$B$3+205 -> 205 | HC4: =Master!$B$3+206 -> 206 | HD4: =Master!$B$3+207 -> 207 | HE4: =Master!$B$3+208 -> 208 | HF4: =Master!$B$3+209 -> 209 | HG4: =Master!$B$3+210 -> 210 | HH4: =Master!$B$3+211 -> 211 | HI4: =Master!$B$3+212 -> 212 | HJ4: =Master!$B$3+213 -> 213 | HK4: =Master!$B$3+214 -> 214 | HL4: =Master!$B$3+215 -> 215 | HM4: =Master!$B$3+216 -> 216 | HN4: =Master!$B$3+217 -> 217 | HO4: =Master!$B$3+218 -> 218 | HP4: =Master!$B$3+219 -> 219 | HQ4: =Master!$B$3+220 -> 220 | HR4: =Master!$B$3+221 -> 221 | HS4: =Master!$B$3+222 -> 222 | HT4: =Master!$B$3+223 -> 223 | HU4: =Master!$B$3+224 -> 224 | HV4: =Master!$B$3+225 -> 225 | HW4: =Master!$B$3+226 -> 226 | HX4: =Master!$B$3+227 -> 227 | HY4: =Master!$B$3+228 -> 228 | HZ4: =Master!$B$3+229 -> 229 | IA4: =Master!$B$3+230 -> 230 | IB4: =Master!$B$3+231 -> 231 | IC4: =Master!$B$3+232 -> 232 | ID4: =Master!$B$3+233 -> 233 | IE4: =Master!$B$3+234 -> 234 | IF4: =Master!$B$3+235 -> 235 | IG4: =Master!$B$3+236 -> 236 | IH4: =Master!$B$3+237 -> 237 | II4: =Master!$B$3+238 -> 238 | IJ4: =Master!$B$3+239 -> 239 | IK4: =Master!$B$3+240 -> 240 | IL4: =Master!$B$3+241 -> 241 | IM4: =Master!$B$3+242 -> 242 | IN4: =Master!$B$3+243 -> 243 | IO4: =Master!$B$3+244 -> 244 | IP4: =Master!$B$3+245 -> 245 | IQ4: =Master!$B$3+246 -> 246 | IR4: =Master!$B$3+247 -> 247 | IS4: =Master!$B$3+248 -> 248 | IT4: =Master!$B$3+249 -> 249 | IU4: =Master!$B$3+250 -> 250 | IV4: =Master!$B$3+251 -> 251 | IW4: =Master!$B$3+252 -> 252 | IX4: =Master!$B$3+253 -> 253 | IY4: =Master!$B$3+254 -> 254 | IZ4: =Master!$B$3+255 -> 255 | JA4: =Master!$B$3+256 -> 256 | JB4: =Master!$B$3+257 -> 257 | JC4: =Master!$B$3+258 -> 258 | JD4: =Master!$B$3+259 -> 259 | JE4: =Master!$B$3+260 -> 260 | JF4: =Master!$B$3+261 -> 261 | JG4: =Master!$B$3+262 -> 262 | JH4: =Master!$B$3+263 -> 263 | JI4: =Master!$B$3+264 -> 264 | JJ4: =Master!$B$3+265 -> 265 | JK4: =Master!$B$3+266 -> 266 | JL4: =Master!$B$3+267 -> 267 | JM4: =Master!$B$3+268 -> 268 | JN4: =Master!$B$3+269 -> 269 | JO4: =Master!$B$3+270 -> 270 | JP4: =Master!$B$3+271 -> 271 | JQ4: =Master!$B$3+272 -> 272 | JR4: =Master!$B$3+273 -> 273 | JS4: =Master!$B$3+274 -> 274 | JT4: =Master!$B$3+275 -> 275 | JU4: =Master!$B$3+276 -> 276 | JV4: =Master!$B$3+277 -> 277 | JW4: =Master!$B$3+278 -> 278 | JX4: =Master!$B$3+279 -> 279 | JY4: =Master!$B$3+280 -> 280 | JZ4: =Master!$B$3+281 -> 281 | KA4: =Master!$B$3+282 -> 282 | KB4: =Master!$B$3+283 -> 283 | KC4: =Master!$B$3+284 -> 284 | KD4: =Master!$B$3+285 -> 285 | KE4: =Master!$B$3+286 -> 286 | KF4: =Master!$B$3+287 -> 287 | KG4: =Master!$B$3+288 -> 288 | KH4: =Master!$B$3+289 -> 289 | KI4: =Master!$B$3+290 -> 290 | KJ4: =Master!$B$3+291 -> 291 | KK4: =Master!$B$3+292 -> 292 | KL4: =Master!$B$3+293 -> 293 | KM4: =Master!$B$3+294 -> 294 | KN4: =Master!$B$3+295 -> 295 | KO4: =Master!$B$3+296 -> 296 | KP4: =Master!$B$3+297 -> 297 | KQ4: =Master!$B$3+298 -> 298 | KR4: =Master!$B$3+299 -> 299 | KS4: =Master!$B$3+300 -> 300 | KT4: =Master!$B$3+301 -> 301 | KU4: =Master!$B$3+302 -> 302 | KV4: =Master!$B$3+303 -> 303 | KW4: =Master!$B$3+304 -> 304 | KX4: =Master!$B$3+305 -> 305 | KY4: =Master!$B$3+306 -> 306 | KZ4: =Master!$B$3+307 -> 307 | LA4: =Master!$B$3+308 -> 308 | LB4: =Master!$B$3+309 -> 309 | LC4: =Master!$B$3+310 -> 310 | LD4: =Master!$B$3+311 -> 311 | LE4: =Master!$B$3+312 -> 312 | LF4: =Master!$B$3+313 -> 313 | LG4: =Master!$B$3+314 -> 314 | LH4: =Master!$B$3+315 -> 315 | LI4: =Master!$B$3+316 -> 316 | LJ4: =Master!$B$3+317 -> 317 | LK4: =Master!$B$3+318 -> 318 | LL4: =Master!$B$3+319 -> 319 | LM4: =Master!$B$3+320 -> 320 | LN4: =Master!$B$3+321 -> 321 | LO4: =Master!$B$3+322 -> 322 | LP4: =Master!$B$3+323 -> 323 | LQ4: =Master!$B$3+324 -> 324 | LR4: =Master!$B$3+325 -> 325 | LS4: =Master!$B$3+326 -> 326 | LT4: =Master!$B$3+327 -> 327 | LU4: =Master!$B$3+328 -> 328 | LV4: =Master!$B$3+329 -> 329 | LW4: =Master!$B$3+330 -> 330 | LX4: =Master!$B$3+331 -> 331 | LY4: =Master!$B$3+332 -> 332 | LZ4: =Master!$B$3+333 -> 333 | MA4: =Master!$B$3+334 -> 334 | MB4: =Master!$B$3+335 -> 335 | MC4: =Master!$B$3+336 -> 336 | MD4: =Master!$B$3+337 -> 337 | ME4: =Master!$B$3+338 -> 338 | MF4: =Master!$B$3+339 -> 339 | MG4: =Master!$B$3+340 -> 340 | MH4: =Master!$B$3+341 -> 341 | MI4: =Master!$B$3+342 -> 342 | MJ4: =Master!$B$3+343 -> 343 | MK4: =Master!$B$3+344 -> 344 | ML4: =Master!$B$3+345 -> 345 | MM4: =Master!$B$3+346 -> 346 | MN4: =Master!$B$3+347 -> 347 | MO4: =Master!$B$3+348 -> 348 | MP4: =Master!$B$3+349 -> 349 | MQ4: =Master!$B$3+350 -> 350 | MR4: =Master!$B$3+351 -> 351 | MS4: =Master!$B$3+352 -> 352 | MT4: =Master!$B$3+353 -> 353 | MU4: =Master!$B$3+354 -> 354 | MV4: =Master!$B$3+355 -> 355 | MW4: =Master!$B$3+356 -> 356 | MX4: =Master!$B$3+357 -> 357 | MY4: =Master!$B$3+358 -> 358 | MZ4: =Master!$B$3+359 -> 359 | NA4: =Master!$B$3+360 -> 360 | NB4: =Master!$B$3+361 -> 361 | NC4: =Master!$B$3+362 -> 362 | ND4: =Master!$B$3+363 -> 363 | NE4: =Master!$B$3+364 -> 364
A5: =Master!A$6 -> 0 | B5: ='Activity List'!A2 -> T1-001 | C5: ='Activity List'!D2 -> Land Clearing | D5: ='Activity List'!C2 -> Nursery
A6: =Master!A$6 -> 0 | B6: ='Activity List'!A3 -> T1-002 | C6: ='Activity List'!D3 -> Tree Felling | D6: ='Activity List'!C3 -> Nursery
A7: =Master!A$6 -> 0 | B7: ='Activity List'!A4 -> T1-003 | C7: ='Activity List'!D4 -> Soil Heaping | D7: ='Activity List'!C4 -> Nursery
A8: =Master!A$6 -> 0 | B8: ='Activity List'!A5 -> T1-004 | C8: ='Activity List'!D5 -> Polytube Cutting | D8: ='Activity List'!C5 -> Nursery
A9: =Master!A$6 -> 0 | B9: ='Activity List'!A6 -> T1-005 | C9: ='Activity List'!D6 -> Polytube Filling | D9: ='Activity List'!C6 -> Nursery
A10: =Master!A$6 -> 0 | B10: ='Activity List'!A7 -> T1-006 | C10: ='Activity List'!D7 -> Seedbed Preparation | D10: ='Activity List'!C7 -> Nursery
A11: =Master!A$6 -> 0 | B11: ='Activity List'!A8 -> T1-007 | C11: ='Activity List'!D8 -> Polytube Arranging | D11: ='Activity List'!C8 -> Nursery
A12: =Master!A$6 -> 0 | B12: ='Activity List'!A9 -> T1-008 | C12: ='Activity List'!D9 -> Seed Sowing | D12: ='Activity List'!C9 -> Nursery
A13: =Master!A$6 -> 0 | B13: ='Activity List'!A10 -> T1-009 | C13: ='Activity List'!D10 -> Mulch Material Preparation | D13: ='Activity List'!C10 -> Nursery
A14: =Master!A$6 -> 0 | B14: ='Activity List'!A11 -> T1-010 | C14: ='Activity List'!D11 -> Mulch Application | D14: ='Activity List'!C11 -> Nursery
A15: =Master!A$6 -> 0 | B15: ='Activity List'!A12 -> T1-011 | C15: ='Activity List'!D12 -> Shade Material Preparation | D15: ='Activity List'!C12 -> Nursery
A16: =Master!A$6 -> 0 | B16: ='Activity List'!A13 -> T1-012 | C16: ='Activity List'!D13 -> Shade Construction | D16: ='Activity List'!C13 -> Nursery
... A138: =Master!A$6 -> 0 | B138: ='Activity List'!A135 -> T3-035 | C138: ='Activity List'!D135 -> Buyer Hosting at SpiralLabs | D138: ='Activity List'!C135 -> B. Technical and Laboratory Services
A140: Shading is generated by conditional formatting reading the Annual Election sheet, so it updates live as ticks, windows and Planned Duration change there. Activities with no default window never auto-shade; plan those manually once agreed.

Sheet Monthly Client Report
B1: Monthly Report — [Farm Name] — [Reporting Month]
B2: Prepared under the Cropfort Process Assurance Protocol™. This sheet pulls its figures from the live operating data on the other sheets — it is a summary layer, not a separate record.
B4: 1. EXECUTIVE SUMMARY
B5: % of Year 1 Plan Complete | C5: =IFERROR(AVERAGE('Supervisor Progress'!$G$2:$G$135),"")
B6: Total Budget (ETB) | C6: ='Total Budget Summary'!F5 -> 0
B7: Actual Labor Cost Booked to Date (ETB) | C7: =SUM('Supervisor Progress'!$I$2:$I$135) -> 0
B8: Activities Flagged At Risk | C8: =COUNTIF('Supervisor Progress'!$M$2:$M$135,"AT RISK*") -> 0
B9: Activities Rolled Over | C9: =COUNTIF('Supervisor Progress'!$O$2:$O$135,"ROLL*") -> 0
B11: Narrative (one or two lines, entered by the supervisor/manager each month):
B14: 2. PROGRESS VS. PLAN, BY TIER
B15: Tier | C15: Planned Qty (sum) | D15: Actual Qty Done (sum) | E15: % Complete (avg)
B16: Tier 1 — Core Services | C16: =SUMIFS('Supervisor Progress'!$D$2:$D$135,'Supervisor Progress'!$B$2:$B$135,"T1-*") -> 0 | D16: =SUMIFS('Supervisor Progress'!$H$2:$H$135,'Supervisor Progress'!$B$2:$B$135,"T1-*") -> 0 | E16: =IFERROR(AVERAGEIFS('Supervisor Progress'!$G$2:$G$135,'Supervisor Progress'!$B$2:$B$135,"T1-*"),"")
B17: Tier 2 — Projects | C17: =SUMIFS('Supervisor Progress'!$D$2:$D$135,'Supervisor Progress'!$B$2:$B$135,"T2-*") -> 0 | D17: =SUMIFS('Supervisor Progress'!$H$2:$H$135,'Supervisor Progress'!$B$2:$B$135,"T2-*") -> 0 | E17: =IFERROR(AVERAGEIFS('Supervisor Progress'!$G$2:$G$135,'Supervisor Progress'!$B$2:$B$135,"T2-*"),"")
B18: Tier 3 — Interventions | C18: =SUMIFS('Supervisor Progress'!$D$2:$D$135,'Supervisor Progress'!$B$2:$B$135,"T3-*") -> 0 | D18: =SUMIFS('Supervisor Progress'!$H$2:$H$135,'Supervisor Progress'!$B$2:$B$135,"T3-*") -> 0 | E18: =IFERROR(AVERAGEIFS('Supervisor Progress'!$G$2:$G$135,'Supervisor Progress'!$B$2:$B$135,"T3-*"),"")
B20: 3. BUDGET VS. ACTUAL
C21: Labor | D21: Material | E21: Service | F21: Total
B22: Budget (ETB) | C22: ='Total Budget Summary'!C5 -> 0 | D22: ='Total Budget Summary'!D5 -> 0 | E22: ='Total Budget Summary'!E5 -> 0 | F22: ='Total Budget Summary'!F5 -> 0
B23: Actual to Date (ETB) | C23: =SUM('Supervisor Progress'!$I$2:$I$135) -> 0 | F23: =SUM(C23:E23) -> 0
B25: 4. RISK REGISTER
B26: Auto-flagged count (from Supervisor Progress, "AT RISK"), see Executive Summary above.
B27: =IF(COUNTIF('Supervisor Progress'!$M$2:$M$135,"AT RISK*")>0,"Yes — open Supervisor Progress and filter column M for the full list of flagged activities.","None currently flagged.") -> None currently flagged.
B28: Other risks / open AFEs (manual):
B31: 5. LOOK-AHEAD, NEXT MONTH
B32: See the relevant month band on the block Calendar tab(s) for exact shaded activities.
B34: 6. FIELD OBSERVATIONS
B37: 7. ASSURANCE NOTE
B38: This report is prepared by Cropfort's manager under the Cropfort Process Assurance Protocol™ — a documented field methodology addressing rigor and traceability, aligned with the principles of internationally recognized coffee-sustainability standards, without itself constituting certification. The dashboard figures above are the manager's own reporting and should be read as such, not as independent proof: a manager validating its own work is not, by itself, verification. Independent assurance comes from three channels: (1) audit-trail and drill-down rights to the underlying Annual Farm Program / Authorization for Expenditure / Work Order / Field Ticket chain, available on request; (2) externally verifiable facts — yield against the baseline assessment, export volumes and revenue, and any third-party certification audits; (3) the farm owner's own independent oversight channel, which sits entirely outside this reporting pipeline.
